Workbook

Sheet Guide
A1: GT AI Opportunity Discovery Toolkit
A2: Where exactly does AI fit in this organisation - and where is automation enough? A facilitated workshop tool of the GT AI Strategy & Roadmap service, built on a 240-entry, standards-based AI use-case library.
B4: WHAT THIS TOOLKIT ANSWERS
B5: 1. Is the organisation positioned for AI? | C5: Do you have the DATA (digital, joined-up, reliable, with history and outcomes) and the SCALE / CAPACITY (volumes, people, budget, technology team) for AI - or is automation enough for now? Result: one of four archetypes and a ceiling on solution complexity.
B6: 2. Where exactly does AI fit? | C6: Process by process, selected from the GT AI Use-Case Library for the client's sector: which solution family fits (automate, off-the-shelf AI, configured AI, custom / agentic AI), is the data there, what is the risk tier - and what exactly GT recommends.
B7: 3. What should be done first? | C7: Value x feasibility, risk-adjusted priority, horizon (H1 / H2 / H3), opportunity report, roadmap lanes and one-page use-case canvases.
B8: Not a readiness test | C8: Governance and capability maturity are measured by the GT AI Readiness & Risk Assessment (AI Ready7-based). This toolkit locates the opportunities and the right type of solution for each.
B10: HOW TO USE IT (WORKSHOP SEQUENCE)
B11: 1. AI Position | C11: Select the sector, then answer 12 questions with leadership, IT and finance (about 30 minutes). Data Position and Scale & Capacity scores place the organisation in an archetype.
B12: 2. Use-Case Library | C12: 240 use cases: 60 cross-industry plus 180 sector-specific entries (banking, insurance, capital markets, healthcare, telecom, government, retail, hospitality, manufacturing, energy, logistics, real estate, education, professional services). Each entry carries the GT recommendation, data needed, KPIs, regulatory notes and a minimum risk tier.
B13: 3. AI Fit Diagnostic | C13: Select up to 50 use cases from the library (the list shows cross-industry + the selected sector) and answer 9 inputs each (yellow). Custom processes can be typed in - then select the task nature and function. Everything else calculates, including the library recommendation.
B14: 4. Opportunity Report | C14: The client-ready output: AI position, verdict mix, where AI fits by function, the top 10 opportunities with GT recommendations and the sector lens.
B15: 5. Roadmap | C15: Opportunities placed automatically in H1 / H2 / H3 lanes plus the enabling foundations they depend on.
B16: 6. Use-Case Canvas | C16: Pick an opportunity number; a one-page canvas is produced (recommendation, data, KPIs, risk tier, regulatory notes, minimum controls, next step).
B17: 7. Sector Profiles | C17: Value at stake, automation & AI potential, value pools and key regulators for each sector.
B18: Reference | C18: Solution families, archetypes, verdicts, minimum controls, function taxonomy (APQC) and the standards behind each step.
B19: Colour legend | C19: Yellow = input | Purple / lavender = header or calculated | Verdict colours: green = AI fit now, blue = automate, yellow = data gap, orange = stretch, grey = redesign first
B21: DECISION LOGIC (SUMMARY)
B22: Solution family | C22: From the nature of the task (library default, or override). 10 families, ISO/IEC 22989 / OECD-based, each with a complexity level 1-5 and a minimum data requirement.
B23: Data gate | C23: Data available for the process >= the family's minimum requirement -> 'Data ready', otherwise 'Data gap'.
B24: Organisational fit | C24: Family level <= the archetype's ceiling -> 'Within current position', otherwise 'Beyond current position'.
B25: Verdict (in order) | C25: Process not standardised -> Redesign first; family needs no AI -> Automate; data gap -> AI later; beyond position -> Stretch; otherwise -> AI fit now.
B26: Value (1-5) | C26: 30% volume + 25% effort (hours / month) + 25% strategic importance + 20% customer / quality impact.
B27: Feasibility (1-5) | C27: 30% data fit + 25% process standardisation + 25% solution simplicity + 20% organisational fit.
B28: Risk tier | C28: AIAF-style inherent risk: affects individuals' rights / access (+2), personal or confidential data (+1), autonomy (+0 to +2), impact of errors (+1 if 4, +2 if 5): 4+ High, 2-3 Medium, 0-1 Low; never below the library's minimum tier (EU AI Act Annex III / sector rules).
B29: Priority | C29: Value x Feasibility, reduced 15% for High risk and 20% where the process must be redesigned first. Ranked 1..n.
B30: Horizon | C30: H1: quick wins / fill-ins that fit now or need only automation. H2: strategic bets, stretch items, redesigned processes - and any High-risk or agentic (level 5) use case, which waits for its impact assessment and controls. H3: items blocked by data gaps. Backlog: deprioritised.

Sheet 1. AI Position
A1: 1. Organisational AI Position
A2: Does the organisation have the data and the scale / capacity for AI - or is automation enough for now? Select the sector and one answer per question (yellow). This screen does not measure governance maturity.
B4: Organisation | C4: Grant Thornton Bahrain (illustrative)
B5: Sector (filters the use-case library) | C5: Professional services
B6: Scope of discovery | C6: Whole firm - audit, tax, advisory and support functions
B7: Assessment date | C7: 04/10/2026
B8: Facilitated by | C8: GT AI Service Line
A10: # | B10: Question | C10: Answer (select) | D10: Why it matters | E10: Points
A11: A. DATA POSITION - is the data there for AI?
A12: D1 | B12: How are your core business processes run today? | C12: Core systems (e.g., ERP, CRM, core banking) for the main processes | D12: Think of the 3-5 processes that generate most of your revenue or workload. | E12: =IFERROR(MATCH(C12,Lists!$S$2:$S$5,0),"") -> 3
A13: D2 | B13: How much digital history do you keep for your core activities (transactions, customers, cases, operations)? | C13: 3+ years in core systems | D13: AI that predicts, scores or detects patterns learns from history. | E13: =IFERROR(MATCH(C13,Lists!$T$2:$T$5,0),"") -> 3
A14: D3 | B14: How reliable is that data, and does it have owners? | C14: Some owners; known quality issues not tracked | D14: Data quality and ownership - ISO/IEC 5259 / ISO/IEC 42001 Annex A.7. | E14: =IFERROR(MATCH(C14,Lists!$U$2:$U$5,0),"") -> 2
A15: D4 | B15: Where do your documents and knowledge live (contracts, policies, reports, emails, manuals)? | C15: A document-management system or SharePoint with structure | D15: Generative AI and knowledge assistants work on documents rather than tables. | E15: =IFERROR(MATCH(C15,Lists!$V$2:$V$5,0),"") -> 3
A16: D5 | B16: Can data move between your systems? | C16: Some APIs or integrations between key systems | D16: Integration determines whether AI outputs can be used inside the workflow. | E16: =IFERROR(MATCH(C16,Lists!$W$2:$W$5,0),"") -> 3
A17: D6 | B17: Do you record outcomes against your data (e.g., fraud confirmed, claim paid, customer churned, invoice disputed)? | C17: Occasionally / informally | D17: Recorded outcomes ('labels') are what supervised machine learning needs. | E17: =IFERROR(MATCH(C17,Lists!$X$2:$X$5,0),"") -> 2
A18: B. SCALE & CAPACITY - is there enough volume and capacity to justify and run AI?
A19: S1 | B19: How many employees does the organisation have? | C19: 50 - 249 | D19: Scale drives the size of the prize and what can be sustained. | E19: =IFERROR(MATCH(C19,Lists!$Y$2:$Y$5,0),"") -> 2
A20: S2 | B20: How many repetitive transactions / cases does your largest process handle per month? | C20: 500 - 5,000 | D20: e.g., invoices, applications, claims, customer requests, bookings. | E20: =IFERROR(MATCH(C20,Lists!$Z$2:$Z$5,0),"") -> 2
A21: S3 | B21: What technology capability do you have in-house? | C21: Small IT team (support and vendor management) | D21: Who would configure, integrate and run a solution? | E21: =IFERROR(MATCH(C21,Lists!$AA$2:$AA$5,0),"") -> 2
A22: S4 | B22: What budget could be made available for digital / AI initiatives in the next 12 months? | C22: BHD 50,000 - 250,000 | D22: Indicative only - used to size the type of solution that is realistic. | E22: =IFERROR(MATCH(C22,Lists!$AB$2:$AB$5,0),"") -> 3
A23: S5 | B23: How many customer / citizen interactions do you handle through digital channels? | C23: Moderate | D23: Web, app, email, WhatsApp, call centre. | E23: =IFERROR(MATCH(C23,Lists!$AC$2:$AC$5,0),"") -> 2
A24: S6 | B24: What capacity do you have to run change projects alongside day-to-day work? | C24: Several projects in parallel | D24: Leadership bandwidth, project management, change management. | E24: =IFERROR(MATCH(C24,Lists!$AD$2:$AD$5,0),"") -> 3
A26: RESULT - AI POSITION
B27: Answered | C27: =COUNT(E12,E13,E14,E15,E16,E17)+COUNT(E19,E20,E21,E22,E23,E24)&" of 12" -> 12 of 12
B28: Data Position score | C28: =IF(COUNT(E12,E13,E14,E15,E16,E17)=6,(N(E12)+N(E13)+N(E14)+N(E15)+N(E16)+N(E17)-6)/18,"") -> 0.55555556
B29: Scale & Capacity score | C29: =IF(COUNT(E19,E20,E21,E22,E23,E24)=6,(N(E19)+N(E20)+N(E21)+N(E22)+N(E23)+N(E24)-6)/18,"") -> 0.44444444
B30: Archetype | C30: =IF(OR(C28="",C29=""),"",IF(C28<0.5,IF(C29<0.5,1,2),IF(C29<0.5,3,4))) -> 3
B31: AI position | C31: =IF(C30="","Complete all 12 questions",INDEX(Lists!$AH$2:$AH$5,C30)) -> Buy and configure AI
B32: Solution ceiling today | C32: =IF(C30="","",INDEX(Lists!$AI$2:$AI$5,C30)&" - "&INDEX(Lists!$AM$2:$AM$6,INDEX(Lists!$AI$2:$AI$5,C30))) -> 4 - Configured AI on own data
B33: What it means | C33: =IF(C30="","",INDEX(Lists!$AJ$2:$AJ$5,C30)) -> Good data, limited scale / capacity: adopt and configure proven AI products rather than build.
B34: Detail | C34: =IF(C30="","",INDEX(Lists!$AK$2:$AK$5,C30)) -> The data supports AI, but in-house capacity and scale favour buying. Configure AI products on your own data (knowledge assistants, intelligent document processing, conversational AI, vendor ML modules). Custom models and autonomous agents only through partners and pilots.
B35: Foundation flag | C35: =IF(E12=1,"Core processes are largely manual / paper-based: digitise them first - AI and automation need digital inputs.",IF(AND(N(E13)>0,N(E13)<=2,N(E17)<=1),"Little digital history and no recorded outcomes: predictive / ML use cases will fail the data gate until data is captured.","No foundation red flags from the position screen.")) -> No foundation red flags from the position screen.
A37: POSITION MATRIX - the highlighted box is where the organisation sits
B38: Data Position HIGH (>= 50%) | C38: C. Buy and configure AI Good data, limited scale / capacity: adopt and configure proven AI products rather than build. | D38: D. Build and scale AI Data and scale support custom AI: build a portfolio, including advanced analytics and governed agentic AI.
B39: Data Position LOW (< 50%) | C39: A. Automation is enough - for now Digitise and automate first; use AI that is already built into everyday tools. | D39: B. Data foundations first Scale is there but the data is not: fix data foundations while automating and adopting off-the-shelf AI.
C40: Scale & Capacity LOW (< 50%) | D40: Scale & Capacity HIGH (>= 50%)

Sheet 2. Use-Case Library
A1: 2. GT AI Use-Case Library (240 entries)
A2: Cross-industry (APQC functions) and sector-specific AI and automation use cases with GT recommendations, data needs, KPIs, regulatory notes and a minimum risk tier. Select entries in the AI Fit Diagnostic; the dropdown there shows cross-industry + the sector chosen on sheet 1.
A4: ID | B4: Sector | C4: Function (APQC) | D4: Process / use case | E4: Typical pain point | F4: Nature of the task | G4: Solution family | H4: GT recommendation | I4: Data needed | J4: KPIs | K4: Regulatory & risk notes | L4: Min. risk
A5: XI-01 | B5: Cross-industry | C5: Finance & accounting | D5: Supplier invoice capture & posting | E5: Invoices keyed manually from PDF / email into the ERP | F5: Extract information from documents, forms or emails | G5: Intelligent document processing (IDP) | H5: Capture invoices with intelligent document processing, validate against PO and vendor master, post automatically; route exceptions to AP. | I5: Invoice PDFs / scans, vendor master, purchase orders | J5: Touchless invoice rate; cost per invoice; posting cycle time | K5: Segregation of duties in approval; vendor bank-detail change controls (payment fraud). | L5: Low | M5: XI-01 | Supplier invoice capture & posting | N5: =OR('1. AI Position'!$C$5="",'1. AI Position'!$C$5="Other",B5="Cross-industry",B5='1. AI Position'!$C$5) -> TRUE | O5: =IF(N5,COUNTIF($N$5:N5,TRUE),"") -> 1
A6: XI-02 | B6: Cross-industry | C6: Finance & accounting | D6: Three-way match & payment approval | E6: PO, goods receipt and invoice checked by hand | F6: Check or approve items against fixed criteria (rules, thresholds, checklists) | G6: Rules engine / workflow automation | H6: Configure tolerance-based three-way matching in the ERP workflow; auto-approve within tolerance and escalate exceptions. | I6: POs, goods receipts, invoices | J6: Auto-match rate; late-payment penalties; exceptions per 100 invoices | K6: Approval limits and SoD must be enforced in the workflow. | L6: Low | M6: XI-02 | Three-way match & payment approval | N6: =OR('1. AI Position'!$C$5="",'1. AI Position'!$C$5="Other",B6="Cross-industry",B6='1. AI Position'!$C$5) -> TRUE | O6: =IF(N6,COUNTIF($N$5:N6,TRUE),"") -> 2
A7: XI-03 | B7: Cross-industry | C7: Finance & accounting | D7: Bank reconciliations | E7: Spreadsheet matching every month | F7: Produce reports, dashboards or reconciliations from existing data | G7: BI, dashboards & reconciliation automation | H7: Deploy a reconciliation tool with rule-based auto-matching; add ML-assisted fuzzy matching only once rules are exhausted. | I7: Bank statements (MT940 / CSV), GL cash entries | J7: Auto-match %; days to reconcile; unreconciled items ageing | K7: Reviewer sign-off retained; audit trail of matches. | L7: Low | M7: XI-03 | Bank reconciliations | N7: =OR('1. AI Position'!$C$5="",'1. AI Position'!$C$5="Other",B7="Cross-industry",B7='1. AI Position'!$C$5) -> TRUE | O7: =IF(N7,COUNTIF($N$5:N7,TRUE),"") -> 3
A8: XI-04 | B8: Cross-industry | C8: Finance & accounting | D8: Intercompany reconciliation & eliminations | E8: Late intercompany agreements delay the close | F8: Produce reports, dashboards or reconciliations from existing data | G8: BI, dashboards & reconciliation automation | H8: Standardise intercompany coding, automate matching and elimination journals in the consolidation tool. | I8: Intercompany ledgers, entity mapping | J8: Intercompany differences at close; close days | K8: - | L8: Low | M8: XI-04 | Intercompany reconciliation & eliminations | N8: =OR('1. AI Position'!$C$5="",'1. AI Position'!$C$5="Other",B8="Cross-industry",B8='1. AI Position'!$C$5) -> TRUE | O8: =IF(N8,COUNTIF($N$5:N8,TRUE),"") -> 4
A9: XI-05 | B9: Cross-industry | C9: Finance & accounting | D9: Month-end close & management packs | E9: Manual report packs delivered late | F9: Produce reports, dashboards or reconciliations from existing data | G9: BI, dashboards & reconciliation automation | H9: Close-checklist workflow plus automated report packs (e.g., Power BI); GenAI drafts variance commentary for finance review. | I9: GL, budgets, KPI definitions | J9: Close days; report delivery date; manual adjustments | K9: GenAI commentary reviewed before release; no confidential data in public tools. | L9: Low | M9: XI-05 | Month-end close & management packs | N9: =OR('1. AI Position'!$C$5="",'1. AI Position'!$C$5="Other",B9="Cross-industry",B9='1. AI Position'!$C$5) -> TRUE | O9: =IF(N9,COUNTIF($N$5:N9,TRUE),"") -> 5
A10: XI-06 | B10: Cross-industry | C10: Finance & accounting | D10: Cash-flow forecasting | E10: Spreadsheet forecasts with poor accuracy | F10: Forecast, score, classify or detect anomalies from historical data | G10: Predictive analytics / machine learning | H10: Driver-based ML forecast using AR / AP history and seasonality; run in parallel with the manual forecast for three cycles before relying on it. | I10: 2-3 years of AR / AP, bank and payroll history | J10: Forecast accuracy (MAPE); idle cash; borrowing cost | K10: Model owner and back-testing documented. | L10: Low | M10: XI-06 | Cash-flow forecasting | N10: =OR('1. AI Position'!$C$5="",'1. AI Position'!$C$5="Other",B10="Cross-industry",B10='1. AI Position'!$C$5) -> TRUE | O10: =IF(N10,COUNTIF($N$5:N10,TRUE),"") -> 6
A11: XI-07 | B11: Cross-industry | C11: Finance & accounting | D11: Collections & dunning | E11: Overdue invoices chased manually | F11: Move or re-key data between systems following fixed rules | G11: Workflow automation / RPA | H11: Automated dunning workflow with reminders by email / WhatsApp and promise-to-pay tracking; add payment-propensity scoring once history allows. | I11: AR ledger, customer contacts, payment history | J11: DSO; overdue %; collector productivity | K11: Fair-treatment and contact-time rules; customer consent for WhatsApp. | L11: Low | M11: XI-07 | Collections & dunning | N11: =OR('1. AI Position'!$C$5="",'1. AI Position'!$C$5="Other",B11="Cross-industry",B11='1. AI Position'!$C$5) -> TRUE | O11: =IF(N11,COUNTIF($N$5:N11,TRUE),"") -> 7
A12: XI-08 | B12: Cross-industry | C12: Finance & accounting | D12: VAT return preparation | E12: Collating transactions and VAT codes by hand | F12: Move or re-key data between systems following fixed rules | G12: Workflow automation / RPA | H12: Automate extraction and validation of VAT-coded transactions and populate the NBR VAT return template; reviewer sign-off before filing. | I12: Sales / purchase ledgers, VAT codes | J12: Preparation hours; filing errors; penalties | K12: NBR VAT law compliance; maker-checker on filing. | L12: Low | M12: XI-08 | VAT return preparation | N12: =OR('1. AI Position'!$C$5="",'1. AI Position'!$C$5="Other",B12="Cross-industry",B12='1. AI Position'!$C$5) -> TRUE | O12: =IF(N12,COUNTIF($N$5:N12,TRUE),"") -> 8
A13: XI-09 | B13: Cross-industry | C13: Finance & accounting | D13: Expense claims audit | E13: Receipts checked manually against policy | F13: Extract information from documents, forms or emails | G13: Intelligent document processing (IDP) | H13: Receipt capture with IDP, a rules engine for policy checks and duplicate / anomaly flags for review. | I13: Receipts, expense policy, card feeds | J13: Claims processed per FTE; policy breaches detected; reimbursement time | K13: Employee data - PDPL; transparent policy rules. | L13: Low | M13: XI-09 | Expense claims audit | N13: =OR('1. AI Position'!$C$5="",'1. AI Position'!$C$5="Other",B13="Cross-industry",B13='1. AI Position'!$C$5) -> TRUE | O13: =IF(N13,COUNTIF($N$5:N13,TRUE),"") -> 9
A14: XI-10 | B14: Cross-industry | C14: Finance & accounting | D14: Financial statements & disclosure drafting | E14: Mapping trial balances and drafting notes manually | F14: Draft, summarise, translate or review text | G14: Generative AI assistant (off-the-shelf) | H14: Rules-based TB-to-line mapping with AI suggestions; GenAI drafts notes from approved templates; qualified accountant review and sign-off. | I14: Trial balance, prior-year FS, IFRS disclosure checklist | J14: Preparation hours; review points; restatements | K14: IFRS compliance; professional review mandatory; IESBA independence where an auditor provides it (GT AI FS tool - in preparation). | L14: Medium | M14: XI-10 | Financial statements & disclosure drafting | N14: =OR('1. AI Position'!$C$5="",'1. AI Position'!$C$5="Other",B14="Cross-industry",B14='1. AI Position'!$C$5) -> TRUE | O14: =IF(N14,COUNTIF($N$5:N14,TRUE),"") -> 10
A15: XI-11 | B15: Cross-industry | C15: Finance & accounting | D15: Budget narratives & variance commentary | E15: Commentary written from scratch each month | F15: Draft, summarise, translate or review text | G15: Generative AI assistant (off-the-shelf) | H15: GenAI drafts budget and variance commentary from approved KPI tables; finance edits and approves. | I15: Budget vs actuals, KPI definitions | J15: Hours per pack; timeliness | K15: Confidential financials only in approved enterprise tools. | L15: Low | M15: XI-11 | Budget narratives & variance commentary | N15: =OR('1. AI Position'!$C$5="",'1. AI Position'!$C$5="Other",B15="Cross-industry",B15='1. AI Position'!$C$5) -> TRUE | O15: =IF(N15,COUNTIF($N$5:N15,TRUE),"") -> 11
A16: XI-12 | B16: Cross-industry | C16: Finance & accounting | D16: Fixed-asset register & depreciation | E16: Asset additions and disposals updated manually | F16: Move or re-key data between systems following fixed rules | G16: Workflow automation / RPA | H16: Automate asset creation from capex POs and depreciation runs; dashboard for physical-verification exceptions. | I16: Capex POs, asset register | J16: Register accuracy; close hours | K16: - | L16: Low | M16: XI-12 | Fixed-asset register & depreciation | N16: =OR('1. AI Position'!$C$5="",'1. AI Position'!$C$5="Other",B16="Cross-industry",B16='1. AI Position'!$C$5) -> TRUE | O16: =IF(N16,COUNTIF($N$5:N16,TRUE),"") -> 12
... A244: PRO-15 | B244: Professional services | C244: Knowledge & collaboration | D244: Methodology & knowledge Q&A | E244: Staff search across manuals and past work | F244: Answer questions from internal knowledge, policies or past work | G244: GenAI knowledge assistant (RAG on own content) | H244: Grounded assistant over firm methodologies and sanitised precedents. | I244: Methodologies, sanitised precedents | J244: Search time; reuse | K244: Client confidentiality in precedents. | L244: Low | M244: PRO-15 | Methodology & knowledge Q&A | N244: =OR('1. AI Position'!$C$5="",'1. AI Position'!$C$5="Other",B244="Cross-industry",B244='1. AI Position'!$C$5) -> TRUE | O244: =IF(N244,COUNTIF($N$5:N244,TRUE),"") -> 75

Sheet 3. AI Fit Diagnostic
A1: 3. AI Fit Diagnostic - process by process
A2: Select a use case from the library (column B; type a custom process if it is not in the library, then select its task nature and function in D-E) and answer the yellow inputs F-N. Effort = staff hours spent on the process per month (all people involved).
B3: Organisation's AI position (from sheet 1): | C3: ='1. AI Position'!$C$31 -> Buy and configure AI | F3: Solution ceiling level: | I3: =IF('1. AI Position'!$C$30="",5,INDEX(Lists!$AI$2:$AI$5,'1. AI Position'!$C$30)) -> 4
B4: Quadrant threshold (value and feasibility, 1-5): | C4: 3.25 | D4: ="Library entries offered: "&COUNTIF(Lists!$BA$2:$BA$241,"?*") -> Library entries offered: 75
A6: INPUTS (yellow) | O6: AUTO-CALCULATED (recommendation and notes come from the GT AI Use-Case Library)
A7: # | B7: Use case (select from library, or type a custom process) | C7: Client-specific note (optional) | D7: Task nature - custom entries / override | E7: Function - custom entries only | F7: Volume | G7: Effort (hrs / month) | H7: Process standardised? | I7: Data available for this process | J7: Strategic importance (1-5) | K7: Customer / quality impact (1-5) | L7: Affects individuals' rights or access? | M7: Personal or confidential data? | N7: Intended autonomy | O7: Library ID | P7: Function | Q7: Nature of the task | R7: Solution family | S7: Level | T7: AI? | U7: Data gate | V7: Organisational fit | W7: VERDICT | X7: Value | Y7: Feasib-ility | Z7: Risk tier | AA7: Quadrant | AB7: Priority score | AC7: Rank | AD7: Horizon | AE7: Est. hours released / yr | AF7: GT recommendation (library) | AG7: Regulatory & risk notes (library) | AH7: h | AI7: key | AJ7: name
A8: 1 | B8: PRO-01 | Audit - journal-entry testing (full population) | F8: High (more than 1,000 a month) | G8: 300 | H8: Partly - common steps, some variation | I8: Digital history available | J8: 5 | K8: 5 | L8: No | M8: Yes | N8: Human approves each AI output | O8: =IF(B8="","",IFERROR(INDEX('2. Use-Case Library'!$A$5:$A$244,MATCH(B8,'2. Use-Case Library'!$M$5:$M$244,0)),"Custom")) -> PRO-01 | P8: =IF(B8="","",IF(O8="Custom",IF(E8="","(select function in E)",E8),INDEX('2. Use-Case Library'!$C$5:$C$244,MATCH($O8,'2. Use-Case Library'!$A$5:$A$244,0)))) -> Core operations & service delivery | Q8: =IF(B8="","",IF(D8<>"",D8,IF(O8="Custom","",INDEX('2. Use-Case Library'!$F$5:$F$244,MATCH($O8,'2. Use-Case Library'!$A$5:$A$244,0))))) -> Forecast, score, classify or detect anomalies from historical data | R8: =IF(Q8="","",INDEX(Lists!$B$2:$B$11,MATCH(Q8,Lists!$A$2:$A$11,0))) -> Predictive analytics / machine learning | S8: =IF(R8="","",INDEX(Lists!$C$2:$C$11,MATCH(R8,Lists!$B$2:$B$11,0))) -> 5 | T8: =IF(R8="","",INDEX(Lists!$D$2:$D$11,MATCH(R8,Lists!$B$2:$B$11,0))) -> Yes | U8: =IF(OR(R8="",I8=""),"",IF(INDEX(Lists!$N$2:$N$5,MATCH(I8,Lists!$M$2:$M$5,0))>=INDEX(Lists!$E$2:$E$11,MATCH(R8,Lists!$B$2:$B$11,0)),"Data ready","Data gap")) -> Data ready | V8: =IF(R8="","",IF(S8<=IF('1. AI Position'!$C$30="",5,INDEX(Lists!$AI$2:$AI$5,'1. AI Position'!$C$30)),"Within current position","Beyond current position")) -> Beyond current position | W8: =IF(B8="","",IF(OR(COUNTA(F8:N8)<9,Q8=""),"Complete inputs",IF(H8="No - varies by person / team","Redesign / standardise first",IF(T8="No","Automate - AI not needed",IF(U8="Data gap","AI later - close data gap first",IF(V8="Beyond current position","Stretch - partner or later stage","AI fit now")))))) -> Stretch - partner or later stage | X8: =IF(OR(W8="",W8="Complete inputs"),"",ROUND(0.3*INDEX(Lists!$N$8:$N$10,MATCH(F8,Lists!$M$8:$M$10,0))+0.25*IF(G8<20,1,IF(G8<80,2,IF(G8<160,3,IF(G8<480,4,5))))+0.25*J8+0.2*K8,2)) -> 4.75 | Y8: =IF(X8="","",ROUND(0.3*IF(U8="Data ready",5,IF(INDEX(Lists!$N$2:$N$5,MATCH(I8,Lists!$M$2:$M$5,0))=INDEX(Lists!$E$2:$E$11,MATCH(R8,Lists!$B$2:$B$11,0))-1,3,1))+0.25*INDEX(Lists!$N$13:$N$15,MATCH(H8,Lists!$M$13:$M$15,0))+0.25*(6-S8)+0.2*IF(V8="Within current position",5,2),2)) -> 2.9 | Z8: =IF(X8="","",CHOOSE(MAX(IF(T8="No",IF(L8="Yes",2,1),IF(IF(L8="Yes",2,0)+IF(M8="Yes",1,0)+INDEX(Lists!$N$18:$N$20,MATCH(N8,Lists!$M$18:$M$20,0))+IF(K8=5,2,IF(K8>=4,1,0))>=4,3,IF(IF(L8="Yes",2,0)+IF(M8="Yes",1,0)+INDEX(Lists!$N$18:$N$20,MATCH(N8,Lists!$M$18:$M$20,0))+IF(K8=5,2,IF(K8>=4,1,0))>=2,2,1))),IF($O8="Custom",1,MATCH(INDEX('2. Use-Case Library'!$L$5:$L$244,MATCH($O8,'2. Use-Case Library'!$A$5:$A$244,0)),{"Low","Medium","High"},0))),"Low","Medium","High")) -> High | AA8: =IF(X8="","",IF(AND(X8>=$C$4,Y8>=$C$4),"Quick win",IF(X8>=$C$4,"Strategic bet",IF(Y8>=$C$4,"Fill-in","Deprioritise")))) -> Strategic bet | AB8: =IF(X8="","",ROUND(X8*Y8*IF(Z8="High",0.85,1)*IF(W8="Redesign / standardise first",0.8,1),2)) -> 11.71 | AC8: =IF(AB8="","",RANK(AB8,$AB$8:$AB$57)+COUNTIF($AB$7:AB7,AB8)) -> 15 | AD8: =IF(AH8="","",INDEX(Lists!$AV$2:$AV$5,AH8)) -> H2 - Next (6-12 months) | AE8: =IF(AB8="","",ROUND(G8*12*INDEX(Lists!$F$2:$F$11,MATCH(R8,Lists!$B$2:$B$11,0)),0)) -> 720 | AF8: =IF(OR(B8="",R8=""),"",IF(O8="Custom",INDEX(Lists!$I$2:$I$11,MATCH(R8,Lists!$B$2:$B$11,0)),INDEX('2. Use-Case Library'!$H$5:$H$244,MATCH($O8,'2. Use-Case Library'!$A$5:$A$244,0)))) -> Full-population JE analytics with rules and ML anomaly scoring; auditor investigates and concludes. | AG8: =IF(OR(B8="",O8="Custom"),"",INDEX('2. Use-Case Library'!$K$5:$K$244,MATCH($O8,'2. Use-Case Library'!$A$5:$A$244,0))) -> ISA 240 / 330; documentation in working papers; client-data confidentiality. | AH8: =IF(AB8="","",IF(AA8="Deprioritise",4,IF(W8="AI later - close data gap first",3,IF(OR(W8="Redesign / standardise first",W8="Stretch - partner or later stage",AA8="Strategic bet",Z8="High",S8=5),2,1)))) -> 2 | AI8: =IF(AC8="","",AH8*100+AC8) -> 215 | AJ8: =IF(B8="","",IF(O8="Custom",B8,INDEX('2. Use-Case Library'!$D$5:$D$244,MATCH($O8,'2. Use-Case Library'!$A$5:$A$244,0)))) -> Audit - journal-entry testing (full population)
A9: 2 | B9: PRO-02 | Audit - working papers & memo drafting | F9: Medium (100 - 1,000 a month) | G9: 400 | H9: Yes - documented and consistent | I9: Digital history available | J9: 4 | K9: 4 | L9: No | M9: Yes | N9: Human approves each AI output | O9: =IF(B9="","",IFERROR(INDEX('2. Use-Case Library'!$A$5:$A$244,MATCH(B9,'2. Use-Case Library'!$M$5:$M$244,0)),"Custom")) -> PRO-02 | P9: =IF(B9="","",IF(O9="Custom",IF(E9="","(select function in E)",E9),INDEX('2. Use-Case Library'!$C$5:$C$244,MATCH($O9,'2. Use-Case Library'!$A$5:$A$244,0)))) -> Core operations & service delivery | Q9: =IF(B9="","",IF(D9<>"",D9,IF(O9="Custom","",INDEX('2. Use-Case Library'!$F$5:$F$244,MATCH($O9,'2. Use-Case Library'!$A$5:$A$244,0))))) -> Draft, summarise, translate or review text | R9: =IF(Q9="","",INDEX(Lists!$B$2:$B$11,MATCH(Q9,Lists!$A$2:$A$11,0))) -> Generative AI assistant (off-the-shelf) | S9: =IF(R9="","",INDEX(Lists!$C$2:$C$11,MATCH(R9,Lists!$B$2:$B$11,0))) -> 3 | T9: =IF(R9="","",INDEX(Lists!$D$2:$D$11,MATCH(R9,Lists!$B$2:$B$11,0))) -> Yes | U9: =IF(OR(R9="",I9=""),"",IF(INDEX(Lists!$N$2:$N$5,MATCH(I9,Lists!$M$2:$M$5,0))>=INDEX(Lists!$E$2:$E$11,MATCH(R9,Lists!$B$2:$B$11,0)),"Data ready","Data gap")) -> Data ready | V9: =IF(R9="","",IF(S9<=IF('1. AI Position'!$C$30="",5,INDEX(Lists!$AI$2:$AI$5,'1. AI Position'!$C$30)),"Within current position","Beyond current position")) -> Within current position | W9: =IF(B9="","",IF(OR(COUNTA(F9:N9)<9,Q9=""),"Complete inputs",IF(H9="No - varies by person / team","Redesign / standardise first",IF(T9="No","Automate - AI not needed",IF(U9="Data gap","AI later - close data gap first",IF(V9="Beyond current position","Stretch - partner or later stage","AI fit now")))))) -> AI fit now | X9: =IF(OR(W9="",W9="Complete inputs"),"",ROUND(0.3*INDEX(Lists!$N$8:$N$10,MATCH(F9,Lists!$M$8:$M$10,0))+0.25*IF(G9<20,1,IF(G9<80,2,IF(G9<160,3,IF(G9<480,4,5))))+0.25*J9+0.2*K9,2)) -> 3.7 | Y9: =IF(X9="","",ROUND(0.3*IF(U9="Data ready",5,IF(INDEX(Lists!$N$2:$N$5,MATCH(I9,Lists!$M$2:$M$5,0))=INDEX(Lists!$E$2:$E$11,MATCH(R9,Lists!$B$2:$B$11,0))-1,3,1))+0.25*INDEX(Lists!$N$13:$N$15,MATCH(H9,Lists!$M$13:$M$15,0))+0.25*(6-S9)+0.2*IF(V9="Within current position",5,2),2)) -> 4.5 | Z9: =IF(X9="","",CHOOSE(MAX(IF(T9="No",IF(L9="Yes",2,1),IF(IF(L9="Yes",2,0)+IF(M9="Yes",1,0)+INDEX(Lists!$N$18:$N$20,MATCH(N9,Lists!$M$18:$M$20,0))+IF(K9=5,2,IF(K9>=4,1,0))>=4,3,IF(IF(L9="Yes",2,0)+IF(M9="Yes",1,0)+INDEX(Lists!$N$18:$N$20,MATCH(N9,Lists!$M$18:$M$20,0))+IF(K9=5,2,IF(K9>=4,1,0))>=2,2,1))),IF($O9="Custom",1,MATCH(INDEX('2. Use-Case Library'!$L$5:$L$244,MATCH($O9,'2. Use-Case Library'!$A$5:$A$244,0)),{"Low","Medium","High"},0))),"Low","Medium","High")) -> Medium | AA9: =IF(X9="","",IF(AND(X9>=$C$4,Y9>=$C$4),"Quick win",IF(X9>=$C$4,"Strategic bet",IF(Y9>=$C$4,"Fill-in","Deprioritise")))) -> Quick win | AB9: =IF(X9="","",ROUND(X9*Y9*IF(Z9="High",0.85,1)*IF(W9="Redesign / standardise first",0.8,1),2)) -> 16.65 | AC9: =IF(AB9="","",RANK(AB9,$AB$8:$AB$57)+COUNTIF($AB$7:AB8,AB9)) -> 4 | AD9: =IF(AH9="","",INDEX(Lists!$AV$2:$AV$5,AH9)) -> H1 - Now (0-6 months) | AE9: =IF(AB9="","",ROUND(G9*12*INDEX(Lists!$F$2:$F$11,MATCH(R9,Lists!$B$2:$B$11,0)),0)) -> 1440 | AF9: =IF(OR(B9="",R9=""),"",IF(O9="Custom",INDEX(Lists!$I$2:$I$11,MATCH(R9,Lists!$B$2:$B$11,0)),INDEX('2. Use-Case Library'!$H$5:$H$244,MATCH($O9,'2. Use-Case Library'!$A$5:$A$244,0)))) -> GenAI drafting within methodology templates in an approved environment; reviewer sign-off. | AG9: =IF(OR(B9="",O9="Custom"),"",INDEX('2. Use-Case Library'!$K$5:$K$244,MATCH($O9,'2. Use-Case Library'!$A$5:$A$244,0))) -> ISQM 1; human review; client confidentiality. | AH9: =IF(AB9="","",IF(AA9="Deprioritise",4,IF(W9="AI later - close data gap first",3,IF(OR(W9="Redesign / standardise first",W9="Stretch - partner or later stage",AA9="Strategic bet",Z9="High",S9=5),2,1)))) -> 1 | AI9: =IF(AC9="","",AH9*100+AC9) -> 104 | AJ9: =IF(B9="","",IF(O9="Custom",B9,INDEX('2. Use-Case Library'!$D$5:$D$244,MATCH($O9,'2. Use-Case Library'!$A$5:$A$244,0)))) -> Audit - working papers & memo drafting
A10: 3 | B10: PRO-03 | Audit - bank & external confirmations | F10: High (more than 1,000 a month) | G10: 120 | H10: Yes - documented and consistent | I10: Digital history available | J10: 3 | K10: 3 | L10: No | M10: Yes | N10: Human approves each AI output | O10: =IF(B10="","",IFERROR(INDEX('2. Use-Case Library'!$A$5:$A$244,MATCH(B10,'2. Use-Case Library'!$M$5:$M$244,0)),"Custom")) -> PRO-03 | P10: =IF(B10="","",IF(O10="Custom",IF(E10="","(select function in E)",E10),INDEX('2. Use-Case Library'!$C$5:$C$244,MATCH($O10,'2. Use-Case Library'!$A$5:$A$244,0)))) -> Core operations & service delivery | Q10: =IF(B10="","",IF(D10<>"",D10,IF(O10="Custom","",INDEX('2. Use-Case Library'!$F$5:$F$244,MATCH($O10,'2. Use-Case Library'!$A$5:$A$244,0))))) -> Extract information from documents, forms or emails | R10: =IF(Q10="","",INDEX(Lists!$B$2:$B$11,MATCH(Q10,Lists!$A$2:$A$11,0))) -> Intelligent document processing (IDP) | S10: =IF(R10="","",INDEX(Lists!$C$2:$C$11,MATCH(R10,Lists!$B$2:$B$11,0))) -> 3 | T10: =IF(R10="","",INDEX(Lists!$D$2:$D$11,MATCH(R10,Lists!$B$2:$B$11,0))) -> Light | U10: =IF(OR(R10="",I10=""),"",IF(INDEX(Lists!$N$2:$N$5,MATCH(I10,Lists!$M$2:$M$5,0))>=INDEX(Lists!$E$2:$E$11,MATCH(R10,Lists!$B$2:$B$11,0)),"Data ready","Data gap")) -> Data ready | V10: =IF(R10="","",IF(S10<=IF('1. AI Position'!$C$30="",5,INDEX(Lists!$AI$2:$AI$5,'1. AI Position'!$C$30)),"Within current position","Beyond current position")) -> Within current position | W10: =IF(B10="","",IF(OR(COUNTA(F10:N10)<9,Q10=""),"Complete inputs",IF(H10="No - varies by person / team","Redesign / standardise first",IF(T10="No","Automate - AI not needed",IF(U10="Data gap","AI later - close data gap first",IF(V10="Beyond current position","Stretch - partner or later stage","AI fit now")))))) -> AI fit now | X10: =IF(OR(W10="",W10="Complete inputs"),"",ROUND(0.3*INDEX(Lists!$N$8:$N$10,MATCH(F10,Lists!$M$8:$M$10,0))+0.25*IF(G10<20,1,IF(G10<80,2,IF(G10<160,3,IF(G10<480,4,5))))+0.25*J10+0.2*K10,2)) -> 3.6 | Y10: =IF(X10="","",ROUND(0.3*IF(U10="Data ready",5,IF(INDEX(Lists!$N$2:$N$5,MATCH(I10,Lists!$M$2:$M$5,0))=INDEX(Lists!$E$2:$E$11,MATCH(R10,Lists!$B$2:$B$11,0))-1,3,1))+0.25*INDEX(Lists!$N$13:$N$15,MATCH(H10,Lists!$M$13:$M$15,0))+0.25*(6-S10)+0.2*IF(V10="Within current position",5,2),2)) -> 4.5 | Z10: =IF(X10="","",CHOOSE(MAX(IF(T10="No",IF(L10="Yes",2,1),IF(IF(L10="Yes",2,0)+IF(M10="Yes",1,0)+INDEX(Lists!$N$18:$N$20,MATCH(N10,Lists!$M$18:$M$20,0))+IF(K10=5,2,IF(K10>=4,1,0))>=4,3,IF(IF(L10="Yes",2,0)+IF(M10="Yes",1,0)+INDEX(Lists!$N$18:$N$20,MATCH(N10,Lists!$M$18:$M$20,0))+IF(K10=5,2,IF(K10>=4,1,0))>=2,2,1))),IF($O10="Custom",1,MATCH(INDEX('2. Use-Case Library'!$L$5:$L$244,MATCH($O10,'2. Use-Case Library'!$A$5:$A$244,0)),{"Low","Medium","High"},0))),"Low","Medium","High")) -> Medium | AA10: =IF(X10="","",IF(AND(X10>=$C$4,Y10>=$C$4),"Quick win",IF(X10>=$C$4,"Strategic bet",IF(Y10>=$C$4,"Fill-in","Deprioritise")))) -> Quick win | AB10: =IF(X10="","",ROUND(X10*Y10*IF(Z10="High",0.85,1)*IF(W10="Redesign / standardise first",0.8,1),2)) -> 16.2 | AC10: =IF(AB10="","",RANK(AB10,$AB$8:$AB$57)+COUNTIF($AB$7:AB9,AB10)) -> 6 | AD10: =IF(AH10="","",INDEX(Lists!$AV$2:$AV$5,AH10)) -> H1 - Now (0-6 months) | AE10: =IF(AB10="","",ROUND(G10*12*INDEX(Lists!$F$2:$F$11,MATCH(R10,Lists!$B$2:$B$11,0)),0)) -> 720 | AF10: =IF(OR(B10="",R10=""),"",IF(O10="Custom",INDEX(Lists!$I$2:$I$11,MATCH(R10,Lists!$B$2:$B$11,0)),INDEX('2. Use-Case Library'!$H$5:$H$244,MATCH($O10,'2. Use-Case Library'!$A$5:$A$244,0)))) -> IDP of confirmation responses with automatic agreement to records. | AG10: =IF(OR(B10="",O10="Custom"),"",INDEX('2. Use-Case Library'!$K$5:$K$244,MATCH($O10,'2. Use-Case Library'!$A$5:$A$244,0))) -> ISA 505 evidence requirements. | AH10: =IF(AB10="","",IF(AA10="Deprioritise",4,IF(W10="AI later - close data gap first",3,IF(OR(W10="Redesign / standardise first",W10="Stretch - partner or later stage",AA10="Strategic bet",Z10="High",S10=5),2,1)))) -> 1 | AI10: =IF(AC10="","",AH10*100+AC10) -> 106 | AJ10: =IF(B10="","",IF(O10="Custom",B10,INDEX('2. Use-Case Library'!$D$5:$D$244,MATCH($O10,'2. Use-Case Library'!$A$5:$A$244,0)))) -> Audit - bank & external confirmations
A11: 4 | B11: PRO-04 | Tax research & technical Q&A | F11: Medium (100 - 1,000 a month) | G11: 160 | H11: Partly - common steps, some variation | I11: Digital history available | J11: 4 | K11: 4 | L11: No | M11: No | N11: Assist - AI suggests, a person does the work | O11: =IF(B11="","",IFERROR(INDEX('2. Use-Case Library'!$A$5:$A$244,MATCH(B11,'2. Use-Case Library'!$M$5:$M$244,0)),"Custom")) -> PRO-04 | P11: =IF(B11="","",IF(O11="Custom",IF(E11="","(select function in E)",E11),INDEX('2. Use-Case Library'!$C$5:$C$244,MATCH($O11,'2. Use-Case Library'!$A$5:$A$244,0)))) -> Core operations & service delivery | Q11: =IF(B11="","",IF(D11<>"",D11,IF(O11="Custom","",INDEX('2. Use-Case Library'!$F$5:$F$244,MATCH($O11,'2. Use-Case Library'!$A$5:$A$244,0))))) -> Answer questions from internal knowledge, policies or past work | R11: =IF(Q11="","",INDEX(Lists!$B$2:$B$11,MATCH(Q11,Lists!$A$2:$A$11,0))) -> GenAI knowledge assistant (RAG on own content) | S11: =IF(R11="","",INDEX(Lists!$C$2:$C$11,MATCH(R11,Lists!$B$2:$B$11,0))) -> 4 | T11: =IF(R11="","",INDEX(Lists!$D$2:$D$11,MATCH(R11,Lists!$B$2:$B$11,0))) -> Yes | U11: =IF(OR(R11="",I11=""),"",IF(INDEX(Lists!$N$2:$N$5,MATCH(I11,Lists!$M$2:$M$5,0))>=INDEX(Lists!$E$2:$E$11,MATCH(R11,Lists!$B$2:$B$11,0)),"Data ready","Data gap")) -> Data ready | V11: =IF(R11="","",IF(S11<=IF('1. AI Position'!$C$30="",5,INDEX(Lists!$AI$2:$AI$5,'1. AI Position'!$C$30)),"Within current position","Beyond current position")) -> Within current position | W11: =IF(B11="","",IF(OR(COUNTA(F11:N11)<9,Q11=""),"Complete inputs",IF(H11="No - varies by person / team","Redesign / standardise first",IF(T11="No","Automate - AI not needed",IF(U11="Data gap","AI later - close data gap first",IF(V11="Beyond current position","Stretch - partner or later stage","AI fit now")))))) -> AI fit now | X11: =IF(OR(W11="",W11="Complete inputs"),"",ROUND(0.3*INDEX(Lists!$N$8:$N$10,MATCH(F11,Lists!$M$8:$M$10,0))+0.25*IF(G11<20,1,IF(G11<80,2,IF(G11<160,3,IF(G11<480,4,5))))+0.25*J11+0.2*K11,2)) -> 3.7 | Y11: =IF(X11="","",ROUND(0.3*IF(U11="Data ready",5,IF(INDEX(Lists!$N$2:$N$5,MATCH(I11,Lists!$M$2:$M$5,0))=INDEX(Lists!$E$2:$E$11,MATCH(R11,Lists!$B$2:$B$11,0))-1,3,1))+0.25*INDEX(Lists!$N$13:$N$15,MATCH(H11,Lists!$M$13:$M$15,0))+0.25*(6-S11)+0.2*IF(V11="Within current position",5,2),2)) -> 3.75 | Z11: =IF(X11="","",CHOOSE(MAX(IF(T11="No",IF(L11="Yes",2,1),IF(IF(L11="Yes",2,0)+IF(M11="Yes",1,0)+INDEX(Lists!$N$18:$N$20,MATCH(N11,Lists!$M$18:$M$20,0))+IF(K11=5,2,IF(K11>=4,1,0))>=4,3,IF(IF(L11="Yes",2,0)+IF(M11="Yes",1,0)+INDEX(Lists!$N$18:$N$20,MATCH(N11,Lists!$M$18:$M$20,0))+IF(K11=5,2,IF(K11>=4,1,0))>=2,2,1))),IF($O11="Custom",1,MATCH(INDEX('2. Use-Case Library'!$L$5:$L$244,MATCH($O11,'2. Use-Case Library'!$A$5:$A$244,0)),{"Low","Medium","High"},0))),"Low","Medium","High")) -> Low | AA11: =IF(X11="","",IF(AND(X11>=$C$4,Y11>=$C$4),"Quick win",IF(X11>=$C$4,"Strategic bet",IF(Y11>=$C$4,"Fill-in","Deprioritise")))) -> Quick win | AB11: =IF(X11="","",ROUND(X11*Y11*IF(Z11="High",0.85,1)*IF(W11="Redesign / standardise first",0.8,1),2)) -> 13.88 | AC11: =IF(AB11="","",RANK(AB11,$AB$8:$AB$57)+COUNTIF($AB$7:AB10,AB11)) -> 9 | AD11: =IF(AH11="","",INDEX(Lists!$AV$2:$AV$5,AH11)) -> H1 - Now (0-6 months) | AE11: =IF(AB11="","",ROUND(G11*12*INDEX(Lists!$F$2:$F$11,MATCH(R11,Lists!$B$2:$B$11,0)),0)) -> 480 | AF11: =IF(OR(B11="",R11=""),"",IF(O11="Custom",INDEX(Lists!$I$2:$I$11,MATCH(R11,Lists!$B$2:$B$11,0)),INDEX('2. Use-Case Library'!$H$5:$H$244,MATCH($O11,'2. Use-Case Library'!$A$5:$A$244,0)))) -> Grounded tax assistant over Bahrain / GCC tax law, NBR guidance and approved internal positions with citations. | AG11: =IF(OR(B11="",O11="Custom"),"",INDEX('2. Use-Case Library'!$K$5:$K$244,MATCH($O11,'2. Use-Case Library'!$A$5:$A$244,0))) -> Partner review of advice; verify citations. | AH11: =IF(AB11="","",IF(AA11="Deprioritise",4,IF(W11="AI later - close data gap first",3,IF(OR(W11="Redesign / standardise first",W11="Stretch - partner or later stage",AA11="Strategic bet",Z11="High",S11=5),2,1)))) -> 1 | AI11: =IF(AC11="","",AH11*100+AC11) -> 109 | AJ11: =IF(B11="","",IF(O11="Custom",B11,INDEX('2. Use-Case Library'!$D$5:$D$244,MATCH($O11,'2. Use-Case Library'!$A$5:$A$244,0)))) -> Tax research & technical Q&A
A12: 5 | B12: PRO-05 | Tax - VAT / tax return data preparation | F12: High (more than 1,000 a month) | G12: 200 | H12: Yes - documented and consistent | I12: Digital history available | J12: 3 | K12: 4 | L12: No | M12: Yes | N12: Human approves each AI output | O12: =IF(B12="","",IFERROR(INDEX('2. Use-Case Library'!$A$5:$A$244,MATCH(B12,'2. Use-Case Library'!$M$5:$M$244,0)),"Custom")) -> PRO-05 | P12: =IF(B12="","",IF(O12="Custom",IF(E12="","(select function in E)",E12),INDEX('2. Use-Case Library'!$C$5:$C$244,MATCH($O12,'2. Use-Case Library'!$A$5:$A$244,0)))) -> Core operations & service delivery | Q12: =IF(B12="","",IF(D12<>"",D12,IF(O12="Custom","",INDEX('2. Use-Case Library'!$F$5:$F$244,MATCH($O12,'2. Use-Case Library'!$A$5:$A$244,0))))) -> Move or re-key data between systems following fixed rules | R12: =IF(Q12="","",INDEX(Lists!$B$2:$B$11,MATCH(Q12,Lists!$A$2:$A$11,0))) -> Workflow automation / RPA | S12: =IF(R12="","",INDEX(Lists!$C$2:$C$11,MATCH(R12,Lists!$B$2:$B$11,0))) -> 2 | T12: =IF(R12="","",INDEX(Lists!$D$2:$D$11,MATCH(R12,Lists!$B$2:$B$11,0))) -> No | U12: =IF(OR(R12="",I12=""),"",IF(INDEX(Lists!$N$2:$N$5,MATCH(I12,Lists!$M$2:$M$5,0))>=INDEX(Lists!$E$2:$E$11,MATCH(R12,Lists!$B$2:$B$11,0)),"Data ready","Data gap")) -> Data ready | V12: =IF(R12="","",IF(S12<=IF('1. AI Position'!$C$30="",5,INDEX(Lists!$AI$2:$AI$5,'1. AI Position'!$C$30)),"Within current position","Beyond current position")) -> Within current position | W12: =IF(B12="","",IF(OR(COUNTA(F12:N12)<9,Q12=""),"Complete inputs",IF(H12="No - varies by person / team","Redesign / standardise first",IF(T12="No","Automate - AI not needed",IF(U12="Data gap","AI later - close data gap first",IF(V12="Beyond current position","Stretch - partner or later stage","AI fit now")))))) -> Automate - AI not needed | X12: =IF(OR(W12="",W12="Complete inputs"),"",ROUND(0.3*INDEX(Lists!$N$8:$N$10,MATCH(F12,Lists!$M$8:$M$10,0))+0.25*IF(G12<20,1,IF(G12<80,2,IF(G12<160,3,IF(G12<480,4,5))))+0.25*J12+0.2*K12,2)) -> 4.05 | Y12: =IF(X12="","",ROUND(0.3*IF(U12="Data ready",5,IF(INDEX(Lists!$N$2:$N$5,MATCH(I12,Lists!$M$2:$M$5,0))=INDEX(Lists!$E$2:$E$11,MATCH(R12,Lists!$B$2:$B$11,0))-1,3,1))+0.25*INDEX(Lists!$N$13:$N$15,MATCH(H12,Lists!$M$13:$M$15,0))+0.25*(6-S12)+0.2*IF(V12="Within current position",5,2),2)) -> 4.75 | Z12: =IF(X12="","",CHOOSE(MAX(IF(T12="No",IF(L12="Yes",2,1),IF(IF(L12="Yes",2,0)+IF(M12="Yes",1,0)+INDEX(Lists!$N$18:$N$20,MATCH(N12,Lists!$M$18:$M$20,0))+IF(K12=5,2,IF(K12>=4,1,0))>=4,3,IF(IF(L12="Yes",2,0)+IF(M12="Yes",1,0)+INDEX(Lists!$N$18:$N$20,MATCH(N12,Lists!$M$18:$M$20,0))+IF(K12=5,2,IF(K12>=4,1,0))>=2,2,1))),IF($O12="Custom",1,MATCH(INDEX('2. Use-Case Library'!$L$5:$L$244,MATCH($O12,'2. Use-Case Library'!$A$5:$A$244,0)),{"Low","Medium","High"},0))),"Low","Medium","High")) -> Low | AA12: =IF(X12="","",IF(AND(X12>=$C$4,Y12>=$C$4),"Quick win",IF(X12>=$C$4,"Strategic bet",IF(Y12>=$C$4,"Fill-in","Deprioritise")))) -> Quick win | AB12: =IF(X12="","",ROUND(X12*Y12*IF(Z12="High",0.85,1)*IF(W12="Redesign / standardise first",0.8,1),2)) -> 19.24 | AC12: =IF(AB12="","",RANK(AB12,$AB$8:$AB$57)+COUNTIF($AB$7:AB11,AB12)) -> 1 | AD12: =IF(AH12="","",INDEX(Lists!$AV$2:$AV$5,AH12)) -> H1 - Now (0-6 months) | AE12: =IF(AB12="","",ROUND(G12*12*INDEX(Lists!$F$2:$F$11,MATCH(R12,Lists!$B$2:$B$11,0)),0)) -> 1440 | AF12: =IF(OR(B12="",R12=""),"",IF(O12="Custom",INDEX(Lists!$I$2:$I$11,MATCH(R12,Lists!$B$2:$B$11,0)),INDEX('2. Use-Case Library'!$H$5:$H$244,MATCH($O12,'2. Use-Case Library'!$A$5:$A$244,0)))) -> Automated extraction, mapping and validation of client data into returns. | AG12: =IF(OR(B12="",O12="Custom"),"",INDEX('2. Use-Case Library'!$K$5:$K$244,MATCH($O12,'2. Use-Case Library'!$A$5:$A$244,0))) -> Maker-checker; client sign-off. | AH12: =IF(AB12="","",IF(AA12="Deprioritise",4,IF(W12="AI later - close data gap first",3,IF(OR(W12="Redesign / standardise first",W12="Stretch - partner or later stage",AA12="Strategic bet",Z12="High",S12=5),2,1)))) -> 1 | AI12: =IF(AC12="","",AH12*100+AC12) -> 101 | AJ12: =IF(B12="","",IF(O12="Custom",B12,INDEX('2. Use-Case Library'!$D$5:$D$244,MATCH($O12,'2. Use-Case Library'!$A$5:$A$244,0)))) -> Tax - VAT / tax return data preparation
A13: 6 | B13: PRO-06 | Predictive tax scenario modelling | F13: Low (fewer than 100 a month) | G13: 80 | H13: Partly - common steps, some variation | I13: Digital history available | J13: 4 | K13: 4 | L13: No | M13: Yes | N13: Assist - AI suggests, a person does the work | O13: =IF(B13="","",IFERROR(INDEX('2. Use-Case Library'!$A$5:$A$244,MATCH(B13,'2. Use-Case Library'!$M$5:$M$244,0)),"Custom")) -> PRO-06 | P13: =IF(B13="","",IF(O13="Custom",IF(E13="","(select function in E)",E13),INDEX('2. Use-Case Library'!$C$5:$C$244,MATCH($O13,'2. Use-Case Library'!$A$5:$A$244,0)))) -> Core operations & service delivery | Q13: =IF(B13="","",IF(D13<>"",D13,IF(O13="Custom","",INDEX('2. Use-Case Library'!$F$5:$F$244,MATCH($O13,'2. Use-Case Library'!$A$5:$A$244,0))))) -> Forecast, score, classify or detect anomalies from historical data | R13: =IF(Q13="","",INDEX(Lists!$B$2:$B$11,MATCH(Q13,Lists!$A$2:$A$11,0))) -> Predictive analytics / machine learning | S13: =IF(R13="","",INDEX(Lists!$C$2:$C$11,MATCH(R13,Lists!$B$2:$B$11,0))) -> 5 | T13: =IF(R13="","",INDEX(Lists!$D$2:$D$11,MATCH(R13,Lists!$B$2:$B$11,0))) -> Yes | U13: =IF(OR(R13="",I13=""),"",IF(INDEX(Lists!$N$2:$N$5,MATCH(I13,Lists!$M$2:$M$5,0))>=INDEX(Lists!$E$2:$E$11,MATCH(R13,Lists!$B$2:$B$11,0)),"Data ready","Data gap")) -> Data ready | V13: =IF(R13="","",IF(S13<=IF('1. AI Position'!$C$30="",5,INDEX(Lists!$AI$2:$AI$5,'1. AI Position'!$C$30)),"Within current position","Beyond current position")) -> Beyond current position | W13: =IF(B13="","",IF(OR(COUNTA(F13:N13)<9,Q13=""),"Complete inputs",IF(H13="No - varies by person / team","Redesign / standardise first",IF(T13="No","Automate - AI not needed",IF(U13="Data gap","AI later - close data gap first",IF(V13="Beyond current position","Stretch - partner or later stage","AI fit now")))))) -> Stretch - partner or later stage | X13: =IF(OR(W13="",W13="Complete inputs"),"",ROUND(0.3*INDEX(Lists!$N$8:$N$10,MATCH(F13,Lists!$M$8:$M$10,0))+0.25*IF(G13<20,1,IF(G13<80,2,IF(G13<160,3,IF(G13<480,4,5))))+0.25*J13+0.2*K13,2)) -> 2.85 | Y13: =IF(X13="","",ROUND(0.3*IF(U13="Data ready",5,IF(INDEX(Lists!$N$2:$N$5,MATCH(I13,Lists!$M$2:$M$5,0))=INDEX(Lists!$E$2:$E$11,MATCH(R13,Lists!$B$2:$B$11,0))-1,3,1))+0.25*INDEX(Lists!$N$13:$N$15,MATCH(H13,Lists!$M$13:$M$15,0))+0.25*(6-S13)+0.2*IF(V13="Within current position",5,2),2)) -> 2.9 | Z13: =IF(X13="","",CHOOSE(MAX(IF(T13="No",IF(L13="Yes",2,1),IF(IF(L13="Yes",2,0)+IF(M13="Yes",1,0)+INDEX(Lists!$N$18:$N$20,MATCH(N13,Lists!$M$18:$M$20,0))+IF(K13=5,2,IF(K13>=4,1,0))>=4,3,IF(IF(L13="Yes",2,0)+IF(M13="Yes",1,0)+INDEX(Lists!$N$18:$N$20,MATCH(N13,Lists!$M$18:$M$20,0))+IF(K13=5,2,IF(K13>=4,1,0))>=2,2,1))),IF($O13="Custom",1,MATCH(INDEX('2. Use-Case Library'!$L$5:$L$244,MATCH($O13,'2. Use-Case Library'!$A$5:$A$244,0)),{"Low","Medium","High"},0))),"Low","Medium","High")) -> Medium | AA13: =IF(X13="","",IF(AND(X13>=$C$4,Y13>=$C$4),"Quick win",IF(X13>=$C$4,"Strategic bet",IF(Y13>=$C$4,"Fill-in","Deprioritise")))) -> Deprioritise | AB13: =IF(X13="","",ROUND(X13*Y13*IF(Z13="High",0.85,1)*IF(W13="Redesign / standardise first",0.8,1),2)) -> 8.27 | AC13: =IF(AB13="","",RANK(AB13,$AB$8:$AB$57)+COUNTIF($AB$7:AB12,AB13)) -> 20 | AD13: =IF(AH13="","",INDEX(Lists!$AV$2:$AV$5,AH13)) -> Backlog / not prioritised | AE13: =IF(AB13="","",ROUND(G13*12*INDEX(Lists!$F$2:$F$11,MATCH(R13,Lists!$B$2:$B$11,0)),0)) -> 192 | AF13: =IF(OR(B13="",R13=""),"",IF(O13="Custom",INDEX(Lists!$I$2:$I$11,MATCH(R13,Lists!$B$2:$B$11,0)),INDEX('2. Use-Case Library'!$H$5:$H$244,MATCH($O13,'2. Use-Case Library'!$A$5:$A$244,0)))) -> Scenario models of tax outcomes for planning decisions (e.g., Pillar Two, CIT). | AG13: =IF(OR(B13="",O13="Custom"),"",INDEX('2. Use-Case Library'!$K$5:$K$244,MATCH($O13,'2. Use-Case Library'!$A$5:$A$244,0))) -> Assumptions documented; partner review. | AH13: =IF(AB13="","",IF(AA13="Deprioritise",4,IF(W13="AI later - close data gap first",3,IF(OR(W13="Redesign / standardise first",W13="Stretch - partner or later stage",AA13="Strategic bet",Z13="High",S13=5),2,1)))) -> 4 | AI13: =IF(AC13="","",AH13*100+AC13) -> 420 | AJ13: =IF(B13="","",IF(O13="Custom",B13,INDEX('2. Use-Case Library'!$D$5:$D$244,MATCH($O13,'2. Use-Case Library'!$A$5:$A$244,0)))) -> Predictive tax scenario modelling
A14: 7 | B14: XI-26 | Proposal, quotation & tender responses | F14: Medium (100 - 1,000 a month) | G14: 350 | H14: Partly - common steps, some variation | I14: Digital history available | J14: 4 | K14: 4 | L14: No | M14: No | N14: Assist - AI suggests, a person does the work | O14: =IF(B14="","",IFERROR(INDEX('2. Use-Case Library'!$A$5:$A$244,MATCH(B14,'2. Use-Case Library'!$M$5:$M$244,0)),"Custom")) -> XI-26 | P14: =IF(B14="","",IF(O14="Custom",IF(E14="","(select function in E)",E14),INDEX('2. Use-Case Library'!$C$5:$C$244,MATCH($O14,'2. Use-Case Library'!$A$5:$A$244,0)))) -> Sales & marketing | Q14: =IF(B14="","",IF(D14<>"",D14,IF(O14="Custom","",INDEX('2. Use-Case Library'!$F$5:$F$244,MATCH($O14,'2. Use-Case Library'!$A$5:$A$244,0))))) -> Answer questions from internal knowledge, policies or past work | R14: =IF(Q14="","",INDEX(Lists!$B$2:$B$11,MATCH(Q14,Lists!$A$2:$A$11,0))) -> GenAI knowledge assistant (RAG on own content) | S14: =IF(R14="","",INDEX(Lists!$C$2:$C$11,MATCH(R14,Lists!$B$2:$B$11,0))) -> 4 | T14: =IF(R14="","",INDEX(Lists!$D$2:$D$11,MATCH(R14,Lists!$B$2:$B$11,0))) -> Yes | U14: =IF(OR(R14="",I14=""),"",IF(INDEX(Lists!$N$2:$N$5,MATCH(I14,Lists!$M$2:$M$5,0))>=INDEX(Lists!$E$2:$E$11,MATCH(R14,Lists!$B$2:$B$11,0)),"Data ready","Data gap")) -> Data ready | V14: =IF(R14="","",IF(S14<=IF('1. AI Position'!$C$30="",5,INDEX(Lists!$AI$2:$AI$5,'1. AI Position'!$C$30)),"Within current position","Beyond current position")) -> Within current position | W14: =IF(B14="","",IF(OR(COUNTA(F14:N14)<9,Q14=""),"Complete inputs",IF(H14="No - varies by person / team","Redesign / standardise first",IF(T14="No","Automate - AI not needed",IF(U14="Data gap","AI later - close data gap first",IF(V14="Beyond current position","Stretch - partner or later stage","AI fit now")))))) -> AI fit now | X14: =IF(OR(W14="",W14="Complete inputs"),"",ROUND(0.3*INDEX(Lists!$N$8:$N$10,MATCH(F14,Lists!$M$8:$M$10,0))+0.25*IF(G14<20,1,IF(G14<80,2,IF(G14<160,3,IF(G14<480,4,5))))+0.25*J14+0.2*K14,2)) -> 3.7 | Y14: =IF(X14="","",ROUND(0.3*IF(U14="Data ready",5,IF(INDEX(Lists!$N$2:$N$5,MATCH(I14,Lists!$M$2:$M$5,0))=INDEX(Lists!$E$2:$E$11,MATCH(R14,Lists!$B$2:$B$11,0))-1,3,1))+0.25*INDEX(Lists!$N$13:$N$15,MATCH(H14,Lists!$M$13:$M$15,0))+0.25*(6-S14)+0.2*IF(V14="Within current position",5,2),2)) -> 3.75 | Z14: =IF(X14="","",CHOOSE(MAX(IF(T14="No",IF(L14="Yes",2,1),IF(IF(L14="Yes",2,0)+IF(M14="Yes",1,0)+INDEX(Lists!$N$18:$N$20,MATCH(N14,Lists!$M$18:$M$20,0))+IF(K14=5,2,IF(K14>=4,1,0))>=4,3,IF(IF(L14="Yes",2,0)+IF(M14="Yes",1,0)+INDEX(Lists!$N$18:$N$20,MATCH(N14,Lists!$M$18:$M$20,0))+IF(K14=5,2,IF(K14>=4,1,0))>=2,2,1))),IF($O14="Custom",1,MATCH(INDEX('2. Use-Case Library'!$L$5:$L$244,MATCH($O14,'2. Use-Case Library'!$A$5:$A$244,0)),{"Low","Medium","High"},0))),"Low","Medium","High")) -> Low | AA14: =IF(X14="","",IF(AND(X14>=$C$4,Y14>=$C$4),"Quick win",IF(X14>=$C$4,"Strategic bet",IF(Y14>=$C$4,"Fill-in","Deprioritise")))) -> Quick win | AB14: =IF(X14="","",ROUND(X14*Y14*IF(Z14="High",0.85,1)*IF(W14="Redesign / standardise first",0.8,1),2)) -> 13.88 | AC14: =IF(AB14="","",RANK(AB14,$AB$8:$AB$57)+COUNTIF($AB$7:AB13,AB14)) -> 10 | AD14: =IF(AH14="","",INDEX(Lists!$AV$2:$AV$5,AH14)) -> H1 - Now (0-6 months) | AE14: =IF(AB14="","",ROUND(G14*12*INDEX(Lists!$F$2:$F$11,MATCH(R14,Lists!$B$2:$B$11,0)),0)) -> 1050 | AF14: =IF(OR(B14="",R14=""),"",IF(O14="Custom",INDEX(Lists!$I$2:$I$11,MATCH(R14,Lists!$B$2:$B$11,0)),INDEX('2. Use-Case Library'!$H$5:$H$244,MATCH($O14,'2. Use-Case Library'!$A$5:$A$244,0)))) -> Knowledge assistant over approved credentials, CVs and past proposals to draft responses; bid manager review. | AG14: =IF(OR(B14="",O14="Custom"),"",INDEX('2. Use-Case Library'!$K$5:$K$244,MATCH($O14,'2. Use-Case Library'!$A$5:$A$244,0))) -> Client confidentiality - sanitise past work; human review. | AH14: =IF(AB14="","",IF(AA14="Deprioritise",4,IF(W14="AI later - close data gap first",3,IF(OR(W14="Redesign / standardise first",W14="Stretch - partner or later stage",AA14="Strategic bet",Z14="High",S14=5),2,1)))) -> 1 | AI14: =IF(AC14="","",AH14*100+AC14) -> 110 | AJ14: =IF(B14="","",IF(O14="Custom",B14,INDEX('2. Use-Case Library'!$D$5:$D$244,MATCH($O14,'2. Use-Case Library'!$A$5:$A$244,0)))) -> Proposal, quotation & tender responses
A15: 8 | B15: PRO-07 | Advisory - due-diligence data-room review | F15: Medium (100 - 1,000 a month) | G15: 220 | H15: Partly - common steps, some variation | I15: Digital history available | J15: 4 | K15: 4 | L15: No | M15: Yes | N15: Human approves each AI output | O15: =IF(B15="","",IFERROR(INDEX('2. Use-Case Library'!$A$5:$A$244,MATCH(B15,'2. Use-Case Library'!$M$5:$M$244,0)),"Custom")) -> PRO-07 | P15: =IF(B15="","",IF(O15="Custom",IF(E15="","(select function in E)",E15),INDEX('2. Use-Case Library'!$C$5:$C$244,MATCH($O15,'2. Use-Case Library'!$A$5:$A$244,0)))) -> Core operations & service delivery | Q15: =IF(B15="","",IF(D15<>"",D15,IF(O15="Custom","",INDEX('2. Use-Case Library'!$F$5:$F$244,MATCH($O15,'2. Use-Case Library'!$A$5:$A$244,0))))) -> Draft, summarise, translate or review text | R15: =IF(Q15="","",INDEX(Lists!$B$2:$B$11,MATCH(Q15,Lists!$A$2:$A$11,0))) -> Generative AI assistant (off-the-shelf) | S15: =IF(R15="","",INDEX(Lists!$C$2:$C$11,MATCH(R15,Lists!$B$2:$B$11,0))) -> 3 | T15: =IF(R15="","",INDEX(Lists!$D$2:$D$11,MATCH(R15,Lists!$B$2:$B$11,0))) -> Yes | U15: =IF(OR(R15="",I15=""),"",IF(INDEX(Lists!$N$2:$N$5,MATCH(I15,Lists!$M$2:$M$5,0))>=INDEX(Lists!$E$2:$E$11,MATCH(R15,Lists!$B$2:$B$11,0)),"Data ready","Data gap")) -> Data ready | V15: =IF(R15="","",IF(S15<=IF('1. AI Position'!$C$30="",5,INDEX(Lists!$AI$2:$AI$5,'1. AI Position'!$C$30)),"Within current position","Beyond current position")) -> Within current position | W15: =IF(B15="","",IF(OR(COUNTA(F15:N15)<9,Q15=""),"Complete inputs",IF(H15="No - varies by person / team","Redesign / standardise first",IF(T15="No","Automate - AI not needed",IF(U15="Data gap","AI later - close data gap first",IF(V15="Beyond current position","Stretch - partner or later stage","AI fit now")))))) -> AI fit now | X15: =IF(OR(W15="",W15="Complete inputs"),"",ROUND(0.3*INDEX(Lists!$N$8:$N$10,MATCH(F15,Lists!$M$8:$M$10,0))+0.25*IF(G15<20,1,IF(G15<80,2,IF(G15<160,3,IF(G15<480,4,5))))+0.25*J15+0.2*K15,2)) -> 3.7 | Y15: =IF(X15="","",ROUND(0.3*IF(U15="Data ready",5,IF(INDEX(Lists!$N$2:$N$5,MATCH(I15,Lists!$M$2:$M$5,0))=INDEX(Lists!$E$2:$E$11,MATCH(R15,Lists!$B$2:$B$11,0))-1,3,1))+0.25*INDEX(Lists!$N$13:$N$15,MATCH(H15,Lists!$M$13:$M$15,0))+0.25*(6-S15)+0.2*IF(V15="Within current position",5,2),2)) -> 4 | Z15: =IF(X15="","",CHOOSE(MAX(IF(T15="No",IF(L15="Yes",2,1),IF(IF(L15="Yes",2,0)+IF(M15="Yes",1,0)+INDEX(Lists!$N$18:$N$20,MATCH(N15,Lists!$M$18:$M$20,0))+IF(K15=5,2,IF(K15>=4,1,0))>=4,3,IF(IF(L15="Yes",2,0)+IF(M15="Yes",1,0)+INDEX(Lists!$N$18:$N$20,MATCH(N15,Lists!$M$18:$M$20,0))+IF(K15=5,2,IF(K15>=4,1,0))>=2,2,1))),IF($O15="Custom",1,MATCH(INDEX('2. Use-Case Library'!$L$5:$L$244,MATCH($O15,'2. Use-Case Library'!$A$5:$A$244,0)),{"Low","Medium","High"},0))),"Low","Medium","High")) -> Medium | AA15: =IF(X15="","",IF(AND(X15>=$C$4,Y15>=$C$4),"Quick win",IF(X15>=$C$4,"Strategic bet",IF(Y15>=$C$4,"Fill-in","Deprioritise")))) -> Quick win | AB15: =IF(X15="","",ROUND(X15*Y15*IF(Z15="High",0.85,1)*IF(W15="Redesign / standardise first",0.8,1),2)) -> 14.8 | AC15: =IF(AB15="","",RANK(AB15,$AB$8:$AB$57)+COUNTIF($AB$7:AB14,AB15)) -> 8 | AD15: =IF(AH15="","",INDEX(Lists!$AV$2:$AV$5,AH15)) -> H1 - Now (0-6 months) | AE15: =IF(AB15="","",ROUND(G15*12*INDEX(Lists!$F$2:$F$11,MATCH(R15,Lists!$B$2:$B$11,0)),0)) -> 792 | AF15: =IF(OR(B15="",R15=""),"",IF(O15="Custom",INDEX(Lists!$I$2:$I$11,MATCH(R15,Lists!$B$2:$B$11,0)),INDEX('2. Use-Case Library'!$H$5:$H$244,MATCH($O15,'2. Use-Case Library'!$A$5:$A$244,0)))) -> GenAI review of data-room documents against DD checklists with red-flag summaries. | AG15: =IF(OR(B15="",O15="Custom"),"",INDEX('2. Use-Case Library'!$K$5:$K$244,MATCH($O15,'2. Use-Case Library'!$A$5:$A$244,0))) -> Confidentiality; NDA terms; verify findings. | AH15: =IF(AB15="","",IF(AA15="Deprioritise",4,IF(W15="AI later - close data gap first",3,IF(OR(W15="Redesign / standardise first",W15="Stretch - partner or later stage",AA15="Strategic bet",Z15="High",S15=5),2,1)))) -> 1 | AI15: =IF(AC15="","",AH15*100+AC15) -> 108 | AJ15: =IF(B15="","",IF(O15="Custom",B15,INDEX('2. Use-Case Library'!$D$5:$D$244,MATCH($O15,'2. Use-Case Library'!$A$5:$A$244,0)))) -> Advisory - due-diligence data-room review
A16: 9 | B16: XI-54 | Meeting minutes & action tracking | F16: High (more than 1,000 a month) | G16: 250 | H16: Yes - documented and consistent | I16: Partial or paper-based | J16: 3 | K16: 3 | L16: No | M16: No | N16: Assist - AI suggests, a person does the work | O16: =IF(B16="","",IFERROR(INDEX('2. Use-Case Library'!$A$5:$A$244,MATCH(B16,'2. Use-Case Library'!$M$5:$M$244,0)),"Custom")) -> XI-54 | P16: =IF(B16="","",IF(O16="Custom",IF(E16="","(select function in E)",E16),INDEX('2. Use-Case Library'!$C$5:$C$244,MATCH($O16,'2. Use-Case Library'!$A$5:$A$244,0)))) -> Strategy, management & reporting | Q16: =IF(B16="","",IF(D16<>"",D16,IF(O16="Custom","",INDEX('2. Use-Case Library'!$F$5:$F$244,MATCH($O16,'2. Use-Case Library'!$A$5:$A$244,0))))) -> Draft, summarise, translate or review text | R16: =IF(Q16="","",INDEX(Lists!$B$2:$B$11,MATCH(Q16,Lists!$A$2:$A$11,0))) -> Generative AI assistant (off-the-shelf) | S16: =IF(R16="","",INDEX(Lists!$C$2:$C$11,MATCH(R16,Lists!$B$2:$B$11,0))) -> 3 | T16: =IF(R16="","",INDEX(Lists!$D$2:$D$11,MATCH(R16,Lists!$B$2:$B$11,0))) -> Yes | U16: =IF(OR(R16="",I16=""),"",IF(INDEX(Lists!$N$2:$N$5,MATCH(I16,Lists!$M$2:$M$5,0))>=INDEX(Lists!$E$2:$E$11,MATCH(R16,Lists!$B$2:$B$11,0)),"Data ready","Data gap")) -> Data ready | V16: =IF(R16="","",IF(S16<=IF('1. AI Position'!$C$30="",5,INDEX(Lists!$AI$2:$AI$5,'1. AI Position'!$C$30)),"Within current position","Beyond current position")) -> Within current position | W16: =IF(B16="","",IF(OR(COUNTA(F16:N16)<9,Q16=""),"Complete inputs",IF(H16="No - varies by person / team","Redesign / standardise first",IF(T16="No","Automate - AI not needed",IF(U16="Data gap","AI later - close data gap first",IF(V16="Beyond current position","Stretch - partner or later stage","AI fit now")))))) -> AI fit now | X16: =IF(OR(W16="",W16="Complete inputs"),"",ROUND(0.3*INDEX(Lists!$N$8:$N$10,MATCH(F16,Lists!$M$8:$M$10,0))+0.25*IF(G16<20,1,IF(G16<80,2,IF(G16<160,3,IF(G16<480,4,5))))+0.25*J16+0.2*K16,2)) -> 3.85 | Y16: =IF(X16="","",ROUND(0.3*IF(U16="Data ready",5,IF(INDEX(Lists!$N$2:$N$5,MATCH(I16,Lists!$M$2:$M$5,0))=INDEX(Lists!$E$2:$E$11,MATCH(R16,Lists!$B$2:$B$11,0))-1,3,1))+0.25*INDEX(Lists!$N$13:$N$15,MATCH(H16,Lists!$M$13:$M$15,0))+0.25*(6-S16)+0.2*IF(V16="Within current position",5,2),2)) -> 4.5 | Z16: =IF(X16="","",CHOOSE(MAX(IF(T16="No",IF(L16="Yes",2,1),IF(IF(L16="Yes",2,0)+IF(M16="Yes",1,0)+INDEX(Lists!$N$18:$N$20,MATCH(N16,Lists!$M$18:$M$20,0))+IF(K16=5,2,IF(K16>=4,1,0))>=4,3,IF(IF(L16="Yes",2,0)+IF(M16="Yes",1,0)+INDEX(Lists!$N$18:$N$20,MATCH(N16,Lists!$M$18:$M$20,0))+IF(K16=5,2,IF(K16>=4,1,0))>=2,2,1))),IF($O16="Custom",1,MATCH(INDEX('2. Use-Case Library'!$L$5:$L$244,MATCH($O16,'2. Use-Case Library'!$A$5:$A$244,0)),{"Low","Medium","High"},0))),"Low","Medium","High")) -> Low | AA16: =IF(X16="","",IF(AND(X16>=$C$4,Y16>=$C$4),"Quick win",IF(X16>=$C$4,"Strategic bet",IF(Y16>=$C$4,"Fill-in","Deprioritise")))) -> Quick win | AB16: =IF(X16="","",ROUND(X16*Y16*IF(Z16="High",0.85,1)*IF(W16="Redesign / standardise first",0.8,1),2)) -> 17.33 | AC16: =IF(AB16="","",RANK(AB16,$AB$8:$AB$57)+COUNTIF($AB$7:AB15,AB16)) -> 3 | AD16: =IF(AH16="","",INDEX(Lists!$AV$2:$AV$5,AH16)) -> H1 - Now (0-6 months) | AE16: =IF(AB16="","",ROUND(G16*12*INDEX(Lists!$F$2:$F$11,MATCH(R16,Lists!$B$2:$B$11,0)),0)) -> 900 | AF16: =IF(OR(B16="",R16=""),"",IF(O16="Custom",INDEX(Lists!$I$2:$I$11,MATCH(R16,Lists!$B$2:$B$11,0)),INDEX('2. Use-Case Library'!$H$5:$H$244,MATCH($O16,'2. Use-Case Library'!$A$5:$A$244,0)))) -> Enterprise meeting assistant for transcripts, summaries and action tracking (with participant notice). | AG16: =IF(OR(B16="",O16="Custom"),"",INDEX('2. Use-Case Library'!$K$5:$K$244,MATCH($O16,'2. Use-Case Library'!$A$5:$A$244,0))) -> Participant consent; confidential meetings excluded. | AH16: =IF(AB16="","",IF(AA16="Deprioritise",4,IF(W16="AI later - close data gap first",3,IF(OR(W16="Redesign / standardise first",W16="Stretch - partner or later stage",AA16="Strategic bet",Z16="High",S16=5),2,1)))) -> 1 | AI16: =IF(AC16="","",AH16*100+AC16) -> 103 | AJ16: =IF(B16="","",IF(O16="Custom",B16,INDEX('2. Use-Case Library'!$D$5:$D$244,MATCH($O16,'2. Use-Case Library'!$A$5:$A$244,0)))) -> Meeting minutes & action tracking
A17: 10 | B17: PRO-15 | Methodology & knowledge Q&A | F17: High (more than 1,000 a month) | G17: 200 | H17: Partly - common steps, some variation | I17: Digital history available | J17: 4 | K17: 3 | L17: No | M17: No | N17: Assist - AI suggests, a person does the work | O17: =IF(B17="","",IFERROR(INDEX('2. Use-Case Library'!$A$5:$A$244,MATCH(B17,'2. Use-Case Library'!$M$5:$M$244,0)),"Custom")) -> PRO-15 | P17: =IF(B17="","",IF(O17="Custom",IF(E17="","(select function in E)",E17),INDEX('2. Use-Case Library'!$C$5:$C$244,MATCH($O17,'2. Use-Case Library'!$A$5:$A$244,0)))) -> Knowledge & collaboration | Q17: =IF(B17="","",IF(D17<>"",D17,IF(O17="Custom","",INDEX('2. Use-Case Library'!$F$5:$F$244,MATCH($O17,'2. Use-Case Library'!$A$5:$A$244,0))))) -> Answer questions from internal knowledge, policies or past work | R17: =IF(Q17="","",INDEX(Lists!$B$2:$B$11,MATCH(Q17,Lists!$A$2:$A$11,0))) -> GenAI knowledge assistant (RAG on own content) | S17: =IF(R17="","",INDEX(Lists!$C$2:$C$11,MATCH(R17,Lists!$B$2:$B$11,0))) -> 4 | T17: =IF(R17="","",INDEX(Lists!$D$2:$D$11,MATCH(R17,Lists!$B$2:$B$11,0))) -> Yes | U17: =IF(OR(R17="",I17=""),"",IF(INDEX(Lists!$N$2:$N$5,MATCH(I17,Lists!$M$2:$M$5,0))>=INDEX(Lists!$E$2:$E$11,MATCH(R17,Lists!$B$2:$B$11,0)),"Data ready","Data gap")) -> Data ready | V17: =IF(R17="","",IF(S17<=IF('1. AI Position'!$C$30="",5,INDEX(Lists!$AI$2:$AI$5,'1. AI Position'!$C$30)),"Within current position","Beyond current position")) -> Within current position | W17: =IF(B17="","",IF(OR(COUNTA(F17:N17)<9,Q17=""),"Complete inputs",IF(H17="No - varies by person / team","Redesign / standardise first",IF(T17="No","Automate - AI not needed",IF(U17="Data gap","AI later - close data gap first",IF(V17="Beyond current position","Stretch - partner or later stage","AI fit now")))))) -> AI fit now | X17: =IF(OR(W17="",W17="Complete inputs"),"",ROUND(0.3*INDEX(Lists!$N$8:$N$10,MATCH(F17,Lists!$M$8:$M$10,0))+0.25*IF(G17<20,1,IF(G17<80,2,IF(G17<160,3,IF(G17<480,4,5))))+0.25*J17+0.2*K17,2)) -> 4.1 | Y17: =IF(X17="","",ROUND(0.3*IF(U17="Data ready",5,IF(INDEX(Lists!$N$2:$N$5,MATCH(I17,Lists!$M$2:$M$5,0))=INDEX(Lists!$E$2:$E$11,MATCH(R17,Lists!$B$2:$B$11,0))-1,3,1))+0.25*INDEX(Lists!$N$13:$N$15,MATCH(H17,Lists!$M$13:$M$15,0))+0.25*(6-S17)+0.2*IF(V17="Within current position",5,2),2)) -> 3.75 | Z17: =IF(X17="","",CHOOSE(MAX(IF(T17="No",IF(L17="Yes",2,1),IF(IF(L17="Yes",2,0)+IF(M17="Yes",1,0)+INDEX(Lists!$N$18:$N$20,MATCH(N17,Lists!$M$18:$M$20,0))+IF(K17=5,2,IF(K17>=4,1,0))>=4,3,IF(IF(L17="Yes",2,0)+IF(M17="Yes",1,0)+INDEX(Lists!$N$18:$N$20,MATCH(N17,Lists!$M$18:$M$20,0))+IF(K17=5,2,IF(K17>=4,1,0))>=2,2,1))),IF($O17="Custom",1,MATCH(INDEX('2. Use-Case Library'!$L$5:$L$244,MATCH($O17,'2. Use-Case Library'!$A$5:$A$244,0)),{"Low","Medium","High"},0))),"Low","Medium","High")) -> Low | AA17: =IF(X17="","",IF(AND(X17>=$C$4,Y17>=$C$4),"Quick win",IF(X17>=$C$4,"Strategic bet",IF(Y17>=$C$4,"Fill-in","Deprioritise")))) -> Quick win | AB17: =IF(X17="","",ROUND(X17*Y17*IF(Z17="High",0.85,1)*IF(W17="Redesign / standardise first",0.8,1),2)) -> 15.38 | AC17: =IF(AB17="","",RANK(AB17,$AB$8:$AB$57)+COUNTIF($AB$7:AB16,AB17)) -> 7 | AD17: =IF(AH17="","",INDEX(Lists!$AV$2:$AV$5,AH17)) -> H1 - Now (0-6 months) | AE17: =IF(AB17="","",ROUND(G17*12*INDEX(Lists!$F$2:$F$11,MATCH(R17,Lists!$B$2:$B$11,0)),0)) -> 600 | AF17: =IF(OR(B17="",R17=""),"",IF(O17="Custom",INDEX(Lists!$I$2:$I$11,MATCH(R17,Lists!$B$2:$B$11,0)),INDEX('2. Use-Case Library'!$H$5:$H$244,MATCH($O17,'2. Use-Case Library'!$A$5:$A$244,0)))) -> Grounded assistant over firm methodologies and sanitised precedents. | AG17: =IF(OR(B17="",O17="Custom"),"",INDEX('2. Use-Case Library'!$K$5:$K$244,MATCH($O17,'2. Use-Case Library'!$A$5:$A$244,0))) -> Client confidentiality in precedents. | AH17: =IF(AB17="","",IF(AA17="Deprioritise",4,IF(W17="AI later - close data gap first",3,IF(OR(W17="Redesign / standardise first",W17="Stretch - partner or later stage",AA17="Strategic bet",Z17="High",S17=5),2,1)))) -> 1 | AI17: =IF(AC17="","",AH17*100+AC17) -> 107 | AJ17: =IF(B17="","",IF(O17="Custom",B17,INDEX('2. Use-Case Library'!$D$5:$D$244,MATCH($O17,'2. Use-Case Library'!$A$5:$A$244,0)))) -> Methodology & knowledge Q&A
A18: 11 | B18: PRO-08 | Client acceptance & independence checks | F18: Medium (100 - 1,000 a month) | G18: 140 | H18: Yes - documented and consistent | I18: Digital history available | J18: 4 | K18: 4 | L18: No | M18: Yes | N18: Human approves each AI output | O18: =IF(B18="","",IFERROR(INDEX('2. Use-Case Library'!$A$5:$A$244,MATCH(B18,'2. Use-Case Library'!$M$5:$M$244,0)),"Custom")) -> PRO-08 | P18: =IF(B18="","",IF(O18="Custom",IF(E18="","(select function in E)",E18),INDEX('2. Use-Case Library'!$C$5:$C$244,MATCH($O18,'2. Use-Case Library'!$A$5:$A$244,0)))) -> Risk, compliance & legal | Q18: =IF(B18="","",IF(D18<>"",D18,IF(O18="Custom","",INDEX('2. Use-Case Library'!$F$5:$F$244,MATCH($O18,'2. Use-Case Library'!$A$5:$A$244,0))))) -> Check or approve items against fixed criteria (rules, thresholds, checklists) | R18: =IF(Q18="","",INDEX(Lists!$B$2:$B$11,MATCH(Q18,Lists!$A$2:$A$11,0))) -> Rules engine / workflow automation | S18: =IF(R18="","",INDEX(Lists!$C$2:$C$11,MATCH(R18,Lists!$B$2:$B$11,0))) -> 2 | T18: =IF(R18="","",INDEX(Lists!$D$2:$D$11,MATCH(R18,Lists!$B$2:$B$11,0))) -> No | U18: =IF(OR(R18="",I18=""),"",IF(INDEX(Lists!$N$2:$N$5,MATCH(I18,Lists!$M$2:$M$5,0))>=INDEX(Lists!$E$2:$E$11,MATCH(R18,Lists!$B$2:$B$11,0)),"Data ready","Data gap")) -> Data ready | V18: =IF(R18="","",IF(S18<=IF('1. AI Position'!$C$30="",5,INDEX(Lists!$AI$2:$AI$5,'1. AI Position'!$C$30)),"Within current position","Beyond current position")) -> Within current position | W18: =IF(B18="","",IF(OR(COUNTA(F18:N18)<9,Q18=""),"Complete inputs",IF(H18="No - varies by person / team","Redesign / standardise first",IF(T18="No","Automate - AI not needed",IF(U18="Data gap","AI later - close data gap first",IF(V18="Beyond current position","Stretch - partner or later stage","AI fit now")))))) -> Automate - AI not needed | X18: =IF(OR(W18="",W18="Complete inputs"),"",ROUND(0.3*INDEX(Lists!$N$8:$N$10,MATCH(F18,Lists!$M$8:$M$10,0))+0.25*IF(G18<20,1,IF(G18<80,2,IF(G18<160,3,IF(G18<480,4,5))))+0.25*J18+0.2*K18,2)) -> 3.45 | Y18: =IF(X18="","",ROUND(0.3*IF(U18="Data ready",5,IF(INDEX(Lists!$N$2:$N$5,MATCH(I18,Lists!$M$2:$M$5,0))=INDEX(Lists!$E$2:$E$11,MATCH(R18,Lists!$B$2:$B$11,0))-1,3,1))+0.25*INDEX(Lists!$N$13:$N$15,MATCH(H18,Lists!$M$13:$M$15,0))+0.25*(6-S18)+0.2*IF(V18="Within current position",5,2),2)) -> 4.75 | Z18: =IF(X18="","",CHOOSE(MAX(IF(T18="No",IF(L18="Yes",2,1),IF(IF(L18="Yes",2,0)+IF(M18="Yes",1,0)+INDEX(Lists!$N$18:$N$20,MATCH(N18,Lists!$M$18:$M$20,0))+IF(K18=5,2,IF(K18>=4,1,0))>=4,3,IF(IF(L18="Yes",2,0)+IF(M18="Yes",1,0)+INDEX(Lists!$N$18:$N$20,MATCH(N18,Lists!$M$18:$M$20,0))+IF(K18=5,2,IF(K18>=4,1,0))>=2,2,1))),IF($O18="Custom",1,MATCH(INDEX('2. Use-Case Library'!$L$5:$L$244,MATCH($O18,'2. Use-Case Library'!$A$5:$A$244,0)),{"Low","Medium","High"},0))),"Low","Medium","High")) -> Low | AA18: =IF(X18="","",IF(AND(X18>=$C$4,Y18>=$C$4),"Quick win",IF(X18>=$C$4,"Strategic bet",IF(Y18>=$C$4,"Fill-in","Deprioritise")))) -> Quick win | AB18: =IF(X18="","",ROUND(X18*Y18*IF(Z18="High",0.85,1)*IF(W18="Redesign / standardise first",0.8,1),2)) -> 16.39 | AC18: =IF(AB18="","",RANK(AB18,$AB$8:$AB$57)+COUNTIF($AB$7:AB17,AB18)) -> 5 | AD18: =IF(AH18="","",INDEX(Lists!$AV$2:$AV$5,AH18)) -> H1 - Now (0-6 months) | AE18: =IF(AB18="","",ROUND(G18*12*INDEX(Lists!$F$2:$F$11,MATCH(R18,Lists!$B$2:$B$11,0)),0)) -> 840 | AF18: =IF(OR(B18="",R18=""),"",IF(O18="Custom",INDEX(Lists!$I$2:$I$11,MATCH(R18,Lists!$B$2:$B$11,0)),INDEX('2. Use-Case Library'!$H$5:$H$244,MATCH($O18,'2. Use-Case Library'!$A$5:$A$244,0)))) -> Workflow with rules-based independence and conflict checks against the client database. | AG18: =IF(OR(B18="",O18="Custom"),"",INDEX('2. Use-Case Library'!$K$5:$K$244,MATCH($O18,'2. Use-Case Library'!$A$5:$A$244,0))) -> IESBA Code; ISQM 1. | AH18: =IF(AB18="","",IF(AA18="Deprioritise",4,IF(W18="AI later - close data gap first",3,IF(OR(W18="Redesign / standardise first",W18="Stretch - partner or later stage",AA18="Strategic bet",Z18="High",S18=5),2,1)))) -> 1 | AI18: =IF(AC18="","",AH18*100+AC18) -> 105 | AJ18: =IF(B18="","",IF(O18="Custom",B18,INDEX('2. Use-Case Library'!$D$5:$D$244,MATCH($O18,'2. Use-Case Library'!$A$5:$A$244,0)))) -> Client acceptance & independence checks
A19: 12 | B19: PRO-09 | Timesheets, WIP & billing | F19: High (more than 1,000 a month) | G19: 180 | H19: Yes - documented and consistent | I19: Digital history with recorded outcomes | J19: 3 | K19: 3 | L19: No | M19: No | N19: Human approves each AI output | O19: =IF(B19="","",IFERROR(INDEX('2. Use-Case Library'!$A$5:$A$244,MATCH(B19,'2. Use-Case Library'!$M$5:$M$244,0)),"Custom")) -> PRO-09 | P19: =IF(B19="","",IF(O19="Custom",IF(E19="","(select function in E)",E19),INDEX('2. Use-Case Library'!$C$5:$C$244,MATCH($O19,'2. Use-Case Library'!$A$5:$A$244,0)))) -> Finance & accounting | Q19: =IF(B19="","",IF(D19<>"",D19,IF(O19="Custom","",INDEX('2. Use-Case Library'!$F$5:$F$244,MATCH($O19,'2. Use-Case Library'!$A$5:$A$244,0))))) -> Move or re-key data between systems following fixed rules | R19: =IF(Q19="","",INDEX(Lists!$B$2:$B$11,MATCH(Q19,Lists!$A$2:$A$11,0))) -> Workflow automation / RPA | S19: =IF(R19="","",INDEX(Lists!$C$2:$C$11,MATCH(R19,Lists!$B$2:$B$11,0))) -> 2 | T19: =IF(R19="","",INDEX(Lists!$D$2:$D$11,MATCH(R19,Lists!$B$2:$B$11,0))) -> No | U19: =IF(OR(R19="",I19=""),"",IF(INDEX(Lists!$N$2:$N$5,MATCH(I19,Lists!$M$2:$M$5,0))>=INDEX(Lists!$E$2:$E$11,MATCH(R19,Lists!$B$2:$B$11,0)),"Data ready","Data gap")) -> Data ready | V19: =IF(R19="","",IF(S19<=IF('1. AI Position'!$C$30="",5,INDEX(Lists!$AI$2:$AI$5,'1. AI Position'!$C$30)),"Within current position","Beyond current position")) -> Within current position | W19: =IF(B19="","",IF(OR(COUNTA(F19:N19)<9,Q19=""),"Complete inputs",IF(H19="No - varies by person / team","Redesign / standardise first",IF(T19="No","Automate - AI not needed",IF(U19="Data gap","AI later - close data gap first",IF(V19="Beyond current position","Stretch - partner or later stage","AI fit now")))))) -> Automate - AI not needed | X19: =IF(OR(W19="",W19="Complete inputs"),"",ROUND(0.3*INDEX(Lists!$N$8:$N$10,MATCH(F19,Lists!$M$8:$M$10,0))+0.25*IF(G19<20,1,IF(G19<80,2,IF(G19<160,3,IF(G19<480,4,5))))+0.25*J19+0.2*K19,2)) -> 3.85 | Y19: =IF(X19="","",ROUND(0.3*IF(U19="Data ready",5,IF(INDEX(Lists!$N$2:$N$5,MATCH(I19,Lists!$M$2:$M$5,0))=INDEX(Lists!$E$2:$E$11,MATCH(R19,Lists!$B$2:$B$11,0))-1,3,1))+0.25*INDEX(Lists!$N$13:$N$15,MATCH(H19,Lists!$M$13:$M$15,0))+0.25*(6-S19)+0.2*IF(V19="Within current position",5,2),2)) -> 4.75 | Z19: =IF(X19="","",CHOOSE(MAX(IF(T19="No",IF(L19="Yes",2,1),IF(IF(L19="Yes",2,0)+IF(M19="Yes",1,0)+INDEX(Lists!$N$18:$N$20,MATCH(N19,Lists!$M$18:$M$20,0))+IF(K19=5,2,IF(K19>=4,1,0))>=4,3,IF(IF(L19="Yes",2,0)+IF(M19="Yes",1,0)+INDEX(Lists!$N$18:$N$20,MATCH(N19,Lists!$M$18:$M$20,0))+IF(K19=5,2,IF(K19>=4,1,0))>=2,2,1))),IF($O19="Custom",1,MATCH(INDEX('2. Use-Case Library'!$L$5:$L$244,MATCH($O19,'2. Use-Case Library'!$A$5:$A$244,0)),{"Low","Medium","High"},0))),"Low","Medium","High")) -> Low | AA19: =IF(X19="","",IF(AND(X19>=$C$4,Y19>=$C$4),"Quick win",IF(X19>=$C$4,"Strategic bet",IF(Y19>=$C$4,"Fill-in","Deprioritise")))) -> Quick win | AB19: =IF(X19="","",ROUND(X19*Y19*IF(Z19="High",0.85,1)*IF(W19="Redesign / standardise first",0.8,1),2)) -> 18.29 | AC19: =IF(AB19="","",RANK(AB19,$AB$8:$AB$57)+COUNTIF($AB$7:AB18,AB19)) -> 2 | AD19: =IF(AH19="","",INDEX(Lists!$AV$2:$AV$5,AH19)) -> H1 - Now (0-6 months) | AE19: =IF(AB19="","",ROUND(G19*12*INDEX(Lists!$F$2:$F$11,MATCH(R19,Lists!$B$2:$B$11,0)),0)) -> 1296 | AF19: =IF(OR(B19="",R19=""),"",IF(O19="Custom",INDEX(Lists!$I$2:$I$11,MATCH(R19,Lists!$B$2:$B$11,0)),INDEX('2. Use-Case Library'!$H$5:$H$244,MATCH($O19,'2. Use-Case Library'!$A$5:$A$244,0)))) -> Automated timesheet reminders, WIP reports and draft billing narratives. | AG19: =IF(OR(B19="",O19="Custom"),"",INDEX('2. Use-Case Library'!$K$5:$K$244,MATCH($O19,'2. Use-Case Library'!$A$5:$A$244,0))) -> - | AH19: =IF(AB19="","",IF(AA19="Deprioritise",4,IF(W19="AI later - close data gap first",3,IF(OR(W19="Redesign / standardise first",W19="Stretch - partner or later stage",AA19="Strategic bet",Z19="High",S19=5),2,1)))) -> 1 | AI19: =IF(AC19="","",AH19*100+AC19) -> 102 | AJ19: =IF(B19="","",IF(O19="Custom",B19,INDEX('2. Use-Case Library'!$D$5:$D$244,MATCH($O19,'2. Use-Case Library'!$A$5:$A$244,0)))) -> Timesheets, WIP & billing
... A29: 22 | B29: XI-28 | Customer churn prediction | F29: Medium (100 - 1,000 a month) | G29: 200 | H29: Partly - common steps, some variation | I29: Partial or paper-based | J29: 4 | K29: 4 | L29: No | M29: Yes | N29: Assist - AI suggests, a person does the work | O29: =IF(B29="","",IFERROR(INDEX('2. Use-Case Library'!$A$5:$A$244,MATCH(B29,'2. Use-Case Library'!$M$5:$M$244,0)),"Custom")) -> XI-28 | P29: =IF(B29="","",IF(O29="Custom",IF(E29="","(select function in E)",E29),INDEX('2. Use-Case Library'!$C$5:$C$244,MATCH($O29,'2. Use-Case Library'!$A$5:$A$244,0)))) -> Sales & marketing | Q29: =IF(B29="","",IF(D29<>"",D29,IF(O29="Custom","",INDEX('2. Use-Case Library'!$F$5:$F$244,MATCH($O29,'2. Use-Case Library'!$A$5:$A$244,0))))) -> Forecast, score, classify or detect anomalies from historical data | R29: =IF(Q29="","",INDEX(Lists!$B$2:$B$11,MATCH(Q29,Lists!$A$2:$A$11,0))) -> Predictive analytics / machine learning | S29: =IF(R29="","",INDEX(Lists!$C$2:$C$11,MATCH(R29,Lists!$B$2:$B$11,0))) -> 5 | T29: =IF(R29="","",INDEX(Lists!$D$2:$D$11,MATCH(R29,Lists!$B$2:$B$11,0))) -> Yes | U29: =IF(OR(R29="",I29=""),"",IF(INDEX(Lists!$N$2:$N$5,MATCH(I29,Lists!$M$2:$M$5,0))>=INDEX(Lists!$E$2:$E$11,MATCH(R29,Lists!$B$2:$B$11,0)),"Data ready","Data gap")) -> Data gap | V29: =IF(R29="","",IF(S29<=IF('1. AI Position'!$C$30="",5,INDEX(Lists!$AI$2:$AI$5,'1. AI Position'!$C$30)),"Within current position","Beyond current position")) -> Beyond current position | W29: =IF(B29="","",IF(OR(COUNTA(F29:N29)<9,Q29=""),"Complete inputs",IF(H29="No - varies by person / team","Redesign / standardise first",IF(T29="No","Automate - AI not needed",IF(U29="Data gap","AI later - close data gap first",IF(V29="Beyond current position","Stretch - partner or later stage","AI fit now")))))) -> AI later - close data gap first | X29: =IF(OR(W29="",W29="Complete inputs"),"",ROUND(0.3*INDEX(Lists!$N$8:$N$10,MATCH(F29,Lists!$M$8:$M$10,0))+0.25*IF(G29<20,1,IF(G29<80,2,IF(G29<160,3,IF(G29<480,4,5))))+0.25*J29+0.2*K29,2)) -> 3.7 | Y29: =IF(X29="","",ROUND(0.3*IF(U29="Data ready",5,IF(INDEX(Lists!$N$2:$N$5,MATCH(I29,Lists!$M$2:$M$5,0))=INDEX(Lists!$E$2:$E$11,MATCH(R29,Lists!$B$2:$B$11,0))-1,3,1))+0.25*INDEX(Lists!$N$13:$N$15,MATCH(H29,Lists!$M$13:$M$15,0))+0.25*(6-S29)+0.2*IF(V29="Within current position",5,2),2)) -> 2.3 | Z29: =IF(X29="","",CHOOSE(MAX(IF(T29="No",IF(L29="Yes",2,1),IF(IF(L29="Yes",2,0)+IF(M29="Yes",1,0)+INDEX(Lists!$N$18:$N$20,MATCH(N29,Lists!$M$18:$M$20,0))+IF(K29=5,2,IF(K29>=4,1,0))>=4,3,IF(IF(L29="Yes",2,0)+IF(M29="Yes",1,0)+INDEX(Lists!$N$18:$N$20,MATCH(N29,Lists!$M$18:$M$20,0))+IF(K29=5,2,IF(K29>=4,1,0))>=2,2,1))),IF($O29="Custom",1,MATCH(INDEX('2. Use-Case Library'!$L$5:$L$244,MATCH($O29,'2. Use-Case Library'!$A$5:$A$244,0)),{"Low","Medium","High"},0))),"Low","Medium","High")) -> Medium | AA29: =IF(X29="","",IF(AND(X29>=$C$4,Y29>=$C$4),"Quick win",IF(X29>=$C$4,"Strategic bet",IF(Y29>=$C$4,"Fill-in","Deprioritise")))) -> Strategic bet | AB29: =IF(X29="","",ROUND(X29*Y29*IF(Z29="High",0.85,1)*IF(W29="Redesign / standardise first",0.8,1),2)) -> 8.51 | AC29: =IF(AB29="","",RANK(AB29,$AB$8:$AB$57)+COUNTIF($AB$7:AB28,AB29)) -> 19 | AD29: =IF(AH29="","",INDEX(Lists!$AV$2:$AV$5,AH29)) -> H3 - Later (12-24 months) | AE29: =IF(AB29="","",ROUND(G29*12*INDEX(Lists!$F$2:$F$11,MATCH(R29,Lists!$B$2:$B$11,0)),0)) -> 480 | AF29: =IF(OR(B29="",R29=""),"",IF(O29="Custom",INDEX(Lists!$I$2:$I$11,MATCH(R29,Lists!$B$2:$B$11,0)),INDEX('2. Use-Case Library'!$H$5:$H$244,MATCH($O29,'2. Use-Case Library'!$A$5:$A$244,0)))) -> Churn model on usage and service history feeding retention campaigns; measure uplift with control groups. | AG29: =IF(OR(B29="",O29="Custom"),"",INDEX('2. Use-Case Library'!$K$5:$K$244,MATCH($O29,'2. Use-Case Library'!$A$5:$A$244,0))) -> Consent for marketing use; fairness of offers. | AH29: =IF(AB29="","",IF(AA29="Deprioritise",4,IF(W29="AI later - close data gap first",3,IF(OR(W29="Redesign / standardise first",W29="Stretch - partner or later stage",AA29="Strategic bet",Z29="High",S29=5),2,1)))) -> 3 | AI29: =IF(AC29="","",AH29*100+AC29) -> 319 | AJ29: =IF(B29="","",IF(O29="Custom",B29,INDEX('2. Use-Case Library'!$D$5:$D$244,MATCH($O29,'2. Use-Case Library'!$A$5:$A$244,0)))) -> Customer churn prediction
A30: 23 | O30: =IF(B30="","",IFERROR(INDEX('2. Use-Case Library'!$A$5:$A$244,MATCH(B30,'2. Use-Case Library'!$M$5:$M$244,0)),"Custom")) | P30: =IF(B30="","",IF(O30="Custom",IF(E30="","(select function in E)",E30),INDEX('2. Use-Case Library'!$C$5:$C$244,MATCH($O30,'2. Use-Case Library'!$A$5:$A$244,0)))) | Q30: =IF(B30="","",IF(D30<>"",D30,IF(O30="Custom","",INDEX('2. Use-Case Library'!$F$5:$F$244,MATCH($O30,'2. Use-Case Library'!$A$5:$A$244,0))))) | R30: =IF(Q30="","",INDEX(Lists!$B$2:$B$11,MATCH(Q30,Lists!$A$2:$A$11,0))) | S30: =IF(R30="","",INDEX(Lists!$C$2:$C$11,MATCH(R30,Lists!$B$2:$B$11,0))) | T30: =IF(R30="","",INDEX(Lists!$D$2:$D$11,MATCH(R30,Lists!$B$2:$B$11,0))) | U30: =IF(OR(R30="",I30=""),"",IF(INDEX(Lists!$N$2:$N$5,MATCH(I30,Lists!$M$2:$M$5,0))>=INDEX(Lists!$E$2:$E$11,MATCH(R30,Lists!$B$2:$B$11,0)),"Data ready","Data gap")) | V30: =IF(R30="","",IF(S30<=IF('1. AI Position'!$C$30="",5,INDEX(Lists!$AI$2:$AI$5,'1. AI Position'!$C$30)),"Within current position","Beyond current position")) | W30: =IF(B30="","",IF(OR(COUNTA(F30:N30)<9,Q30=""),"Complete inputs",IF(H30="No - varies by person / team","Redesign / standardise first",IF(T30="No","Automate - AI not needed",IF(U30="Data gap","AI later - close data gap first",IF(V30="Beyond current position","Stretch - partner or later stage","AI fit now")))))) | X30: =IF(OR(W30="",W30="Complete inputs"),"",ROUND(0.3*INDEX(Lists!$N$8:$N$10,MATCH(F30,Lists!$M$8:$M$10,0))+0.25*IF(G30<20,1,IF(G30<80,2,IF(G30<160,3,IF(G30<480,4,5))))+0.25*J30+0.2*K30,2)) | Y30: =IF(X30="","",ROUND(0.3*IF(U30="Data ready",5,IF(INDEX(Lists!$N$2:$N$5,MATCH(I30,Lists!$M$2:$M$5,0))=INDEX(Lists!$E$2:$E$11,MATCH(R30,Lists!$B$2:$B$11,0))-1,3,1))+0.25*INDEX(Lists!$N$13:$N$15,MATCH(H30,Lists!$M$13:$M$15,0))+0.25*(6-S30)+0.2*IF(V30="Within current position",5,2),2)) | Z30: =IF(X30="","",CHOOSE(MAX(IF(T30="No",IF(L30="Yes",2,1),IF(IF(L30="Yes",2,0)+IF(M30="Yes",1,0)+INDEX(Lists!$N$18:$N$20,MATCH(N30,Lists!$M$18:$M$20,0))+IF(K30=5,2,IF(K30>=4,1,0))>=4,3,IF(IF(L30="Yes",2,0)+IF(M30="Yes",1,0)+INDEX(Lists!$N$18:$N$20,MATCH(N30,Lists!$M$18:$M$20,0))+IF(K30=5,2,IF(K30>=4,1,0))>=2,2,1))),IF($O30="Custom",1,MATCH(INDEX('2. Use-Case Library'!$L$5:$L$244,MATCH($O30,'2. Use-Case Library'!$A$5:$A$244,0)),{"Low","Medium","High"},0))),"Low","Medium","High")) | AA30: =IF(X30="","",IF(AND(X30>=$C$4,Y30>=$C$4),"Quick win",IF(X30>=$C$4,"Strategic bet",IF(Y30>=$C$4,"Fill-in","Deprioritise")))) | AB30: =IF(X30="","",ROUND(X30*Y30*IF(Z30="High",0.85,1)*IF(W30="Redesign / standardise first",0.8,1),2)) | AC30: =IF(AB30="","",RANK(AB30,$AB$8:$AB$57)+COUNTIF($AB$7:AB29,AB30)) | AD30: =IF(AH30="","",INDEX(Lists!$AV$2:$AV$5,AH30)) | AE30: =IF(AB30="","",ROUND(G30*12*INDEX(Lists!$F$2:$F$11,MATCH(R30,Lists!$B$2:$B$11,0)),0)) | AF30: =IF(OR(B30="",R30=""),"",IF(O30="Custom",INDEX(Lists!$I$2:$I$11,MATCH(R30,Lists!$B$2:$B$11,0)),INDEX('2. Use-Case Library'!$H$5:$H$244,MATCH($O30,'2. Use-Case Library'!$A$5:$A$244,0)))) | AG30: =IF(OR(B30="",O30="Custom"),"",INDEX('2. Use-Case Library'!$K$5:$K$244,MATCH($O30,'2. Use-Case Library'!$A$5:$A$244,0))) | AH30: =IF(AB30="","",IF(AA30="Deprioritise",4,IF(W30="AI later - close data gap first",3,IF(OR(W30="Redesign / standardise first",W30="Stretch - partner or later stage",AA30="Strategic bet",Z30="High",S30=5),2,1)))) | AI30: =IF(AC30="","",AH30*100+AC30) | AJ30: =IF(B30="","",IF(O30="Custom",B30,INDEX('2. Use-Case Library'!$D$5:$D$244,MATCH($O30,'2. Use-Case Library'!$A$5:$A$244,0))))
A31: 24 | O31: =IF(B31="","",IFERROR(INDEX('2. Use-Case Library'!$A$5:$A$244,MATCH(B31,'2. Use-Case Library'!$M$5:$M$244,0)),"Custom")) | P31: =IF(B31="","",IF(O31="Custom",IF(E31="","(select function in E)",E31),INDEX('2. Use-Case Library'!$C$5:$C$244,MATCH($O31,'2. Use-Case Library'!$A$5:$A$244,0)))) | Q31: =IF(B31="","",IF(D31<>"",D31,IF(O31="Custom","",INDEX('2. Use-Case Library'!$F$5:$F$244,MATCH($O31,'2. Use-Case Library'!$A$5:$A$244,0))))) | R31: =IF(Q31="","",INDEX(Lists!$B$2:$B$11,MATCH(Q31,Lists!$A$2:$A$11,0))) | S31: =IF(R31="","",INDEX(Lists!$C$2:$C$11,MATCH(R31,Lists!$B$2:$B$11,0))) | T31: =IF(R31="","",INDEX(Lists!$D$2:$D$11,MATCH(R31,Lists!$B$2:$B$11,0))) | U31: =IF(OR(R31="",I31=""),"",IF(INDEX(Lists!$N$2:$N$5,MATCH(I31,Lists!$M$2:$M$5,0))>=INDEX(Lists!$E$2:$E$11,MATCH(R31,Lists!$B$2:$B$11,0)),"Data ready","Data gap")) | V31: =IF(R31="","",IF(S31<=IF('1. AI Position'!$C$30="",5,INDEX(Lists!$AI$2:$AI$5,'1. AI Position'!$C$30)),"Within current position","Beyond current position")) | W31: =IF(B31="","",IF(OR(COUNTA(F31:N31)<9,Q31=""),"Complete inputs",IF(H31="No - varies by person / team","Redesign / standardise first",IF(T31="No","Automate - AI not needed",IF(U31="Data gap","AI later - close data gap first",IF(V31="Beyond current position","Stretch - partner or later stage","AI fit now")))))) | X31: =IF(OR(W31="",W31="Complete inputs"),"",ROUND(0.3*INDEX(Lists!$N$8:$N$10,MATCH(F31,Lists!$M$8:$M$10,0))+0.25*IF(G31<20,1,IF(G31<80,2,IF(G31<160,3,IF(G31<480,4,5))))+0.25*J31+0.2*K31,2)) | Y31: =IF(X31="","",ROUND(0.3*IF(U31="Data ready",5,IF(INDEX(Lists!$N$2:$N$5,MATCH(I31,Lists!$M$2:$M$5,0))=INDEX(Lists!$E$2:$E$11,MATCH(R31,Lists!$B$2:$B$11,0))-1,3,1))+0.25*INDEX(Lists!$N$13:$N$15,MATCH(H31,Lists!$M$13:$M$15,0))+0.25*(6-S31)+0.2*IF(V31="Within current position",5,2),2)) | Z31: =IF(X31="","",CHOOSE(MAX(IF(T31="No",IF(L31="Yes",2,1),IF(IF(L31="Yes",2,0)+IF(M31="Yes",1,0)+INDEX(Lists!$N$18:$N$20,MATCH(N31,Lists!$M$18:$M$20,0))+IF(K31=5,2,IF(K31>=4,1,0))>=4,3,IF(IF(L31="Yes",2,0)+IF(M31="Yes",1,0)+INDEX(Lists!$N$18:$N$20,MATCH(N31,Lists!$M$18:$M$20,0))+IF(K31=5,2,IF(K31>=4,1,0))>=2,2,1))),IF($O31="Custom",1,MATCH(INDEX('2. Use-Case Library'!$L$5:$L$244,MATCH($O31,'2. Use-Case Library'!$A$5:$A$244,0)),{"Low","Medium","High"},0))),"Low","Medium","High")) | AA31: =IF(X31="","",IF(AND(X31>=$C$4,Y31>=$C$4),"Quick win",IF(X31>=$C$4,"Strategic bet",IF(Y31>=$C$4,"Fill-in","Deprioritise")))) | AB31: =IF(X31="","",ROUND(X31*Y31*IF(Z31="High",0.85,1)*IF(W31="Redesign / standardise first",0.8,1),2)) | AC31: =IF(AB31="","",RANK(AB31,$AB$8:$AB$57)+COUNTIF($AB$7:AB30,AB31)) | AD31: =IF(AH31="","",INDEX(Lists!$AV$2:$AV$5,AH31)) | AE31: =IF(AB31="","",ROUND(G31*12*INDEX(Lists!$F$2:$F$11,MATCH(R31,Lists!$B$2:$B$11,0)),0)) | AF31: =IF(OR(B31="",R31=""),"",IF(O31="Custom",INDEX(Lists!$I$2:$I$11,MATCH(R31,Lists!$B$2:$B$11,0)),INDEX('2. Use-Case Library'!$H$5:$H$244,MATCH($O31,'2. Use-Case Library'!$A$5:$A$244,0)))) | AG31: =IF(OR(B31="",O31="Custom"),"",INDEX('2. Use-Case Library'!$K$5:$K$244,MATCH($O31,'2. Use-Case Library'!$A$5:$A$244,0))) | AH31: =IF(AB31="","",IF(AA31="Deprioritise",4,IF(W31="AI later - close data gap first",3,IF(OR(W31="Redesign / standardise first",W31="Stretch - partner or later stage",AA31="Strategic bet",Z31="High",S31=5),2,1)))) | AI31: =IF(AC31="","",AH31*100+AC31) | AJ31: =IF(B31="","",IF(O31="Custom",B31,INDEX('2. Use-Case Library'!$D$5:$D$244,MATCH($O31,'2. Use-Case Library'!$A$5:$A$244,0))))
A32: 25 | O32: =IF(B32="","",IFERROR(INDEX('2. Use-Case Library'!$A$5:$A$244,MATCH(B32,'2. Use-Case Library'!$M$5:$M$244,0)),"Custom")) | P32: =IF(B32="","",IF(O32="Custom",IF(E32="","(select function in E)",E32),INDEX('2. Use-Case Library'!$C$5:$C$244,MATCH($O32,'2. Use-Case Library'!$A$5:$A$244,0)))) | Q32: =IF(B32="","",IF(D32<>"",D32,IF(O32="Custom","",INDEX('2. Use-Case Library'!$F$5:$F$244,MATCH($O32,'2. Use-Case Library'!$A$5:$A$244,0))))) | R32: =IF(Q32="","",INDEX(Lists!$B$2:$B$11,MATCH(Q32,Lists!$A$2:$A$11,0))) | S32: =IF(R32="","",INDEX(Lists!$C$2:$C$11,MATCH(R32,Lists!$B$2:$B$11,0))) | T32: =IF(R32="","",INDEX(Lists!$D$2:$D$11,MATCH(R32,Lists!$B$2:$B$11,0))) | U32: =IF(OR(R32="",I32=""),"",IF(INDEX(Lists!$N$2:$N$5,MATCH(I32,Lists!$M$2:$M$5,0))>=INDEX(Lists!$E$2:$E$11,MATCH(R32,Lists!$B$2:$B$11,0)),"Data ready","Data gap")) | V32: =IF(R32="","",IF(S32<=IF('1. AI Position'!$C$30="",5,INDEX(Lists!$AI$2:$AI$5,'1. AI Position'!$C$30)),"Within current position","Beyond current position")) | W32: =IF(B32="","",IF(OR(COUNTA(F32:N32)<9,Q32=""),"Complete inputs",IF(H32="No - varies by person / team","Redesign / standardise first",IF(T32="No","Automate - AI not needed",IF(U32="Data gap","AI later - close data gap first",IF(V32="Beyond current position","Stretch - partner or later stage","AI fit now")))))) | X32: =IF(OR(W32="",W32="Complete inputs"),"",ROUND(0.3*INDEX(Lists!$N$8:$N$10,MATCH(F32,Lists!$M$8:$M$10,0))+0.25*IF(G32<20,1,IF(G32<80,2,IF(G32<160,3,IF(G32<480,4,5))))+0.25*J32+0.2*K32,2)) | Y32: =IF(X32="","",ROUND(0.3*IF(U32="Data ready",5,IF(INDEX(Lists!$N$2:$N$5,MATCH(I32,Lists!$M$2:$M$5,0))=INDEX(Lists!$E$2:$E$11,MATCH(R32,Lists!$B$2:$B$11,0))-1,3,1))+0.25*INDEX(Lists!$N$13:$N$15,MATCH(H32,Lists!$M$13:$M$15,0))+0.25*(6-S32)+0.2*IF(V32="Within current position",5,2),2)) | Z32: =IF(X32="","",CHOOSE(MAX(IF(T32="No",IF(L32="Yes",2,1),IF(IF(L32="Yes",2,0)+IF(M32="Yes",1,0)+INDEX(Lists!$N$18:$N$20,MATCH(N32,Lists!$M$18:$M$20,0))+IF(K32=5,2,IF(K32>=4,1,0))>=4,3,IF(IF(L32="Yes",2,0)+IF(M32="Yes",1,0)+INDEX(Lists!$N$18:$N$20,MATCH(N32,Lists!$M$18:$M$20,0))+IF(K32=5,2,IF(K32>=4,1,0))>=2,2,1))),IF($O32="Custom",1,MATCH(INDEX('2. Use-Case Library'!$L$5:$L$244,MATCH($O32,'2. Use-Case Library'!$A$5:$A$244,0)),{"Low","Medium","High"},0))),"Low","Medium","High")) | AA32: =IF(X32="","",IF(AND(X32>=$C$4,Y32>=$C$4),"Quick win",IF(X32>=$C$4,"Strategic bet",IF(Y32>=$C$4,"Fill-in","Deprioritise")))) | AB32: =IF(X32="","",ROUND(X32*Y32*IF(Z32="High",0.85,1)*IF(W32="Redesign / standardise first",0.8,1),2)) | AC32: =IF(AB32="","",RANK(AB32,$AB$8:$AB$57)+COUNTIF($AB$7:AB31,AB32)) | AD32: =IF(AH32="","",INDEX(Lists!$AV$2:$AV$5,AH32)) | AE32: =IF(AB32="","",ROUND(G32*12*INDEX(Lists!$F$2:$F$11,MATCH(R32,Lists!$B$2:$B$11,0)),0)) | AF32: =IF(OR(B32="",R32=""),"",IF(O32="Custom",INDEX(Lists!$I$2:$I$11,MATCH(R32,Lists!$B$2:$B$11,0)),INDEX('2. Use-Case Library'!$H$5:$H$244,MATCH($O32,'2. Use-Case Library'!$A$5:$A$244,0)))) | AG32: =IF(OR(B32="",O32="Custom"),"",INDEX('2. Use-Case Library'!$K$5:$K$244,MATCH($O32,'2. Use-Case Library'!$A$5:$A$244,0))) | AH32: =IF(AB32="","",IF(AA32="Deprioritise",4,IF(W32="AI later - close data gap first",3,IF(OR(W32="Redesign / standardise first",W32="Stretch - partner or later stage",AA32="Strategic bet",Z32="High",S32=5),2,1)))) | AI32: =IF(AC32="","",AH32*100+AC32) | AJ32: =IF(B32="","",IF(O32="Custom",B32,INDEX('2. Use-Case Library'!$D$5:$D$244,MATCH($O32,'2. Use-Case Library'!$A$5:$A$244,0))))
A33: 26 | O33: =IF(B33="","",IFERROR(INDEX('2. Use-Case Library'!$A$5:$A$244,MATCH(B33,'2. Use-Case Library'!$M$5:$M$244,0)),"Custom")) | P33: =IF(B33="","",IF(O33="Custom",IF(E33="","(select function in E)",E33),INDEX('2. Use-Case Library'!$C$5:$C$244,MATCH($O33,'2. Use-Case Library'!$A$5:$A$244,0)))) | Q33: =IF(B33="","",IF(D33<>"",D33,IF(O33="Custom","",INDEX('2. Use-Case Library'!$F$5:$F$244,MATCH($O33,'2. Use-Case Library'!$A$5:$A$244,0))))) | R33: =IF(Q33="","",INDEX(Lists!$B$2:$B$11,MATCH(Q33,Lists!$A$2:$A$11,0))) | S33: =IF(R33="","",INDEX(Lists!$C$2:$C$11,MATCH(R33,Lists!$B$2:$B$11,0))) | T33: =IF(R33="","",INDEX(Lists!$D$2:$D$11,MATCH(R33,Lists!$B$2:$B$11,0))) | U33: =IF(OR(R33="",I33=""),"",IF(INDEX(Lists!$N$2:$N$5,MATCH(I33,Lists!$M$2:$M$5,0))>=INDEX(Lists!$E$2:$E$11,MATCH(R33,Lists!$B$2:$B$11,0)),"Data ready","Data gap")) | V33: =IF(R33="","",IF(S33<=IF('1. AI Position'!$C$30="",5,INDEX(Lists!$AI$2:$AI$5,'1. AI Position'!$C$30)),"Within current position","Beyond current position")) | W33: =IF(B33="","",IF(OR(COUNTA(F33:N33)<9,Q33=""),"Complete inputs",IF(H33="No - varies by person / team","Redesign / standardise first",IF(T33="No","Automate - AI not needed",IF(U33="Data gap","AI later - close data gap first",IF(V33="Beyond current position","Stretch - partner or later stage","AI fit now")))))) | X33: =IF(OR(W33="",W33="Complete inputs"),"",ROUND(0.3*INDEX(Lists!$N$8:$N$10,MATCH(F33,Lists!$M$8:$M$10,0))+0.25*IF(G33<20,1,IF(G33<80,2,IF(G33<160,3,IF(G33<480,4,5))))+0.25*J33+0.2*K33,2)) | Y33: =IF(X33="","",ROUND(0.3*IF(U33="Data ready",5,IF(INDEX(Lists!$N$2:$N$5,MATCH(I33,Lists!$M$2:$M$5,0))=INDEX(Lists!$E$2:$E$11,MATCH(R33,Lists!$B$2:$B$11,0))-1,3,1))+0.25*INDEX(Lists!$N$13:$N$15,MATCH(H33,Lists!$M$13:$M$15,0))+0.25*(6-S33)+0.2*IF(V33="Within current position",5,2),2)) | Z33: =IF(X33="","",CHOOSE(MAX(IF(T33="No",IF(L33="Yes",2,1),IF(IF(L33="Yes",2,0)+IF(M33="Yes",1,0)+INDEX(Lists!$N$18:$N$20,MATCH(N33,Lists!$M$18:$M$20,0))+IF(K33=5,2,IF(K33>=4,1,0))>=4,3,IF(IF(L33="Yes",2,0)+IF(M33="Yes",1,0)+INDEX(Lists!$N$18:$N$20,MATCH(N33,Lists!$M$18:$M$20,0))+IF(K33=5,2,IF(K33>=4,1,0))>=2,2,1))),IF($O33="Custom",1,MATCH(INDEX('2. Use-Case Library'!$L$5:$L$244,MATCH($O33,'2. Use-Case Library'!$A$5:$A$244,0)),{"Low","Medium","High"},0))),"Low","Medium","High")) | AA33: =IF(X33="","",IF(AND(X33>=$C$4,Y33>=$C$4),"Quick win",IF(X33>=$C$4,"Strategic bet",IF(Y33>=$C$4,"Fill-in","Deprioritise")))) | AB33: =IF(X33="","",ROUND(X33*Y33*IF(Z33="High",0.85,1)*IF(W33="Redesign / standardise first",0.8,1),2)) | AC33: =IF(AB33="","",RANK(AB33,$AB$8:$AB$57)+COUNTIF($AB$7:AB32,AB33)) | AD33: =IF(AH33="","",INDEX(Lists!$AV$2:$AV$5,AH33)) | AE33: =IF(AB33="","",ROUND(G33*12*INDEX(Lists!$F$2:$F$11,MATCH(R33,Lists!$B$2:$B$11,0)),0)) | AF33: =IF(OR(B33="",R33=""),"",IF(O33="Custom",INDEX(Lists!$I$2:$I$11,MATCH(R33,Lists!$B$2:$B$11,0)),INDEX('2. Use-Case Library'!$H$5:$H$244,MATCH($O33,'2. Use-Case Library'!$A$5:$A$244,0)))) | AG33: =IF(OR(B33="",O33="Custom"),"",INDEX('2. Use-Case Library'!$K$5:$K$244,MATCH($O33,'2. Use-Case Library'!$A$5:$A$244,0))) | AH33: =IF(AB33="","",IF(AA33="Deprioritise",4,IF(W33="AI later - close data gap first",3,IF(OR(W33="Redesign / standardise first",W33="Stretch - partner or later stage",AA33="Strategic bet",Z33="High",S33=5),2,1)))) | AI33: =IF(AC33="","",AH33*100+AC33) | AJ33: =IF(B33="","",IF(O33="Custom",B33,INDEX('2. Use-Case Library'!$D$5:$D$244,MATCH($O33,'2. Use-Case Library'!$A$5:$A$244,0))))
A34: 27 | O34: =IF(B34="","",IFERROR(INDEX('2. Use-Case Library'!$A$5:$A$244,MATCH(B34,'2. Use-Case Library'!$M$5:$M$244,0)),"Custom")) | P34: =IF(B34="","",IF(O34="Custom",IF(E34="","(select function in E)",E34),INDEX('2. Use-Case Library'!$C$5:$C$244,MATCH($O34,'2. Use-Case Library'!$A$5:$A$244,0)))) | Q34: =IF(B34="","",IF(D34<>"",D34,IF(O34="Custom","",INDEX('2. Use-Case Library'!$F$5:$F$244,MATCH($O34,'2. Use-Case Library'!$A$5:$A$244,0))))) | R34: =IF(Q34="","",INDEX(Lists!$B$2:$B$11,MATCH(Q34,Lists!$A$2:$A$11,0))) | S34: =IF(R34="","",INDEX(Lists!$C$2:$C$11,MATCH(R34,Lists!$B$2:$B$11,0))) | T34: =IF(R34="","",INDEX(Lists!$D$2:$D$11,MATCH(R34,Lists!$B$2:$B$11,0))) | U34: =IF(OR(R34="",I34=""),"",IF(INDEX(Lists!$N$2:$N$5,MATCH(I34,Lists!$M$2:$M$5,0))>=INDEX(Lists!$E$2:$E$11,MATCH(R34,Lists!$B$2:$B$11,0)),"Data ready","Data gap")) | V34: =IF(R34="","",IF(S34<=IF('1. AI Position'!$C$30="",5,INDEX(Lists!$AI$2:$AI$5,'1. AI Position'!$C$30)),"Within current position","Beyond current position")) | W34: =IF(B34="","",IF(OR(COUNTA(F34:N34)<9,Q34=""),"Complete inputs",IF(H34="No - varies by person / team","Redesign / standardise first",IF(T34="No","Automate - AI not needed",IF(U34="Data gap","AI later - close data gap first",IF(V34="Beyond current position","Stretch - partner or later stage","AI fit now")))))) | X34: =IF(OR(W34="",W34="Complete inputs"),"",ROUND(0.3*INDEX(Lists!$N$8:$N$10,MATCH(F34,Lists!$M$8:$M$10,0))+0.25*IF(G34<20,1,IF(G34<80,2,IF(G34<160,3,IF(G34<480,4,5))))+0.25*J34+0.2*K34,2)) | Y34: =IF(X34="","",ROUND(0.3*IF(U34="Data ready",5,IF(INDEX(Lists!$N$2:$N$5,MATCH(I34,Lists!$M$2:$M$5,0))=INDEX(Lists!$E$2:$E$11,MATCH(R34,Lists!$B$2:$B$11,0))-1,3,1))+0.25*INDEX(Lists!$N$13:$N$15,MATCH(H34,Lists!$M$13:$M$15,0))+0.25*(6-S34)+0.2*IF(V34="Within current position",5,2),2)) | Z34: =IF(X34="","",CHOOSE(MAX(IF(T34="No",IF(L34="Yes",2,1),IF(IF(L34="Yes",2,0)+IF(M34="Yes",1,0)+INDEX(Lists!$N$18:$N$20,MATCH(N34,Lists!$M$18:$M$20,0))+IF(K34=5,2,IF(K34>=4,1,0))>=4,3,IF(IF(L34="Yes",2,0)+IF(M34="Yes",1,0)+INDEX(Lists!$N$18:$N$20,MATCH(N34,Lists!$M$18:$M$20,0))+IF(K34=5,2,IF(K34>=4,1,0))>=2,2,1))),IF($O34="Custom",1,MATCH(INDEX('2. Use-Case Library'!$L$5:$L$244,MATCH($O34,'2. Use-Case Library'!$A$5:$A$244,0)),{"Low","Medium","High"},0))),"Low","Medium","High")) | AA34: =IF(X34="","",IF(AND(X34>=$C$4,Y34>=$C$4),"Quick win",IF(X34>=$C$4,"Strategic bet",IF(Y34>=$C$4,"Fill-in","Deprioritise")))) | AB34: =IF(X34="","",ROUND(X34*Y34*IF(Z34="High",0.85,1)*IF(W34="Redesign / standardise first",0.8,1),2)) | AC34: =IF(AB34="","",RANK(AB34,$AB$8:$AB$57)+COUNTIF($AB$7:AB33,AB34)) | AD34: =IF(AH34="","",INDEX(Lists!$AV$2:$AV$5,AH34)) | AE34: =IF(AB34="","",ROUND(G34*12*INDEX(Lists!$F$2:$F$11,MATCH(R34,Lists!$B$2:$B$11,0)),0)) | AF34: =IF(OR(B34="",R34=""),"",IF(O34="Custom",INDEX(Lists!$I$2:$I$11,MATCH(R34,Lists!$B$2:$B$11,0)),INDEX('2. Use-Case Library'!$H$5:$H$244,MATCH($O34,'2. Use-Case Library'!$A$5:$A$244,0)))) | AG34: =IF(OR(B34="",O34="Custom"),"",INDEX('2. Use-Case Library'!$K$5:$K$244,MATCH($O34,'2. Use-Case Library'!$A$5:$A$244,0))) | AH34: =IF(AB34="","",IF(AA34="Deprioritise",4,IF(W34="AI later - close data gap first",3,IF(OR(W34="Redesign / standardise first",W34="Stretch - partner or later stage",AA34="Strategic bet",Z34="High",S34=5),2,1)))) | AI34: =IF(AC34="","",AH34*100+AC34) | AJ34: =IF(B34="","",IF(O34="Custom",B34,INDEX('2. Use-Case Library'!$D$5:$D$244,MATCH($O34,'2. Use-Case Library'!$A$5:$A$244,0))))
A35: 28 | O35: =IF(B35="","",IFERROR(INDEX('2. Use-Case Library'!$A$5:$A$244,MATCH(B35,'2. Use-Case Library'!$M$5:$M$244,0)),"Custom")) | P35: =IF(B35="","",IF(O35="Custom",IF(E35="","(select function in E)",E35),INDEX('2. Use-Case Library'!$C$5:$C$244,MATCH($O35,'2. Use-Case Library'!$A$5:$A$244,0)))) | Q35: =IF(B35="","",IF(D35<>"",D35,IF(O35="Custom","",INDEX('2. Use-Case Library'!$F$5:$F$244,MATCH($O35,'2. Use-Case Library'!$A$5:$A$244,0))))) | R35: =IF(Q35="","",INDEX(Lists!$B$2:$B$11,MATCH(Q35,Lists!$A$2:$A$11,0))) | S35: =IF(R35="","",INDEX(Lists!$C$2:$C$11,MATCH(R35,Lists!$B$2:$B$11,0))) | T35: =IF(R35="","",INDEX(Lists!$D$2:$D$11,MATCH(R35,Lists!$B$2:$B$11,0))) | U35: =IF(OR(R35="",I35=""),"",IF(INDEX(Lists!$N$2:$N$5,MATCH(I35,Lists!$M$2:$M$5,0))>=INDEX(Lists!$E$2:$E$11,MATCH(R35,Lists!$B$2:$B$11,0)),"Data ready","Data gap")) | V35: =IF(R35="","",IF(S35<=IF('1. AI Position'!$C$30="",5,INDEX(Lists!$AI$2:$AI$5,'1. AI Position'!$C$30)),"Within current position","Beyond current position")) | W35: =IF(B35="","",IF(OR(COUNTA(F35:N35)<9,Q35=""),"Complete inputs",IF(H35="No - varies by person / team","Redesign / standardise first",IF(T35="No","Automate - AI not needed",IF(U35="Data gap","AI later - close data gap first",IF(V35="Beyond current position","Stretch - partner or later stage","AI fit now")))))) | X35: =IF(OR(W35="",W35="Complete inputs"),"",ROUND(0.3*INDEX(Lists!$N$8:$N$10,MATCH(F35,Lists!$M$8:$M$10,0))+0.25*IF(G35<20,1,IF(G35<80,2,IF(G35<160,3,IF(G35<480,4,5))))+0.25*J35+0.2*K35,2)) | Y35: =IF(X35="","",ROUND(0.3*IF(U35="Data ready",5,IF(INDEX(Lists!$N$2:$N$5,MATCH(I35,Lists!$M$2:$M$5,0))=INDEX(Lists!$E$2:$E$11,MATCH(R35,Lists!$B$2:$B$11,0))-1,3,1))+0.25*INDEX(Lists!$N$13:$N$15,MATCH(H35,Lists!$M$13:$M$15,0))+0.25*(6-S35)+0.2*IF(V35="Within current position",5,2),2)) | Z35: =IF(X35="","",CHOOSE(MAX(IF(T35="No",IF(L35="Yes",2,1),IF(IF(L35="Yes",2,0)+IF(M35="Yes",1,0)+INDEX(Lists!$N$18:$N$20,MATCH(N35,Lists!$M$18:$M$20,0))+IF(K35=5,2,IF(K35>=4,1,0))>=4,3,IF(IF(L35="Yes",2,0)+IF(M35="Yes",1,0)+INDEX(Lists!$N$18:$N$20,MATCH(N35,Lists!$M$18:$M$20,0))+IF(K35=5,2,IF(K35>=4,1,0))>=2,2,1))),IF($O35="Custom",1,MATCH(INDEX('2. Use-Case Library'!$L$5:$L$244,MATCH($O35,'2. Use-Case Library'!$A$5:$A$244,0)),{"Low","Medium","High"},0))),"Low","Medium","High")) | AA35: =IF(X35="","",IF(AND(X35>=$C$4,Y35>=$C$4),"Quick win",IF(X35>=$C$4,"Strategic bet",IF(Y35>=$C$4,"Fill-in","Deprioritise")))) | AB35: =IF(X35="","",ROUND(X35*Y35*IF(Z35="High",0.85,1)*IF(W35="Redesign / standardise first",0.8,1),2)) | AC35: =IF(AB35="","",RANK(AB35,$AB$8:$AB$57)+COUNTIF($AB$7:AB34,AB35)) | AD35: =IF(AH35="","",INDEX(Lists!$AV$2:$AV$5,AH35)) | AE35: =IF(AB35="","",ROUND(G35*12*INDEX(Lists!$F$2:$F$11,MATCH(R35,Lists!$B$2:$B$11,0)),0)) | AF35: =IF(OR(B35="",R35=""),"",IF(O35="Custom",INDEX(Lists!$I$2:$I$11,MATCH(R35,Lists!$B$2:$B$11,0)),INDEX('2. Use-Case Library'!$H$5:$H$244,MATCH($O35,'2. Use-Case Library'!$A$5:$A$244,0)))) | AG35: =IF(OR(B35="",O35="Custom"),"",INDEX('2. Use-Case Library'!$K$5:$K$244,MATCH($O35,'2. Use-Case Library'!$A$5:$A$244,0))) | AH35: =IF(AB35="","",IF(AA35="Deprioritise",4,IF(W35="AI later - close data gap first",3,IF(OR(W35="Redesign / standardise first",W35="Stretch - partner or later stage",AA35="Strategic bet",Z35="High",S35=5),2,1)))) | AI35: =IF(AC35="","",AH35*100+AC35) | AJ35: =IF(B35="","",IF(O35="Custom",B35,INDEX('2. Use-Case Library'!$D$5:$D$244,MATCH($O35,'2. Use-Case Library'!$A$5:$A$244,0))))
A36: 29 | O36: =IF(B36="","",IFERROR(INDEX('2. Use-Case Library'!$A$5:$A$244,MATCH(B36,'2. Use-Case Library'!$M$5:$M$244,0)),"Custom")) | P36: =IF(B36="","",IF(O36="Custom",IF(E36="","(select function in E)",E36),INDEX('2. Use-Case Library'!$C$5:$C$244,MATCH($O36,'2. Use-Case Library'!$A$5:$A$244,0)))) | Q36: =IF(B36="","",IF(D36<>"",D36,IF(O36="Custom","",INDEX('2. Use-Case Library'!$F$5:$F$244,MATCH($O36,'2. Use-Case Library'!$A$5:$A$244,0))))) | R36: =IF(Q36="","",INDEX(Lists!$B$2:$B$11,MATCH(Q36,Lists!$A$2:$A$11,0))) | S36: =IF(R36="","",INDEX(Lists!$C$2:$C$11,MATCH(R36,Lists!$B$2:$B$11,0))) | T36: =IF(R36="","",INDEX(Lists!$D$2:$D$11,MATCH(R36,Lists!$B$2:$B$11,0))) | U36: =IF(OR(R36="",I36=""),"",IF(INDEX(Lists!$N$2:$N$5,MATCH(I36,Lists!$M$2:$M$5,0))>=INDEX(Lists!$E$2:$E$11,MATCH(R36,Lists!$B$2:$B$11,0)),"Data ready","Data gap")) | V36: =IF(R36="","",IF(S36<=IF('1. AI Position'!$C$30="",5,INDEX(Lists!$AI$2:$AI$5,'1. AI Position'!$C$30)),"Within current position","Beyond current position")) | W36: =IF(B36="","",IF(OR(COUNTA(F36:N36)<9,Q36=""),"Complete inputs",IF(H36="No - varies by person / team","Redesign / standardise first",IF(T36="No","Automate - AI not needed",IF(U36="Data gap","AI later - close data gap first",IF(V36="Beyond current position","Stretch - partner or later stage","AI fit now")))))) | X36: =IF(OR(W36="",W36="Complete inputs"),"",ROUND(0.3*INDEX(Lists!$N$8:$N$10,MATCH(F36,Lists!$M$8:$M$10,0))+0.25*IF(G36<20,1,IF(G36<80,2,IF(G36<160,3,IF(G36<480,4,5))))+0.25*J36+0.2*K36,2)) | Y36: =IF(X36="","",ROUND(0.3*IF(U36="Data ready",5,IF(INDEX(Lists!$N$2:$N$5,MATCH(I36,Lists!$M$2:$M$5,0))=INDEX(Lists!$E$2:$E$11,MATCH(R36,Lists!$B$2:$B$11,0))-1,3,1))+0.25*INDEX(Lists!$N$13:$N$15,MATCH(H36,Lists!$M$13:$M$15,0))+0.25*(6-S36)+0.2*IF(V36="Within current position",5,2),2)) | Z36: =IF(X36="","",CHOOSE(MAX(IF(T36="No",IF(L36="Yes",2,1),IF(IF(L36="Yes",2,0)+IF(M36="Yes",1,0)+INDEX(Lists!$N$18:$N$20,MATCH(N36,Lists!$M$18:$M$20,0))+IF(K36=5,2,IF(K36>=4,1,0))>=4,3,IF(IF(L36="Yes",2,0)+IF(M36="Yes",1,0)+INDEX(Lists!$N$18:$N$20,MATCH(N36,Lists!$M$18:$M$20,0))+IF(K36=5,2,IF(K36>=4,1,0))>=2,2,1))),IF($O36="Custom",1,MATCH(INDEX('2. Use-Case Library'!$L$5:$L$244,MATCH($O36,'2. Use-Case Library'!$A$5:$A$244,0)),{"Low","Medium","High"},0))),"Low","Medium","High")) | AA36: =IF(X36="","",IF(AND(X36>=$C$4,Y36>=$C$4),"Quick win",IF(X36>=$C$4,"Strategic bet",IF(Y36>=$C$4,"Fill-in","Deprioritise")))) | AB36: =IF(X36="","",ROUND(X36*Y36*IF(Z36="High",0.85,1)*IF(W36="Redesign / standardise first",0.8,1),2)) | AC36: =IF(AB36="","",RANK(AB36,$AB$8:$AB$57)+COUNTIF($AB$7:AB35,AB36)) | AD36: =IF(AH36="","",INDEX(Lists!$AV$2:$AV$5,AH36)) | AE36: =IF(AB36="","",ROUND(G36*12*INDEX(Lists!$F$2:$F$11,MATCH(R36,Lists!$B$2:$B$11,0)),0)) | AF36: =IF(OR(B36="",R36=""),"",IF(O36="Custom",INDEX(Lists!$I$2:$I$11,MATCH(R36,Lists!$B$2:$B$11,0)),INDEX('2. Use-Case Library'!$H$5:$H$244,MATCH($O36,'2. Use-Case Library'!$A$5:$A$244,0)))) | AG36: =IF(OR(B36="",O36="Custom"),"",INDEX('2. Use-Case Library'!$K$5:$K$244,MATCH($O36,'2. Use-Case Library'!$A$5:$A$244,0))) | AH36: =IF(AB36="","",IF(AA36="Deprioritise",4,IF(W36="AI later - close data gap first",3,IF(OR(W36="Redesign / standardise first",W36="Stretch - partner or later stage",AA36="Strategic bet",Z36="High",S36=5),2,1)))) | AI36: =IF(AC36="","",AH36*100+AC36) | AJ36: =IF(B36="","",IF(O36="Custom",B36,INDEX('2. Use-Case Library'!$D$5:$D$244,MATCH($O36,'2. Use-Case Library'!$A$5:$A$244,0))))
A37: 30 | O37: =IF(B37="","",IFERROR(INDEX('2. Use-Case Library'!$A$5:$A$244,MATCH(B37,'2. Use-Case Library'!$M$5:$M$244,0)),"Custom")) | P37: =IF(B37="","",IF(O37="Custom",IF(E37="","(select function in E)",E37),INDEX('2. Use-Case Library'!$C$5:$C$244,MATCH($O37,'2. Use-Case Library'!$A$5:$A$244,0)))) | Q37: =IF(B37="","",IF(D37<>"",D37,IF(O37="Custom","",INDEX('2. Use-Case Library'!$F$5:$F$244,MATCH($O37,'2. Use-Case Library'!$A$5:$A$244,0))))) | R37: =IF(Q37="","",INDEX(Lists!$B$2:$B$11,MATCH(Q37,Lists!$A$2:$A$11,0))) | S37: =IF(R37="","",INDEX(Lists!$C$2:$C$11,MATCH(R37,Lists!$B$2:$B$11,0))) | T37: =IF(R37="","",INDEX(Lists!$D$2:$D$11,MATCH(R37,Lists!$B$2:$B$11,0))) | U37: =IF(OR(R37="",I37=""),"",IF(INDEX(Lists!$N$2:$N$5,MATCH(I37,Lists!$M$2:$M$5,0))>=INDEX(Lists!$E$2:$E$11,MATCH(R37,Lists!$B$2:$B$11,0)),"Data ready","Data gap")) | V37: =IF(R37="","",IF(S37<=IF('1. AI Position'!$C$30="",5,INDEX(Lists!$AI$2:$AI$5,'1. AI Position'!$C$30)),"Within current position","Beyond current position")) | W37: =IF(B37="","",IF(OR(COUNTA(F37:N37)<9,Q37=""),"Complete inputs",IF(H37="No - varies by person / team","Redesign / standardise first",IF(T37="No","Automate - AI not needed",IF(U37="Data gap","AI later - close data gap first",IF(V37="Beyond current position","Stretch - partner or later stage","AI fit now")))))) | X37: =IF(OR(W37="",W37="Complete inputs"),"",ROUND(0.3*INDEX(Lists!$N$8:$N$10,MATCH(F37,Lists!$M$8:$M$10,0))+0.25*IF(G37<20,1,IF(G37<80,2,IF(G37<160,3,IF(G37<480,4,5))))+0.25*J37+0.2*K37,2)) | Y37: =IF(X37="","",ROUND(0.3*IF(U37="Data ready",5,IF(INDEX(Lists!$N$2:$N$5,MATCH(I37,Lists!$M$2:$M$5,0))=INDEX(Lists!$E$2:$E$11,MATCH(R37,Lists!$B$2:$B$11,0))-1,3,1))+0.25*INDEX(Lists!$N$13:$N$15,MATCH(H37,Lists!$M$13:$M$15,0))+0.25*(6-S37)+0.2*IF(V37="Within current position",5,2),2)) | Z37: =IF(X37="","",CHOOSE(MAX(IF(T37="No",IF(L37="Yes",2,1),IF(IF(L37="Yes",2,0)+IF(M37="Yes",1,0)+INDEX(Lists!$N$18:$N$20,MATCH(N37,Lists!$M$18:$M$20,0))+IF(K37=5,2,IF(K37>=4,1,0))>=4,3,IF(IF(L37="Yes",2,0)+IF(M37="Yes",1,0)+INDEX(Lists!$N$18:$N$20,MATCH(N37,Lists!$M$18:$M$20,0))+IF(K37=5,2,IF(K37>=4,1,0))>=2,2,1))),IF($O37="Custom",1,MATCH(INDEX('2. Use-Case Library'!$L$5:$L$244,MATCH($O37,'2. Use-Case Library'!$A$5:$A$244,0)),{"Low","Medium","High"},0))),"Low","Medium","High")) | AA37: =IF(X37="","",IF(AND(X37>=$C$4,Y37>=$C$4),"Quick win",IF(X37>=$C$4,"Strategic bet",IF(Y37>=$C$4,"Fill-in","Deprioritise")))) | AB37: =IF(X37="","",ROUND(X37*Y37*IF(Z37="High",0.85,1)*IF(W37="Redesign / standardise first",0.8,1),2)) | AC37: =IF(AB37="","",RANK(AB37,$AB$8:$AB$57)+COUNTIF($AB$7:AB36,AB37)) | AD37: =IF(AH37="","",INDEX(Lists!$AV$2:$AV$5,AH37)) | AE37: =IF(AB37="","",ROUND(G37*12*INDEX(Lists!$F$2:$F$11,MATCH(R37,Lists!$B$2:$B$11,0)),0)) | AF37: =IF(OR(B37="",R37=""),"",IF(O37="Custom",INDEX(Lists!$I$2:$I$11,MATCH(R37,Lists!$B$2:$B$11,0)),INDEX('2. Use-Case Library'!$H$5:$H$244,MATCH($O37,'2. Use-Case Library'!$A$5:$A$244,0)))) | AG37: =IF(OR(B37="",O37="Custom"),"",INDEX('2. Use-Case Library'!$K$5:$K$244,MATCH($O37,'2. Use-Case Library'!$A$5:$A$244,0))) | AH37: =IF(AB37="","",IF(AA37="Deprioritise",4,IF(W37="AI later - close data gap first",3,IF(OR(W37="Redesign / standardise first",W37="Stretch - partner or later stage",AA37="Strategic bet",Z37="High",S37=5),2,1)))) | AI37: =IF(AC37="","",AH37*100+AC37) | AJ37: =IF(B37="","",IF(O37="Custom",B37,INDEX('2. Use-Case Library'!$D$5:$D$244,MATCH($O37,'2. Use-Case Library'!$A$5:$A$244,0))))
A38: 31 | O38: =IF(B38="","",IFERROR(INDEX('2. Use-Case Library'!$A$5:$A$244,MATCH(B38,'2. Use-Case Library'!$M$5:$M$244,0)),"Custom")) | P38: =IF(B38="","",IF(O38="Custom",IF(E38="","(select function in E)",E38),INDEX('2. Use-Case Library'!$C$5:$C$244,MATCH($O38,'2. Use-Case Library'!$A$5:$A$244,0)))) | Q38: =IF(B38="","",IF(D38<>"",D38,IF(O38="Custom","",INDEX('2. Use-Case Library'!$F$5:$F$244,MATCH($O38,'2. Use-Case Library'!$A$5:$A$244,0))))) | R38: =IF(Q38="","",INDEX(Lists!$B$2:$B$11,MATCH(Q38,Lists!$A$2:$A$11,0))) | S38: =IF(R38="","",INDEX(Lists!$C$2:$C$11,MATCH(R38,Lists!$B$2:$B$11,0))) | T38: =IF(R38="","",INDEX(Lists!$D$2:$D$11,MATCH(R38,Lists!$B$2:$B$11,0))) | U38: =IF(OR(R38="",I38=""),"",IF(INDEX(Lists!$N$2:$N$5,MATCH(I38,Lists!$M$2:$M$5,0))>=INDEX(Lists!$E$2:$E$11,MATCH(R38,Lists!$B$2:$B$11,0)),"Data ready","Data gap")) | V38: =IF(R38="","",IF(S38<=IF('1. AI Position'!$C$30="",5,INDEX(Lists!$AI$2:$AI$5,'1. AI Position'!$C$30)),"Within current position","Beyond current position")) | W38: =IF(B38="","",IF(OR(COUNTA(F38:N38)<9,Q38=""),"Complete inputs",IF(H38="No - varies by person / team","Redesign / standardise first",IF(T38="No","Automate - AI not needed",IF(U38="Data gap","AI later - close data gap first",IF(V38="Beyond current position","Stretch - partner or later stage","AI fit now")))))) | X38: =IF(OR(W38="",W38="Complete inputs"),"",ROUND(0.3*INDEX(Lists!$N$8:$N$10,MATCH(F38,Lists!$M$8:$M$10,0))+0.25*IF(G38<20,1,IF(G38<80,2,IF(G38<160,3,IF(G38<480,4,5))))+0.25*J38+0.2*K38,2)) | Y38: =IF(X38="","",ROUND(0.3*IF(U38="Data ready",5,IF(INDEX(Lists!$N$2:$N$5,MATCH(I38,Lists!$M$2:$M$5,0))=INDEX(Lists!$E$2:$E$11,MATCH(R38,Lists!$B$2:$B$11,0))-1,3,1))+0.25*INDEX(Lists!$N$13:$N$15,MATCH(H38,Lists!$M$13:$M$15,0))+0.25*(6-S38)+0.2*IF(V38="Within current position",5,2),2)) | Z38: =IF(X38="","",CHOOSE(MAX(IF(T38="No",IF(L38="Yes",2,1),IF(IF(L38="Yes",2,0)+IF(M38="Yes",1,0)+INDEX(Lists!$N$18:$N$20,MATCH(N38,Lists!$M$18:$M$20,0))+IF(K38=5,2,IF(K38>=4,1,0))>=4,3,IF(IF(L38="Yes",2,0)+IF(M38="Yes",1,0)+INDEX(Lists!$N$18:$N$20,MATCH(N38,Lists!$M$18:$M$20,0))+IF(K38=5,2,IF(K38>=4,1,0))>=2,2,1))),IF($O38="Custom",1,MATCH(INDEX('2. Use-Case Library'!$L$5:$L$244,MATCH($O38,'2. Use-Case Library'!$A$5:$A$244,0)),{"Low","Medium","High"},0))),"Low","Medium","High")) | AA38: =IF(X38="","",IF(AND(X38>=$C$4,Y38>=$C$4),"Quick win",IF(X38>=$C$4,"Strategic bet",IF(Y38>=$C$4,"Fill-in","Deprioritise")))) | AB38: =IF(X38="","",ROUND(X38*Y38*IF(Z38="High",0.85,1)*IF(W38="Redesign / standardise first",0.8,1),2)) | AC38: =IF(AB38="","",RANK(AB38,$AB$8:$AB$57)+COUNTIF($AB$7:AB37,AB38)) | AD38: =IF(AH38="","",INDEX(Lists!$AV$2:$AV$5,AH38)) | AE38: =IF(AB38="","",ROUND(G38*12*INDEX(Lists!$F$2:$F$11,MATCH(R38,Lists!$B$2:$B$11,0)),0)) | AF38: =IF(OR(B38="",R38=""),"",IF(O38="Custom",INDEX(Lists!$I$2:$I$11,MATCH(R38,Lists!$B$2:$B$11,0)),INDEX('2. Use-Case Library'!$H$5:$H$244,MATCH($O38,'2. Use-Case Library'!$A$5:$A$244,0)))) | AG38: =IF(OR(B38="",O38="Custom"),"",INDEX('2. Use-Case Library'!$K$5:$K$244,MATCH($O38,'2. Use-Case Library'!$A$5:$A$244,0))) | AH38: =IF(AB38="","",IF(AA38="Deprioritise",4,IF(W38="AI later - close data gap first",3,IF(OR(W38="Redesign / standardise first",W38="Stretch - partner or later stage",AA38="Strategic bet",Z38="High",S38=5),2,1)))) | AI38: =IF(AC38="","",AH38*100+AC38) | AJ38: =IF(B38="","",IF(O38="Custom",B38,INDEX('2. Use-Case Library'!$D$5:$D$244,MATCH($O38,'2. Use-Case Library'!$A$5:$A$244,0))))
A39: 32 | O39: =IF(B39="","",IFERROR(INDEX('2. Use-Case Library'!$A$5:$A$244,MATCH(B39,'2. Use-Case Library'!$M$5:$M$244,0)),"Custom")) | P39: =IF(B39="","",IF(O39="Custom",IF(E39="","(select function in E)",E39),INDEX('2. Use-Case Library'!$C$5:$C$244,MATCH($O39,'2. Use-Case Library'!$A$5:$A$244,0)))) | Q39: =IF(B39="","",IF(D39<>"",D39,IF(O39="Custom","",INDEX('2. Use-Case Library'!$F$5:$F$244,MATCH($O39,'2. Use-Case Library'!$A$5:$A$244,0))))) | R39: =IF(Q39="","",INDEX(Lists!$B$2:$B$11,MATCH(Q39,Lists!$A$2:$A$11,0))) | S39: =IF(R39="","",INDEX(Lists!$C$2:$C$11,MATCH(R39,Lists!$B$2:$B$11,0))) | T39: =IF(R39="","",INDEX(Lists!$D$2:$D$11,MATCH(R39,Lists!$B$2:$B$11,0))) | U39: =IF(OR(R39="",I39=""),"",IF(INDEX(Lists!$N$2:$N$5,MATCH(I39,Lists!$M$2:$M$5,0))>=INDEX(Lists!$E$2:$E$11,MATCH(R39,Lists!$B$2:$B$11,0)),"Data ready","Data gap")) | V39: =IF(R39="","",IF(S39<=IF('1. AI Position'!$C$30="",5,INDEX(Lists!$AI$2:$AI$5,'1. AI Position'!$C$30)),"Within current position","Beyond current position")) | W39: =IF(B39="","",IF(OR(COUNTA(F39:N39)<9,Q39=""),"Complete inputs",IF(H39="No - varies by person / team","Redesign / standardise first",IF(T39="No","Automate - AI not needed",IF(U39="Data gap","AI later - close data gap first",IF(V39="Beyond current position","Stretch - partner or later stage","AI fit now")))))) | X39: =IF(OR(W39="",W39="Complete inputs"),"",ROUND(0.3*INDEX(Lists!$N$8:$N$10,MATCH(F39,Lists!$M$8:$M$10,0))+0.25*IF(G39<20,1,IF(G39<80,2,IF(G39<160,3,IF(G39<480,4,5))))+0.25*J39+0.2*K39,2)) | Y39: =IF(X39="","",ROUND(0.3*IF(U39="Data ready",5,IF(INDEX(Lists!$N$2:$N$5,MATCH(I39,Lists!$M$2:$M$5,0))=INDEX(Lists!$E$2:$E$11,MATCH(R39,Lists!$B$2:$B$11,0))-1,3,1))+0.25*INDEX(Lists!$N$13:$N$15,MATCH(H39,Lists!$M$13:$M$15,0))+0.25*(6-S39)+0.2*IF(V39="Within current position",5,2),2)) | Z39: =IF(X39="","",CHOOSE(MAX(IF(T39="No",IF(L39="Yes",2,1),IF(IF(L39="Yes",2,0)+IF(M39="Yes",1,0)+INDEX(Lists!$N$18:$N$20,MATCH(N39,Lists!$M$18:$M$20,0))+IF(K39=5,2,IF(K39>=4,1,0))>=4,3,IF(IF(L39="Yes",2,0)+IF(M39="Yes",1,0)+INDEX(Lists!$N$18:$N$20,MATCH(N39,Lists!$M$18:$M$20,0))+IF(K39=5,2,IF(K39>=4,1,0))>=2,2,1))),IF($O39="Custom",1,MATCH(INDEX('2. Use-Case Library'!$L$5:$L$244,MATCH($O39,'2. Use-Case Library'!$A$5:$A$244,0)),{"Low","Medium","High"},0))),"Low","Medium","High")) | AA39: =IF(X39="","",IF(AND(X39>=$C$4,Y39>=$C$4),"Quick win",IF(X39>=$C$4,"Strategic bet",IF(Y39>=$C$4,"Fill-in","Deprioritise")))) | AB39: =IF(X39="","",ROUND(X39*Y39*IF(Z39="High",0.85,1)*IF(W39="Redesign / standardise first",0.8,1),2)) | AC39: =IF(AB39="","",RANK(AB39,$AB$8:$AB$57)+COUNTIF($AB$7:AB38,AB39)) | AD39: =IF(AH39="","",INDEX(Lists!$AV$2:$AV$5,AH39)) | AE39: =IF(AB39="","",ROUND(G39*12*INDEX(Lists!$F$2:$F$11,MATCH(R39,Lists!$B$2:$B$11,0)),0)) | AF39: =IF(OR(B39="",R39=""),"",IF(O39="Custom",INDEX(Lists!$I$2:$I$11,MATCH(R39,Lists!$B$2:$B$11,0)),INDEX('2. Use-Case Library'!$H$5:$H$244,MATCH($O39,'2. Use-Case Library'!$A$5:$A$244,0)))) | AG39: =IF(OR(B39="",O39="Custom"),"",INDEX('2. Use-Case Library'!$K$5:$K$244,MATCH($O39,'2. Use-Case Library'!$A$5:$A$244,0))) | AH39: =IF(AB39="","",IF(AA39="Deprioritise",4,IF(W39="AI later - close data gap first",3,IF(OR(W39="Redesign / standardise first",W39="Stretch - partner or later stage",AA39="Strategic bet",Z39="High",S39=5),2,1)))) | AI39: =IF(AC39="","",AH39*100+AC39) | AJ39: =IF(B39="","",IF(O39="Custom",B39,INDEX('2. Use-Case Library'!$D$5:$D$244,MATCH($O39,'2. Use-Case Library'!$A$5:$A$244,0))))
A40: 33 | O40: =IF(B40="","",IFERROR(INDEX('2. Use-Case Library'!$A$5:$A$244,MATCH(B40,'2. Use-Case Library'!$M$5:$M$244,0)),"Custom")) | P40: =IF(B40="","",IF(O40="Custom",IF(E40="","(select function in E)",E40),INDEX('2. Use-Case Library'!$C$5:$C$244,MATCH($O40,'2. Use-Case Library'!$A$5:$A$244,0)))) | Q40: =IF(B40="","",IF(D40<>"",D40,IF(O40="Custom","",INDEX('2. Use-Case Library'!$F$5:$F$244,MATCH($O40,'2. Use-Case Library'!$A$5:$A$244,0))))) | R40: =IF(Q40="","",INDEX(Lists!$B$2:$B$11,MATCH(Q40,Lists!$A$2:$A$11,0))) | S40: =IF(R40="","",INDEX(Lists!$C$2:$C$11,MATCH(R40,Lists!$B$2:$B$11,0))) | T40: =IF(R40="","",INDEX(Lists!$D$2:$D$11,MATCH(R40,Lists!$B$2:$B$11,0))) | U40: =IF(OR(R40="",I40=""),"",IF(INDEX(Lists!$N$2:$N$5,MATCH(I40,Lists!$M$2:$M$5,0))>=INDEX(Lists!$E$2:$E$11,MATCH(R40,Lists!$B$2:$B$11,0)),"Data ready","Data gap")) | V40: =IF(R40="","",IF(S40<=IF('1. AI Position'!$C$30="",5,INDEX(Lists!$AI$2:$AI$5,'1. AI Position'!$C$30)),"Within current position","Beyond current position")) | W40: =IF(B40="","",IF(OR(COUNTA(F40:N40)<9,Q40=""),"Complete inputs",IF(H40="No - varies by person / team","Redesign / standardise first",IF(T40="No","Automate - AI not needed",IF(U40="Data gap","AI later - close data gap first",IF(V40="Beyond current position","Stretch - partner or later stage","AI fit now")))))) | X40: =IF(OR(W40="",W40="Complete inputs"),"",ROUND(0.3*INDEX(Lists!$N$8:$N$10,MATCH(F40,Lists!$M$8:$M$10,0))+0.25*IF(G40<20,1,IF(G40<80,2,IF(G40<160,3,IF(G40<480,4,5))))+0.25*J40+0.2*K40,2)) | Y40: =IF(X40="","",ROUND(0.3*IF(U40="Data ready",5,IF(INDEX(Lists!$N$2:$N$5,MATCH(I40,Lists!$M$2:$M$5,0))=INDEX(Lists!$E$2:$E$11,MATCH(R40,Lists!$B$2:$B$11,0))-1,3,1))+0.25*INDEX(Lists!$N$13:$N$15,MATCH(H40,Lists!$M$13:$M$15,0))+0.25*(6-S40)+0.2*IF(V40="Within current position",5,2),2)) | Z40: =IF(X40="","",CHOOSE(MAX(IF(T40="No",IF(L40="Yes",2,1),IF(IF(L40="Yes",2,0)+IF(M40="Yes",1,0)+INDEX(Lists!$N$18:$N$20,MATCH(N40,Lists!$M$18:$M$20,0))+IF(K40=5,2,IF(K40>=4,1,0))>=4,3,IF(IF(L40="Yes",2,0)+IF(M40="Yes",1,0)+INDEX(Lists!$N$18:$N$20,MATCH(N40,Lists!$M$18:$M$20,0))+IF(K40=5,2,IF(K40>=4,1,0))>=2,2,1))),IF($O40="Custom",1,MATCH(INDEX('2. Use-Case Library'!$L$5:$L$244,MATCH($O40,'2. Use-Case Library'!$A$5:$A$244,0)),{"Low","Medium","High"},0))),"Low","Medium","High")) | AA40: =IF(X40="","",IF(AND(X40>=$C$4,Y40>=$C$4),"Quick win",IF(X40>=$C$4,"Strategic bet",IF(Y40>=$C$4,"Fill-in","Deprioritise")))) | AB40: =IF(X40="","",ROUND(X40*Y40*IF(Z40="High",0.85,1)*IF(W40="Redesign / standardise first",0.8,1),2)) | AC40: =IF(AB40="","",RANK(AB40,$AB$8:$AB$57)+COUNTIF($AB$7:AB39,AB40)) | AD40: =IF(AH40="","",INDEX(Lists!$AV$2:$AV$5,AH40)) | AE40: =IF(AB40="","",ROUND(G40*12*INDEX(Lists!$F$2:$F$11,MATCH(R40,Lists!$B$2:$B$11,0)),0)) | AF40: =IF(OR(B40="",R40=""),"",IF(O40="Custom",INDEX(Lists!$I$2:$I$11,MATCH(R40,Lists!$B$2:$B$11,0)),INDEX('2. Use-Case Library'!$H$5:$H$244,MATCH($O40,'2. Use-Case Library'!$A$5:$A$244,0)))) | AG40: =IF(OR(B40="",O40="Custom"),"",INDEX('2. Use-Case Library'!$K$5:$K$244,MATCH($O40,'2. Use-Case Library'!$A$5:$A$244,0))) | AH40: =IF(AB40="","",IF(AA40="Deprioritise",4,IF(W40="AI later - close data gap first",3,IF(OR(W40="Redesign / standardise first",W40="Stretch - partner or later stage",AA40="Strategic bet",Z40="High",S40=5),2,1)))) | AI40: =IF(AC40="","",AH40*100+AC40) | AJ40: =IF(B40="","",IF(O40="Custom",B40,INDEX('2. Use-Case Library'!$D$5:$D$244,MATCH($O40,'2. Use-Case Library'!$A$5:$A$244,0))))
A41: 34 | O41: =IF(B41="","",IFERROR(INDEX('2. Use-Case Library'!$A$5:$A$244,MATCH(B41,'2. Use-Case Library'!$M$5:$M$244,0)),"Custom")) | P41: =IF(B41="","",IF(O41="Custom",IF(E41="","(select function in E)",E41),INDEX('2. Use-Case Library'!$C$5:$C$244,MATCH($O41,'2. Use-Case Library'!$A$5:$A$244,0)))) | Q41: =IF(B41="","",IF(D41<>"",D41,IF(O41="Custom","",INDEX('2. Use-Case Library'!$F$5:$F$244,MATCH($O41,'2. Use-Case Library'!$A$5:$A$244,0))))) | R41: =IF(Q41="","",INDEX(Lists!$B$2:$B$11,MATCH(Q41,Lists!$A$2:$A$11,0))) | S41: =IF(R41="","",INDEX(Lists!$C$2:$C$11,MATCH(R41,Lists!$B$2:$B$11,0))) | T41: =IF(R41="","",INDEX(Lists!$D$2:$D$11,MATCH(R41,Lists!$B$2:$B$11,0))) | U41: =IF(OR(R41="",I41=""),"",IF(INDEX(Lists!$N$2:$N$5,MATCH(I41,Lists!$M$2:$M$5,0))>=INDEX(Lists!$E$2:$E$11,MATCH(R41,Lists!$B$2:$B$11,0)),"Data ready","Data gap")) | V41: =IF(R41="","",IF(S41<=IF('1. AI Position'!$C$30="",5,INDEX(Lists!$AI$2:$AI$5,'1. AI Position'!$C$30)),"Within current position","Beyond current position")) | W41: =IF(B41="","",IF(OR(COUNTA(F41:N41)<9,Q41=""),"Complete inputs",IF(H41="No - varies by person / team","Redesign / standardise first",IF(T41="No","Automate - AI not needed",IF(U41="Data gap","AI later - close data gap first",IF(V41="Beyond current position","Stretch - partner or later stage","AI fit now")))))) | X41: =IF(OR(W41="",W41="Complete inputs"),"",ROUND(0.3*INDEX(Lists!$N$8:$N$10,MATCH(F41,Lists!$M$8:$M$10,0))+0.25*IF(G41<20,1,IF(G41<80,2,IF(G41<160,3,IF(G41<480,4,5))))+0.25*J41+0.2*K41,2)) | Y41: =IF(X41="","",ROUND(0.3*IF(U41="Data ready",5,IF(INDEX(Lists!$N$2:$N$5,MATCH(I41,Lists!$M$2:$M$5,0))=INDEX(Lists!$E$2:$E$11,MATCH(R41,Lists!$B$2:$B$11,0))-1,3,1))+0.25*INDEX(Lists!$N$13:$N$15,MATCH(H41,Lists!$M$13:$M$15,0))+0.25*(6-S41)+0.2*IF(V41="Within current position",5,2),2)) | Z41: =IF(X41="","",CHOOSE(MAX(IF(T41="No",IF(L41="Yes",2,1),IF(IF(L41="Yes",2,0)+IF(M41="Yes",1,0)+INDEX(Lists!$N$18:$N$20,MATCH(N41,Lists!$M$18:$M$20,0))+IF(K41=5,2,IF(K41>=4,1,0))>=4,3,IF(IF(L41="Yes",2,0)+IF(M41="Yes",1,0)+INDEX(Lists!$N$18:$N$20,MATCH(N41,Lists!$M$18:$M$20,0))+IF(K41=5,2,IF(K41>=4,1,0))>=2,2,1))),IF($O41="Custom",1,MATCH(INDEX('2. Use-Case Library'!$L$5:$L$244,MATCH($O41,'2. Use-Case Library'!$A$5:$A$244,0)),{"Low","Medium","High"},0))),"Low","Medium","High")) | AA41: =IF(X41="","",IF(AND(X41>=$C$4,Y41>=$C$4),"Quick win",IF(X41>=$C$4,"Strategic bet",IF(Y41>=$C$4,"Fill-in","Deprioritise")))) | AB41: =IF(X41="","",ROUND(X41*Y41*IF(Z41="High",0.85,1)*IF(W41="Redesign / standardise first",0.8,1),2)) | AC41: =IF(AB41="","",RANK(AB41,$AB$8:$AB$57)+COUNTIF($AB$7:AB40,AB41)) | AD41: =IF(AH41="","",INDEX(Lists!$AV$2:$AV$5,AH41)) | AE41: =IF(AB41="","",ROUND(G41*12*INDEX(Lists!$F$2:$F$11,MATCH(R41,Lists!$B$2:$B$11,0)),0)) | AF41: =IF(OR(B41="",R41=""),"",IF(O41="Custom",INDEX(Lists!$I$2:$I$11,MATCH(R41,Lists!$B$2:$B$11,0)),INDEX('2. Use-Case Library'!$H$5:$H$244,MATCH($O41,'2. Use-Case Library'!$A$5:$A$244,0)))) | AG41: =IF(OR(B41="",O41="Custom"),"",INDEX('2. Use-Case Library'!$K$5:$K$244,MATCH($O41,'2. Use-Case Library'!$A$5:$A$244,0))) | AH41: =IF(AB41="","",IF(AA41="Deprioritise",4,IF(W41="AI later - close data gap first",3,IF(OR(W41="Redesign / standardise first",W41="Stretch - partner or later stage",AA41="Strategic bet",Z41="High",S41=5),2,1)))) | AI41: =IF(AC41="","",AH41*100+AC41) | AJ41: =IF(B41="","",IF(O41="Custom",B41,INDEX('2. Use-Case Library'!$D$5:$D$244,MATCH($O41,'2. Use-Case Library'!$A$5:$A$244,0))))
... A57: 50 | O57: =IF(B57="","",IFERROR(INDEX('2. Use-Case Library'!$A$5:$A$244,MATCH(B57,'2. Use-Case Library'!$M$5:$M$244,0)),"Custom")) | P57: =IF(B57="","",IF(O57="Custom",IF(E57="","(select function in E)",E57),INDEX('2. Use-Case Library'!$C$5:$C$244,MATCH($O57,'2. Use-Case Library'!$A$5:$A$244,0)))) | Q57: =IF(B57="","",IF(D57<>"",D57,IF(O57="Custom","",INDEX('2. Use-Case Library'!$F$5:$F$244,MATCH($O57,'2. Use-Case Library'!$A$5:$A$244,0))))) | R57: =IF(Q57="","",INDEX(Lists!$B$2:$B$11,MATCH(Q57,Lists!$A$2:$A$11,0))) | S57: =IF(R57="","",INDEX(Lists!$C$2:$C$11,MATCH(R57,Lists!$B$2:$B$11,0))) | T57: =IF(R57="","",INDEX(Lists!$D$2:$D$11,MATCH(R57,Lists!$B$2:$B$11,0))) | U57: =IF(OR(R57="",I57=""),"",IF(INDEX(Lists!$N$2:$N$5,MATCH(I57,Lists!$M$2:$M$5,0))>=INDEX(Lists!$E$2:$E$11,MATCH(R57,Lists!$B$2:$B$11,0)),"Data ready","Data gap")) | V57: =IF(R57="","",IF(S57<=IF('1. AI Position'!$C$30="",5,INDEX(Lists!$AI$2:$AI$5,'1. AI Position'!$C$30)),"Within current position","Beyond current position")) | W57: =IF(B57="","",IF(OR(COUNTA(F57:N57)<9,Q57=""),"Complete inputs",IF(H57="No - varies by person / team","Redesign / standardise first",IF(T57="No","Automate - AI not needed",IF(U57="Data gap","AI later - close data gap first",IF(V57="Beyond current position","Stretch - partner or later stage","AI fit now")))))) | X57: =IF(OR(W57="",W57="Complete inputs"),"",ROUND(0.3*INDEX(Lists!$N$8:$N$10,MATCH(F57,Lists!$M$8:$M$10,0))+0.25*IF(G57<20,1,IF(G57<80,2,IF(G57<160,3,IF(G57<480,4,5))))+0.25*J57+0.2*K57,2)) | Y57: =IF(X57="","",ROUND(0.3*IF(U57="Data ready",5,IF(INDEX(Lists!$N$2:$N$5,MATCH(I57,Lists!$M$2:$M$5,0))=INDEX(Lists!$E$2:$E$11,MATCH(R57,Lists!$B$2:$B$11,0))-1,3,1))+0.25*INDEX(Lists!$N$13:$N$15,MATCH(H57,Lists!$M$13:$M$15,0))+0.25*(6-S57)+0.2*IF(V57="Within current position",5,2),2)) | Z57: =IF(X57="","",CHOOSE(MAX(IF(T57="No",IF(L57="Yes",2,1),IF(IF(L57="Yes",2,0)+IF(M57="Yes",1,0)+INDEX(Lists!$N$18:$N$20,MATCH(N57,Lists!$M$18:$M$20,0))+IF(K57=5,2,IF(K57>=4,1,0))>=4,3,IF(IF(L57="Yes",2,0)+IF(M57="Yes",1,0)+INDEX(Lists!$N$18:$N$20,MATCH(N57,Lists!$M$18:$M$20,0))+IF(K57=5,2,IF(K57>=4,1,0))>=2,2,1))),IF($O57="Custom",1,MATCH(INDEX('2. Use-Case Library'!$L$5:$L$244,MATCH($O57,'2. Use-Case Library'!$A$5:$A$244,0)),{"Low","Medium","High"},0))),"Low","Medium","High")) | AA57: =IF(X57="","",IF(AND(X57>=$C$4,Y57>=$C$4),"Quick win",IF(X57>=$C$4,"Strategic bet",IF(Y57>=$C$4,"Fill-in","Deprioritise")))) | AB57: =IF(X57="","",ROUND(X57*Y57*IF(Z57="High",0.85,1)*IF(W57="Redesign / standardise first",0.8,1),2)) | AC57: =IF(AB57="","",RANK(AB57,$AB$8:$AB$57)+COUNTIF($AB$7:AB56,AB57)) | AD57: =IF(AH57="","",INDEX(Lists!$AV$2:$AV$5,AH57)) | AE57: =IF(AB57="","",ROUND(G57*12*INDEX(Lists!$F$2:$F$11,MATCH(R57,Lists!$B$2:$B$11,0)),0)) | AF57: =IF(OR(B57="",R57=""),"",IF(O57="Custom",INDEX(Lists!$I$2:$I$11,MATCH(R57,Lists!$B$2:$B$11,0)),INDEX('2. Use-Case Library'!$H$5:$H$244,MATCH($O57,'2. Use-Case Library'!$A$5:$A$244,0)))) | AG57: =IF(OR(B57="",O57="Custom"),"",INDEX('2. Use-Case Library'!$K$5:$K$244,MATCH($O57,'2. Use-Case Library'!$A$5:$A$244,0))) | AH57: =IF(AB57="","",IF(AA57="Deprioritise",4,IF(W57="AI later - close data gap first",3,IF(OR(W57="Redesign / standardise first",W57="Stretch - partner or later stage",AA57="Strategic bet",Z57="High",S57=5),2,1)))) | AI57: =IF(AC57="","",AH57*100+AC57) | AJ57: =IF(B57="","",IF(O57="Custom",B57,INDEX('2. Use-Case Library'!$D$5:$D$244,MATCH($O57,'2. Use-Case Library'!$A$5:$A$244,0))))

Sheet 4. Opportunity Report
A1: 4. AI Opportunity Report
A2: Where AI fits - and where automation is enough - by function, with the top-ranked opportunities and GT recommendations from the use-case library.
A4: A. ORGANISATIONAL AI POSITION
A5: Organisation | C5: ='1. AI Position'!C4 -> Grant Thornton Bahrain (illustrative)
A6: Sector | C6: ='1. AI Position'!$C$5&"" -> Professional services
A7: AI position (archetype) | C7: ='1. AI Position'!$C$31 -> Buy and configure AI
A8: Data Position / Scale & Capacity | C8: =IF('1. AI Position'!$C$28="","",TEXT('1. AI Position'!$C$28,"0%")&" / "&TEXT('1. AI Position'!$C$29,"0%")) -> 56% / 44%
A9: What it means | C9: ='1. AI Position'!C33 -> Good data, limited scale / capacity: adopt and configure proven AI products rather than build.
A10: Foundation flag | C10: ='1. AI Position'!$C$35 -> No foundation red flags from the position screen.
A12: B. VERDICT SUMMARY - what kind of solution fits the processes assessed
B13: Verdict | C13: Processes | D13: % of total | E13: Hours released / yr | G13: Meaning
B14: AI fit now | C14: =COUNTIF('3. AI Fit Diagnostic'!$W$8:$W$57,B14) -> 11 | D14: =IF(SUM($C$14:$C$18)=0,"",C14/SUM($C$14:$C$18)) -> 0.5 | E14: =SUMIF('3. AI Fit Diagnostic'!$W$8:$W$57,B14,'3. AI Fit Diagnostic'!$AE$8:$AE$57) -> 7566 | F14: AI is the right tool, the data exists and it is within the organisation's current position.
B15: Automate - AI not needed | C15: =COUNTIF('3. AI Fit Diagnostic'!$W$8:$W$57,B15) -> 5 | D15: =IF(SUM($C$14:$C$18)=0,"",C15/SUM($C$14:$C$18)) -> 0.22727273 | E15: =SUMIF('3. AI Fit Diagnostic'!$W$8:$W$57,B15,'3. AI Fit Diagnostic'!$AE$8:$AE$57) -> 4164 | F15: The work follows fixed rules or is a data / reporting problem; automation or BI delivers the value with less risk and cost.
B16: AI later - close data gap first | C16: =COUNTIF('3. AI Fit Diagnostic'!$W$8:$W$57,B16) -> 2 | D16: =IF(SUM($C$14:$C$18)=0,"",C16/SUM($C$14:$C$18)) -> 0.090909091 | E16: =SUMIF('3. AI Fit Diagnostic'!$W$8:$W$57,B16,'3. AI Fit Diagnostic'!$AE$8:$AE$57) -> 672 | F16: AI would fit, but the data it needs is not captured, digital or labelled yet.
B17: Stretch - partner or later stage | C17: =COUNTIF('3. AI Fit Diagnostic'!$W$8:$W$57,B17) -> 3 | D17: =IF(SUM($C$14:$C$18)=0,"",C17/SUM($C$14:$C$18)) -> 0.13636364 | E17: =SUMIF('3. AI Fit Diagnostic'!$W$8:$W$57,B17,'3. AI Fit Diagnostic'!$AE$8:$AE$57) -> 1536 | F17: AI fits and the data exists, but the solution is more complex than the organisation can build or run today.
B18: Redesign / standardise first | C18: =COUNTIF('3. AI Fit Diagnostic'!$W$8:$W$57,B18) -> 1 | D18: =IF(SUM($C$14:$C$18)=0,"",C18/SUM($C$14:$C$18)) -> 0.045454545 | E18: =SUMIF('3. AI Fit Diagnostic'!$W$8:$W$57,B18,'3. AI Fit Diagnostic'!$AE$8:$AE$57) -> 720 | F18: The process varies by person or team; automating or adding AI would scale inconsistency.
B19: Total assessed | C19: =SUM(C14:C18) -> 22 | E19: =SUM(E14:E18) -> 14658
B20: =IF(C19=0,"",TEXT((C14+C17)/C19,"0%")&" of assessed processes are AI opportunities (now or with a partner); "&TEXT(C15/C19,"0%")&" are better served by automation without AI; "&TEXT((C16+C18)/C19,"0%")&" need data or process foundations first.") -> 64% of assessed processes are AI opportunities (now or with a partner); 23% are better served by automation without AI; 14% need data or process foundations first.
A22: C. WHERE AI FITS BY FUNCTION (number of processes)
B23: Function | C23: AI fit now | D23: Stretch | E23: AI later (data) | F23: Automate (no AI) | G23: Redesign first | H23: Total | I23: Hours / yr | J23: High-risk items | K23: Headline
B24: Core operations & service delivery | C24: =COUNTIFS('3. AI Fit Diagnostic'!$P$8:$P$57,$B24,'3. AI Fit Diagnostic'!$W$8:$W$57,"AI fit now") -> 4 | D24: =COUNTIFS('3. AI Fit Diagnostic'!$P$8:$P$57,$B24,'3. AI Fit Diagnostic'!$W$8:$W$57,"Stretch - partner or later stage") -> 3 | E24: =COUNTIFS('3. AI Fit Diagnostic'!$P$8:$P$57,$B24,'3. AI Fit Diagnostic'!$W$8:$W$57,"AI later - close data gap first") -> 0 | F24: =COUNTIFS('3. AI Fit Diagnostic'!$P$8:$P$57,$B24,'3. AI Fit Diagnostic'!$W$8:$W$57,"Automate - AI not needed") -> 2 | G24: =COUNTIFS('3. AI Fit Diagnostic'!$P$8:$P$57,$B24,'3. AI Fit Diagnostic'!$W$8:$W$57,"Redesign / standardise first") -> 1 | H24: =SUM(C24:G24) -> 10 | I24: =SUMIF('3. AI Fit Diagnostic'!$P$8:$P$57,$B24,'3. AI Fit Diagnostic'!$AE$8:$AE$57) -> 7416 | J24: =COUNTIFS('3. AI Fit Diagnostic'!$P$8:$P$57,$B24,'3. AI Fit Diagnostic'!$Z$8:$Z$57,"High") -> 2 | K24: =IF(H24=0,"",IF(C24+D24>=MAX(E24,F24,G24),"AI opportunity",IF(F24>=MAX(E24,G24),"Automation is enough",IF(E24>=G24,"Fix data first","Redesign first")))) -> AI opportunity
B25: Customer service | C25: =COUNTIFS('3. AI Fit Diagnostic'!$P$8:$P$57,$B25,'3. AI Fit Diagnostic'!$W$8:$W$57,"AI fit now") -> 0 | D25: =COUNTIFS('3. AI Fit Diagnostic'!$P$8:$P$57,$B25,'3. AI Fit Diagnostic'!$W$8:$W$57,"Stretch - partner or later stage") -> 0 | E25: =COUNTIFS('3. AI Fit Diagnostic'!$P$8:$P$57,$B25,'3. AI Fit Diagnostic'!$W$8:$W$57,"AI later - close data gap first") -> 0 | F25: =COUNTIFS('3. AI Fit Diagnostic'!$P$8:$P$57,$B25,'3. AI Fit Diagnostic'!$W$8:$W$57,"Automate - AI not needed") -> 0 | G25: =COUNTIFS('3. AI Fit Diagnostic'!$P$8:$P$57,$B25,'3. AI Fit Diagnostic'!$W$8:$W$57,"Redesign / standardise first") -> 0 | H25: =SUM(C25:G25) -> 0 | I25: =SUMIF('3. AI Fit Diagnostic'!$P$8:$P$57,$B25,'3. AI Fit Diagnostic'!$AE$8:$AE$57) -> 0 | J25: =COUNTIFS('3. AI Fit Diagnostic'!$P$8:$P$57,$B25,'3. AI Fit Diagnostic'!$Z$8:$Z$57,"High") -> 0 | K25: =IF(H25=0,"",IF(C25+D25>=MAX(E25,F25,G25),"AI opportunity",IF(F25>=MAX(E25,G25),"Automation is enough",IF(E25>=G25,"Fix data first","Redesign first"))))
B26: Sales & marketing | C26: =COUNTIFS('3. AI Fit Diagnostic'!$P$8:$P$57,$B26,'3. AI Fit Diagnostic'!$W$8:$W$57,"AI fit now") -> 2 | D26: =COUNTIFS('3. AI Fit Diagnostic'!$P$8:$P$57,$B26,'3. AI Fit Diagnostic'!$W$8:$W$57,"Stretch - partner or later stage") -> 0 | E26: =COUNTIFS('3. AI Fit Diagnostic'!$P$8:$P$57,$B26,'3. AI Fit Diagnostic'!$W$8:$W$57,"AI later - close data gap first") -> 1 | F26: =COUNTIFS('3. AI Fit Diagnostic'!$P$8:$P$57,$B26,'3. AI Fit Diagnostic'!$W$8:$W$57,"Automate - AI not needed") -> 0 | G26: =COUNTIFS('3. AI Fit Diagnostic'!$P$8:$P$57,$B26,'3. AI Fit Diagnostic'!$W$8:$W$57,"Redesign / standardise first") -> 0 | H26: =SUM(C26:G26) -> 3 | I26: =SUMIF('3. AI Fit Diagnostic'!$P$8:$P$57,$B26,'3. AI Fit Diagnostic'!$AE$8:$AE$57) -> 1818 | J26: =COUNTIFS('3. AI Fit Diagnostic'!$P$8:$P$57,$B26,'3. AI Fit Diagnostic'!$Z$8:$Z$57,"High") -> 0 | K26: =IF(H26=0,"",IF(C26+D26>=MAX(E26,F26,G26),"AI opportunity",IF(F26>=MAX(E26,G26),"Automation is enough",IF(E26>=G26,"Fix data first","Redesign first")))) -> AI opportunity
B27: Finance & accounting | C27: =COUNTIFS('3. AI Fit Diagnostic'!$P$8:$P$57,$B27,'3. AI Fit Diagnostic'!$W$8:$W$57,"AI fit now") -> 1 | D27: =COUNTIFS('3. AI Fit Diagnostic'!$P$8:$P$57,$B27,'3. AI Fit Diagnostic'!$W$8:$W$57,"Stretch - partner or later stage") -> 0 | E27: =COUNTIFS('3. AI Fit Diagnostic'!$P$8:$P$57,$B27,'3. AI Fit Diagnostic'!$W$8:$W$57,"AI later - close data gap first") -> 0 | F27: =COUNTIFS('3. AI Fit Diagnostic'!$P$8:$P$57,$B27,'3. AI Fit Diagnostic'!$W$8:$W$57,"Automate - AI not needed") -> 1 | G27: =COUNTIFS('3. AI Fit Diagnostic'!$P$8:$P$57,$B27,'3. AI Fit Diagnostic'!$W$8:$W$57,"Redesign / standardise first") -> 0 | H27: =SUM(C27:G27) -> 2 | I27: =SUMIF('3. AI Fit Diagnostic'!$P$8:$P$57,$B27,'3. AI Fit Diagnostic'!$AE$8:$AE$57) -> 1656 | J27: =COUNTIFS('3. AI Fit Diagnostic'!$P$8:$P$57,$B27,'3. AI Fit Diagnostic'!$Z$8:$Z$57,"High") -> 0 | K27: =IF(H27=0,"",IF(C27+D27>=MAX(E27,F27,G27),"AI opportunity",IF(F27>=MAX(E27,G27),"Automation is enough",IF(E27>=G27,"Fix data first","Redesign first")))) -> AI opportunity
B28: HR & people | C28: =COUNTIFS('3. AI Fit Diagnostic'!$P$8:$P$57,$B28,'3. AI Fit Diagnostic'!$W$8:$W$57,"AI fit now") -> 1 | D28: =COUNTIFS('3. AI Fit Diagnostic'!$P$8:$P$57,$B28,'3. AI Fit Diagnostic'!$W$8:$W$57,"Stretch - partner or later stage") -> 0 | E28: =COUNTIFS('3. AI Fit Diagnostic'!$P$8:$P$57,$B28,'3. AI Fit Diagnostic'!$W$8:$W$57,"AI later - close data gap first") -> 1 | F28: =COUNTIFS('3. AI Fit Diagnostic'!$P$8:$P$57,$B28,'3. AI Fit Diagnostic'!$W$8:$W$57,"Automate - AI not needed") -> 0 | G28: =COUNTIFS('3. AI Fit Diagnostic'!$P$8:$P$57,$B28,'3. AI Fit Diagnostic'!$W$8:$W$57,"Redesign / standardise first") -> 0 | H28: =SUM(C28:G28) -> 2 | I28: =SUMIF('3. AI Fit Diagnostic'!$P$8:$P$57,$B28,'3. AI Fit Diagnostic'!$AE$8:$AE$57) -> 408 | J28: =COUNTIFS('3. AI Fit Diagnostic'!$P$8:$P$57,$B28,'3. AI Fit Diagnostic'!$Z$8:$Z$57,"High") -> 1 | K28: =IF(H28=0,"",IF(C28+D28>=MAX(E28,F28,G28),"AI opportunity",IF(F28>=MAX(E28,G28),"Automation is enough",IF(E28>=G28,"Fix data first","Redesign first")))) -> AI opportunity
B29: Procurement & supply chain | C29: =COUNTIFS('3. AI Fit Diagnostic'!$P$8:$P$57,$B29,'3. AI Fit Diagnostic'!$W$8:$W$57,"AI fit now") -> 0 | D29: =COUNTIFS('3. AI Fit Diagnostic'!$P$8:$P$57,$B29,'3. AI Fit Diagnostic'!$W$8:$W$57,"Stretch - partner or later stage") -> 0 | E29: =COUNTIFS('3. AI Fit Diagnostic'!$P$8:$P$57,$B29,'3. AI Fit Diagnostic'!$W$8:$W$57,"AI later - close data gap first") -> 0 | F29: =COUNTIFS('3. AI Fit Diagnostic'!$P$8:$P$57,$B29,'3. AI Fit Diagnostic'!$W$8:$W$57,"Automate - AI not needed") -> 0 | G29: =COUNTIFS('3. AI Fit Diagnostic'!$P$8:$P$57,$B29,'3. AI Fit Diagnostic'!$W$8:$W$57,"Redesign / standardise first") -> 0 | H29: =SUM(C29:G29) -> 0 | I29: =SUMIF('3. AI Fit Diagnostic'!$P$8:$P$57,$B29,'3. AI Fit Diagnostic'!$AE$8:$AE$57) -> 0 | J29: =COUNTIFS('3. AI Fit Diagnostic'!$P$8:$P$57,$B29,'3. AI Fit Diagnostic'!$Z$8:$Z$57,"High") -> 0 | K29: =IF(H29=0,"",IF(C29+D29>=MAX(E29,F29,G29),"AI opportunity",IF(F29>=MAX(E29,G29),"Automation is enough",IF(E29>=G29,"Fix data first","Redesign first"))))
B30: Risk, compliance & legal | C30: =COUNTIFS('3. AI Fit Diagnostic'!$P$8:$P$57,$B30,'3. AI Fit Diagnostic'!$W$8:$W$57,"AI fit now") -> 1 | D30: =COUNTIFS('3. AI Fit Diagnostic'!$P$8:$P$57,$B30,'3. AI Fit Diagnostic'!$W$8:$W$57,"Stretch - partner or later stage") -> 0 | E30: =COUNTIFS('3. AI Fit Diagnostic'!$P$8:$P$57,$B30,'3. AI Fit Diagnostic'!$W$8:$W$57,"AI later - close data gap first") -> 0 | F30: =COUNTIFS('3. AI Fit Diagnostic'!$P$8:$P$57,$B30,'3. AI Fit Diagnostic'!$W$8:$W$57,"Automate - AI not needed") -> 1 | G30: =COUNTIFS('3. AI Fit Diagnostic'!$P$8:$P$57,$B30,'3. AI Fit Diagnostic'!$W$8:$W$57,"Redesign / standardise first") -> 0 | H30: =SUM(C30:G30) -> 2 | I30: =SUMIF('3. AI Fit Diagnostic'!$P$8:$P$57,$B30,'3. AI Fit Diagnostic'!$AE$8:$AE$57) -> 1560 | J30: =COUNTIFS('3. AI Fit Diagnostic'!$P$8:$P$57,$B30,'3. AI Fit Diagnostic'!$Z$8:$Z$57,"High") -> 0 | K30: =IF(H30=0,"",IF(C30+D30>=MAX(E30,F30,G30),"AI opportunity",IF(F30>=MAX(E30,G30),"Automation is enough",IF(E30>=G30,"Fix data first","Redesign first")))) -> AI opportunity
B31: IT & cybersecurity | C31: =COUNTIFS('3. AI Fit Diagnostic'!$P$8:$P$57,$B31,'3. AI Fit Diagnostic'!$W$8:$W$57,"AI fit now") -> 0 | D31: =COUNTIFS('3. AI Fit Diagnostic'!$P$8:$P$57,$B31,'3. AI Fit Diagnostic'!$W$8:$W$57,"Stretch - partner or later stage") -> 0 | E31: =COUNTIFS('3. AI Fit Diagnostic'!$P$8:$P$57,$B31,'3. AI Fit Diagnostic'!$W$8:$W$57,"AI later - close data gap first") -> 0 | F31: =COUNTIFS('3. AI Fit Diagnostic'!$P$8:$P$57,$B31,'3. AI Fit Diagnostic'!$W$8:$W$57,"Automate - AI not needed") -> 0 | G31: =COUNTIFS('3. AI Fit Diagnostic'!$P$8:$P$57,$B31,'3. AI Fit Diagnostic'!$W$8:$W$57,"Redesign / standardise first") -> 0 | H31: =SUM(C31:G31) -> 0 | I31: =SUMIF('3. AI Fit Diagnostic'!$P$8:$P$57,$B31,'3. AI Fit Diagnostic'!$AE$8:$AE$57) -> 0 | J31: =COUNTIFS('3. AI Fit Diagnostic'!$P$8:$P$57,$B31,'3. AI Fit Diagnostic'!$Z$8:$Z$57,"High") -> 0 | K31: =IF(H31=0,"",IF(C31+D31>=MAX(E31,F31,G31),"AI opportunity",IF(F31>=MAX(E31,G31),"Automation is enough",IF(E31>=G31,"Fix data first","Redesign first"))))
B32: Assets, facilities & maintenance | C32: =COUNTIFS('3. AI Fit Diagnostic'!$P$8:$P$57,$B32,'3. AI Fit Diagnostic'!$W$8:$W$57,"AI fit now") -> 0 | D32: =COUNTIFS('3. AI Fit Diagnostic'!$P$8:$P$57,$B32,'3. AI Fit Diagnostic'!$W$8:$W$57,"Stretch - partner or later stage") -> 0 | E32: =COUNTIFS('3. AI Fit Diagnostic'!$P$8:$P$57,$B32,'3. AI Fit Diagnostic'!$W$8:$W$57,"AI later - close data gap first") -> 0 | F32: =COUNTIFS('3. AI Fit Diagnostic'!$P$8:$P$57,$B32,'3. AI Fit Diagnostic'!$W$8:$W$57,"Automate - AI not needed") -> 0 | G32: =COUNTIFS('3. AI Fit Diagnostic'!$P$8:$P$57,$B32,'3. AI Fit Diagnostic'!$W$8:$W$57,"Redesign / standardise first") -> 0 | H32: =SUM(C32:G32) -> 0 | I32: =SUMIF('3. AI Fit Diagnostic'!$P$8:$P$57,$B32,'3. AI Fit Diagnostic'!$AE$8:$AE$57) -> 0 | J32: =COUNTIFS('3. AI Fit Diagnostic'!$P$8:$P$57,$B32,'3. AI Fit Diagnostic'!$Z$8:$Z$57,"High") -> 0 | K32: =IF(H32=0,"",IF(C32+D32>=MAX(E32,F32,G32),"AI opportunity",IF(F32>=MAX(E32,G32),"Automation is enough",IF(E32>=G32,"Fix data first","Redesign first"))))
B33: Strategy, management & reporting | C33: =COUNTIFS('3. AI Fit Diagnostic'!$P$8:$P$57,$B33,'3. AI Fit Diagnostic'!$W$8:$W$57,"AI fit now") -> 1 | D33: =COUNTIFS('3. AI Fit Diagnostic'!$P$8:$P$57,$B33,'3. AI Fit Diagnostic'!$W$8:$W$57,"Stretch - partner or later stage") -> 0 | E33: =COUNTIFS('3. AI Fit Diagnostic'!$P$8:$P$57,$B33,'3. AI Fit Diagnostic'!$W$8:$W$57,"AI later - close data gap first") -> 0 | F33: =COUNTIFS('3. AI Fit Diagnostic'!$P$8:$P$57,$B33,'3. AI Fit Diagnostic'!$W$8:$W$57,"Automate - AI not needed") -> 1 | G33: =COUNTIFS('3. AI Fit Diagnostic'!$P$8:$P$57,$B33,'3. AI Fit Diagnostic'!$W$8:$W$57,"Redesign / standardise first") -> 0 | H33: =SUM(C33:G33) -> 2 | I33: =SUMIF('3. AI Fit Diagnostic'!$P$8:$P$57,$B33,'3. AI Fit Diagnostic'!$AE$8:$AE$57) -> 1200 | J33: =COUNTIFS('3. AI Fit Diagnostic'!$P$8:$P$57,$B33,'3. AI Fit Diagnostic'!$Z$8:$Z$57,"High") -> 0 | K33: =IF(H33=0,"",IF(C33+D33>=MAX(E33,F33,G33),"AI opportunity",IF(F33>=MAX(E33,G33),"Automation is enough",IF(E33>=G33,"Fix data first","Redesign first")))) -> AI opportunity
B34: Knowledge & collaboration | C34: =COUNTIFS('3. AI Fit Diagnostic'!$P$8:$P$57,$B34,'3. AI Fit Diagnostic'!$W$8:$W$57,"AI fit now") -> 1 | D34: =COUNTIFS('3. AI Fit Diagnostic'!$P$8:$P$57,$B34,'3. AI Fit Diagnostic'!$W$8:$W$57,"Stretch - partner or later stage") -> 0 | E34: =COUNTIFS('3. AI Fit Diagnostic'!$P$8:$P$57,$B34,'3. AI Fit Diagnostic'!$W$8:$W$57,"AI later - close data gap first") -> 0 | F34: =COUNTIFS('3. AI Fit Diagnostic'!$P$8:$P$57,$B34,'3. AI Fit Diagnostic'!$W$8:$W$57,"Automate - AI not needed") -> 0 | G34: =COUNTIFS('3. AI Fit Diagnostic'!$P$8:$P$57,$B34,'3. AI Fit Diagnostic'!$W$8:$W$57,"Redesign / standardise first") -> 0 | H34: =SUM(C34:G34) -> 1 | I34: =SUMIF('3. AI Fit Diagnostic'!$P$8:$P$57,$B34,'3. AI Fit Diagnostic'!$AE$8:$AE$57) -> 600 | J34: =COUNTIFS('3. AI Fit Diagnostic'!$P$8:$P$57,$B34,'3. AI Fit Diagnostic'!$Z$8:$Z$57,"High") -> 0 | K34: =IF(H34=0,"",IF(C34+D34>=MAX(E34,F34,G34),"AI opportunity",IF(F34>=MAX(E34,G34),"Automation is enough",IF(E34>=G34,"Fix data first","Redesign first")))) -> AI opportunity
B35: Total | C35: =SUM(C24:C34) -> 11 | D35: =SUM(D24:D34) -> 3 | E35: =SUM(E24:E34) -> 2 | F35: =SUM(F24:F34) -> 5 | G35: =SUM(G24:G34) -> 1 | H35: =SUM(H24:H34) -> 22 | I35: =SUM(I24:I34) -> 14658 | J35: =SUM(J24:J34) -> 3
A57: D. TOP 10 OPPORTUNITIES (risk-adjusted priority) - with GT recommendations
A58: Rank | B58: Process / use case | C58: Solution family | E58: Verdict | G58: Risk | H58: Horizon | I58: GT recommendation
A59: 1 | B59: =IFERROR(INDEX('3. AI Fit Diagnostic'!$AJ$8:$AJ$57,MATCH(1,'3. AI Fit Diagnostic'!$AC$8:$AC$57,0)),"") -> Tax - VAT / tax return data preparation | C59: =IFERROR(INDEX('3. AI Fit Diagnostic'!$R$8:$R$57,MATCH(1,'3. AI Fit Diagnostic'!$AC$8:$AC$57,0)),"") -> Workflow automation / RPA | E59: =IFERROR(INDEX('3. AI Fit Diagnostic'!$W$8:$W$57,MATCH(1,'3. AI Fit Diagnostic'!$AC$8:$AC$57,0)),"") -> Automate - AI not needed | G59: =IFERROR(INDEX('3. AI Fit Diagnostic'!$Z$8:$Z$57,MATCH(1,'3. AI Fit Diagnostic'!$AC$8:$AC$57,0)),"") -> Low | H59: =IFERROR(INDEX('3. AI Fit Diagnostic'!$AD$8:$AD$57,MATCH(1,'3. AI Fit Diagnostic'!$AC$8:$AC$57,0)),"") -> H1 - Now (0-6 months) | I59: =IFERROR(INDEX('3. AI Fit Diagnostic'!$AF$8:$AF$57,MATCH(1,'3. AI Fit Diagnostic'!$AC$8:$AC$57,0)),"") -> Automated extraction, mapping and validation of client data into returns.
A60: 2 | B60: =IFERROR(INDEX('3. AI Fit Diagnostic'!$AJ$8:$AJ$57,MATCH(2,'3. AI Fit Diagnostic'!$AC$8:$AC$57,0)),"") -> Timesheets, WIP & billing | C60: =IFERROR(INDEX('3. AI Fit Diagnostic'!$R$8:$R$57,MATCH(2,'3. AI Fit Diagnostic'!$AC$8:$AC$57,0)),"") -> Workflow automation / RPA | E60: =IFERROR(INDEX('3. AI Fit Diagnostic'!$W$8:$W$57,MATCH(2,'3. AI Fit Diagnostic'!$AC$8:$AC$57,0)),"") -> Automate - AI not needed | G60: =IFERROR(INDEX('3. AI Fit Diagnostic'!$Z$8:$Z$57,MATCH(2,'3. AI Fit Diagnostic'!$AC$8:$AC$57,0)),"") -> Low | H60: =IFERROR(INDEX('3. AI Fit Diagnostic'!$AD$8:$AD$57,MATCH(2,'3. AI Fit Diagnostic'!$AC$8:$AC$57,0)),"") -> H1 - Now (0-6 months) | I60: =IFERROR(INDEX('3. AI Fit Diagnostic'!$AF$8:$AF$57,MATCH(2,'3. AI Fit Diagnostic'!$AC$8:$AC$57,0)),"") -> Automated timesheet reminders, WIP reports and draft billing narratives.
A61: 3 | B61: =IFERROR(INDEX('3. AI Fit Diagnostic'!$AJ$8:$AJ$57,MATCH(3,'3. AI Fit Diagnostic'!$AC$8:$AC$57,0)),"") -> Meeting minutes & action tracking | C61: =IFERROR(INDEX('3. AI Fit Diagnostic'!$R$8:$R$57,MATCH(3,'3. AI Fit Diagnostic'!$AC$8:$AC$57,0)),"") -> Generative AI assistant (off-the-shelf) | E61: =IFERROR(INDEX('3. AI Fit Diagnostic'!$W$8:$W$57,MATCH(3,'3. AI Fit Diagnostic'!$AC$8:$AC$57,0)),"") -> AI fit now | G61: =IFERROR(INDEX('3. AI Fit Diagnostic'!$Z$8:$Z$57,MATCH(3,'3. AI Fit Diagnostic'!$AC$8:$AC$57,0)),"") -> Low | H61: =IFERROR(INDEX('3. AI Fit Diagnostic'!$AD$8:$AD$57,MATCH(3,'3. AI Fit Diagnostic'!$AC$8:$AC$57,0)),"") -> H1 - Now (0-6 months) | I61: =IFERROR(INDEX('3. AI Fit Diagnostic'!$AF$8:$AF$57,MATCH(3,'3. AI Fit Diagnostic'!$AC$8:$AC$57,0)),"") -> Enterprise meeting assistant for transcripts, summaries and action tracking (with participant notice).
A62: 4 | B62: =IFERROR(INDEX('3. AI Fit Diagnostic'!$AJ$8:$AJ$57,MATCH(4,'3. AI Fit Diagnostic'!$AC$8:$AC$57,0)),"") -> Audit - working papers & memo drafting | C62: =IFERROR(INDEX('3. AI Fit Diagnostic'!$R$8:$R$57,MATCH(4,'3. AI Fit Diagnostic'!$AC$8:$AC$57,0)),"") -> Generative AI assistant (off-the-shelf) | E62: =IFERROR(INDEX('3. AI Fit Diagnostic'!$W$8:$W$57,MATCH(4,'3. AI Fit Diagnostic'!$AC$8:$AC$57,0)),"") -> AI fit now | G62: =IFERROR(INDEX('3. AI Fit Diagnostic'!$Z$8:$Z$57,MATCH(4,'3. AI Fit Diagnostic'!$AC$8:$AC$57,0)),"") -> Medium | H62: =IFERROR(INDEX('3. AI Fit Diagnostic'!$AD$8:$AD$57,MATCH(4,'3. AI Fit Diagnostic'!$AC$8:$AC$57,0)),"") -> H1 - Now (0-6 months) | I62: =IFERROR(INDEX('3. AI Fit Diagnostic'!$AF$8:$AF$57,MATCH(4,'3. AI Fit Diagnostic'!$AC$8:$AC$57,0)),"") -> GenAI drafting within methodology templates in an approved environment; reviewer sign-off.
A63: 5 | B63: =IFERROR(INDEX('3. AI Fit Diagnostic'!$AJ$8:$AJ$57,MATCH(5,'3. AI Fit Diagnostic'!$AC$8:$AC$57,0)),"") -> Client acceptance & independence checks | C63: =IFERROR(INDEX('3. AI Fit Diagnostic'!$R$8:$R$57,MATCH(5,'3. AI Fit Diagnostic'!$AC$8:$AC$57,0)),"") -> Rules engine / workflow automation | E63: =IFERROR(INDEX('3. AI Fit Diagnostic'!$W$8:$W$57,MATCH(5,'3. AI Fit Diagnostic'!$AC$8:$AC$57,0)),"") -> Automate - AI not needed | G63: =IFERROR(INDEX('3. AI Fit Diagnostic'!$Z$8:$Z$57,MATCH(5,'3. AI Fit Diagnostic'!$AC$8:$AC$57,0)),"") -> Low | H63: =IFERROR(INDEX('3. AI Fit Diagnostic'!$AD$8:$AD$57,MATCH(5,'3. AI Fit Diagnostic'!$AC$8:$AC$57,0)),"") -> H1 - Now (0-6 months) | I63: =IFERROR(INDEX('3. AI Fit Diagnostic'!$AF$8:$AF$57,MATCH(5,'3. AI Fit Diagnostic'!$AC$8:$AC$57,0)),"") -> Workflow with rules-based independence and conflict checks against the client database.
A64: 6 | B64: =IFERROR(INDEX('3. AI Fit Diagnostic'!$AJ$8:$AJ$57,MATCH(6,'3. AI Fit Diagnostic'!$AC$8:$AC$57,0)),"") -> Audit - bank & external confirmations | C64: =IFERROR(INDEX('3. AI Fit Diagnostic'!$R$8:$R$57,MATCH(6,'3. AI Fit Diagnostic'!$AC$8:$AC$57,0)),"") -> Intelligent document processing (IDP) | E64: =IFERROR(INDEX('3. AI Fit Diagnostic'!$W$8:$W$57,MATCH(6,'3. AI Fit Diagnostic'!$AC$8:$AC$57,0)),"") -> AI fit now | G64: =IFERROR(INDEX('3. AI Fit Diagnostic'!$Z$8:$Z$57,MATCH(6,'3. AI Fit Diagnostic'!$AC$8:$AC$57,0)),"") -> Medium | H64: =IFERROR(INDEX('3. AI Fit Diagnostic'!$AD$8:$AD$57,MATCH(6,'3. AI Fit Diagnostic'!$AC$8:$AC$57,0)),"") -> H1 - Now (0-6 months) | I64: =IFERROR(INDEX('3. AI Fit Diagnostic'!$AF$8:$AF$57,MATCH(6,'3. AI Fit Diagnostic'!$AC$8:$AC$57,0)),"") -> IDP of confirmation responses with automatic agreement to records.
A65: 7 | B65: =IFERROR(INDEX('3. AI Fit Diagnostic'!$AJ$8:$AJ$57,MATCH(7,'3. AI Fit Diagnostic'!$AC$8:$AC$57,0)),"") -> Methodology & knowledge Q&A | C65: =IFERROR(INDEX('3. AI Fit Diagnostic'!$R$8:$R$57,MATCH(7,'3. AI Fit Diagnostic'!$AC$8:$AC$57,0)),"") -> GenAI knowledge assistant (RAG on own content) | E65: =IFERROR(INDEX('3. AI Fit Diagnostic'!$W$8:$W$57,MATCH(7,'3. AI Fit Diagnostic'!$AC$8:$AC$57,0)),"") -> AI fit now | G65: =IFERROR(INDEX('3. AI Fit Diagnostic'!$Z$8:$Z$57,MATCH(7,'3. AI Fit Diagnostic'!$AC$8:$AC$57,0)),"") -> Low | H65: =IFERROR(INDEX('3. AI Fit Diagnostic'!$AD$8:$AD$57,MATCH(7,'3. AI Fit Diagnostic'!$AC$8:$AC$57,0)),"") -> H1 - Now (0-6 months) | I65: =IFERROR(INDEX('3. AI Fit Diagnostic'!$AF$8:$AF$57,MATCH(7,'3. AI Fit Diagnostic'!$AC$8:$AC$57,0)),"") -> Grounded assistant over firm methodologies and sanitised precedents.
A66: 8 | B66: =IFERROR(INDEX('3. AI Fit Diagnostic'!$AJ$8:$AJ$57,MATCH(8,'3. AI Fit Diagnostic'!$AC$8:$AC$57,0)),"") -> Advisory - due-diligence data-room review | C66: =IFERROR(INDEX('3. AI Fit Diagnostic'!$R$8:$R$57,MATCH(8,'3. AI Fit Diagnostic'!$AC$8:$AC$57,0)),"") -> Generative AI assistant (off-the-shelf) | E66: =IFERROR(INDEX('3. AI Fit Diagnostic'!$W$8:$W$57,MATCH(8,'3. AI Fit Diagnostic'!$AC$8:$AC$57,0)),"") -> AI fit now | G66: =IFERROR(INDEX('3. AI Fit Diagnostic'!$Z$8:$Z$57,MATCH(8,'3. AI Fit Diagnostic'!$AC$8:$AC$57,0)),"") -> Medium | H66: =IFERROR(INDEX('3. AI Fit Diagnostic'!$AD$8:$AD$57,MATCH(8,'3. AI Fit Diagnostic'!$AC$8:$AC$57,0)),"") -> H1 - Now (0-6 months) | I66: =IFERROR(INDEX('3. AI Fit Diagnostic'!$AF$8:$AF$57,MATCH(8,'3. AI Fit Diagnostic'!$AC$8:$AC$57,0)),"") -> GenAI review of data-room documents against DD checklists with red-flag summaries.
A67: 9 | B67: =IFERROR(INDEX('3. AI Fit Diagnostic'!$AJ$8:$AJ$57,MATCH(9,'3. AI Fit Diagnostic'!$AC$8:$AC$57,0)),"") -> Tax research & technical Q&A | C67: =IFERROR(INDEX('3. AI Fit Diagnostic'!$R$8:$R$57,MATCH(9,'3. AI Fit Diagnostic'!$AC$8:$AC$57,0)),"") -> GenAI knowledge assistant (RAG on own content) | E67: =IFERROR(INDEX('3. AI Fit Diagnostic'!$W$8:$W$57,MATCH(9,'3. AI Fit Diagnostic'!$AC$8:$AC$57,0)),"") -> AI fit now | G67: =IFERROR(INDEX('3. AI Fit Diagnostic'!$Z$8:$Z$57,MATCH(9,'3. AI Fit Diagnostic'!$AC$8:$AC$57,0)),"") -> Low | H67: =IFERROR(INDEX('3. AI Fit Diagnostic'!$AD$8:$AD$57,MATCH(9,'3. AI Fit Diagnostic'!$AC$8:$AC$57,0)),"") -> H1 - Now (0-6 months) | I67: =IFERROR(INDEX('3. AI Fit Diagnostic'!$AF$8:$AF$57,MATCH(9,'3. AI Fit Diagnostic'!$AC$8:$AC$57,0)),"") -> Grounded tax assistant over Bahrain / GCC tax law, NBR guidance and approved internal positions with citations.
A68: 10 | B68: =IFERROR(INDEX('3. AI Fit Diagnostic'!$AJ$8:$AJ$57,MATCH(10,'3. AI Fit Diagnostic'!$AC$8:$AC$57,0)),"") -> Proposal, quotation & tender responses | C68: =IFERROR(INDEX('3. AI Fit Diagnostic'!$R$8:$R$57,MATCH(10,'3. AI Fit Diagnostic'!$AC$8:$AC$57,0)),"") -> GenAI knowledge assistant (RAG on own content) | E68: =IFERROR(INDEX('3. AI Fit Diagnostic'!$W$8:$W$57,MATCH(10,'3. AI Fit Diagnostic'!$AC$8:$AC$57,0)),"") -> AI fit now | G68: =IFERROR(INDEX('3. AI Fit Diagnostic'!$Z$8:$Z$57,MATCH(10,'3. AI Fit Diagnostic'!$AC$8:$AC$57,0)),"") -> Low | H68: =IFERROR(INDEX('3. AI Fit Diagnostic'!$AD$8:$AD$57,MATCH(10,'3. AI Fit Diagnostic'!$AC$8:$AC$57,0)),"") -> H1 - Now (0-6 months) | I68: =IFERROR(INDEX('3. AI Fit Diagnostic'!$AF$8:$AF$57,MATCH(10,'3. AI Fit Diagnostic'!$AC$8:$AC$57,0)),"") -> Knowledge assistant over approved credentials, CVs and past proposals to draft responses; bid manager review.
A70: E. SECTOR LENS
A71: Value at stake by 2030 | C71: =IFERROR(INDEX('7. Sector Profiles'!$B$5:$B$18,MATCH('1. AI Position'!$C$5,'7. Sector Profiles'!$A$5:$A$18,0)),"Select a sector on sheet 1") -> Not sized separately in the 2030 analysis - value from audit, tax and advisory delivery (e.g., full-population auditing, predictive tax modelling, DD review)
A72: Automation & AI potential | C72: =IFERROR(INDEX('7. Sector Profiles'!$C$5:$C$18,MATCH('1. AI Position'!$C$5,'7. Sector Profiles'!$A$5:$A$18,0)),"Select a sector on sheet 1") -> High
A73: Where the value is | C73: =IFERROR(INDEX('7. Sector Profiles'!$D$5:$D$18,MATCH('1. AI Position'!$C$5,'7. Sector Profiles'!$A$5:$A$18,0)),"Select a sector on sheet 1") -> Audit analytics, drafting, tax research, DD review, practice operations
A74: Regulators & key rules | C74: =IFERROR(INDEX('7. Sector Profiles'!$E$5:$E$18,MATCH('1. AI Position'!$C$5,'7. Sector Profiles'!$A$5:$A$18,0)),"Select a sector on sheet 1") -> ISQM 1; IESBA Code; ISAs; client confidentiality; PDPL
A75: Library entries for this sector | C75: =IFERROR(INDEX('7. Sector Profiles'!$F$5:$F$18,MATCH('1. AI Position'!$C$5,'7. Sector Profiles'!$A$5:$A$18,0)),"Select a sector on sheet 1") -> 15
A77: Value and feasibility scored 1-5 (sheet 3). Hours released are indicative (effort x typical reduction for the solution family) and must be validated in the business case. Risk tiers are inherent (before controls) and never below the library minimum. Recommendations come from the GT AI Use-Case Library.

Sheet 5. Roadmap
A1: 5. Opportunity Roadmap
A2: Opportunities placed automatically by horizon (ordered by priority rank), with the foundations they depend on.
A4: H1 - Now (0-6 months)
A5: Rank | B5: Process / use case | C5: Function | D5: Solution family | E5: Verdict | F5: Risk tier | G5: Hours / yr
A6: =IF($H6="","",INDEX('3. AI Fit Diagnostic'!$AC$8:$AC$57,MATCH($H6,'3. AI Fit Diagnostic'!$AI$8:$AI$57,0))) -> 1 | B6: =IF($H6="","",INDEX('3. AI Fit Diagnostic'!$AJ$8:$AJ$57,MATCH($H6,'3. AI Fit Diagnostic'!$AI$8:$AI$57,0))) -> Tax - VAT / tax return data preparation | C6: =IF($H6="","",INDEX('3. AI Fit Diagnostic'!$P$8:$P$57,MATCH($H6,'3. AI Fit Diagnostic'!$AI$8:$AI$57,0))) -> Core operations & service delivery | D6: =IF($H6="","",INDEX('3. AI Fit Diagnostic'!$R$8:$R$57,MATCH($H6,'3. AI Fit Diagnostic'!$AI$8:$AI$57,0))) -> Workflow automation / RPA | E6: =IF($H6="","",INDEX('3. AI Fit Diagnostic'!$W$8:$W$57,MATCH($H6,'3. AI Fit Diagnostic'!$AI$8:$AI$57,0))) -> Automate - AI not needed | F6: =IF($H6="","",INDEX('3. AI Fit Diagnostic'!$Z$8:$Z$57,MATCH($H6,'3. AI Fit Diagnostic'!$AI$8:$AI$57,0))) -> Low | G6: =IF($H6="","",INDEX('3. AI Fit Diagnostic'!$AE$8:$AE$57,MATCH($H6,'3. AI Fit Diagnostic'!$AI$8:$AI$57,0))) -> 1440 | H6: =IF(IFERROR(SMALL('3. AI Fit Diagnostic'!$AI$8:$AI$57,COUNTIF('3. AI Fit Diagnostic'!$AI$8:$AI$57,"<"&100)+1),"")="","",IF(IFERROR(SMALL('3. AI Fit Diagnostic'!$AI$8:$AI$57,COUNTIF('3. AI Fit Diagnostic'!$AI$8:$AI$57,"<"&100)+1),"")<200,IFERROR(SMALL('3. AI Fit Diagnostic'!$AI$8:$AI$57,COUNTIF('3. AI Fit Diagnostic'!$AI$8:$AI$57,"<"&100)+1),""),"")) -> 101
A7: =IF($H7="","",INDEX('3. AI Fit Diagnostic'!$AC$8:$AC$57,MATCH($H7,'3. AI Fit Diagnostic'!$AI$8:$AI$57,0))) -> 2 | B7: =IF($H7="","",INDEX('3. AI Fit Diagnostic'!$AJ$8:$AJ$57,MATCH($H7,'3. AI Fit Diagnostic'!$AI$8:$AI$57,0))) -> Timesheets, WIP & billing | C7: =IF($H7="","",INDEX('3. AI Fit Diagnostic'!$P$8:$P$57,MATCH($H7,'3. AI Fit Diagnostic'!$AI$8:$AI$57,0))) -> Finance & accounting | D7: =IF($H7="","",INDEX('3. AI Fit Diagnostic'!$R$8:$R$57,MATCH($H7,'3. AI Fit Diagnostic'!$AI$8:$AI$57,0))) -> Workflow automation / RPA | E7: =IF($H7="","",INDEX('3. AI Fit Diagnostic'!$W$8:$W$57,MATCH($H7,'3. AI Fit Diagnostic'!$AI$8:$AI$57,0))) -> Automate - AI not needed | F7: =IF($H7="","",INDEX('3. AI Fit Diagnostic'!$Z$8:$Z$57,MATCH($H7,'3. AI Fit Diagnostic'!$AI$8:$AI$57,0))) -> Low | G7: =IF($H7="","",INDEX('3. AI Fit Diagnostic'!$AE$8:$AE$57,MATCH($H7,'3. AI Fit Diagnostic'!$AI$8:$AI$57,0))) -> 1296 | H7: =IF(IFERROR(SMALL('3. AI Fit Diagnostic'!$AI$8:$AI$57,COUNTIF('3. AI Fit Diagnostic'!$AI$8:$AI$57,"<"&100)+2),"")="","",IF(IFERROR(SMALL('3. AI Fit Diagnostic'!$AI$8:$AI$57,COUNTIF('3. AI Fit Diagnostic'!$AI$8:$AI$57,"<"&100)+2),"")<200,IFERROR(SMALL('3. AI Fit Diagnostic'!$AI$8:$AI$57,COUNTIF('3. AI Fit Diagnostic'!$AI$8:$AI$57,"<"&100)+2),""),"")) -> 102
A8: =IF($H8="","",INDEX('3. AI Fit Diagnostic'!$AC$8:$AC$57,MATCH($H8,'3. AI Fit Diagnostic'!$AI$8:$AI$57,0))) -> 3 | B8: =IF($H8="","",INDEX('3. AI Fit Diagnostic'!$AJ$8:$AJ$57,MATCH($H8,'3. AI Fit Diagnostic'!$AI$8:$AI$57,0))) -> Meeting minutes & action tracking | C8: =IF($H8="","",INDEX('3. AI Fit Diagnostic'!$P$8:$P$57,MATCH($H8,'3. AI Fit Diagnostic'!$AI$8:$AI$57,0))) -> Strategy, management & reporting | D8: =IF($H8="","",INDEX('3. AI Fit Diagnostic'!$R$8:$R$57,MATCH($H8,'3. AI Fit Diagnostic'!$AI$8:$AI$57,0))) -> Generative AI assistant (off-the-shelf) | E8: =IF($H8="","",INDEX('3. AI Fit Diagnostic'!$W$8:$W$57,MATCH($H8,'3. AI Fit Diagnostic'!$AI$8:$AI$57,0))) -> AI fit now | F8: =IF($H8="","",INDEX('3. AI Fit Diagnostic'!$Z$8:$Z$57,MATCH($H8,'3. AI Fit Diagnostic'!$AI$8:$AI$57,0))) -> Low | G8: =IF($H8="","",INDEX('3. AI Fit Diagnostic'!$AE$8:$AE$57,MATCH($H8,'3. AI Fit Diagnostic'!$AI$8:$AI$57,0))) -> 900 | H8: =IF(IFERROR(SMALL('3. AI Fit Diagnostic'!$AI$8:$AI$57,COUNTIF('3. AI Fit Diagnostic'!$AI$8:$AI$57,"<"&100)+3),"")="","",IF(IFERROR(SMALL('3. AI Fit Diagnostic'!$AI$8:$AI$57,COUNTIF('3. AI Fit Diagnostic'!$AI$8:$AI$57,"<"&100)+3),"")<200,IFERROR(SMALL('3. AI Fit Diagnostic'!$AI$8:$AI$57,COUNTIF('3. AI Fit Diagnostic'!$AI$8:$AI$57,"<"&100)+3),""),"")) -> 103
A9: =IF($H9="","",INDEX('3. AI Fit Diagnostic'!$AC$8:$AC$57,MATCH($H9,'3. AI Fit Diagnostic'!$AI$8:$AI$57,0))) -> 4 | B9: =IF($H9="","",INDEX('3. AI Fit Diagnostic'!$AJ$8:$AJ$57,MATCH($H9,'3. AI Fit Diagnostic'!$AI$8:$AI$57,0))) -> Audit - working papers & memo drafting | C9: =IF($H9="","",INDEX('3. AI Fit Diagnostic'!$P$8:$P$57,MATCH($H9,'3. AI Fit Diagnostic'!$AI$8:$AI$57,0))) -> Core operations & service delivery | D9: =IF($H9="","",INDEX('3. AI Fit Diagnostic'!$R$8:$R$57,MATCH($H9,'3. AI Fit Diagnostic'!$AI$8:$AI$57,0))) -> Generative AI assistant (off-the-shelf) | E9: =IF($H9="","",INDEX('3. AI Fit Diagnostic'!$W$8:$W$57,MATCH($H9,'3. AI Fit Diagnostic'!$AI$8:$AI$57,0))) -> AI fit now | F9: =IF($H9="","",INDEX('3. AI Fit Diagnostic'!$Z$8:$Z$57,MATCH($H9,'3. AI Fit Diagnostic'!$AI$8:$AI$57,0))) -> Medium | G9: =IF($H9="","",INDEX('3. AI Fit Diagnostic'!$AE$8:$AE$57,MATCH($H9,'3. AI Fit Diagnostic'!$AI$8:$AI$57,0))) -> 1440 | H9: =IF(IFERROR(SMALL('3. AI Fit Diagnostic'!$AI$8:$AI$57,COUNTIF('3. AI Fit Diagnostic'!$AI$8:$AI$57,"<"&100)+4),"")="","",IF(IFERROR(SMALL('3. AI Fit Diagnostic'!$AI$8:$AI$57,COUNTIF('3. AI Fit Diagnostic'!$AI$8:$AI$57,"<"&100)+4),"")<200,IFERROR(SMALL('3. AI Fit Diagnostic'!$AI$8:$AI$57,COUNTIF('3. AI Fit Diagnostic'!$AI$8:$AI$57,"<"&100)+4),""),"")) -> 104
A10: =IF($H10="","",INDEX('3. AI Fit Diagnostic'!$AC$8:$AC$57,MATCH($H10,'3. AI Fit Diagnostic'!$AI$8:$AI$57,0))) -> 5 | B10: =IF($H10="","",INDEX('3. AI Fit Diagnostic'!$AJ$8:$AJ$57,MATCH($H10,'3. AI Fit Diagnostic'!$AI$8:$AI$57,0))) -> Client acceptance & independence checks | C10: =IF($H10="","",INDEX('3. AI Fit Diagnostic'!$P$8:$P$57,MATCH($H10,'3. AI Fit Diagnostic'!$AI$8:$AI$57,0))) -> Risk, compliance & legal | D10: =IF($H10="","",INDEX('3. AI Fit Diagnostic'!$R$8:$R$57,MATCH($H10,'3. AI Fit Diagnostic'!$AI$8:$AI$57,0))) -> Rules engine / workflow automation | E10: =IF($H10="","",INDEX('3. AI Fit Diagnostic'!$W$8:$W$57,MATCH($H10,'3. AI Fit Diagnostic'!$AI$8:$AI$57,0))) -> Automate - AI not needed | F10: =IF($H10="","",INDEX('3. AI Fit Diagnostic'!$Z$8:$Z$57,MATCH($H10,'3. AI Fit Diagnostic'!$AI$8:$AI$57,0))) -> Low | G10: =IF($H10="","",INDEX('3. AI Fit Diagnostic'!$AE$8:$AE$57,MATCH($H10,'3. AI Fit Diagnostic'!$AI$8:$AI$57,0))) -> 840 | H10: =IF(IFERROR(SMALL('3. AI Fit Diagnostic'!$AI$8:$AI$57,COUNTIF('3. AI Fit Diagnostic'!$AI$8:$AI$57,"<"&100)+5),"")="","",IF(IFERROR(SMALL('3. AI Fit Diagnostic'!$AI$8:$AI$57,COUNTIF('3. AI Fit Diagnostic'!$AI$8:$AI$57,"<"&100)+5),"")<200,IFERROR(SMALL('3. AI Fit Diagnostic'!$AI$8:$AI$57,COUNTIF('3. AI Fit Diagnostic'!$AI$8:$AI$57,"<"&100)+5),""),"")) -> 105
A11: =IF($H11="","",INDEX('3. AI Fit Diagnostic'!$AC$8:$AC$57,MATCH($H11,'3. AI Fit Diagnostic'!$AI$8:$AI$57,0))) -> 6 | B11: =IF($H11="","",INDEX('3. AI Fit Diagnostic'!$AJ$8:$AJ$57,MATCH($H11,'3. AI Fit Diagnostic'!$AI$8:$AI$57,0))) -> Audit - bank & external confirmations | C11: =IF($H11="","",INDEX('3. AI Fit Diagnostic'!$P$8:$P$57,MATCH($H11,'3. AI Fit Diagnostic'!$AI$8:$AI$57,0))) -> Core operations & service delivery | D11: =IF($H11="","",INDEX('3. AI Fit Diagnostic'!$R$8:$R$57,MATCH($H11,'3. AI Fit Diagnostic'!$AI$8:$AI$57,0))) -> Intelligent document processing (IDP) | E11: =IF($H11="","",INDEX('3. AI Fit Diagnostic'!$W$8:$W$57,MATCH($H11,'3. AI Fit Diagnostic'!$AI$8:$AI$57,0))) -> AI fit now | F11: =IF($H11="","",INDEX('3. AI Fit Diagnostic'!$Z$8:$Z$57,MATCH($H11,'3. AI Fit Diagnostic'!$AI$8:$AI$57,0))) -> Medium | G11: =IF($H11="","",INDEX('3. AI Fit Diagnostic'!$AE$8:$AE$57,MATCH($H11,'3. AI Fit Diagnostic'!$AI$8:$AI$57,0))) -> 720 | H11: =IF(IFERROR(SMALL('3. AI Fit Diagnostic'!$AI$8:$AI$57,COUNTIF('3. AI Fit Diagnostic'!$AI$8:$AI$57,"<"&100)+6),"")="","",IF(IFERROR(SMALL('3. AI Fit Diagnostic'!$AI$8:$AI$57,COUNTIF('3. AI Fit Diagnostic'!$AI$8:$AI$57,"<"&100)+6),"")<200,IFERROR(SMALL('3. AI Fit Diagnostic'!$AI$8:$AI$57,COUNTIF('3. AI Fit Diagnostic'!$AI$8:$AI$57,"<"&100)+6),""),"")) -> 106
A12: =IF($H12="","",INDEX('3. AI Fit Diagnostic'!$AC$8:$AC$57,MATCH($H12,'3. AI Fit Diagnostic'!$AI$8:$AI$57,0))) -> 7 | B12: =IF($H12="","",INDEX('3. AI Fit Diagnostic'!$AJ$8:$AJ$57,MATCH($H12,'3. AI Fit Diagnostic'!$AI$8:$AI$57,0))) -> Methodology & knowledge Q&A | C12: =IF($H12="","",INDEX('3. AI Fit Diagnostic'!$P$8:$P$57,MATCH($H12,'3. AI Fit Diagnostic'!$AI$8:$AI$57,0))) -> Knowledge & collaboration | D12: =IF($H12="","",INDEX('3. AI Fit Diagnostic'!$R$8:$R$57,MATCH($H12,'3. AI Fit Diagnostic'!$AI$8:$AI$57,0))) -> GenAI knowledge assistant (RAG on own content) | E12: =IF($H12="","",INDEX('3. AI Fit Diagnostic'!$W$8:$W$57,MATCH($H12,'3. AI Fit Diagnostic'!$AI$8:$AI$57,0))) -> AI fit now | F12: =IF($H12="","",INDEX('3. AI Fit Diagnostic'!$Z$8:$Z$57,MATCH($H12,'3. AI Fit Diagnostic'!$AI$8:$AI$57,0))) -> Low | G12: =IF($H12="","",INDEX('3. AI Fit Diagnostic'!$AE$8:$AE$57,MATCH($H12,'3. AI Fit Diagnostic'!$AI$8:$AI$57,0))) -> 600 | H12: =IF(IFERROR(SMALL('3. AI Fit Diagnostic'!$AI$8:$AI$57,COUNTIF('3. AI Fit Diagnostic'!$AI$8:$AI$57,"<"&100)+7),"")="","",IF(IFERROR(SMALL('3. AI Fit Diagnostic'!$AI$8:$AI$57,COUNTIF('3. AI Fit Diagnostic'!$AI$8:$AI$57,"<"&100)+7),"")<200,IFERROR(SMALL('3. AI Fit Diagnostic'!$AI$8:$AI$57,COUNTIF('3. AI Fit Diagnostic'!$AI$8:$AI$57,"<"&100)+7),""),"")) -> 107
A13: =IF($H13="","",INDEX('3. AI Fit Diagnostic'!$AC$8:$AC$57,MATCH($H13,'3. AI Fit Diagnostic'!$AI$8:$AI$57,0))) -> 8 | B13: =IF($H13="","",INDEX('3. AI Fit Diagnostic'!$AJ$8:$AJ$57,MATCH($H13,'3. AI Fit Diagnostic'!$AI$8:$AI$57,0))) -> Advisory - due-diligence data-room review | C13: =IF($H13="","",INDEX('3. AI Fit Diagnostic'!$P$8:$P$57,MATCH($H13,'3. AI Fit Diagnostic'!$AI$8:$AI$57,0))) -> Core operations & service delivery | D13: =IF($H13="","",INDEX('3. AI Fit Diagnostic'!$R$8:$R$57,MATCH($H13,'3. AI Fit Diagnostic'!$AI$8:$AI$57,0))) -> Generative AI assistant (off-the-shelf) | E13: =IF($H13="","",INDEX('3. AI Fit Diagnostic'!$W$8:$W$57,MATCH($H13,'3. AI Fit Diagnostic'!$AI$8:$AI$57,0))) -> AI fit now | F13: =IF($H13="","",INDEX('3. AI Fit Diagnostic'!$Z$8:$Z$57,MATCH($H13,'3. AI Fit Diagnostic'!$AI$8:$AI$57,0))) -> Medium | G13: =IF($H13="","",INDEX('3. AI Fit Diagnostic'!$AE$8:$AE$57,MATCH($H13,'3. AI Fit Diagnostic'!$AI$8:$AI$57,0))) -> 792 | H13: =IF(IFERROR(SMALL('3. AI Fit Diagnostic'!$AI$8:$AI$57,COUNTIF('3. AI Fit Diagnostic'!$AI$8:$AI$57,"<"&100)+8),"")="","",IF(IFERROR(SMALL('3. AI Fit Diagnostic'!$AI$8:$AI$57,COUNTIF('3. AI Fit Diagnostic'!$AI$8:$AI$57,"<"&100)+8),"")<200,IFERROR(SMALL('3. AI Fit Diagnostic'!$AI$8:$AI$57,COUNTIF('3. AI Fit Diagnostic'!$AI$8:$AI$57,"<"&100)+8),""),"")) -> 108
A14: =IF($H14="","",INDEX('3. AI Fit Diagnostic'!$AC$8:$AC$57,MATCH($H14,'3. AI Fit Diagnostic'!$AI$8:$AI$57,0))) -> 9 | B14: =IF($H14="","",INDEX('3. AI Fit Diagnostic'!$AJ$8:$AJ$57,MATCH($H14,'3. AI Fit Diagnostic'!$AI$8:$AI$57,0))) -> Tax research & technical Q&A | C14: =IF($H14="","",INDEX('3. AI Fit Diagnostic'!$P$8:$P$57,MATCH($H14,'3. AI Fit Diagnostic'!$AI$8:$AI$57,0))) -> Core operations & service delivery | D14: =IF($H14="","",INDEX('3. AI Fit Diagnostic'!$R$8:$R$57,MATCH($H14,'3. AI Fit Diagnostic'!$AI$8:$AI$57,0))) -> GenAI knowledge assistant (RAG on own content) | E14: =IF($H14="","",INDEX('3. AI Fit Diagnostic'!$W$8:$W$57,MATCH($H14,'3. AI Fit Diagnostic'!$AI$8:$AI$57,0))) -> AI fit now | F14: =IF($H14="","",INDEX('3. AI Fit Diagnostic'!$Z$8:$Z$57,MATCH($H14,'3. AI Fit Diagnostic'!$AI$8:$AI$57,0))) -> Low | G14: =IF($H14="","",INDEX('3. AI Fit Diagnostic'!$AE$8:$AE$57,MATCH($H14,'3. AI Fit Diagnostic'!$AI$8:$AI$57,0))) -> 480 | H14: =IF(IFERROR(SMALL('3. AI Fit Diagnostic'!$AI$8:$AI$57,COUNTIF('3. AI Fit Diagnostic'!$AI$8:$AI$57,"<"&100)+9),"")="","",IF(IFERROR(SMALL('3. AI Fit Diagnostic'!$AI$8:$AI$57,COUNTIF('3. AI Fit Diagnostic'!$AI$8:$AI$57,"<"&100)+9),"")<200,IFERROR(SMALL('3. AI Fit Diagnostic'!$AI$8:$AI$57,COUNTIF('3. AI Fit Diagnostic'!$AI$8:$AI$57,"<"&100)+9),""),"")) -> 109
A15: =IF($H15="","",INDEX('3. AI Fit Diagnostic'!$AC$8:$AC$57,MATCH($H15,'3. AI Fit Diagnostic'!$AI$8:$AI$57,0))) -> 10 | B15: =IF($H15="","",INDEX('3. AI Fit Diagnostic'!$AJ$8:$AJ$57,MATCH($H15,'3. AI Fit Diagnostic'!$AI$8:$AI$57,0))) -> Proposal, quotation & tender responses | C15: =IF($H15="","",INDEX('3. AI Fit Diagnostic'!$P$8:$P$57,MATCH($H15,'3. AI Fit Diagnostic'!$AI$8:$AI$57,0))) -> Sales & marketing | D15: =IF($H15="","",INDEX('3. AI Fit Diagnostic'!$R$8:$R$57,MATCH($H15,'3. AI Fit Diagnostic'!$AI$8:$AI$57,0))) -> GenAI knowledge assistant (RAG on own content) | E15: =IF($H15="","",INDEX('3. AI Fit Diagnostic'!$W$8:$W$57,MATCH($H15,'3. AI Fit Diagnostic'!$AI$8:$AI$57,0))) -> AI fit now | F15: =IF($H15="","",INDEX('3. AI Fit Diagnostic'!$Z$8:$Z$57,MATCH($H15,'3. AI Fit Diagnostic'!$AI$8:$AI$57,0))) -> Low | G15: =IF($H15="","",INDEX('3. AI Fit Diagnostic'!$AE$8:$AE$57,MATCH($H15,'3. AI Fit Diagnostic'!$AI$8:$AI$57,0))) -> 1050 | H15: =IF(IFERROR(SMALL('3. AI Fit Diagnostic'!$AI$8:$AI$57,COUNTIF('3. AI Fit Diagnostic'!$AI$8:$AI$57,"<"&100)+10),"")="","",IF(IFERROR(SMALL('3. AI Fit Diagnostic'!$AI$8:$AI$57,COUNTIF('3. AI Fit Diagnostic'!$AI$8:$AI$57,"<"&100)+10),"")<200,IFERROR(SMALL('3. AI Fit Diagnostic'!$AI$8:$AI$57,COUNTIF('3. AI Fit Diagnostic'!$AI$8:$AI$57,"<"&100)+10),""),"")) -> 110
A16: =IF($H16="","",INDEX('3. AI Fit Diagnostic'!$AC$8:$AC$57,MATCH($H16,'3. AI Fit Diagnostic'!$AI$8:$AI$57,0))) -> 11 | B16: =IF($H16="","",INDEX('3. AI Fit Diagnostic'!$AJ$8:$AJ$57,MATCH($H16,'3. AI Fit Diagnostic'!$AI$8:$AI$57,0))) -> Client BCP & business impact analysis (GT AI BCP tool - in preparation) | C16: =IF($H16="","",INDEX('3. AI Fit Diagnostic'!$P$8:$P$57,MATCH($H16,'3. AI Fit Diagnostic'!$AI$8:$AI$57,0))) -> Risk, compliance & legal | D16: =IF($H16="","",INDEX('3. AI Fit Diagnostic'!$R$8:$R$57,MATCH($H16,'3. AI Fit Diagnostic'!$AI$8:$AI$57,0))) -> Generative AI assistant (off-the-shelf) | E16: =IF($H16="","",INDEX('3. AI Fit Diagnostic'!$W$8:$W$57,MATCH($H16,'3. AI Fit Diagnostic'!$AI$8:$AI$57,0))) -> AI fit now | F16: =IF($H16="","",INDEX('3. AI Fit Diagnostic'!$Z$8:$Z$57,MATCH($H16,'3. AI Fit Diagnostic'!$AI$8:$AI$57,0))) -> Medium | G16: =IF($H16="","",INDEX('3. AI Fit Diagnostic'!$AE$8:$AE$57,MATCH($H16,'3. AI Fit Diagnostic'!$AI$8:$AI$57,0))) -> 720 | H16: =IF(IFERROR(SMALL('3. AI Fit Diagnostic'!$AI$8:$AI$57,COUNTIF('3. AI Fit Diagnostic'!$AI$8:$AI$57,"<"&100)+11),"")="","",IF(IFERROR(SMALL('3. AI Fit Diagnostic'!$AI$8:$AI$57,COUNTIF('3. AI Fit Diagnostic'!$AI$8:$AI$57,"<"&100)+11),"")<200,IFERROR(SMALL('3. AI Fit Diagnostic'!$AI$8:$AI$57,COUNTIF('3. AI Fit Diagnostic'!$AI$8:$AI$57,"<"&100)+11),""),"")) -> 111
A17: =IF($H17="","",INDEX('3. AI Fit Diagnostic'!$AC$8:$AC$57,MATCH($H17,'3. AI Fit Diagnostic'!$AI$8:$AI$57,0))) -> 12 | B17: =IF($H17="","",INDEX('3. AI Fit Diagnostic'!$AJ$8:$AJ$57,MATCH($H17,'3. AI Fit Diagnostic'!$AI$8:$AI$57,0))) -> Marketing content & campaigns | C17: =IF($H17="","",INDEX('3. AI Fit Diagnostic'!$P$8:$P$57,MATCH($H17,'3. AI Fit Diagnostic'!$AI$8:$AI$57,0))) -> Sales & marketing | D17: =IF($H17="","",INDEX('3. AI Fit Diagnostic'!$R$8:$R$57,MATCH($H17,'3. AI Fit Diagnostic'!$AI$8:$AI$57,0))) -> Generative AI assistant (off-the-shelf) | E17: =IF($H17="","",INDEX('3. AI Fit Diagnostic'!$W$8:$W$57,MATCH($H17,'3. AI Fit Diagnostic'!$AI$8:$AI$57,0))) -> AI fit now | F17: =IF($H17="","",INDEX('3. AI Fit Diagnostic'!$Z$8:$Z$57,MATCH($H17,'3. AI Fit Diagnostic'!$AI$8:$AI$57,0))) -> Low | G17: =IF($H17="","",INDEX('3. AI Fit Diagnostic'!$AE$8:$AE$57,MATCH($H17,'3. AI Fit Diagnostic'!$AI$8:$AI$57,0))) -> 288 | H17: =IF(IFERROR(SMALL('3. AI Fit Diagnostic'!$AI$8:$AI$57,COUNTIF('3. AI Fit Diagnostic'!$AI$8:$AI$57,"<"&100)+12),"")="","",IF(IFERROR(SMALL('3. AI Fit Diagnostic'!$AI$8:$AI$57,COUNTIF('3. AI Fit Diagnostic'!$AI$8:$AI$57,"<"&100)+12),"")<200,IFERROR(SMALL('3. AI Fit Diagnostic'!$AI$8:$AI$57,COUNTIF('3. AI Fit Diagnostic'!$AI$8:$AI$57,"<"&100)+12),""),"")) -> 112
A18: =IF($H18="","",INDEX('3. AI Fit Diagnostic'!$AC$8:$AC$57,MATCH($H18,'3. AI Fit Diagnostic'!$AI$8:$AI$57,0))) -> 13 | B18: =IF($H18="","",INDEX('3. AI Fit Diagnostic'!$AJ$8:$AJ$57,MATCH($H18,'3. AI Fit Diagnostic'!$AI$8:$AI$57,0))) -> Assessment & maturity report production | C18: =IF($H18="","",INDEX('3. AI Fit Diagnostic'!$P$8:$P$57,MATCH($H18,'3. AI Fit Diagnostic'!$AI$8:$AI$57,0))) -> Core operations & service delivery | D18: =IF($H18="","",INDEX('3. AI Fit Diagnostic'!$R$8:$R$57,MATCH($H18,'3. AI Fit Diagnostic'!$AI$8:$AI$57,0))) -> Workflow automation / RPA | E18: =IF($H18="","",INDEX('3. AI Fit Diagnostic'!$W$8:$W$57,MATCH($H18,'3. AI Fit Diagnostic'!$AI$8:$AI$57,0))) -> Automate - AI not needed | F18: =IF($H18="","",INDEX('3. AI Fit Diagnostic'!$Z$8:$Z$57,MATCH($H18,'3. AI Fit Diagnostic'!$AI$8:$AI$57,0))) -> Low | G18: =IF($H18="","",INDEX('3. AI Fit Diagnostic'!$AE$8:$AE$57,MATCH($H18,'3. AI Fit Diagnostic'!$AI$8:$AI$57,0))) -> 288 | H18: =IF(IFERROR(SMALL('3. AI Fit Diagnostic'!$AI$8:$AI$57,COUNTIF('3. AI Fit Diagnostic'!$AI$8:$AI$57,"<"&100)+13),"")="","",IF(IFERROR(SMALL('3. AI Fit Diagnostic'!$AI$8:$AI$57,COUNTIF('3. AI Fit Diagnostic'!$AI$8:$AI$57,"<"&100)+13),"")<200,IFERROR(SMALL('3. AI Fit Diagnostic'!$AI$8:$AI$57,COUNTIF('3. AI Fit Diagnostic'!$AI$8:$AI$57,"<"&100)+13),""),"")) -> 113
A19: =IF($H19="","",INDEX('3. AI Fit Diagnostic'!$AC$8:$AC$57,MATCH($H19,'3. AI Fit Diagnostic'!$AI$8:$AI$57,0))) -> 16 | B19: =IF($H19="","",INDEX('3. AI Fit Diagnostic'!$AJ$8:$AJ$57,MATCH($H19,'3. AI Fit Diagnostic'!$AI$8:$AI$57,0))) -> KPI dashboards | C19: =IF($H19="","",INDEX('3. AI Fit Diagnostic'!$P$8:$P$57,MATCH($H19,'3. AI Fit Diagnostic'!$AI$8:$AI$57,0))) -> Strategy, management & reporting | D19: =IF($H19="","",INDEX('3. AI Fit Diagnostic'!$R$8:$R$57,MATCH($H19,'3. AI Fit Diagnostic'!$AI$8:$AI$57,0))) -> BI, dashboards & reconciliation automation | E19: =IF($H19="","",INDEX('3. AI Fit Diagnostic'!$W$8:$W$57,MATCH($H19,'3. AI Fit Diagnostic'!$AI$8:$AI$57,0))) -> Automate - AI not needed | F19: =IF($H19="","",INDEX('3. AI Fit Diagnostic'!$Z$8:$Z$57,MATCH($H19,'3. AI Fit Diagnostic'!$AI$8:$AI$57,0))) -> Low | G19: =IF($H19="","",INDEX('3. AI Fit Diagnostic'!$AE$8:$AE$57,MATCH($H19,'3. AI Fit Diagnostic'!$AI$8:$AI$57,0))) -> 300 | H19: =IF(IFERROR(SMALL('3. AI Fit Diagnostic'!$AI$8:$AI$57,COUNTIF('3. AI Fit Diagnostic'!$AI$8:$AI$57,"<"&100)+14),"")="","",IF(IFERROR(SMALL('3. AI Fit Diagnostic'!$AI$8:$AI$57,COUNTIF('3. AI Fit Diagnostic'!$AI$8:$AI$57,"<"&100)+14),"")<200,IFERROR(SMALL('3. AI Fit Diagnostic'!$AI$8:$AI$57,COUNTIF('3. AI Fit Diagnostic'!$AI$8:$AI$57,"<"&100)+14),""),"")) -> 116
A20: =IF($H20="","",INDEX('3. AI Fit Diagnostic'!$AC$8:$AC$57,MATCH($H20,'3. AI Fit Diagnostic'!$AI$8:$AI$57,0))) -> 17 | B20: =IF($H20="","",INDEX('3. AI Fit Diagnostic'!$AJ$8:$AJ$57,MATCH($H20,'3. AI Fit Diagnostic'!$AI$8:$AI$57,0))) -> Employee HR queries (leave, policies, payslips) | C20: =IF($H20="","",INDEX('3. AI Fit Diagnostic'!$P$8:$P$57,MATCH($H20,'3. AI Fit Diagnostic'!$AI$8:$AI$57,0))) -> HR & people | D20: =IF($H20="","",INDEX('3. AI Fit Diagnostic'!$R$8:$R$57,MATCH($H20,'3. AI Fit Diagnostic'!$AI$8:$AI$57,0))) -> Conversational AI / virtual agent | E20: =IF($H20="","",INDEX('3. AI Fit Diagnostic'!$W$8:$W$57,MATCH($H20,'3. AI Fit Diagnostic'!$AI$8:$AI$57,0))) -> AI fit now | F20: =IF($H20="","",INDEX('3. AI Fit Diagnostic'!$Z$8:$Z$57,MATCH($H20,'3. AI Fit Diagnostic'!$AI$8:$AI$57,0))) -> Low | G20: =IF($H20="","",INDEX('3. AI Fit Diagnostic'!$AE$8:$AE$57,MATCH($H20,'3. AI Fit Diagnostic'!$AI$8:$AI$57,0))) -> 216 | H20: =IF(IFERROR(SMALL('3. AI Fit Diagnostic'!$AI$8:$AI$57,COUNTIF('3. AI Fit Diagnostic'!$AI$8:$AI$57,"<"&100)+15),"")="","",IF(IFERROR(SMALL('3. AI Fit Diagnostic'!$AI$8:$AI$57,COUNTIF('3. AI Fit Diagnostic'!$AI$8:$AI$57,"<"&100)+15),"")<200,IFERROR(SMALL('3. AI Fit Diagnostic'!$AI$8:$AI$57,COUNTIF('3. AI Fit Diagnostic'!$AI$8:$AI$57,"<"&100)+15),""),"")) -> 117
A21: =IF($H21="","",INDEX('3. AI Fit Diagnostic'!$AC$8:$AC$57,MATCH($H21,'3. AI Fit Diagnostic'!$AI$8:$AI$57,0))) -> 18 | B21: =IF($H21="","",INDEX('3. AI Fit Diagnostic'!$AJ$8:$AJ$57,MATCH($H21,'3. AI Fit Diagnostic'!$AI$8:$AI$57,0))) -> Expense claims audit | C21: =IF($H21="","",INDEX('3. AI Fit Diagnostic'!$P$8:$P$57,MATCH($H21,'3. AI Fit Diagnostic'!$AI$8:$AI$57,0))) -> Finance & accounting | D21: =IF($H21="","",INDEX('3. AI Fit Diagnostic'!$R$8:$R$57,MATCH($H21,'3. AI Fit Diagnostic'!$AI$8:$AI$57,0))) -> Intelligent document processing (IDP) | E21: =IF($H21="","",INDEX('3. AI Fit Diagnostic'!$W$8:$W$57,MATCH($H21,'3. AI Fit Diagnostic'!$AI$8:$AI$57,0))) -> AI fit now | F21: =IF($H21="","",INDEX('3. AI Fit Diagnostic'!$Z$8:$Z$57,MATCH($H21,'3. AI Fit Diagnostic'!$AI$8:$AI$57,0))) -> Medium | G21: =IF($H21="","",INDEX('3. AI Fit Diagnostic'!$AE$8:$AE$57,MATCH($H21,'3. AI Fit Diagnostic'!$AI$8:$AI$57,0))) -> 360 | H21: =IF(IFERROR(SMALL('3. AI Fit Diagnostic'!$AI$8:$AI$57,COUNTIF('3. AI Fit Diagnostic'!$AI$8:$AI$57,"<"&100)+16),"")="","",IF(IFERROR(SMALL('3. AI Fit Diagnostic'!$AI$8:$AI$57,COUNTIF('3. AI Fit Diagnostic'!$AI$8:$AI$57,"<"&100)+16),"")<200,IFERROR(SMALL('3. AI Fit Diagnostic'!$AI$8:$AI$57,COUNTIF('3. AI Fit Diagnostic'!$AI$8:$AI$57,"<"&100)+16),""),"")) -> 118
A22: =IF($H22="","",INDEX('3. AI Fit Diagnostic'!$AC$8:$AC$57,MATCH($H22,'3. AI Fit Diagnostic'!$AI$8:$AI$57,0))) | B22: =IF($H22="","",INDEX('3. AI Fit Diagnostic'!$AJ$8:$AJ$57,MATCH($H22,'3. AI Fit Diagnostic'!$AI$8:$AI$57,0))) | C22: =IF($H22="","",INDEX('3. AI Fit Diagnostic'!$P$8:$P$57,MATCH($H22,'3. AI Fit Diagnostic'!$AI$8:$AI$57,0))) | D22: =IF($H22="","",INDEX('3. AI Fit Diagnostic'!$R$8:$R$57,MATCH($H22,'3. AI Fit Diagnostic'!$AI$8:$AI$57,0))) | E22: =IF($H22="","",INDEX('3. AI Fit Diagnostic'!$W$8:$W$57,MATCH($H22,'3. AI Fit Diagnostic'!$AI$8:$AI$57,0))) | F22: =IF($H22="","",INDEX('3. AI Fit Diagnostic'!$Z$8:$Z$57,MATCH($H22,'3. AI Fit Diagnostic'!$AI$8:$AI$57,0))) | G22: =IF($H22="","",INDEX('3. AI Fit Diagnostic'!$AE$8:$AE$57,MATCH($H22,'3. AI Fit Diagnostic'!$AI$8:$AI$57,0))) | H22: =IF(IFERROR(SMALL('3. AI Fit Diagnostic'!$AI$8:$AI$57,COUNTIF('3. AI Fit Diagnostic'!$AI$8:$AI$57,"<"&100)+17),"")="","",IF(IFERROR(SMALL('3. AI Fit Diagnostic'!$AI$8:$AI$57,COUNTIF('3. AI Fit Diagnostic'!$AI$8:$AI$57,"<"&100)+17),"")<200,IFERROR(SMALL('3. AI Fit Diagnostic'!$AI$8:$AI$57,COUNTIF('3. AI Fit Diagnostic'!$AI$8:$AI$57,"<"&100)+17),""),""))
A23: =IF($H23="","",INDEX('3. AI Fit Diagnostic'!$AC$8:$AC$57,MATCH($H23,'3. AI Fit Diagnostic'!$AI$8:$AI$57,0))) | B23: =IF($H23="","",INDEX('3. AI Fit Diagnostic'!$AJ$8:$AJ$57,MATCH($H23,'3. AI Fit Diagnostic'!$AI$8:$AI$57,0))) | C23: =IF($H23="","",INDEX('3. AI Fit Diagnostic'!$P$8:$P$57,MATCH($H23,'3. AI Fit Diagnostic'!$AI$8:$AI$57,0))) | D23: =IF($H23="","",INDEX('3. AI Fit Diagnostic'!$R$8:$R$57,MATCH($H23,'3. AI Fit Diagnostic'!$AI$8:$AI$57,0))) | E23: =IF($H23="","",INDEX('3. AI Fit Diagnostic'!$W$8:$W$57,MATCH($H23,'3. AI Fit Diagnostic'!$AI$8:$AI$57,0))) | F23: =IF($H23="","",INDEX('3. AI Fit Diagnostic'!$Z$8:$Z$57,MATCH($H23,'3. AI Fit Diagnostic'!$AI$8:$AI$57,0))) | G23: =IF($H23="","",INDEX('3. AI Fit Diagnostic'!$AE$8:$AE$57,MATCH($H23,'3. AI Fit Diagnostic'!$AI$8:$AI$57,0))) | H23: =IF(IFERROR(SMALL('3. AI Fit Diagnostic'!$AI$8:$AI$57,COUNTIF('3. AI Fit Diagnostic'!$AI$8:$AI$57,"<"&100)+18),"")="","",IF(IFERROR(SMALL('3. AI Fit Diagnostic'!$AI$8:$AI$57,COUNTIF('3. AI Fit Diagnostic'!$AI$8:$AI$57,"<"&100)+18),"")<200,IFERROR(SMALL('3. AI Fit Diagnostic'!$AI$8:$AI$57,COUNTIF('3. AI Fit Diagnostic'!$AI$8:$AI$57,"<"&100)+18),""),""))
A24: =IF($H24="","",INDEX('3. AI Fit Diagnostic'!$AC$8:$AC$57,MATCH($H24,'3. AI Fit Diagnostic'!$AI$8:$AI$57,0))) | B24: =IF($H24="","",INDEX('3. AI Fit Diagnostic'!$AJ$8:$AJ$57,MATCH($H24,'3. AI Fit Diagnostic'!$AI$8:$AI$57,0))) | C24: =IF($H24="","",INDEX('3. AI Fit Diagnostic'!$P$8:$P$57,MATCH($H24,'3. AI Fit Diagnostic'!$AI$8:$AI$57,0))) | D24: =IF($H24="","",INDEX('3. AI Fit Diagnostic'!$R$8:$R$57,MATCH($H24,'3. AI Fit Diagnostic'!$AI$8:$AI$57,0))) | E24: =IF($H24="","",INDEX('3. AI Fit Diagnostic'!$W$8:$W$57,MATCH($H24,'3. AI Fit Diagnostic'!$AI$8:$AI$57,0))) | F24: =IF($H24="","",INDEX('3. AI Fit Diagnostic'!$Z$8:$Z$57,MATCH($H24,'3. AI Fit Diagnostic'!$AI$8:$AI$57,0))) | G24: =IF($H24="","",INDEX('3. AI Fit Diagnostic'!$AE$8:$AE$57,MATCH($H24,'3. AI Fit Diagnostic'!$AI$8:$AI$57,0))) | H24: =IF(IFERROR(SMALL('3. AI Fit Diagnostic'!$AI$8:$AI$57,COUNTIF('3. AI Fit Diagnostic'!$AI$8:$AI$57,"<"&100)+19),"")="","",IF(IFERROR(SMALL('3. AI Fit Diagnostic'!$AI$8:$AI$57,COUNTIF('3. AI Fit Diagnostic'!$AI$8:$AI$57,"<"&100)+19),"")<200,IFERROR(SMALL('3. AI Fit Diagnostic'!$AI$8:$AI$57,COUNTIF('3. AI Fit Diagnostic'!$AI$8:$AI$57,"<"&100)+19),""),""))
A25: =IF($H25="","",INDEX('3. AI Fit Diagnostic'!$AC$8:$AC$57,MATCH($H25,'3. AI Fit Diagnostic'!$AI$8:$AI$57,0))) | B25: =IF($H25="","",INDEX('3. AI Fit Diagnostic'!$AJ$8:$AJ$57,MATCH($H25,'3. AI Fit Diagnostic'!$AI$8:$AI$57,0))) | C25: =IF($H25="","",INDEX('3. AI Fit Diagnostic'!$P$8:$P$57,MATCH($H25,'3. AI Fit Diagnostic'!$AI$8:$AI$57,0))) | D25: =IF($H25="","",INDEX('3. AI Fit Diagnostic'!$R$8:$R$57,MATCH($H25,'3. AI Fit Diagnostic'!$AI$8:$AI$57,0))) | E25: =IF($H25="","",INDEX('3. AI Fit Diagnostic'!$W$8:$W$57,MATCH($H25,'3. AI Fit Diagnostic'!$AI$8:$AI$57,0))) | F25: =IF($H25="","",INDEX('3. AI Fit Diagnostic'!$Z$8:$Z$57,MATCH($H25,'3. AI Fit Diagnostic'!$AI$8:$AI$57,0))) | G25: =IF($H25="","",INDEX('3. AI Fit Diagnostic'!$AE$8:$AE$57,MATCH($H25,'3. AI Fit Diagnostic'!$AI$8:$AI$57,0))) | H25: =IF(IFERROR(SMALL('3. AI Fit Diagnostic'!$AI$8:$AI$57,COUNTIF('3. AI Fit Diagnostic'!$AI$8:$AI$57,"<"&100)+20),"")="","",IF(IFERROR(SMALL('3. AI Fit Diagnostic'!$AI$8:$AI$57,COUNTIF('3. AI Fit Diagnostic'!$AI$8:$AI$57,"<"&100)+20),"")<200,IFERROR(SMALL('3. AI Fit Diagnostic'!$AI$8:$AI$57,COUNTIF('3. AI Fit Diagnostic'!$AI$8:$AI$57,"<"&100)+20),""),""))
A27: H2 - Next (6-12 months)
A28: Rank | B28: Process / use case | C28: Function | D28: Solution family | E28: Verdict | F28: Risk tier | G28: Hours / yr
A29: =IF($H29="","",INDEX('3. AI Fit Diagnostic'!$AC$8:$AC$57,MATCH($H29,'3. AI Fit Diagnostic'!$AI$8:$AI$57,0))) -> 14 | B29: =IF($H29="","",INDEX('3. AI Fit Diagnostic'!$AJ$8:$AJ$57,MATCH($H29,'3. AI Fit Diagnostic'!$AI$8:$AI$57,0))) -> Financial statements preparation (GT AI FS tool - in preparation) | C29: =IF($H29="","",INDEX('3. AI Fit Diagnostic'!$P$8:$P$57,MATCH($H29,'3. AI Fit Diagnostic'!$AI$8:$AI$57,0))) -> Core operations & service delivery | D29: =IF($H29="","",INDEX('3. AI Fit Diagnostic'!$R$8:$R$57,MATCH($H29,'3. AI Fit Diagnostic'!$AI$8:$AI$57,0))) -> Predictive analytics / machine learning | E29: =IF($H29="","",INDEX('3. AI Fit Diagnostic'!$W$8:$W$57,MATCH($H29,'3. AI Fit Diagnostic'!$AI$8:$AI$57,0))) -> Stretch - partner or later stage | F29: =IF($H29="","",INDEX('3. AI Fit Diagnostic'!$Z$8:$Z$57,MATCH($H29,'3. AI Fit Diagnostic'!$AI$8:$AI$57,0))) -> High | G29: =IF($H29="","",INDEX('3. AI Fit Diagnostic'!$AE$8:$AE$57,MATCH($H29,'3. AI Fit Diagnostic'!$AI$8:$AI$57,0))) -> 624 | H29: =IF(IFERROR(SMALL('3. AI Fit Diagnostic'!$AI$8:$AI$57,COUNTIF('3. AI Fit Diagnostic'!$AI$8:$AI$57,"<"&200)+1),"")="","",IF(IFERROR(SMALL('3. AI Fit Diagnostic'!$AI$8:$AI$57,COUNTIF('3. AI Fit Diagnostic'!$AI$8:$AI$57,"<"&200)+1),"")<300,IFERROR(SMALL('3. AI Fit Diagnostic'!$AI$8:$AI$57,COUNTIF('3. AI Fit Diagnostic'!$AI$8:$AI$57,"<"&200)+1),""),"")) -> 214
A30: =IF($H30="","",INDEX('3. AI Fit Diagnostic'!$AC$8:$AC$57,MATCH($H30,'3. AI Fit Diagnostic'!$AI$8:$AI$57,0))) -> 15 | B30: =IF($H30="","",INDEX('3. AI Fit Diagnostic'!$AJ$8:$AJ$57,MATCH($H30,'3. AI Fit Diagnostic'!$AI$8:$AI$57,0))) -> Audit - journal-entry testing (full population) | C30: =IF($H30="","",INDEX('3. AI Fit Diagnostic'!$P$8:$P$57,MATCH($H30,'3. AI Fit Diagnostic'!$AI$8:$AI$57,0))) -> Core operations & service delivery | D30: =IF($H30="","",INDEX('3. AI Fit Diagnostic'!$R$8:$R$57,MATCH($H30,'3. AI Fit Diagnostic'!$AI$8:$AI$57,0))) -> Predictive analytics / machine learning | E30: =IF($H30="","",INDEX('3. AI Fit Diagnostic'!$W$8:$W$57,MATCH($H30,'3. AI Fit Diagnostic'!$AI$8:$AI$57,0))) -> Stretch - partner or later stage | F30: =IF($H30="","",INDEX('3. AI Fit Diagnostic'!$Z$8:$Z$57,MATCH($H30,'3. AI Fit Diagnostic'!$AI$8:$AI$57,0))) -> High | G30: =IF($H30="","",INDEX('3. AI Fit Diagnostic'!$AE$8:$AE$57,MATCH($H30,'3. AI Fit Diagnostic'!$AI$8:$AI$57,0))) -> 720 | H30: =IF(IFERROR(SMALL('3. AI Fit Diagnostic'!$AI$8:$AI$57,COUNTIF('3. AI Fit Diagnostic'!$AI$8:$AI$57,"<"&200)+2),"")="","",IF(IFERROR(SMALL('3. AI Fit Diagnostic'!$AI$8:$AI$57,COUNTIF('3. AI Fit Diagnostic'!$AI$8:$AI$57,"<"&200)+2),"")<300,IFERROR(SMALL('3. AI Fit Diagnostic'!$AI$8:$AI$57,COUNTIF('3. AI Fit Diagnostic'!$AI$8:$AI$57,"<"&200)+2),""),"")) -> 215
A31: =IF($H31="","",INDEX('3. AI Fit Diagnostic'!$AC$8:$AC$57,MATCH($H31,'3. AI Fit Diagnostic'!$AI$8:$AI$57,0))) -> 22 | B31: =IF($H31="","",INDEX('3. AI Fit Diagnostic'!$AJ$8:$AJ$57,MATCH($H31,'3. AI Fit Diagnostic'!$AI$8:$AI$57,0))) -> Engagement workflow coordination | C31: =IF($H31="","",INDEX('3. AI Fit Diagnostic'!$P$8:$P$57,MATCH($H31,'3. AI Fit Diagnostic'!$AI$8:$AI$57,0))) -> Core operations & service delivery | D31: =IF($H31="","",INDEX('3. AI Fit Diagnostic'!$R$8:$R$57,MATCH($H31,'3. AI Fit Diagnostic'!$AI$8:$AI$57,0))) -> Agentic AI (supervised agents) | E31: =IF($H31="","",INDEX('3. AI Fit Diagnostic'!$W$8:$W$57,MATCH($H31,'3. AI Fit Diagnostic'!$AI$8:$AI$57,0))) -> Redesign / standardise first | F31: =IF($H31="","",INDEX('3. AI Fit Diagnostic'!$Z$8:$Z$57,MATCH($H31,'3. AI Fit Diagnostic'!$AI$8:$AI$57,0))) -> Medium | G31: =IF($H31="","",INDEX('3. AI Fit Diagnostic'!$AE$8:$AE$57,MATCH($H31,'3. AI Fit Diagnostic'!$AI$8:$AI$57,0))) -> 720 | H31: =IF(IFERROR(SMALL('3. AI Fit Diagnostic'!$AI$8:$AI$57,COUNTIF('3. AI Fit Diagnostic'!$AI$8:$AI$57,"<"&200)+3),"")="","",IF(IFERROR(SMALL('3. AI Fit Diagnostic'!$AI$8:$AI$57,COUNTIF('3. AI Fit Diagnostic'!$AI$8:$AI$57,"<"&200)+3),"")<300,IFERROR(SMALL('3. AI Fit Diagnostic'!$AI$8:$AI$57,COUNTIF('3. AI Fit Diagnostic'!$AI$8:$AI$57,"<"&200)+3),""),"")) -> 222
A32: =IF($H32="","",INDEX('3. AI Fit Diagnostic'!$AC$8:$AC$57,MATCH($H32,'3. AI Fit Diagnostic'!$AI$8:$AI$57,0))) | B32: =IF($H32="","",INDEX('3. AI Fit Diagnostic'!$AJ$8:$AJ$57,MATCH($H32,'3. AI Fit Diagnostic'!$AI$8:$AI$57,0))) | C32: =IF($H32="","",INDEX('3. AI Fit Diagnostic'!$P$8:$P$57,MATCH($H32,'3. AI Fit Diagnostic'!$AI$8:$AI$57,0))) | D32: =IF($H32="","",INDEX('3. AI Fit Diagnostic'!$R$8:$R$57,MATCH($H32,'3. AI Fit Diagnostic'!$AI$8:$AI$57,0))) | E32: =IF($H32="","",INDEX('3. AI Fit Diagnostic'!$W$8:$W$57,MATCH($H32,'3. AI Fit Diagnostic'!$AI$8:$AI$57,0))) | F32: =IF($H32="","",INDEX('3. AI Fit Diagnostic'!$Z$8:$Z$57,MATCH($H32,'3. AI Fit Diagnostic'!$AI$8:$AI$57,0))) | G32: =IF($H32="","",INDEX('3. AI Fit Diagnostic'!$AE$8:$AE$57,MATCH($H32,'3. AI Fit Diagnostic'!$AI$8:$AI$57,0))) | H32: =IF(IFERROR(SMALL('3. AI Fit Diagnostic'!$AI$8:$AI$57,COUNTIF('3. AI Fit Diagnostic'!$AI$8:$AI$57,"<"&200)+4),"")="","",IF(IFERROR(SMALL('3. AI Fit Diagnostic'!$AI$8:$AI$57,COUNTIF('3. AI Fit Diagnostic'!$AI$8:$AI$57,"<"&200)+4),"")<300,IFERROR(SMALL('3. AI Fit Diagnostic'!$AI$8:$AI$57,COUNTIF('3. AI Fit Diagnostic'!$AI$8:$AI$57,"<"&200)+4),""),""))
A33: =IF($H33="","",INDEX('3. AI Fit Diagnostic'!$AC$8:$AC$57,MATCH($H33,'3. AI Fit Diagnostic'!$AI$8:$AI$57,0))) | B33: =IF($H33="","",INDEX('3. AI Fit Diagnostic'!$AJ$8:$AJ$57,MATCH($H33,'3. AI Fit Diagnostic'!$AI$8:$AI$57,0))) | C33: =IF($H33="","",INDEX('3. AI Fit Diagnostic'!$P$8:$P$57,MATCH($H33,'3. AI Fit Diagnostic'!$AI$8:$AI$57,0))) | D33: =IF($H33="","",INDEX('3. AI Fit Diagnostic'!$R$8:$R$57,MATCH($H33,'3. AI Fit Diagnostic'!$AI$8:$AI$57,0))) | E33: =IF($H33="","",INDEX('3. AI Fit Diagnostic'!$W$8:$W$57,MATCH($H33,'3. AI Fit Diagnostic'!$AI$8:$AI$57,0))) | F33: =IF($H33="","",INDEX('3. AI Fit Diagnostic'!$Z$8:$Z$57,MATCH($H33,'3. AI Fit Diagnostic'!$AI$8:$AI$57,0))) | G33: =IF($H33="","",INDEX('3. AI Fit Diagnostic'!$AE$8:$AE$57,MATCH($H33,'3. AI Fit Diagnostic'!$AI$8:$AI$57,0))) | H33: =IF(IFERROR(SMALL('3. AI Fit Diagnostic'!$AI$8:$AI$57,COUNTIF('3. AI Fit Diagnostic'!$AI$8:$AI$57,"<"&200)+5),"")="","",IF(IFERROR(SMALL('3. AI Fit Diagnostic'!$AI$8:$AI$57,COUNTIF('3. AI Fit Diagnostic'!$AI$8:$AI$57,"<"&200)+5),"")<300,IFERROR(SMALL('3. AI Fit Diagnostic'!$AI$8:$AI$57,COUNTIF('3. AI Fit Diagnostic'!$AI$8:$AI$57,"<"&200)+5),""),""))
A34: =IF($H34="","",INDEX('3. AI Fit Diagnostic'!$AC$8:$AC$57,MATCH($H34,'3. AI Fit Diagnostic'!$AI$8:$AI$57,0))) | B34: =IF($H34="","",INDEX('3. AI Fit Diagnostic'!$AJ$8:$AJ$57,MATCH($H34,'3. AI Fit Diagnostic'!$AI$8:$AI$57,0))) | C34: =IF($H34="","",INDEX('3. AI Fit Diagnostic'!$P$8:$P$57,MATCH($H34,'3. AI Fit Diagnostic'!$AI$8:$AI$57,0))) | D34: =IF($H34="","",INDEX('3. AI Fit Diagnostic'!$R$8:$R$57,MATCH($H34,'3. AI Fit Diagnostic'!$AI$8:$AI$57,0))) | E34: =IF($H34="","",INDEX('3. AI Fit Diagnostic'!$W$8:$W$57,MATCH($H34,'3. AI Fit Diagnostic'!$AI$8:$AI$57,0))) | F34: =IF($H34="","",INDEX('3. AI Fit Diagnostic'!$Z$8:$Z$57,MATCH($H34,'3. AI Fit Diagnostic'!$AI$8:$AI$57,0))) | G34: =IF($H34="","",INDEX('3. AI Fit Diagnostic'!$AE$8:$AE$57,MATCH($H34,'3. AI Fit Diagnostic'!$AI$8:$AI$57,0))) | H34: =IF(IFERROR(SMALL('3. AI Fit Diagnostic'!$AI$8:$AI$57,COUNTIF('3. AI Fit Diagnostic'!$AI$8:$AI$57,"<"&200)+6),"")="","",IF(IFERROR(SMALL('3. AI Fit Diagnostic'!$AI$8:$AI$57,COUNTIF('3. AI Fit Diagnostic'!$AI$8:$AI$57,"<"&200)+6),"")<300,IFERROR(SMALL('3. AI Fit Diagnostic'!$AI$8:$AI$57,COUNTIF('3. AI Fit Diagnostic'!$AI$8:$AI$57,"<"&200)+6),""),""))
A35: =IF($H35="","",INDEX('3. AI Fit Diagnostic'!$AC$8:$AC$57,MATCH($H35,'3. AI Fit Diagnostic'!$AI$8:$AI$57,0))) | B35: =IF($H35="","",INDEX('3. AI Fit Diagnostic'!$AJ$8:$AJ$57,MATCH($H35,'3. AI Fit Diagnostic'!$AI$8:$AI$57,0))) | C35: =IF($H35="","",INDEX('3. AI Fit Diagnostic'!$P$8:$P$57,MATCH($H35,'3. AI Fit Diagnostic'!$AI$8:$AI$57,0))) | D35: =IF($H35="","",INDEX('3. AI Fit Diagnostic'!$R$8:$R$57,MATCH($H35,'3. AI Fit Diagnostic'!$AI$8:$AI$57,0))) | E35: =IF($H35="","",INDEX('3. AI Fit Diagnostic'!$W$8:$W$57,MATCH($H35,'3. AI Fit Diagnostic'!$AI$8:$AI$57,0))) | F35: =IF($H35="","",INDEX('3. AI Fit Diagnostic'!$Z$8:$Z$57,MATCH($H35,'3. AI Fit Diagnostic'!$AI$8:$AI$57,0))) | G35: =IF($H35="","",INDEX('3. AI Fit Diagnostic'!$AE$8:$AE$57,MATCH($H35,'3. AI Fit Diagnostic'!$AI$8:$AI$57,0))) | H35: =IF(IFERROR(SMALL('3. AI Fit Diagnostic'!$AI$8:$AI$57,COUNTIF('3. AI Fit Diagnostic'!$AI$8:$AI$57,"<"&200)+7),"")="","",IF(IFERROR(SMALL('3. AI Fit Diagnostic'!$AI$8:$AI$57,COUNTIF('3. AI Fit Diagnostic'!$AI$8:$AI$57,"<"&200)+7),"")<300,IFERROR(SMALL('3. AI Fit Diagnostic'!$AI$8:$AI$57,COUNTIF('3. AI Fit Diagnostic'!$AI$8:$AI$57,"<"&200)+7),""),""))
A36: =IF($H36="","",INDEX('3. AI Fit Diagnostic'!$AC$8:$AC$57,MATCH($H36,'3. AI Fit Diagnostic'!$AI$8:$AI$57,0))) | B36: =IF($H36="","",INDEX('3. AI Fit Diagnostic'!$AJ$8:$AJ$57,MATCH($H36,'3. AI Fit Diagnostic'!$AI$8:$AI$57,0))) | C36: =IF($H36="","",INDEX('3. AI Fit Diagnostic'!$P$8:$P$57,MATCH($H36,'3. AI Fit Diagnostic'!$AI$8:$AI$57,0))) | D36: =IF($H36="","",INDEX('3. AI Fit Diagnostic'!$R$8:$R$57,MATCH($H36,'3. AI Fit Diagnostic'!$AI$8:$AI$57,0))) | E36: =IF($H36="","",INDEX('3. AI Fit Diagnostic'!$W$8:$W$57,MATCH($H36,'3. AI Fit Diagnostic'!$AI$8:$AI$57,0))) | F36: =IF($H36="","",INDEX('3. AI Fit Diagnostic'!$Z$8:$Z$57,MATCH($H36,'3. AI Fit Diagnostic'!$AI$8:$AI$57,0))) | G36: =IF($H36="","",INDEX('3. AI Fit Diagnostic'!$AE$8:$AE$57,MATCH($H36,'3. AI Fit Diagnostic'!$AI$8:$AI$57,0))) | H36: =IF(IFERROR(SMALL('3. AI Fit Diagnostic'!$AI$8:$AI$57,COUNTIF('3. AI Fit Diagnostic'!$AI$8:$AI$57,"<"&200)+8),"")="","",IF(IFERROR(SMALL('3. AI Fit Diagnostic'!$AI$8:$AI$57,COUNTIF('3. AI Fit Diagnostic'!$AI$8:$AI$57,"<"&200)+8),"")<300,IFERROR(SMALL('3. AI Fit Diagnostic'!$AI$8:$AI$57,COUNTIF('3. AI Fit Diagnostic'!$AI$8:$AI$57,"<"&200)+8),""),""))
A37: =IF($H37="","",INDEX('3. AI Fit Diagnostic'!$AC$8:$AC$57,MATCH($H37,'3. AI Fit Diagnostic'!$AI$8:$AI$57,0))) | B37: =IF($H37="","",INDEX('3. AI Fit Diagnostic'!$AJ$8:$AJ$57,MATCH($H37,'3. AI Fit Diagnostic'!$AI$8:$AI$57,0))) | C37: =IF($H37="","",INDEX('3. AI Fit Diagnostic'!$P$8:$P$57,MATCH($H37,'3. AI Fit Diagnostic'!$AI$8:$AI$57,0))) | D37: =IF($H37="","",INDEX('3. AI Fit Diagnostic'!$R$8:$R$57,MATCH($H37,'3. AI Fit Diagnostic'!$AI$8:$AI$57,0))) | E37: =IF($H37="","",INDEX('3. AI Fit Diagnostic'!$W$8:$W$57,MATCH($H37,'3. AI Fit Diagnostic'!$AI$8:$AI$57,0))) | F37: =IF($H37="","",INDEX('3. AI Fit Diagnostic'!$Z$8:$Z$57,MATCH($H37,'3. AI Fit Diagnostic'!$AI$8:$AI$57,0))) | G37: =IF($H37="","",INDEX('3. AI Fit Diagnostic'!$AE$8:$AE$57,MATCH($H37,'3. AI Fit Diagnostic'!$AI$8:$AI$57,0))) | H37: =IF(IFERROR(SMALL('3. AI Fit Diagnostic'!$AI$8:$AI$57,COUNTIF('3. AI Fit Diagnostic'!$AI$8:$AI$57,"<"&200)+9),"")="","",IF(IFERROR(SMALL('3. AI Fit Diagnostic'!$AI$8:$AI$57,COUNTIF('3. AI Fit Diagnostic'!$AI$8:$AI$57,"<"&200)+9),"")<300,IFERROR(SMALL('3. AI Fit Diagnostic'!$AI$8:$AI$57,COUNTIF('3. AI Fit Diagnostic'!$AI$8:$AI$57,"<"&200)+9),""),""))
A38: =IF($H38="","",INDEX('3. AI Fit Diagnostic'!$AC$8:$AC$57,MATCH($H38,'3. AI Fit Diagnostic'!$AI$8:$AI$57,0))) | B38: =IF($H38="","",INDEX('3. AI Fit Diagnostic'!$AJ$8:$AJ$57,MATCH($H38,'3. AI Fit Diagnostic'!$AI$8:$AI$57,0))) | C38: =IF($H38="","",INDEX('3. AI Fit Diagnostic'!$P$8:$P$57,MATCH($H38,'3. AI Fit Diagnostic'!$AI$8:$AI$57,0))) | D38: =IF($H38="","",INDEX('3. AI Fit Diagnostic'!$R$8:$R$57,MATCH($H38,'3. AI Fit Diagnostic'!$AI$8:$AI$57,0))) | E38: =IF($H38="","",INDEX('3. AI Fit Diagnostic'!$W$8:$W$57,MATCH($H38,'3. AI Fit Diagnostic'!$AI$8:$AI$57,0))) | F38: =IF($H38="","",INDEX('3. AI Fit Diagnostic'!$Z$8:$Z$57,MATCH($H38,'3. AI Fit Diagnostic'!$AI$8:$AI$57,0))) | G38: =IF($H38="","",INDEX('3. AI Fit Diagnostic'!$AE$8:$AE$57,MATCH($H38,'3. AI Fit Diagnostic'!$AI$8:$AI$57,0))) | H38: =IF(IFERROR(SMALL('3. AI Fit Diagnostic'!$AI$8:$AI$57,COUNTIF('3. AI Fit Diagnostic'!$AI$8:$AI$57,"<"&200)+10),"")="","",IF(IFERROR(SMALL('3. AI Fit Diagnostic'!$AI$8:$AI$57,COUNTIF('3. AI Fit Diagnostic'!$AI$8:$AI$57,"<"&200)+10),"")<300,IFERROR(SMALL('3. AI Fit Diagnostic'!$AI$8:$AI$57,COUNTIF('3. AI Fit Diagnostic'!$AI$8:$AI$57,"<"&200)+10),""),""))
A39: =IF($H39="","",INDEX('3. AI Fit Diagnostic'!$AC$8:$AC$57,MATCH($H39,'3. AI Fit Diagnostic'!$AI$8:$AI$57,0))) | B39: =IF($H39="","",INDEX('3. AI Fit Diagnostic'!$AJ$8:$AJ$57,MATCH($H39,'3. AI Fit Diagnostic'!$AI$8:$AI$57,0))) | C39: =IF($H39="","",INDEX('3. AI Fit Diagnostic'!$P$8:$P$57,MATCH($H39,'3. AI Fit Diagnostic'!$AI$8:$AI$57,0))) | D39: =IF($H39="","",INDEX('3. AI Fit Diagnostic'!$R$8:$R$57,MATCH($H39,'3. AI Fit Diagnostic'!$AI$8:$AI$57,0))) | E39: =IF($H39="","",INDEX('3. AI Fit Diagnostic'!$W$8:$W$57,MATCH($H39,'3. AI Fit Diagnostic'!$AI$8:$AI$57,0))) | F39: =IF($H39="","",INDEX('3. AI Fit Diagnostic'!$Z$8:$Z$57,MATCH($H39,'3. AI Fit Diagnostic'!$AI$8:$AI$57,0))) | G39: =IF($H39="","",INDEX('3. AI Fit Diagnostic'!$AE$8:$AE$57,MATCH($H39,'3. AI Fit Diagnostic'!$AI$8:$AI$57,0))) | H39: =IF(IFERROR(SMALL('3. AI Fit Diagnostic'!$AI$8:$AI$57,COUNTIF('3. AI Fit Diagnostic'!$AI$8:$AI$57,"<"&200)+11),"")="","",IF(IFERROR(SMALL('3. AI Fit Diagnostic'!$AI$8:$AI$57,COUNTIF('3. AI Fit Diagnostic'!$AI$8:$AI$57,"<"&200)+11),"")<300,IFERROR(SMALL('3. AI Fit Diagnostic'!$AI$8:$AI$57,COUNTIF('3. AI Fit Diagnostic'!$AI$8:$AI$57,"<"&200)+11),""),""))
A40: =IF($H40="","",INDEX('3. AI Fit Diagnostic'!$AC$8:$AC$57,MATCH($H40,'3. AI Fit Diagnostic'!$AI$8:$AI$57,0))) | B40: =IF($H40="","",INDEX('3. AI Fit Diagnostic'!$AJ$8:$AJ$57,MATCH($H40,'3. AI Fit Diagnostic'!$AI$8:$AI$57,0))) | C40: =IF($H40="","",INDEX('3. AI Fit Diagnostic'!$P$8:$P$57,MATCH($H40,'3. AI Fit Diagnostic'!$AI$8:$AI$57,0))) | D40: =IF($H40="","",INDEX('3. AI Fit Diagnostic'!$R$8:$R$57,MATCH($H40,'3. AI Fit Diagnostic'!$AI$8:$AI$57,0))) | E40: =IF($H40="","",INDEX('3. AI Fit Diagnostic'!$W$8:$W$57,MATCH($H40,'3. AI Fit Diagnostic'!$AI$8:$AI$57,0))) | F40: =IF($H40="","",INDEX('3. AI Fit Diagnostic'!$Z$8:$Z$57,MATCH($H40,'3. AI Fit Diagnostic'!$AI$8:$AI$57,0))) | G40: =IF($H40="","",INDEX('3. AI Fit Diagnostic'!$AE$8:$AE$57,MATCH($H40,'3. AI Fit Diagnostic'!$AI$8:$AI$57,0))) | H40: =IF(IFERROR(SMALL('3. AI Fit Diagnostic'!$AI$8:$AI$57,COUNTIF('3. AI Fit Diagnostic'!$AI$8:$AI$57,"<"&200)+12),"")="","",IF(IFERROR(SMALL('3. AI Fit Diagnostic'!$AI$8:$AI$57,COUNTIF('3. AI Fit Diagnostic'!$AI$8:$AI$57,"<"&200)+12),"")<300,IFERROR(SMALL('3. AI Fit Diagnostic'!$AI$8:$AI$57,COUNTIF('3. AI Fit Diagnostic'!$AI$8:$AI$57,"<"&200)+12),""),""))
A42: H3 - Later (12-24 months)
A43: Rank | B43: Process / use case | C43: Function | D43: Solution family | E43: Verdict | F43: Risk tier | G43: Hours / yr
A44: =IF($H44="","",INDEX('3. AI Fit Diagnostic'!$AC$8:$AC$57,MATCH($H44,'3. AI Fit Diagnostic'!$AI$8:$AI$57,0))) -> 19 | B44: =IF($H44="","",INDEX('3. AI Fit Diagnostic'!$AJ$8:$AJ$57,MATCH($H44,'3. AI Fit Diagnostic'!$AI$8:$AI$57,0))) -> Customer churn prediction | C44: =IF($H44="","",INDEX('3. AI Fit Diagnostic'!$P$8:$P$57,MATCH($H44,'3. AI Fit Diagnostic'!$AI$8:$AI$57,0))) -> Sales & marketing | D44: =IF($H44="","",INDEX('3. AI Fit Diagnostic'!$R$8:$R$57,MATCH($H44,'3. AI Fit Diagnostic'!$AI$8:$AI$57,0))) -> Predictive analytics / machine learning | E44: =IF($H44="","",INDEX('3. AI Fit Diagnostic'!$W$8:$W$57,MATCH($H44,'3. AI Fit Diagnostic'!$AI$8:$AI$57,0))) -> AI later - close data gap first | F44: =IF($H44="","",INDEX('3. AI Fit Diagnostic'!$Z$8:$Z$57,MATCH($H44,'3. AI Fit Diagnostic'!$AI$8:$AI$57,0))) -> Medium | G44: =IF($H44="","",INDEX('3. AI Fit Diagnostic'!$AE$8:$AE$57,MATCH($H44,'3. AI Fit Diagnostic'!$AI$8:$AI$57,0))) -> 480 | H44: =IF(IFERROR(SMALL('3. AI Fit Diagnostic'!$AI$8:$AI$57,COUNTIF('3. AI Fit Diagnostic'!$AI$8:$AI$57,"<"&300)+1),"")="","",IF(IFERROR(SMALL('3. AI Fit Diagnostic'!$AI$8:$AI$57,COUNTIF('3. AI Fit Diagnostic'!$AI$8:$AI$57,"<"&300)+1),"")<400,IFERROR(SMALL('3. AI Fit Diagnostic'!$AI$8:$AI$57,COUNTIF('3. AI Fit Diagnostic'!$AI$8:$AI$57,"<"&300)+1),""),"")) -> 319
A45: =IF($H45="","",INDEX('3. AI Fit Diagnostic'!$AC$8:$AC$57,MATCH($H45,'3. AI Fit Diagnostic'!$AI$8:$AI$57,0))) | B45: =IF($H45="","",INDEX('3. AI Fit Diagnostic'!$AJ$8:$AJ$57,MATCH($H45,'3. AI Fit Diagnostic'!$AI$8:$AI$57,0))) | C45: =IF($H45="","",INDEX('3. AI Fit Diagnostic'!$P$8:$P$57,MATCH($H45,'3. AI Fit Diagnostic'!$AI$8:$AI$57,0))) | D45: =IF($H45="","",INDEX('3. AI Fit Diagnostic'!$R$8:$R$57,MATCH($H45,'3. AI Fit Diagnostic'!$AI$8:$AI$57,0))) | E45: =IF($H45="","",INDEX('3. AI Fit Diagnostic'!$W$8:$W$57,MATCH($H45,'3. AI Fit Diagnostic'!$AI$8:$AI$57,0))) | F45: =IF($H45="","",INDEX('3. AI Fit Diagnostic'!$Z$8:$Z$57,MATCH($H45,'3. AI Fit Diagnostic'!$AI$8:$AI$57,0))) | G45: =IF($H45="","",INDEX('3. AI Fit Diagnostic'!$AE$8:$AE$57,MATCH($H45,'3. AI Fit Diagnostic'!$AI$8:$AI$57,0))) | H45: =IF(IFERROR(SMALL('3. AI Fit Diagnostic'!$AI$8:$AI$57,COUNTIF('3. AI Fit Diagnostic'!$AI$8:$AI$57,"<"&300)+2),"")="","",IF(IFERROR(SMALL('3. AI Fit Diagnostic'!$AI$8:$AI$57,COUNTIF('3. AI Fit Diagnostic'!$AI$8:$AI$57,"<"&300)+2),"")<400,IFERROR(SMALL('3. AI Fit Diagnostic'!$AI$8:$AI$57,COUNTIF('3. AI Fit Diagnostic'!$AI$8:$AI$57,"<"&300)+2),""),""))
A46: =IF($H46="","",INDEX('3. AI Fit Diagnostic'!$AC$8:$AC$57,MATCH($H46,'3. AI Fit Diagnostic'!$AI$8:$AI$57,0))) | B46: =IF($H46="","",INDEX('3. AI Fit Diagnostic'!$AJ$8:$AJ$57,MATCH($H46,'3. AI Fit Diagnostic'!$AI$8:$AI$57,0))) | C46: =IF($H46="","",INDEX('3. AI Fit Diagnostic'!$P$8:$P$57,MATCH($H46,'3. AI Fit Diagnostic'!$AI$8:$AI$57,0))) | D46: =IF($H46="","",INDEX('3. AI Fit Diagnostic'!$R$8:$R$57,MATCH($H46,'3. AI Fit Diagnostic'!$AI$8:$AI$57,0))) | E46: =IF($H46="","",INDEX('3. AI Fit Diagnostic'!$W$8:$W$57,MATCH($H46,'3. AI Fit Diagnostic'!$AI$8:$AI$57,0))) | F46: =IF($H46="","",INDEX('3. AI Fit Diagnostic'!$Z$8:$Z$57,MATCH($H46,'3. AI Fit Diagnostic'!$AI$8:$AI$57,0))) | G46: =IF($H46="","",INDEX('3. AI Fit Diagnostic'!$AE$8:$AE$57,MATCH($H46,'3. AI Fit Diagnostic'!$AI$8:$AI$57,0))) | H46: =IF(IFERROR(SMALL('3. AI Fit Diagnostic'!$AI$8:$AI$57,COUNTIF('3. AI Fit Diagnostic'!$AI$8:$AI$57,"<"&300)+3),"")="","",IF(IFERROR(SMALL('3. AI Fit Diagnostic'!$AI$8:$AI$57,COUNTIF('3. AI Fit Diagnostic'!$AI$8:$AI$57,"<"&300)+3),"")<400,IFERROR(SMALL('3. AI Fit Diagnostic'!$AI$8:$AI$57,COUNTIF('3. AI Fit Diagnostic'!$AI$8:$AI$57,"<"&300)+3),""),""))
A47: =IF($H47="","",INDEX('3. AI Fit Diagnostic'!$AC$8:$AC$57,MATCH($H47,'3. AI Fit Diagnostic'!$AI$8:$AI$57,0))) | B47: =IF($H47="","",INDEX('3. AI Fit Diagnostic'!$AJ$8:$AJ$57,MATCH($H47,'3. AI Fit Diagnostic'!$AI$8:$AI$57,0))) | C47: =IF($H47="","",INDEX('3. AI Fit Diagnostic'!$P$8:$P$57,MATCH($H47,'3. AI Fit Diagnostic'!$AI$8:$AI$57,0))) | D47: =IF($H47="","",INDEX('3. AI Fit Diagnostic'!$R$8:$R$57,MATCH($H47,'3. AI Fit Diagnostic'!$AI$8:$AI$57,0))) | E47: =IF($H47="","",INDEX('3. AI Fit Diagnostic'!$W$8:$W$57,MATCH($H47,'3. AI Fit Diagnostic'!$AI$8:$AI$57,0))) | F47: =IF($H47="","",INDEX('3. AI Fit Diagnostic'!$Z$8:$Z$57,MATCH($H47,'3. AI Fit Diagnostic'!$AI$8:$AI$57,0))) | G47: =IF($H47="","",INDEX('3. AI Fit Diagnostic'!$AE$8:$AE$57,MATCH($H47,'3. AI Fit Diagnostic'!$AI$8:$AI$57,0))) | H47: =IF(IFERROR(SMALL('3. AI Fit Diagnostic'!$AI$8:$AI$57,COUNTIF('3. AI Fit Diagnostic'!$AI$8:$AI$57,"<"&300)+4),"")="","",IF(IFERROR(SMALL('3. AI Fit Diagnostic'!$AI$8:$AI$57,COUNTIF('3. AI Fit Diagnostic'!$AI$8:$AI$57,"<"&300)+4),"")<400,IFERROR(SMALL('3. AI Fit Diagnostic'!$AI$8:$AI$57,COUNTIF('3. AI Fit Diagnostic'!$AI$8:$AI$57,"<"&300)+4),""),""))
A48: =IF($H48="","",INDEX('3. AI Fit Diagnostic'!$AC$8:$AC$57,MATCH($H48,'3. AI Fit Diagnostic'!$AI$8:$AI$57,0))) | B48: =IF($H48="","",INDEX('3. AI Fit Diagnostic'!$AJ$8:$AJ$57,MATCH($H48,'3. AI Fit Diagnostic'!$AI$8:$AI$57,0))) | C48: =IF($H48="","",INDEX('3. AI Fit Diagnostic'!$P$8:$P$57,MATCH($H48,'3. AI Fit Diagnostic'!$AI$8:$AI$57,0))) | D48: =IF($H48="","",INDEX('3. AI Fit Diagnostic'!$R$8:$R$57,MATCH($H48,'3. AI Fit Diagnostic'!$AI$8:$AI$57,0))) | E48: =IF($H48="","",INDEX('3. AI Fit Diagnostic'!$W$8:$W$57,MATCH($H48,'3. AI Fit Diagnostic'!$AI$8:$AI$57,0))) | F48: =IF($H48="","",INDEX('3. AI Fit Diagnostic'!$Z$8:$Z$57,MATCH($H48,'3. AI Fit Diagnostic'!$AI$8:$AI$57,0))) | G48: =IF($H48="","",INDEX('3. AI Fit Diagnostic'!$AE$8:$AE$57,MATCH($H48,'3. AI Fit Diagnostic'!$AI$8:$AI$57,0))) | H48: =IF(IFERROR(SMALL('3. AI Fit Diagnostic'!$AI$8:$AI$57,COUNTIF('3. AI Fit Diagnostic'!$AI$8:$AI$57,"<"&300)+5),"")="","",IF(IFERROR(SMALL('3. AI Fit Diagnostic'!$AI$8:$AI$57,COUNTIF('3. AI Fit Diagnostic'!$AI$8:$AI$57,"<"&300)+5),"")<400,IFERROR(SMALL('3. AI Fit Diagnostic'!$AI$8:$AI$57,COUNTIF('3. AI Fit Diagnostic'!$AI$8:$AI$57,"<"&300)+5),""),""))
A49: =IF($H49="","",INDEX('3. AI Fit Diagnostic'!$AC$8:$AC$57,MATCH($H49,'3. AI Fit Diagnostic'!$AI$8:$AI$57,0))) | B49: =IF($H49="","",INDEX('3. AI Fit Diagnostic'!$AJ$8:$AJ$57,MATCH($H49,'3. AI Fit Diagnostic'!$AI$8:$AI$57,0))) | C49: =IF($H49="","",INDEX('3. AI Fit Diagnostic'!$P$8:$P$57,MATCH($H49,'3. AI Fit Diagnostic'!$AI$8:$AI$57,0))) | D49: =IF($H49="","",INDEX('3. AI Fit Diagnostic'!$R$8:$R$57,MATCH($H49,'3. AI Fit Diagnostic'!$AI$8:$AI$57,0))) | E49: =IF($H49="","",INDEX('3. AI Fit Diagnostic'!$W$8:$W$57,MATCH($H49,'3. AI Fit Diagnostic'!$AI$8:$AI$57,0))) | F49: =IF($H49="","",INDEX('3. AI Fit Diagnostic'!$Z$8:$Z$57,MATCH($H49,'3. AI Fit Diagnostic'!$AI$8:$AI$57,0))) | G49: =IF($H49="","",INDEX('3. AI Fit Diagnostic'!$AE$8:$AE$57,MATCH($H49,'3. AI Fit Diagnostic'!$AI$8:$AI$57,0))) | H49: =IF(IFERROR(SMALL('3. AI Fit Diagnostic'!$AI$8:$AI$57,COUNTIF('3. AI Fit Diagnostic'!$AI$8:$AI$57,"<"&300)+6),"")="","",IF(IFERROR(SMALL('3. AI Fit Diagnostic'!$AI$8:$AI$57,COUNTIF('3. AI Fit Diagnostic'!$AI$8:$AI$57,"<"&300)+6),"")<400,IFERROR(SMALL('3. AI Fit Diagnostic'!$AI$8:$AI$57,COUNTIF('3. AI Fit Diagnostic'!$AI$8:$AI$57,"<"&300)+6),""),""))
A50: =IF($H50="","",INDEX('3. AI Fit Diagnostic'!$AC$8:$AC$57,MATCH($H50,'3. AI Fit Diagnostic'!$AI$8:$AI$57,0))) | B50: =IF($H50="","",INDEX('3. AI Fit Diagnostic'!$AJ$8:$AJ$57,MATCH($H50,'3. AI Fit Diagnostic'!$AI$8:$AI$57,0))) | C50: =IF($H50="","",INDEX('3. AI Fit Diagnostic'!$P$8:$P$57,MATCH($H50,'3. AI Fit Diagnostic'!$AI$8:$AI$57,0))) | D50: =IF($H50="","",INDEX('3. AI Fit Diagnostic'!$R$8:$R$57,MATCH($H50,'3. AI Fit Diagnostic'!$AI$8:$AI$57,0))) | E50: =IF($H50="","",INDEX('3. AI Fit Diagnostic'!$W$8:$W$57,MATCH($H50,'3. AI Fit Diagnostic'!$AI$8:$AI$57,0))) | F50: =IF($H50="","",INDEX('3. AI Fit Diagnostic'!$Z$8:$Z$57,MATCH($H50,'3. AI Fit Diagnostic'!$AI$8:$AI$57,0))) | G50: =IF($H50="","",INDEX('3. AI Fit Diagnostic'!$AE$8:$AE$57,MATCH($H50,'3. AI Fit Diagnostic'!$AI$8:$AI$57,0))) | H50: =IF(IFERROR(SMALL('3. AI Fit Diagnostic'!$AI$8:$AI$57,COUNTIF('3. AI Fit Diagnostic'!$AI$8:$AI$57,"<"&300)+7),"")="","",IF(IFERROR(SMALL('3. AI Fit Diagnostic'!$AI$8:$AI$57,COUNTIF('3. AI Fit Diagnostic'!$AI$8:$AI$57,"<"&300)+7),"")<400,IFERROR(SMALL('3. AI Fit Diagnostic'!$AI$8:$AI$57,COUNTIF('3. AI Fit Diagnostic'!$AI$8:$AI$57,"<"&300)+7),""),""))
A51: =IF($H51="","",INDEX('3. AI Fit Diagnostic'!$AC$8:$AC$57,MATCH($H51,'3. AI Fit Diagnostic'!$AI$8:$AI$57,0))) | B51: =IF($H51="","",INDEX('3. AI Fit Diagnostic'!$AJ$8:$AJ$57,MATCH($H51,'3. AI Fit Diagnostic'!$AI$8:$AI$57,0))) | C51: =IF($H51="","",INDEX('3. AI Fit Diagnostic'!$P$8:$P$57,MATCH($H51,'3. AI Fit Diagnostic'!$AI$8:$AI$57,0))) | D51: =IF($H51="","",INDEX('3. AI Fit Diagnostic'!$R$8:$R$57,MATCH($H51,'3. AI Fit Diagnostic'!$AI$8:$AI$57,0))) | E51: =IF($H51="","",INDEX('3. AI Fit Diagnostic'!$W$8:$W$57,MATCH($H51,'3. AI Fit Diagnostic'!$AI$8:$AI$57,0))) | F51: =IF($H51="","",INDEX('3. AI Fit Diagnostic'!$Z$8:$Z$57,MATCH($H51,'3. AI Fit Diagnostic'!$AI$8:$AI$57,0))) | G51: =IF($H51="","",INDEX('3. AI Fit Diagnostic'!$AE$8:$AE$57,MATCH($H51,'3. AI Fit Diagnostic'!$AI$8:$AI$57,0))) | H51: =IF(IFERROR(SMALL('3. AI Fit Diagnostic'!$AI$8:$AI$57,COUNTIF('3. AI Fit Diagnostic'!$AI$8:$AI$57,"<"&300)+8),"")="","",IF(IFERROR(SMALL('3. AI Fit Diagnostic'!$AI$8:$AI$57,COUNTIF('3. AI Fit Diagnostic'!$AI$8:$AI$57,"<"&300)+8),"")<400,IFERROR(SMALL('3. AI Fit Diagnostic'!$AI$8:$AI$57,COUNTIF('3. AI Fit Diagnostic'!$AI$8:$AI$57,"<"&300)+8),""),""))
