Workbook

Sheet Welcome
B1: GT AI READINESS & RISK ASSESSMENT TOOL
B2: Grant Thornton Bahrain | AI Governance, Risk & Compliance | Combines the NSW AI Assessment Framework, GT AI Ready7 and the GT AI Risk & Control Matrix v2.1
B4: WHEN TO USE THIS TOOL | D4: HOW IT WORKS (approx. 20-25 minutes) | F4: WHAT YOU GET
B5: - Before or early in your AI journey, to baseline readiness - Before scaling AI or deploying AI that affects customers or decisions - When AI is discovered in use without assessment (shadow AI) - When risk or context changes: new data, model, vendor, purpose or less human oversight - Annually, to track maturity progress Public GenAI tools used for low-risk drafting may be governed by your Acceptable Use Policy instead (AIAF approach). | D5: 1. PROFILE - organisation details and regulatory context 2. ASSESSMENT - 20 questions Part A: 4 questions on AI use and inherent risk (AIAF) Part B: 16 questions on readiness across 5 domains (8 on governance & risk) 3. REPORT - generated automatically, print-ready (A4) 4. ACTION PLAN - assign owners and dates to recommended actions | F5: - Overall AI readiness score and maturity level - Inherent AI risk tier (Low / Medium / High / Critical) - Overall AI risk exposure and recommended oversight pathway - Domain radar chart and responsible-AI principle coverage - Findings, potential risks and recommendations per area - Top-5 priorities and a phased roadmap - Applicable regulations (Bahrain PDPL, CBB, EU AI Act, GCC) - Printable report you can save as PDF and email
B7: COLOUR LEGEND | D7: REQUIREMENT TYPES (as in the AIAF) | F7: START HERE
B8: Input cell - select or type | D8: ⟳ Compliance Obligation - linked to laws / regulation | F8: Go to '1. Profile' >>
B9: Low / Largely met | D9: ⚠ Mandatory Requirement - baseline control expected for any AI use
B10: Medium / Moderate / Partially met | D10: ⚖ Ethical Consideration - responsible-AI principle | F10: Go to '2. Assessment' >>
B11: High / Minimal | D11: ☆ Recommended - good practice
B12: Critical / Very high / Not met | F12: View '3. Report' >>
B15: This is a self-assessment tool. Results depend on the accuracy of responses and do not constitute an audit, certification or legal advice. Version 2.0 - October 2026. GT internal scoring engine - do not distribute; clients complete the GT AI Readiness Questionnaire. SAMPLE: pre-completed with illustrative responses for Grant Thornton Bahrain, aligned to its AI Ready7 results (Sept 2026).

Sheet 1. Profile
B1: 1. ORGANISATION PROFILE
B2: Complete the yellow cells. The profile personalises the report and determines which regulatory considerations apply. Takes about 2 minutes.
B4: Organisation name | C4: Grant Thornton Bahrain | E4: Tip
B5: Sector | C5: Professional services | E5: Scope the assessment to the whole organisation for a readiness baseline, or to a single AI system to support a use-case decision. For use-case level risk assessment use the GT AI Risk Assessment Toolkit.
B6: Organisation size | C6: 251-1,000 employees
B7: Scope of assessment | C7: Whole organisation
B8: Scope description (optional) | C8: Firm-wide AI adoption across Audit, Tax, Advisory and internal functions
B9: Completed by | C9: AI Service Line Lead
B10: Role / title | C10: Director, Risk Advisory
B11: Email address (to send yourself the report)
B12: Assessment date (dd/mm/yyyy) | C12: 24/09/2026
B13: Grant Thornton contact (optional)
B15: REGULATORY CONTEXT
B16: Is the organisation licensed by the Central Bank of Bahrain (CBB)? | C16: No
B17: Do AI systems process personal data of individuals in Bahrain? | C17: Yes
B18: Are AI-enabled products / services offered in the EU, or AI outputs used in the EU? | C18: Yes
B19: Does the organisation operate in KSA, UAE or other GCC markets? | C19: Yes
B20: Is the organisation a government entity or public-sector body? | C20: No
B21: Does the organisation develop AI (provider) or only use it (deployer)? | C21: Deployer only (uses AI built by others)

Sheet 2. Assessment
B1: 2. ASSESSMENT - 20 questions | approx. 20 minutes
B2: Select the statement in column E that best describes your current state (choose the lower level if unsure - evidence should exist for the level selected). Part A profiles your AI use and inherent risk (based on the NSW AI Assessment Framework). Part B measures readiness across 5 domains (derived from the 7 GT AI Ready7 pillars), mapped to the GT AI RCM v2.1 controls. Results update live below and in the '3. Report' sheet.
B4: ANSWERED | D4: OVERALL AI READINESS | E4: MATURITY LEVEL | F4: INHERENT RISK TIER | H4: AI RISK EXPOSURE -> PATHWAY | I4: YOUR REPORT
B5: =Calc!B20&" / 20" -> 20 / 20 | D5: =IF(Calc!B45="","-",Calc!B45) -> 0.59166667 | E5: =IF(Calc!B46="","-",Calc!B46) -> Informed | F5: =IF(Calc!C32="","-",Calc!C32) -> Medium | H5: =IF(Calc!B57="","-",Calc!B57&" -> "&Calc!B58) -> Moderate -> PROCEED WITH CONDITIONS | I5: =IF(Calc!B21=1,"Ready - see 3. Report","Complete all questions") -> Ready - see 3. Report
B8: # | C8: Area | D8: Question | E8: Your response (select from list) | F8: Score | G8: Status | H8: What this means / recommended next step | I8: Linked controls (GT AI RCM v2.1) | J8: Requirement type
B9: PART A - AI USE & INHERENT RISK PROFILE (AIAF-based: how much could go wrong?)
B10: A1 | C10: AI use profile | D10: Which statement best describes how AI is used in your organisation today (including AI embedded in software and tools used by staff)? Consider approved and unapproved tools, vendor software with AI features and AI used by suppliers on your behalf. | E10: Approved enterprise GenAI tools and AI features embedded in business software across teams | F10: =IF(L10="","",INDEX(QBank!$C$2:$C$6,L10)) -> 2 | G10: =IF(L10="","Not answered",INDEX(QBank!$D$2:$D$6,L10)) -> Medium | H10: =IF(L10="","",INDEX(QBank!$E$2:$E$6,L10)) -> AI is part of day-to-day work. Exposure spans data protection, output quality, vendor dependence and consistent human review. | I10: Tiering factor (risk framework T1-T3) | J10: Inherent-risk driver | L10: =IF(E10="","",IFERROR(MATCH(E10,QBank!$B$2:$B$6,0),"")) -> 3
B11: A2 | C11: Decision impact | D11: What is the most significant type of decision or outcome your AI systems influence? Answer for the highest-impact AI use case in scope (AIAF: 'worst credible harm'). | E11: Customer- or client-facing outputs with limited individual impact (e.g., FAQ chatbots, marketing content) | F11: =IF(L11="","",INDEX(QBank!$C$7:$C$11,L11)) -> 2 | G11: =IF(L11="","Not answered",INDEX(QBank!$D$7:$D$11,L11)) -> Medium | H11: =IF(L11="","",INDEX(QBank!$E$7:$E$11,L11)) -> External stakeholders see AI outputs - disclosure, accuracy and reputational controls apply (e.g., EU AI Act Art. 50 where relevant). | I11: Tiering factor (risk framework T1-T3) | J11: Inherent-risk driver | L11: =IF(E11="","",IFERROR(MATCH(E11,QBank!$B$7:$B$11,0),"")) -> 3
B12: A3 | C12: Data sensitivity | D12: What is the most sensitive data processed by your AI systems (including data staff enter into AI tools)? Include prompts, uploaded documents, training / fine-tuning data, retrieval sources and logs. | E12: Confidential business or client information | F12: =IF(L12="","",INDEX(QBank!$C$12:$C$16,L12)) -> 2 | G12: =IF(L12="","Not answered",INDEX(QBank!$D$12:$D$16,L12)) -> Medium | H12: =IF(L12="","",INDEX(QBank!$E$12:$E$16,L12)) -> Confidentiality and contractual obligations apply; vendor data-use terms are critical. | I12: Tiering factor (risk framework T1-T3) | J12: Inherent-risk driver | L12: =IF(E12="","",IFERROR(MATCH(E12,QBank!$B$12:$B$16,0),"")) -> 3
B13: A4 | C13: Oversight & reversibility | D13: How much human oversight applies to AI outputs, and how reversible are the outcomes? AIAF considers autonomy, human oversight and whether outputs are reversible or correctable. | E13: A qualified human reviews and approves every AI output before it is used | F13: =IF(L13="","",INDEX(QBank!$C$17:$C$21,L13)) -> 1 | G13: =IF(L13="","Not answered",INDEX(QBank!$D$17:$D$21,L13)) -> Low | H13: =IF(L13="","",INDEX(QBank!$E$17:$E$21,L13)) -> Effective 'human-in-charge' control if reviewers are trained and have time and authority to challenge. | I13: Tiering factor (risk framework T1-T3) | J13: Inherent-risk driver | L13: =IF(E13="","",IFERROR(MATCH(E13,QBank!$B$17:$B$21,0),"")) -> 2
B14: PART B - AI READINESS & CONTROL MATURITY (5 domains + GT AI RCM: how well is it managed?)
B15: Q5 | C15: AI Governance AI governance structure & accountability | D15: Is there a defined AI governance structure - board / executive oversight, an AI committee with decision rights, named owners for every AI system and clear three-lines-of-defence responsibilities? Evidence: board / ExCo terms of reference covering AI, AI committee charter, RACI, AI system owner register, internal-audit coverage. | E15: AI committee or sponsor defined on paper; roles and decision rights partly documented | F15: =IF(L15="","",INDEX(QBank!$C$22:$C$26,L15)) -> 0.5 | G15: =IF(L15="","Not answered",INDEX(QBank!$D$22:$D$26,L15)) -> Partially met | H15: =IF(L15="","",INDEX(QBank!$E$22:$E$26,L15)) -> Assign named business and technical owners to every AI system and publish a RACI across the three lines of defence. | I15: GL-1, GL-2, GL-7, AA-1 | J15: ⚠ Mandatory Requirement | L15: =IF(E15="","",IFERROR(MATCH(E15,QBank!$B$22:$B$26,0),"")) -> 3
B16: Q6 | C16: AI Governance AI policy, acceptable use & regulatory compliance | D16: Do you have an approved AI (acceptable-use) policy and a process to identify and comply with applicable AI-related regulation (e.g., Bahrain PDPL, CBB rules, EU AI Act)? Evidence: AI policy, approved-tools list, staff acknowledgements, obligations register, compliance reviews. | E16: AI policy enforced with staff acknowledgement; obligations register maps regulations to controls and owners | F16: =IF(L16="","",INDEX(QBank!$C$27:$C$31,L16)) -> 0.75 | G16: =IF(L16="","Not answered",INDEX(QBank!$D$27:$D$31,L16)) -> Largely met | H16: =IF(L16="","",INDEX(QBank!$E$27:$E$31,L16)) -> Establish monthly regulatory horizon scanning and periodic compliance testing with evidence retention. | I16: GL-5, RO-1, RO-5 | J16: ⟳ Compliance Obligation | L16: =IF(E16="","",IFERROR(MATCH(E16,QBank!$B$27:$B$31,0),"")) -> 4
B17: Q7 | C17: AI Governance Responsible-AI guardrails & human oversight | D17: Are there practical guardrails for fairness, transparency and human oversight, overseen by an AI committee or centre of excellence? Evidence: committee / CoE charter, guardrail standards, human-in-charge procedures, bias tests, AI disclosures, appeal routes. | E17: AI committee / CoE established; guardrails defined for some areas (e.g., human review of outputs) | F17: =IF(L17="","",INDEX(QBank!$C$32:$C$36,L17)) -> 0.5 | G17: =IF(L17="","Not answered",INDEX(QBank!$D$32:$D$36,L17)) -> Partially met | H17: =IF(L17="","",INDEX(QBank!$E$32:$E$36,L17)) -> Apply mandatory human-in-charge controls and AI disclosure to all relevant AI; require committee approval for High / Critical uses. | I17: GL-7, RS-1, RS-4, RS-5, CO-1, CO-3 | J17: ⚖ Ethical Consideration | L17: =IF(E17="","",IFERROR(MATCH(E17,QBank!$B$32:$B$36,0),"")) -> 3
B18: Q8 | C18: AI Governance AI incidents, monitoring & assurance | D18: Are AI incidents detected, managed and reported, and is AI governance subject to internal audit or independent assurance? Evidence: AI incident categories, notification criteria, incident logs, internal-audit reports, vendor assurance, certification status. | E18: AI incident management with regulatory notification criteria; periodic internal audit of AI governance; assurance obtained from AI vendors | F18: =IF(L18="","",INDEX(QBank!$C$37:$C$41,L18)) -> 0.75 | G18: =IF(L18="","Not answered",INDEX(QBank!$D$37:$D$41,L18)) -> Largely met | H18: =IF(L18="","",INDEX(QBank!$E$37:$E$41,L18)) -> Implement post-incident learning and an ISO/IEC 42001 certification-readiness review. | I18: IM-1, IM-2, IM-3, AA-1, AA-2, RO-4 | J18: ⟳ Compliance Obligation | L18: =IF(E18="","",IFERROR(MATCH(E18,QBank!$B$37:$B$41,0),"")) -> 4
B19: Q9 | C19: AI Risk & Security AI risk management framework | D19: Is there a documented AI risk management framework - risk taxonomy, assessment method, scoring scales and treatment process - integrated with enterprise risk management? Evidence: AI risk framework / methodology (e.g., aligned to ISO/IEC 23894 or NIST AI RMF), AI risk register, link to the enterprise risk register, completed assessments. | E19: AI risks considered informally within general IT or project risk | F19: =IF(L19="","",INDEX(QBank!$C$42:$C$46,L19)) -> 0.25 | G19: =IF(L19="","Not answered",INDEX(QBank!$D$42:$D$46,L19)) -> Minimal | H19: =IF(L19="","",INDEX(QBank!$E$42:$E$46,L19)) -> Formalise the methodology, approve it at executive level and pilot it on current AI initiatives. | I19: RM-1, RM-2, RM-3, RM-5 | J19: ⚠ Mandatory Requirement | L19: =IF(E19="","",IFERROR(MATCH(E19,QBank!$B$42:$B$46,0),"")) -> 2
B20: Q10 | C20: AI Risk & Security AI risk appetite, KRIs & reporting | D20: Has the board approved an AI risk appetite with measurable tolerances, and are key risk indicators (KRIs) monitored and reported with defined escalation? Evidence: approved AI risk appetite statement, KRI library with thresholds, risk dashboards, escalation and breach records. | E20: AI risk appetite drafted; a few indicators tracked informally | F20: =IF(L20="","",INDEX(QBank!$C$47:$C$51,L20)) -> 0.5 | G20: =IF(L20="","Not answered",INDEX(QBank!$D$47:$D$51,L20)) -> Partially met | H20: =IF(L20="","",INDEX(QBank!$E$47:$E$51,L20)) -> Define KRIs with thresholds and escalation for each risk category and report them to the AI committee quarterly. | I20: RM-6, RM-4, GL-1 | J20: ⚠ Mandatory Requirement | L20: =IF(E20="","",IFERROR(MATCH(E20,QBank!$B$47:$B$51,0),"")) -> 3
B21: Q11 | C21: AI Risk & Security AI inventory & risk / impact assessment | D21: Do you maintain an inventory of AI systems with named owners, and assess AI risks and impacts (including third-party AI) before and after deployment? Evidence: AI register, risk-tiering records, impact assessments, vendor AI due diligence, re-assessment records. | E21: AI register with owners; risk assessments performed for some AI systems using a documented method | F21: =IF(L21="","",INDEX(QBank!$C$52:$C$56,L21)) -> 0.5 | G21: =IF(L21="","Not answered",INDEX(QBank!$D$52:$D$56,L21)) -> Partially met | H21: =IF(L21="","",INDEX(QBank!$E$52:$E$56,L21)) -> Extend assessments to all AI systems and third-party AI; set approval authority by risk tier. | I21: GL-8, RM-2, RM-5, TP-2 | J21: ⚠ Mandatory Requirement | L21: =IF(E21="","",IFERROR(MATCH(E21,QBank!$B$52:$B$56,0),"")) -> 3
B22: Q12 | C22: AI Risk & Security Third-party & AI supply-chain risk | D22: Are AI vendors, AI features in purchased software and foundation-model providers risk-assessed before use, with AI-specific contract clauses and ongoing monitoring? Evidence: AI vendor due-diligence questionnaire, contract clauses (no training on your data, residency, incident notice, audit rights), vendor assurance (ISO/IEC 42001, SOC 2), review records. | E22: AI questions added to vendor due diligence for some purchases; contract terms vary | F22: =IF(L22="","",INDEX(QBank!$C$57:$C$61,L22)) -> 0.5 | G22: =IF(L22="","Not answered",INDEX(QBank!$D$57:$D$61,L22)) -> Partially met | H22: =IF(L22="","",INDEX(QBank!$E$57:$E$61,L22)) -> Make AI due diligence mandatory and adopt standard AI contract clauses (no training on client data, residency, audit, incident notice). | I22: TP-1, TP-2, TP-3, SE-7, LC-6 | J22: ⟳ Compliance Obligation | L22: =IF(E22="","",IFERROR(MATCH(E22,QBank!$B$57:$B$61,0),"")) -> 3
B23: Q13 | C23: AI Risk & Security Securing AI systems | D23: Are AI systems protected with least-privilege access, secure development and testing (incl. red teaming for prompt injection), and runtime logging? Evidence: AI threat models, access reviews (incl. agent identities), AI red-team reports, guardrail and sandbox configurations, audit logs. Detailed test: GT AI Security & Agent Audit Checklist. | E23: AI-specific threats (e.g., prompt injection, data leakage) assessed for some systems; access controls and logging in place | F23: =IF(L23="","",INDEX(QBank!$C$62:$C$66,L23)) -> 0.5 | G23: =IF(L23="","Not answered",INDEX(QBank!$D$62:$D$66,L23)) -> Partially met | H23: =IF(L23="","",INDEX(QBank!$E$62:$E$66,L23)) -> Introduce AI red teaming before release, runtime guardrails (input / output filtering) and audit logging. | I23: SE-2, SE-3, SE-6 to SE-10, OM-2, AA-3 | J23: ⚠ Mandatory Requirement | L23: =IF(E23="","",IFERROR(MATCH(E23,QBank!$B$62:$B$66,0),"")) -> 3
B24: Q14 | C24: AI Risk & Security Defending against AI-enabled threats | D24: Is the organisation prepared for AI-enabled attacks such as deepfake impersonation, AI-crafted phishing and automated exploitation? Evidence: AI threat intelligence, out-of-band verification procedures, deepfake simulations, SOC use cases, playbooks, patch metrics. | E24: Deepfake-resilient verification for payments and sensitive requests; behaviour-based detection; AI incident playbooks exercised | F24: =IF(L24="","",INDEX(QBank!$C$67:$C$71,L24)) -> 0.75 | G24: =IF(L24="","Not answered",INDEX(QBank!$D$67:$D$71,L24)) -> Largely met | H24: =IF(L24="","",INDEX(QBank!$E$67:$E$71,L24)) -> Adopt continuous exposure management and AI-specific red teaming; reduce patch cycles to days. | I24: AT-1, AT-2, AT-3, AT-4 | J24: ☆ Recommended | L24: =IF(E24="","",IFERROR(MATCH(E24,QBank!$B$67:$B$71,0),"")) -> 4
B25: Q15 | C25: Training & Awareness AI training, literacy & awareness | D25: Have staff received AI literacy training appropriate to their role, and are specialist AI, governance and security skills being developed? Evidence: training curricula, completion records, role-based pathways, deepfake / phishing simulations, workforce plan. | E25: Mandatory AI literacy before tool access; role-based pathways for developers, oversight staff and leaders; scenario-based security awareness | F25: =IF(L25="","",INDEX(QBank!$C$72:$C$76,L25)) -> 0.75 | G25: =IF(L25="","Not answered",INDEX(QBank!$D$72:$D$76,L25)) -> Largely met | H25: =IF(L25="","",INDEX(QBank!$E$72:$E$76,L25)) -> Measure competence, refresh annually, and build an AI champions network and workforce plan. | I25: GL-4, RS-9 | J25: ⟳ Compliance Obligation | L25: =IF(E25="","",IFERROR(MATCH(E25,QBank!$B$72:$B$76,0),"")) -> 4
B26: Q16 | C26: Strategy & Value AI strategy & executive ownership | D26: Is there executive ownership and an approved AI strategy that defines the ambition, priorities and where AI will (and will not) be used? Evidence: approved AI strategy, named executive sponsor, AI budget, communicated priorities and experimentation boundaries. | E26: Executive sponsor named and AI strategy drafted, but not linked to business objectives or budget | F26: =IF(L26="","",INDEX(QBank!$C$77:$C$81,L26)) -> 0.5 | G26: =IF(L26="","Not answered",INDEX(QBank!$D$77:$D$81,L26)) -> Partially met | H26: =IF(L26="","",INDEX(QBank!$E$77:$E$81,L26)) -> Link the strategy to business objectives and budget; define experimentation ('sandbox') boundaries and communicate them. | I26: GL-1, GL-3 | J26: ☆ Recommended | L26: =IF(E26="","",IFERROR(MATCH(E26,QBank!$B$77:$B$81,0),"")) -> 3
B27: Q17 | C27: Strategy & Value Use-case portfolio & value realisation | D27: How are AI use cases identified, prioritised, approved and measured for value? Evidence: intake form, prioritisation criteria, business cases, benefit KPIs, portfolio reviews. | E27: Use-case intake exists and initiatives are prioritised, but benefits are not systematically tracked | F27: =IF(L27="","",INDEX(QBank!$C$82:$C$86,L27)) -> 0.5 | G27: =IF(L27="","Not answered",INDEX(QBank!$D$82:$D$86,L27)) -> Partially met | H27: =IF(L27="","",INDEX(QBank!$E$82:$E$86,L27)) -> Define benefit KPIs (financial and non-financial) at approval and assign benefit owners. | I27: GL-6, GL-5 | J27: ☆ Recommended | L27: =IF(E27="","",IFERROR(MATCH(E27,QBank!$B$82:$B$86,0),"")) -> 3
B28: Q18 | C28: Data & Technology Data governance, quality & privacy for AI | D28: Is data used by AI classified, quality-assured, traceable and protected in line with privacy requirements (e.g., Bahrain PDPL)? Evidence: data classification applied to AI, data-readiness assessments, lineage, DPIAs, redaction / anonymisation, transfer assessments. | E28: Data readiness assessed before approval; lineage and quality monitored; minimisation, anonymisation and prompt redaction applied; DPIAs standard | F28: =IF(L28="","",INDEX(QBank!$C$87:$C$91,L28)) -> 0.75 | G28: =IF(L28="","Not answered",INDEX(QBank!$D$87:$D$91,L28)) -> Largely met | H28: =IF(L28="","",INDEX(QBank!$E$87:$E$91,L28)) -> Automate data-quality and lineage monitoring; operationalise data-subject rights and transfer assessments for AI. | I28: LC-1, SE-4, PR-1, PR-4, PR-5, PR-6 | J28: ⟳ Compliance Obligation | L28: =IF(E28="","",IFERROR(MATCH(E28,QBank!$B$87:$B$91,0),"")) -> 4
B29: Q19 | C29: Data & Technology AI architecture, integration & monitoring | D29: Is there a common AI reference architecture with standard integration patterns, and are AI systems monitored for performance, drift and cost? Evidence: reference architecture, approved platforms, integration / agent patterns, monitoring dashboards, cost reports. | E29: Reference architecture drafted; approved platforms and integration patterns for most AI; basic performance monitoring | F29: =IF(L29="","",INDEX(QBank!$C$92:$C$96,L29)) -> 0.5 | G29: =IF(L29="","Not answered",INDEX(QBank!$D$92:$D$96,L29)) -> Partially met | H29: =IF(L29="","",INDEX(QBank!$E$92:$E$96,L29)) -> Centralise API / access control for AI, define agent execution authority and implement drift / performance monitoring with thresholds. | I29: LC-2, LC-3, LC-8, LC-12, OM-1, OM-4, RM-6 | J29: ☆ Recommended | L29: =IF(E29="","",IFERROR(MATCH(E29,QBank!$B$92:$B$96,0),"")) -> 3
B30: Q20 | C30: Data & Technology Model risk management & validation | D30: Are material AI / ML models independently validated before use and periodically, with a model inventory, performance thresholds and documented limitations? Evidence: model risk policy, model inventory with risk tiers, independent validation reports, performance monitoring, validation-findings tracker. | E30: Model inventory exists; validation performed for some material models | F30: =IF(L30="","",INDEX(QBank!$C$97:$C$101,L30)) -> 0.5 | G30: =IF(L30="","Not answered",INDEX(QBank!$D$97:$D$101,L30)) -> Partially met | H30: =IF(L30="","",INDEX(QBank!$E$97:$E$101,L30)) -> Validate all material models before use and on a risk-based cycle; document thresholds, limitations and conditions of use. | I30: LC-9, RS-6, LC-13, OM-1 | J30: ☆ Recommended | L30: =IF(E30="","",IFERROR(MATCH(E30,QBank!$B$97:$B$101,0),"")) -> 3

Sheet 3. Report
B1: AI READINESS & RISK ASSESSMENT - RESULTS REPORT | M1: HOW TO PRINT, SAVE OR EMAIL THIS REPORT
B2: =IF('1. Profile'!$C$4="","Organisation: (not specified)",'1. Profile'!$C$4)&" | "&IF('1. Profile'!$C$5="","",'1. Profile'!$C$5&" | ")&"Assessment date: "&IF('1. Profile'!$C$12="","-",IF(ISNUMBER('1. Profile'!$C$12),TEXT('1. Profile'!$C$12,"dd mmmm yyyy"),'1. Profile'!$C$12)) -> Grant Thornton Bahrain | Professional services | Assessment date: 24/09/2026 | M2: SAVE AS PDF (recommended): File > Save As > choose 'PDF' as the file type > Options > 'Active sheet(s)' > Save. Or File > Export > Create PDF/XPS. This uses Excel's built-in PDF engine and does not depend on any printer driver. PRINT: File > Print > 'Print Active Sheets' (A4 portrait, fitted to one page wide, page breaks between sections). Do not choose 'Print Entire Workbook'. IF 'MICROSOFT PRINT TO PDF' SHOWS AN ERROR: the Windows PDF printer driver is failing, not the workbook. Use Save As > PDF above, or select another printer. To repair the driver: Windows 'Turn Windows features on or off' > untick 'Microsoft Print to PDF' > OK > re-tick > OK, then restart Excel. EMAIL: save the PDF, then click the link below to open a pre-filled email with your headline results and attach the PDF. This panel is outside the print area and will not appear on the printed report.
B3: ="Scope: "&IF('1. Profile'!$C$7="","-",'1. Profile'!$C$7)&IF('1. Profile'!$C$8="",""," - "&'1. Profile'!$C$8)&" | Completed by: "&IF('1. Profile'!$C$9="","-",'1. Profile'!$C$9)&IF('1. Profile'!$C$10="",""," ("&'1. Profile'!$C$10&")") -> Scope: Whole organisation - Firm-wide AI adoption across Audit, Tax, Advisory and internal functions | Completed by: AI Service Line Lead (Director, Risk Advisory)
B4: =IF(Calc!B21=1,"Framework basis: NSW AI Assessment Framework (inherent risk) | ISO/IEC 42001, ISO/IEC 23894, NIST AI RMF | EU AI Act, Bahrain PDPL | GT AI RCM v2.1 (controls)","ASSESSMENT INCOMPLETE - "&Calc!B20&" of 20 questions answered. Results below are provisional.") -> Framework basis: NSW AI Assessment Framework (inherent risk) | ISO/IEC 42001, ISO/IEC 23894, NIST AI RMF | EU AI Act, Bahrain PDPL | GT AI RCM v2.1 (controls)
M5: =IF(Calc!B21=0,"Complete the assessment to enable email",IF('1. Profile'!$C$11="","Enter your email address in 1. Profile to enable the email link",HYPERLINK("mailto:"&'1. Profile'!$C$11&"?subject=AI%20Readiness%20Results&body="&SUBSTITUTE(SUBSTITUTE("AI readiness "&TEXT(Calc!B45,"0%")&" ("&Calc!B46&"); risk tier "&Calc!C32&"; exposure "&Calc!B57&". Report attached.","%","%25")," ","%20"),">> Click to email the results summary to "&'1. Profile'!$C$11))) -> Enter your email address in 1. Profile to enable the email link
B6: 1. EXECUTIVE SUMMARY
B7: OVERALL AI READINESS | E7: MATURITY LEVEL | G7: INHERENT RISK TIER | I7: OVERALL AI RISK EXPOSURE
B8: =IF(Calc!B45="","-",Calc!B45) -> 0.59166667 | E8: =IF(Calc!B46="","-",Calc!B46) -> Informed | G8: =IF(Calc!C32="","-",Calc!C32) -> Medium | I8: =IF(Calc!B57="","-",Calc!B57) -> Moderate
B9: ="Maturity scale: <50% Partial | 50-70% Informed | 70-90% Repeatable | 90%+ Adaptive" -> Maturity scale: <50% Partial | 50-70% Informed | 70-90% Repeatable | 90%+ Adaptive | E9: =Calc!B70 -> Awareness and some defined practices exist, but they are not consistently implemented. | G9: =IF(Calc!C30="","",TEXT(Calc!C30,"0%")&" of maximum inherent risk. "&Calc!C33) -> 43% of maximum inherent risk. No override applied | I9: ="Combines inherent risk tier and readiness maturity (see Methodology)" -> Combines inherent risk tier and readiness maturity (see Methodology)
B11: RECOMMENDED PATHWAY | D11: =IF(Calc!B58="","-",Calc!B58) -> PROCEED WITH CONDITIONS
B12: =Calc!C58 -> Continue AI adoption, but address the identified gaps through a time-bound remediation plan (within 90 days for priority items). Obtain SME review (risk, privacy, security) for new AI use cases.
B14: =Calc!B72 -> Based on the responses provided, Grant Thornton Bahrain has an overall AI readiness score of 59%, corresponding to the 'Informed' maturity level: awareness and some defined practices exist, but they are not consistently implemented. Its AI use profile indicates a MEDIUM inherent risk tier (43% of maximum inherent risk), resulting in an overall AI risk exposure rating of MODERATE. The strongest area is Training & Awareness (75%) and the area requiring most attention is AI Risk & Security (50%). Recommended pathway: PROCEED WITH CONDITIONS. Continue AI adoption, but address the identified gaps through a time-bound remediation plan (within 90 days for priority items). Obtain SME review (risk, privacy, security) for new AI use cases.
B16: POSITION ON THE AI ADOPTION MATURITY CURVE
B17: 1 Awareness | D17: 2 Use-case discovery | F17: 3 Controlled adoption | H17: 4 Enterprise enablement | J17: 5 Governance maturity
B18: =IF(Calc!$B$170=1,"▲ Adoption","")&IF(AND(Calc!$B$171=1,Calc!$B$170<>1),"● Governance",IF(Calc!$B$171=1," ● Governance","")) | D18: =IF(Calc!$B$170=2,"▲ Adoption","")&IF(AND(Calc!$B$171=2,Calc!$B$170<>2),"● Governance",IF(Calc!$B$171=2," ● Governance","")) | F18: =IF(Calc!$B$170=3,"▲ Adoption","")&IF(AND(Calc!$B$171=3,Calc!$B$170<>3),"● Governance",IF(Calc!$B$171=3," ● Governance","")) -> ▲ Adoption ● Governance | H18: =IF(Calc!$B$170=4,"▲ Adoption","")&IF(AND(Calc!$B$171=4,Calc!$B$170<>4),"● Governance",IF(Calc!$B$171=4," ● Governance","")) | J18: =IF(Calc!$B$170=5,"▲ Adoption","")&IF(AND(Calc!$B$171=5,Calc!$B$170<>5),"● Governance",IF(Calc!$B$171=5," ● Governance",""))
B19: =Calc!B174 -> Governance is keeping pace with adoption at Stage 3 (Controlled adoption). To move to Stage 4 (Enterprise enablement), put in place an AI committee, monitoring with KRIs, secure architecture and model validation.
B21: 2. READINESS BY DOMAIN
B22: Domain | D22: Score | E22: Maturity | F22: Progress
B23: AI Governance | D23: =IF(Calc!B37="","-",Calc!B37) -> 0.625 | E23: =IF(Calc!C37="","-",Calc!C37) -> Informed | F23: =IF(Calc!B37="",0,Calc!B37) -> 0.625
B24: AI Risk & Security | D24: =IF(Calc!B38="","-",Calc!B38) -> 0.5 | E24: =IF(Calc!C38="","-",Calc!C38) -> Informed | F24: =IF(Calc!B38="",0,Calc!B38) -> 0.5
B25: Training & Awareness | D25: =IF(Calc!B39="","-",Calc!B39) -> 0.75 | E25: =IF(Calc!C39="","-",Calc!C39) -> Repeatable | F25: =IF(Calc!B39="",0,Calc!B39) -> 0.75
B26: Strategy & Value | D26: =IF(Calc!B40="","-",Calc!B40) -> 0.5 | E26: =IF(Calc!C40="","-",Calc!C40) -> Informed | F26: =IF(Calc!B40="",0,Calc!B40) -> 0.5
B27: Data & Technology | D27: =IF(Calc!B41="","-",Calc!B41) -> 0.58333333 | E27: =IF(Calc!C41="","-",Calc!C41) -> Informed | F27: =IF(Calc!B41="",0,Calc!B41) -> 0.58333333
B28: OVERALL | D28: =IF(Calc!B45="","-",Calc!B45) -> 0.59166667 | E28: =IF(Calc!B46="","-",Calc!B46) -> Informed | F28: ="Target 70%" -> Target 70%
B30: Domain | D30: Potential risk if the domain is not strengthened (shown where score < 90%)
B31: AI Governance | D31: =IF(Calc!B37="","",IF(Calc!B37>=0.9,"Adaptive - maintain current practices.",Calc!E37)) -> Without clear accountability, policy, oversight and assurance, AI is adopted inconsistently, misused and breaches regulation without anyone noticing or answering for it.
B32: AI Risk & Security | D32: =IF(Calc!B38="","",IF(Calc!B38>=0.9,"Adaptive - maintain current practices.",Calc!E38)) -> Without an AI risk framework, risk appetite, impact assessments, third-party controls and AI security, the organisation is exposed to unmanaged AI risk, prompt injection, data leakage, model compromise and deepfake-enabled fraud.
B33: Training & Awareness | D33: =IF(Calc!B39="","",IF(Calc!B39>=0.9,"Adaptive - maintain current practices.",Calc!E39)) -> Low AI literacy and awareness increase unsafe use of AI tools, unchecked or biased outputs and susceptibility to AI-enabled phishing and deepfakes.
B34: Strategy & Value | D34: =IF(Calc!B40="","",IF(Calc!B40>=0.9,"Adaptive - maintain current practices.",Calc!E40)) -> Without clear direction, ownership and value tracking, AI adoption is fragmented, duplicated and hard to justify.
B35: Data & Technology | D35: =IF(Calc!B41="","",IF(Calc!B41>=0.9,"Adaptive - maintain current practices.",Calc!E41)) -> Weak data governance, architecture and model validation lead to inaccurate or biased outputs, privacy breaches, undetected drift and unsustainable costs.
B37: 3. AI USE & INHERENT RISK PROFILE (AIAF-based)
B38: Factor | D38: Your response | H38: Risk level | I38: Implication
B39: A1 AI use profile | D39: =IF('2. Assessment'!E10="","Not answered",'2. Assessment'!E10) -> Approved enterprise GenAI tools and AI features embedded in business software across teams | H39: ='2. Assessment'!G10 -> Medium | I39: ='2. Assessment'!H10 -> AI is part of day-to-day work. Exposure spans data protection, output quality, vendor dependence and consistent human review.
B40: A2 Decision impact | D40: =IF('2. Assessment'!E11="","Not answered",'2. Assessment'!E11) -> Customer- or client-facing outputs with limited individual impact (e.g., FAQ chatbots, marketing content) | H40: ='2. Assessment'!G11 -> Medium | I40: ='2. Assessment'!H11 -> External stakeholders see AI outputs - disclosure, accuracy and reputational controls apply (e.g., EU AI Act Art. 50 where relevant).
B41: A3 Data sensitivity | D41: =IF('2. Assessment'!E12="","Not answered",'2. Assessment'!E12) -> Confidential business or client information | H41: ='2. Assessment'!G12 -> Medium | I41: ='2. Assessment'!H12 -> Confidentiality and contractual obligations apply; vendor data-use terms are critical.
B42: A4 Oversight & reversibility | D42: =IF('2. Assessment'!E13="","Not answered",'2. Assessment'!E13) -> A qualified human reviews and approves every AI output before it is used | H42: ='2. Assessment'!G13 -> Low | I42: ='2. Assessment'!H13 -> Effective 'human-in-charge' control if reviewers are trained and have time and authority to challenge.
B43: ="Inherent risk tier: "&IF(Calc!C32="","-",UPPER(Calc!C32))&IF(Calc!C30="",""," ("&TEXT(Calc!C30,"0%")&" weighted inherent-risk score)") -> Inherent risk tier: MEDIUM (43% weighted inherent-risk score) | H43: =Calc!C33 -> No override applied
B45: 4. RESPONSIBLE-AI PRINCIPLE COVERAGE (NSW AIAF ethics principles)
B46: Principle | E46: Coverage | F46: Assessment | H46: Informed by questions
B47: Fairness | E47: =IF(Calc!B76="","-",Calc!B76) -> 0.58333333 | F47: =Calc!D76 -> Partially addressed | H47: =Calc!C76 -> Q7, Q18, Q20
B48: Privacy & Security | E48: =IF(Calc!B77="","-",Calc!B77) -> 0.65 | F48: =Calc!D77 -> Partially addressed | H48: =Calc!C77 -> Q6, Q12, Q13, Q14, Q18
B49: Transparency & Explainability | E49: =IF(Calc!B78="","-",Calc!B78) -> 0.625 | F49: =Calc!D78 -> Partially addressed | H49: =Calc!C78 -> Q7, Q8
B50: Accountability | E50: =IF(Calc!B79="","-",Calc!B79) -> 0.53125 | F50: =Calc!D79 -> Partially addressed | H50: =Calc!C79 -> Q5, Q6, Q8, Q9, Q10, Q11, Q12, Q16
B51: Human, Social & Environmental Wellbeing | E51: =IF(Calc!B80="","-",Calc!B80) -> 0.5 | F51: =Calc!D80 -> Partially addressed | H51: =Calc!C80 -> Q11, Q17
B52: Human-Centred Values | E52: =IF(Calc!B81="","-",Calc!B81) -> 0.625 | F52: =Calc!D81 -> Partially addressed | H52: =Calc!C81 -> Q7, Q15
B53: Reliability & Safety | E53: =IF(Calc!B82="","-",Calc!B82) -> 0.5 | F53: =Calc!D82 -> Partially addressed | H53: =Calc!C82 -> Q8, Q9, Q13, Q19, Q20
B54: Contestability | E54: =IF(Calc!B83="","-",Calc!B83) -> 0.625 | F54: =Calc!D83 -> Partially addressed | H54: =Calc!C83 -> Q7, Q8
B56: 5. DETAILED FINDINGS & RECOMMENDATIONS
B57: Area | D57: Your response & score | G57: Potential risk | I57: Recommended action
B58: Q5 AI governance structure & accountability AI Governance ⚠ Mandatory Requirement | D58: =IF('2. Assessment'!E15="","Not answered",TEXT('2. Assessment'!F15,"0%")&" - "&'2. Assessment'!G15&CHAR(10)&CHAR(10)&'2. Assessment'!E15) -> 50% - Partially met AI committee or sponsor defined on paper; roles and decision rights partly documented | G58: =IF('2. Assessment'!F15=1,"N/A - reported as fully met.","Unclear accountability for AI decisions and outcomes, inconsistent approvals and no escalation route when AI fails.") -> Unclear accountability for AI decisions and outcomes, inconsistent approvals and no escalation route when AI fails. | I58: =IF('2. Assessment'!E15="","",'2. Assessment'!H15&CHAR(10)&CHAR(10)&"Controls: GL-1, GL-2, GL-7, AA-1") -> Assign named business and technical owners to every AI system and publish a RACI across the three lines of defence. Controls: GL-1, GL-2, GL-7, AA-1
B59: Q6 AI policy, acceptable use & regulatory compliance AI Governance ⟳ Compliance Obligation | D59: =IF('2. Assessment'!E16="","Not answered",TEXT('2. Assessment'!F16,"0%")&" - "&'2. Assessment'!G16&CHAR(10)&CHAR(10)&'2. Assessment'!E16) -> 75% - Largely met AI policy enforced with staff acknowledgement; obligations register maps regulations to controls and owners | G59: =IF('2. Assessment'!F16=1,"N/A - reported as fully met.","Misuse of AI, data leakage and breach of legal or regulatory requirements, with exposure to penalties, licence conditions and reputational harm.") -> Misuse of AI, data leakage and breach of legal or regulatory requirements, with exposure to penalties, licence conditions and reputational harm. | I59: =IF('2. Assessment'!E16="","",'2. Assessment'!H16&CHAR(10)&CHAR(10)&"Controls: GL-5, RO-1, RO-5") -> Establish monthly regulatory horizon scanning and periodic compliance testing with evidence retention. Controls: GL-5, RO-1, RO-5
B60: Q7 Responsible-AI guardrails & human oversight AI Governance ⚖ Ethical Consideration | D60: =IF('2. Assessment'!E17="","Not answered",TEXT('2. Assessment'!F17,"0%")&" - "&'2. Assessment'!G17&CHAR(10)&CHAR(10)&'2. Assessment'!E17) -> 50% - Partially met AI committee / CoE established; guardrails defined for some areas (e.g., human review of outputs) | G60: =IF('2. Assessment'!F17=1,"N/A - reported as fully met.","Biased or harmful outcomes, undisclosed AI use and lack of accountability for AI-supported decisions.") -> Biased or harmful outcomes, undisclosed AI use and lack of accountability for AI-supported decisions. | I60: =IF('2. Assessment'!E17="","",'2. Assessment'!H17&CHAR(10)&CHAR(10)&"Controls: GL-7, RS-1, RS-4, RS-5, CO-1, CO-3") -> Apply mandatory human-in-charge controls and AI disclosure to all relevant AI; require committee approval for High / Critical uses. Controls: GL-7, RS-1, RS-4, RS-5, CO-1, CO-3
B61: Q8 AI incidents, monitoring & assurance AI Governance ⟳ Compliance Obligation | D61: =IF('2. Assessment'!E18="","Not answered",TEXT('2. Assessment'!F18,"0%")&" - "&'2. Assessment'!G18&CHAR(10)&CHAR(10)&'2. Assessment'!E18) -> 75% - Largely met AI incident management with regulatory notification criteria; periodic internal audit of AI governance; assurance obtained from AI vendors | G61: =IF('2. Assessment'!F18=1,"N/A - reported as fully met.","Delayed response to AI failures, missed regulatory notifications and lack of defensible evidence for regulators, auditors and clients.") -> Delayed response to AI failures, missed regulatory notifications and lack of defensible evidence for regulators, auditors and clients. | I61: =IF('2. Assessment'!E18="","",'2. Assessment'!H18&CHAR(10)&CHAR(10)&"Controls: IM-1, IM-2, IM-3, AA-1, AA-2, RO-4") -> Implement post-incident learning and an ISO/IEC 42001 certification-readiness review. Controls: IM-1, IM-2, IM-3, AA-1, AA-2, RO-4
B62: Q9 AI risk management framework AI Risk & Security ⚠ Mandatory Requirement | D62: =IF('2. Assessment'!E19="","Not answered",TEXT('2. Assessment'!F19,"0%")&" - "&'2. Assessment'!G19&CHAR(10)&CHAR(10)&'2. Assessment'!E19) -> 25% - Minimal AI risks considered informally within general IT or project risk | G62: =IF('2. Assessment'!F19=1,"N/A - reported as fully met.","AI risks go unidentified or are rated inconsistently, so high-risk AI is approved without proportionate controls.") -> AI risks go unidentified or are rated inconsistently, so high-risk AI is approved without proportionate controls. | I62: =IF('2. Assessment'!E19="","",'2. Assessment'!H19&CHAR(10)&CHAR(10)&"Controls: RM-1, RM-2, RM-3, RM-5") -> Formalise the methodology, approve it at executive level and pilot it on current AI initiatives. Controls: RM-1, RM-2, RM-3, RM-5
B63: Q10 AI risk appetite, KRIs & reporting AI Risk & Security ⚠ Mandatory Requirement | D63: =IF('2. Assessment'!E20="","Not answered",TEXT('2. Assessment'!F20,"0%")&" - "&'2. Assessment'!G20&CHAR(10)&CHAR(10)&'2. Assessment'!E20) -> 50% - Partially met AI risk appetite drafted; a few indicators tracked informally | G63: =IF('2. Assessment'!F20=1,"N/A - reported as fully met.","No shared view of how much AI risk is acceptable - leading to reckless adoption or blocked innovation - and late detection of deteriorating AI risk.") -> No shared view of how much AI risk is acceptable - leading to reckless adoption or blocked innovation - and late detection of deteriorating AI risk. | I63: =IF('2. Assessment'!E20="","",'2. Assessment'!H20&CHAR(10)&CHAR(10)&"Controls: RM-6, RM-4, GL-1") -> Define KRIs with thresholds and escalation for each risk category and report them to the AI committee quarterly. Controls: RM-6, RM-4, GL-1
B64: Q11 AI inventory & risk / impact assessment AI Risk & Security ⚠ Mandatory Requirement | D64: =IF('2. Assessment'!E21="","Not answered",TEXT('2. Assessment'!F21,"0%")&" - "&'2. Assessment'!G21&CHAR(10)&CHAR(10)&'2. Assessment'!E21) -> 50% - Partially met AI register with owners; risk assessments performed for some AI systems using a documented method | G64: =IF('2. Assessment'!F21=1,"N/A - reported as fully met.","Deployment of vulnerable, non-compliant or harmful AI systems and unknown AI exposure across the organisation and its supply chain.") -> Deployment of vulnerable, non-compliant or harmful AI systems and unknown AI exposure across the organisation and its supply chain. | I64: =IF('2. Assessment'!E21="","",'2. Assessment'!H21&CHAR(10)&CHAR(10)&"Controls: GL-8, RM-2, RM-5, TP-2") -> Extend assessments to all AI systems and third-party AI; set approval authority by risk tier. Controls: GL-8, RM-2, RM-5, TP-2
B65: Q12 Third-party & AI supply-chain risk AI Risk & Security ⟳ Compliance Obligation | D65: =IF('2. Assessment'!E22="","Not answered",TEXT('2. Assessment'!F22,"0%")&" - "&'2. Assessment'!G22&CHAR(10)&CHAR(10)&'2. Assessment'!E22) -> 50% - Partially met AI questions added to vendor due diligence for some purchases; contract terms vary | G65: =IF('2. Assessment'!F22=1,"N/A - reported as fully met.","Client or personal data used to train vendor models, unmanaged model changes, concentration on a single provider and regulatory breaches through suppliers.") -> Client or personal data used to train vendor models, unmanaged model changes, concentration on a single provider and regulatory breaches through suppliers. | I65: =IF('2. Assessment'!E22="","",'2. Assessment'!H22&CHAR(10)&CHAR(10)&"Controls: TP-1, TP-2, TP-3, SE-7, LC-6") -> Make AI due diligence mandatory and adopt standard AI contract clauses (no training on client data, residency, audit, incident notice). Controls: TP-1, TP-2, TP-3, SE-7, LC-6
B66: Q13 Securing AI systems AI Risk & Security ⚠ Mandatory Requirement | D66: =IF('2. Assessment'!E23="","Not answered",TEXT('2. Assessment'!F23,"0%")&" - "&'2. Assessment'!G23&CHAR(10)&CHAR(10)&'2. Assessment'!E23) -> 50% - Partially met AI-specific threats (e.g., prompt injection, data leakage) assessed for some systems; access controls and logging in place | G66: =IF('2. Assessment'!F23=1,"N/A - reported as fully met.","Unauthorised access, model compromise, data exfiltration through AI and undetected misuse.") -> Unauthorised access, model compromise, data exfiltration through AI and undetected misuse. | I66: =IF('2. Assessment'!E23="","",'2. Assessment'!H23&CHAR(10)&CHAR(10)&"Controls: SE-2, SE-3, SE-6 to SE-10, OM-2, AA-3") -> Introduce AI red teaming before release, runtime guardrails (input / output filtering) and audit logging. Controls: SE-2, SE-3, SE-6 to SE-10, OM-2, AA-3
B67: Q14 Defending against AI-enabled threats AI Risk & Security ☆ Recommended | D67: =IF('2. Assessment'!E24="","Not answered",TEXT('2. Assessment'!F24,"0%")&" - "&'2. Assessment'!G24&CHAR(10)&CHAR(10)&'2. Assessment'!E24) -> 75% - Largely met Deepfake-resilient verification for payments and sensitive requests; behaviour-based detection; AI incident playbooks exercised | G67: =IF('2. Assessment'!F24=1,"N/A - reported as fully met.","Deepfake-enabled fraud, account compromise and faster, more scalable attacks that outpace defences.") -> Deepfake-enabled fraud, account compromise and faster, more scalable attacks that outpace defences. | I67: =IF('2. Assessment'!E24="","",'2. Assessment'!H24&CHAR(10)&CHAR(10)&"Controls: AT-1, AT-2, AT-3, AT-4") -> Adopt continuous exposure management and AI-specific red teaming; reduce patch cycles to days. Controls: AT-1, AT-2, AT-3, AT-4
B68: Q15 AI training, literacy & awareness Training & Awareness ⟳ Compliance Obligation | D68: =IF('2. Assessment'!E25="","Not answered",TEXT('2. Assessment'!F25,"0%")&" - "&'2. Assessment'!G25&CHAR(10)&CHAR(10)&'2. Assessment'!E25) -> 75% - Largely met Mandatory AI literacy before tool access; role-based pathways for developers, oversight staff and leaders; scenario-based security awareness | G68: =IF('2. Assessment'!F25=1,"N/A - reported as fully met.","Unsafe use, susceptibility to AI-enabled threats and poor adoption; non-compliance with the EU AI Act Art. 4 AI-literacy duty where applicable.") -> Unsafe use, susceptibility to AI-enabled threats and poor adoption; non-compliance with the EU AI Act Art. 4 AI-literacy duty where applicable. | I68: =IF('2. Assessment'!E25="","",'2. Assessment'!H25&CHAR(10)&CHAR(10)&"Controls: GL-4, RS-9") -> Measure competence, refresh annually, and build an AI champions network and workforce plan. Controls: GL-4, RS-9
B69: Q16 AI strategy & executive ownership Strategy & Value ☆ Recommended | D69: =IF('2. Assessment'!E26="","Not answered",TEXT('2. Assessment'!F26,"0%")&" - "&'2. Assessment'!G26&CHAR(10)&CHAR(10)&'2. Assessment'!E26) -> 50% - Partially met Executive sponsor named and AI strategy drafted, but not linked to business objectives or budget | G69: =IF('2. Assessment'!F26=1,"N/A - reported as fully met.","Lack of executive direction leads to inconsistent AI use, unmanaged risk-taking, poor-quality outputs and fragmented adoption.") -> Lack of executive direction leads to inconsistent AI use, unmanaged risk-taking, poor-quality outputs and fragmented adoption. | I69: =IF('2. Assessment'!E26="","",'2. Assessment'!H26&CHAR(10)&CHAR(10)&"Controls: GL-1, GL-3") -> Link the strategy to business objectives and budget; define experimentation ('sandbox') boundaries and communicate them. Controls: GL-1, GL-3
B70: Q17 Use-case portfolio & value realisation Strategy & Value ☆ Recommended | D70: =IF('2. Assessment'!E27="","Not answered",TEXT('2. Assessment'!F27,"0%")&" - "&'2. Assessment'!G27&CHAR(10)&CHAR(10)&'2. Assessment'!E27) -> 50% - Partially met Use-case intake exists and initiatives are prioritised, but benefits are not systematically tracked | G70: =IF('2. Assessment'!F27=1,"N/A - reported as fully met.","Duplicated or low-value AI investment, shadow AI and inability to demonstrate return on investment.") -> Duplicated or low-value AI investment, shadow AI and inability to demonstrate return on investment. | I70: =IF('2. Assessment'!E27="","",'2. Assessment'!H27&CHAR(10)&CHAR(10)&"Controls: GL-6, GL-5") -> Define benefit KPIs (financial and non-financial) at approval and assign benefit owners. Controls: GL-6, GL-5
B71: Q18 Data governance, quality & privacy for AI Data & Technology ⟳ Compliance Obligation | D71: =IF('2. Assessment'!E28="","Not answered",TEXT('2. Assessment'!F28,"0%")&" - "&'2. Assessment'!G28&CHAR(10)&CHAR(10)&'2. Assessment'!E28) -> 75% - Largely met Data readiness assessed before approval; lineage and quality monitored; minimisation, anonymisation and prompt redaction applied; DPIAs standard | G71: =IF('2. Assessment'!F28=1,"N/A - reported as fully met.","Data breaches, PDPL non-compliance, and biased or inaccurate outputs from poor-quality or unsuitable data.") -> Data breaches, PDPL non-compliance, and biased or inaccurate outputs from poor-quality or unsuitable data. | I71: =IF('2. Assessment'!E28="","",'2. Assessment'!H28&CHAR(10)&CHAR(10)&"Controls: LC-1, SE-4, PR-1, PR-4, PR-5, PR-6") -> Automate data-quality and lineage monitoring; operationalise data-subject rights and transfer assessments for AI. Controls: LC-1, SE-4, PR-1, PR-4, PR-5, PR-6
B72: Q19 AI architecture, integration & monitoring Data & Technology ☆ Recommended | D72: =IF('2. Assessment'!E29="","Not answered",TEXT('2. Assessment'!F29,"0%")&" - "&'2. Assessment'!G29&CHAR(10)&CHAR(10)&'2. Assessment'!E29) -> 50% - Partially met Reference architecture drafted; approved platforms and integration patterns for most AI; basic performance monitoring | G72: =IF('2. Assessment'!F29=1,"N/A - reported as fully met.","Inconsistent and insecure implementations, undetected model drift or failure, excessive agent privileges and unsustainable AI costs.") -> Inconsistent and insecure implementations, undetected model drift or failure, excessive agent privileges and unsustainable AI costs. | I72: =IF('2. Assessment'!E29="","",'2. Assessment'!H29&CHAR(10)&CHAR(10)&"Controls: LC-2, LC-3, LC-8, LC-12, OM-1, OM-4, RM-6") -> Centralise API / access control for AI, define agent execution authority and implement drift / performance monitoring with thresholds. Controls: LC-2, LC-3, LC-8, LC-12, OM-1, OM-4, RM-6
B73: Q20 Model risk management & validation Data & Technology ☆ Recommended | D73: =IF('2. Assessment'!E30="","Not answered",TEXT('2. Assessment'!F30,"0%")&" - "&'2. Assessment'!G30&CHAR(10)&CHAR(10)&'2. Assessment'!E30) -> 50% - Partially met Model inventory exists; validation performed for some material models | G73: =IF('2. Assessment'!F30=1,"N/A - reported as fully met.","Inaccurate, biased or unstable models drive decisions unnoticed, with regulatory exposure for financial-services clients.") -> Inaccurate, biased or unstable models drive decisions unnoticed, with regulatory exposure for financial-services clients. | I73: =IF('2. Assessment'!E30="","",'2. Assessment'!H30&CHAR(10)&CHAR(10)&"Controls: LC-9, RS-6, LC-13, OM-1") -> Validate all material models before use and on a risk-based cycle; document thresholds, limitations and conditions of use. Controls: LC-9, RS-6, LC-13, OM-1
B75: 6. TOP 5 PRIORITY ACTIONS
B76: Ranked by size of gap, weighted for compliance / mandatory requirements and the organisation's inherent risk tier.
B77: # | C77: Area | D77: Score | E77: Action | J77: Timing
B78: 1 | C78: =IF(Calc!B87="","",INDEX(Calc!$B:$B,Calc!B87)) -> AI risk management framework | D78: =IF(Calc!B87="","",INDEX(Calc!$E:$E,Calc!B87)) -> 0.25 | E78: =IF(Calc!B87="",IF(0=0,"No gaps identified - maintain current practices.",""),INDEX(Calc!$L:$L,Calc!B87)) -> Formalise the methodology, approve it at executive level and pilot it on current AI initiatives. | J78: =IF(Calc!B87="","",INDEX(Calc!$I:$I,Calc!B87)) -> Immediate (0-3 months)
B79: 2 | C79: =IF(Calc!B88="","",INDEX(Calc!$B:$B,Calc!B88)) -> AI governance structure & accountability | D79: =IF(Calc!B88="","",INDEX(Calc!$E:$E,Calc!B88)) -> 0.5 | E79: =IF(Calc!B88="",IF(1=0,"No gaps identified - maintain current practices.",""),INDEX(Calc!$L:$L,Calc!B88)) -> Assign named business and technical owners to every AI system and publish a RACI across the three lines of defence. | J79: =IF(Calc!B88="","",INDEX(Calc!$I:$I,Calc!B88)) -> Immediate (0-3 months)
B80: 3 | C80: =IF(Calc!B89="","",INDEX(Calc!$B:$B,Calc!B89)) -> AI risk appetite, KRIs & reporting | D80: =IF(Calc!B89="","",INDEX(Calc!$E:$E,Calc!B89)) -> 0.5 | E80: =IF(Calc!B89="",IF(2=0,"No gaps identified - maintain current practices.",""),INDEX(Calc!$L:$L,Calc!B89)) -> Define KRIs with thresholds and escalation for each risk category and report them to the AI committee quarterly. | J80: =IF(Calc!B89="","",INDEX(Calc!$I:$I,Calc!B89)) -> Immediate (0-3 months)
B81: 4 | C81: =IF(Calc!B90="","",INDEX(Calc!$B:$B,Calc!B90)) -> AI inventory & risk / impact assessment | D81: =IF(Calc!B90="","",INDEX(Calc!$E:$E,Calc!B90)) -> 0.5 | E81: =IF(Calc!B90="",IF(3=0,"No gaps identified - maintain current practices.",""),INDEX(Calc!$L:$L,Calc!B90)) -> Extend assessments to all AI systems and third-party AI; set approval authority by risk tier. | J81: =IF(Calc!B90="","",INDEX(Calc!$I:$I,Calc!B90)) -> Immediate (0-3 months)
B82: 5 | C82: =IF(Calc!B91="","",INDEX(Calc!$B:$B,Calc!B91)) -> Third-party & AI supply-chain risk | D82: =IF(Calc!B91="","",INDEX(Calc!$E:$E,Calc!B91)) -> 0.5 | E82: =IF(Calc!B91="",IF(4=0,"No gaps identified - maintain current practices.",""),INDEX(Calc!$L:$L,Calc!B91)) -> Make AI due diligence mandatory and adopt standard AI contract clauses (no training on client data, residency, audit, incident notice). | J82: =IF(Calc!B91="","",INDEX(Calc!$I:$I,Calc!B91)) -> Immediate (0-3 months)
B84: 7. SUGGESTED IMPLEMENTATION ROADMAP
B85: Horizon | D85: Area | F85: Action | K85: Controls
B86: =IF(Calc!C87="","",INDEX(Calc!$I:$I,Calc!C87)) -> Immediate (0-3 months) | D86: =IF(Calc!C87="","",INDEX(Calc!$B:$B,Calc!C87)) -> AI risk management framework | F86: =IF(Calc!C87="","",INDEX(Calc!$L:$L,Calc!C87)) -> Formalise the methodology, approve it at executive level and pilot it on current AI initiatives. | K86: =IF(Calc!C87="","",INDEX(Calc!$M:$M,Calc!C87)) -> RM-1, RM-2, RM-3, RM-5
B87: =IF(Calc!C88="","",INDEX(Calc!$I:$I,Calc!C88)) -> Immediate (0-3 months) | D87: =IF(Calc!C88="","",INDEX(Calc!$B:$B,Calc!C88)) -> AI governance structure & accountability | F87: =IF(Calc!C88="","",INDEX(Calc!$L:$L,Calc!C88)) -> Assign named business and technical owners to every AI system and publish a RACI across the three lines of defence. | K87: =IF(Calc!C88="","",INDEX(Calc!$M:$M,Calc!C88)) -> GL-1, GL-2, GL-7, AA-1
B88: =IF(Calc!C89="","",INDEX(Calc!$I:$I,Calc!C89)) -> Immediate (0-3 months) | D88: =IF(Calc!C89="","",INDEX(Calc!$B:$B,Calc!C89)) -> AI risk appetite, KRIs & reporting | F88: =IF(Calc!C89="","",INDEX(Calc!$L:$L,Calc!C89)) -> Define KRIs with thresholds and escalation for each risk category and report them to the AI committee quarterly. | K88: =IF(Calc!C89="","",INDEX(Calc!$M:$M,Calc!C89)) -> RM-6, RM-4, GL-1
B89: =IF(Calc!C90="","",INDEX(Calc!$I:$I,Calc!C90)) -> Immediate (0-3 months) | D89: =IF(Calc!C90="","",INDEX(Calc!$B:$B,Calc!C90)) -> AI inventory & risk / impact assessment | F89: =IF(Calc!C90="","",INDEX(Calc!$L:$L,Calc!C90)) -> Extend assessments to all AI systems and third-party AI; set approval authority by risk tier. | K89: =IF(Calc!C90="","",INDEX(Calc!$M:$M,Calc!C90)) -> GL-8, RM-2, RM-5, TP-2
B90: =IF(Calc!C91="","",INDEX(Calc!$I:$I,Calc!C91)) -> Immediate (0-3 months) | D90: =IF(Calc!C91="","",INDEX(Calc!$B:$B,Calc!C91)) -> Third-party & AI supply-chain risk | F90: =IF(Calc!C91="","",INDEX(Calc!$L:$L,Calc!C91)) -> Make AI due diligence mandatory and adopt standard AI contract clauses (no training on client data, residency, audit, incident notice). | K90: =IF(Calc!C91="","",INDEX(Calc!$M:$M,Calc!C91)) -> TP-1, TP-2, TP-3, SE-7, LC-6
B91: =IF(Calc!C92="","",INDEX(Calc!$I:$I,Calc!C92)) -> Immediate (0-3 months) | D91: =IF(Calc!C92="","",INDEX(Calc!$B:$B,Calc!C92)) -> Securing AI systems | F91: =IF(Calc!C92="","",INDEX(Calc!$L:$L,Calc!C92)) -> Introduce AI red teaming before release, runtime guardrails (input / output filtering) and audit logging. | K91: =IF(Calc!C92="","",INDEX(Calc!$M:$M,Calc!C92)) -> SE-2, SE-3, SE-6 to SE-10, OM-2, AA-3
B92: =IF(Calc!C93="","",INDEX(Calc!$I:$I,Calc!C93)) -> Short term (3-6 months) | D92: =IF(Calc!C93="","",INDEX(Calc!$B:$B,Calc!C93)) -> Responsible-AI guardrails & human oversight | F92: =IF(Calc!C93="","",INDEX(Calc!$L:$L,Calc!C93)) -> Apply mandatory human-in-charge controls and AI disclosure to all relevant AI; require committee approval for High / Critical uses. | K92: =IF(Calc!C93="","",INDEX(Calc!$M:$M,Calc!C93)) -> GL-7, RS-1, RS-4, RS-5, CO-1, CO-3
B93: =IF(Calc!C94="","",INDEX(Calc!$I:$I,Calc!C94)) -> Short term (3-6 months) | D93: =IF(Calc!C94="","",INDEX(Calc!$B:$B,Calc!C94)) -> AI strategy & executive ownership | F93: =IF(Calc!C94="","",INDEX(Calc!$L:$L,Calc!C94)) -> Link the strategy to business objectives and budget; define experimentation ('sandbox') boundaries and communicate them. | K93: =IF(Calc!C94="","",INDEX(Calc!$M:$M,Calc!C94)) -> GL-1, GL-3
B94: =IF(Calc!C95="","",INDEX(Calc!$I:$I,Calc!C95)) -> Short term (3-6 months) | D94: =IF(Calc!C95="","",INDEX(Calc!$B:$B,Calc!C95)) -> Use-case portfolio & value realisation | F94: =IF(Calc!C95="","",INDEX(Calc!$L:$L,Calc!C95)) -> Define benefit KPIs (financial and non-financial) at approval and assign benefit owners. | K94: =IF(Calc!C95="","",INDEX(Calc!$M:$M,Calc!C95)) -> GL-6, GL-5
B95: =IF(Calc!C96="","",INDEX(Calc!$I:$I,Calc!C96)) -> Short term (3-6 months) | D95: =IF(Calc!C96="","",INDEX(Calc!$B:$B,Calc!C96)) -> AI architecture, integration & monitoring | F95: =IF(Calc!C96="","",INDEX(Calc!$L:$L,Calc!C96)) -> Centralise API / access control for AI, define agent execution authority and implement drift / performance monitoring with thresholds. | K95: =IF(Calc!C96="","",INDEX(Calc!$M:$M,Calc!C96)) -> LC-2, LC-3, LC-8, LC-12, OM-1, OM-4, RM-6
B96: =IF(Calc!C97="","",INDEX(Calc!$I:$I,Calc!C97)) -> Short term (3-6 months) | D96: =IF(Calc!C97="","",INDEX(Calc!$B:$B,Calc!C97)) -> Model risk management & validation | F96: =IF(Calc!C97="","",INDEX(Calc!$L:$L,Calc!C97)) -> Validate all material models before use and on a risk-based cycle; document thresholds, limitations and conditions of use. | K96: =IF(Calc!C97="","",INDEX(Calc!$M:$M,Calc!C97)) -> LC-9, RS-6, LC-13, OM-1
B97: =IF(Calc!C98="","",INDEX(Calc!$I:$I,Calc!C98)) -> Medium term (6-12 months) | D97: =IF(Calc!C98="","",INDEX(Calc!$B:$B,Calc!C98)) -> AI policy, acceptable use & regulatory compliance | F97: =IF(Calc!C98="","",INDEX(Calc!$L:$L,Calc!C98)) -> Establish monthly regulatory horizon scanning and periodic compliance testing with evidence retention. | K97: =IF(Calc!C98="","",INDEX(Calc!$M:$M,Calc!C98)) -> GL-5, RO-1, RO-5
... B101: =IF(Calc!C102="","",INDEX(Calc!$I:$I,Calc!C102)) -> Medium term (6-12 months) | D101: =IF(Calc!C102="","",INDEX(Calc!$B:$B,Calc!C102)) -> Defending against AI-enabled threats | F101: =IF(Calc!C102="","",INDEX(Calc!$L:$L,Calc!C102)) -> Adopt continuous exposure management and AI-specific red teaming; reduce patch cycles to days. | K101: =IF(Calc!C102="","",INDEX(Calc!$M:$M,Calc!C102)) -> AT-1, AT-2, AT-3, AT-4
B103: 8. REGULATORY & STANDARDS CONSIDERATIONS
B104: Applicability is based on the Profile answers; the readiness signal uses the most relevant question scores. Not legal advice - confirm obligations with legal counsel.
B105: Law / regulation / standard | E105: Applies? | F105: Readiness signal | G105: Key considerations
B106: Bahrain Personal Data Protection Law (Law No. 30 of 2018) | E106: =IF(OR('1. Profile'!$C$17="Yes",N(Calc!B28)>=3),"Yes","Check") -> Yes | F106: =IF(COUNT(Calc!E215,Calc!E207)=0,"-",IF(MIN(Calc!E215,Calc!E207)>=0.75,"On track",IF(MIN(Calc!E215,Calc!E207)>=0.5,"Partial gap","Significant gap"))) -> Partial gap | G106: Lawful basis and notice for AI processing; DPIAs; security; data-subject rights incl. objection to automated processing; cross-border transfer rules for AI services hosted outside Bahrain (RCM PR-1 to PR-6).
B107: iGA General Policy for the Use of AI (2025) & GCC Guiding Manual on the Ethics of AI Use | E107: =IF('1. Profile'!$C$20="Yes","Yes","Reference") -> Reference | F107: =IF(COUNT(Calc!E212,Calc!E214)=0,"-",IF(MIN(Calc!E212,Calc!E214)>=0.75,"On track",IF(MIN(Calc!E212,Calc!E214)>=0.5,"Partial gap","Significant gap"))) -> Partial gap | G107: National AI policy pillars (compliance, adoption, awareness, cooperation) and GCC ethics principles - mandatory reference for government entities and good practice for all (RCM GL-1, GL-4, RS-series).
B108: Central Bank of Bahrain Rulebook (HC, RM, OM, BC modules) | E108: =IF('1. Profile'!$C$16="Yes","Yes","No") -> No | F108: =IF(COUNT(Calc!E210,Calc!E217,Calc!E218,Calc!E213)=0,"-",IF(MIN(Calc!E210,Calc!E217,Calc!E218,Calc!E213)>=0.75,"On track",IF(MIN(Calc!E210,Calc!E217,Calc!E218,Calc!E213)>=0.5,"Partial gap","Significant gap"))) -> Partial gap | G108: Board oversight, risk management, cyber security, outsourcing and consumer-protection requirements apply to AI; expect model validation for material models and notification of material outsourcing (RCM LC-9, TP-3, AT-3).
B109: EU AI Act (Regulation 2024/1689) - general obligations | E109: =IF('1. Profile'!$C$18="Yes","Yes","No") -> Yes | F109: =IF(COUNT(Calc!E207,Calc!E214)=0,"-",IF(MIN(Calc!E207,Calc!E214)>=0.75,"On track",IF(MIN(Calc!E207,Calc!E214)>=0.5,"Partial gap","Significant gap"))) -> On track | G109: Extraterritorial reach. Prohibited practices (Art. 5) and AI literacy (Art. 4) apply since Feb 2025; GPAI rules since Aug 2025; transparency (Art. 50) from Aug 2026 (RCM RM-5, GL-4, CO-1, LC-7).
B110: EU AI Act - high-risk AI systems (Annex III) | E110: =IF(AND('1. Profile'!$C$18="Yes",N(Calc!B27)>=3),"Likely",IF('1. Profile'!$C$18="Yes","Check","No")) -> Check | F110: =IF(COUNT(Calc!E208,Calc!E210,Calc!E212,Calc!E213)=0,"-",IF(MIN(Calc!E208,Calc!E210,Calc!E212,Calc!E213)>=0.75,"On track",IF(MIN(Calc!E208,Calc!E210,Calc!E212,Calc!E213)>=0.5,"Partial gap","Significant gap"))) -> Significant gap | G110: Decisions on credit, employment, insurance, essential services etc. may be high-risk: risk management, data governance, logging, human oversight, FRIA and registration (timelines subject to the EU Digital Omnibus outcome) (RCM RO-6).
B111: KSA / UAE / GCC regimes (SDAIA AI Ethics, KSA PDPL, UAE AI Charter, DIFC Regulation 10, QCB AI Guideline) | E111: =IF('1. Profile'!$C$19="Yes","Yes","No") -> Yes | F111: =IF(COUNT(Calc!E207,Calc!E215)=0,"-",IF(MIN(Calc!E207,Calc!E215)>=0.75,"On track",IF(MIN(Calc!E207,Calc!E215)>=0.5,"Partial gap","Significant gap"))) -> Partial gap | G111: Include in the AI obligations register; align data-transfer, ethics and sector AI requirements across GCC operations (RCM RO-5).
B112: ISO/IEC 42001:2023 AI management system | E112: =IF(Calc!B45="","-",IF(Calc!B45>=0.7,"Ready to plan","Build first")) -> Build first | F112: =IF(COUNT(Calc!E206,Calc!E208,Calc!E210,Calc!E213)=0,"-",IF(MIN(Calc!E206,Calc!E208,Calc!E210,Calc!E213)>=0.75,"On track",IF(MIN(Calc!E206,Calc!E208,Calc!E210,Calc!E213)>=0.5,"Partial gap","Significant gap"))) -> Significant gap | G112: International certifiable standard for AI governance; demonstrates trustworthy AI to clients and regulators. Recommended once readiness reaches 'Repeatable' (RCM AA-2).
B113: Bahrain draft AI Regulation Law (Shura Council, 2024) | E113: ="Monitor" -> Monitor | F113: =IF(COUNT(Calc!E207)=0,"-",IF(MIN(Calc!E207)>=0.75,"On track",IF(MIN(Calc!E207)>=0.5,"Partial gap","Significant gap"))) -> On track | G113: Proposed standalone AI law (38 articles) with a new regulator and penalties - not yet in force. Maintain horizon scanning (RCM RO-5).
B115: 9. HOW GRANT THORNTON CAN HELP
...

Sheet 4. Action Plan
B1: 4. ACTION PLAN & RISK TREATMENT TRACKER
B2: Columns B-H update automatically from the assessment. Assign an owner, target date and status (yellow cells) to track remediation. Priority rank 1 = most urgent.
B4: # | C4: Area | D4: Current score | E4: Priority rank | F4: Timing | G4: Recommended action | H4: Linked controls (RCM v2.1) | I4: Owner | J4: Target date | K4: Status | L4: Notes / evidence
B5: Q5 | C5: AI governance structure & accountability (AI Governance) | D5: =IF(Calc!E204="","-",Calc!E204) -> 0.5 | E5: =IFERROR(MATCH(204,Calc!$B$87:$B$102,0),"-") -> 2 | F5: =Calc!I204 -> Immediate (0-3 months) | G5: =Calc!L204 -> Assign named business and technical owners to every AI system and publish a RACI across the three lines of defence. | H5: GL-1, GL-2, GL-7, AA-1
B6: Q6 | C6: AI policy, acceptable use & regulatory compliance (AI Governance) | D6: =IF(Calc!E205="","-",Calc!E205) -> 0.75 | E6: =IFERROR(MATCH(205,Calc!$B$87:$B$102,0),"-") -> 12 | F6: =Calc!I205 -> Medium term (6-12 months) | G6: =Calc!L205 -> Establish monthly regulatory horizon scanning and periodic compliance testing with evidence retention. | H6: GL-5, RO-1, RO-5
B7: Q7 | C7: Responsible-AI guardrails & human oversight (AI Governance) | D7: =IF(Calc!E206="","-",Calc!E206) -> 0.5 | E7: =IFERROR(MATCH(206,Calc!$B$87:$B$102,0),"-") -> 7 | F7: =Calc!I206 -> Short term (3-6 months) | G7: =Calc!L206 -> Apply mandatory human-in-charge controls and AI disclosure to all relevant AI; require committee approval for High / Critical uses. | H7: GL-7, RS-1, RS-4, RS-5, CO-1, CO-3
B8: Q8 | C8: AI incidents, monitoring & assurance (AI Governance) | D8: =IF(Calc!E207="","-",Calc!E207) -> 0.75 | E8: =IFERROR(MATCH(207,Calc!$B$87:$B$102,0),"-") -> 13 | F8: =Calc!I207 -> Medium term (6-12 months) | G8: =Calc!L207 -> Implement post-incident learning and an ISO/IEC 42001 certification-readiness review. | H8: IM-1, IM-2, IM-3, AA-1, AA-2, RO-4
B9: Q9 | C9: AI risk management framework (AI Risk & Security) | D9: =IF(Calc!E208="","-",Calc!E208) -> 0.25 | E9: =IFERROR(MATCH(208,Calc!$B$87:$B$102,0),"-") -> 1 | F9: =Calc!I208 -> Immediate (0-3 months) | G9: =Calc!L208 -> Formalise the methodology, approve it at executive level and pilot it on current AI initiatives. | H9: RM-1, RM-2, RM-3, RM-5
B10: Q10 | C10: AI risk appetite, KRIs & reporting (AI Risk & Security) | D10: =IF(Calc!E209="","-",Calc!E209) -> 0.5 | E10: =IFERROR(MATCH(209,Calc!$B$87:$B$102,0),"-") -> 3 | F10: =Calc!I209 -> Immediate (0-3 months) | G10: =Calc!L209 -> Define KRIs with thresholds and escalation for each risk category and report them to the AI committee quarterly. | H10: RM-6, RM-4, GL-1
B11: Q11 | C11: AI inventory & risk / impact assessment (AI Risk & Security) | D11: =IF(Calc!E210="","-",Calc!E210) -> 0.5 | E11: =IFERROR(MATCH(210,Calc!$B$87:$B$102,0),"-") -> 4 | F11: =Calc!I210 -> Immediate (0-3 months) | G11: =Calc!L210 -> Extend assessments to all AI systems and third-party AI; set approval authority by risk tier. | H11: GL-8, RM-2, RM-5, TP-2
B12: Q12 | C12: Third-party & AI supply-chain risk (AI Risk & Security) | D12: =IF(Calc!E211="","-",Calc!E211) -> 0.5 | E12: =IFERROR(MATCH(211,Calc!$B$87:$B$102,0),"-") -> 5 | F12: =Calc!I211 -> Immediate (0-3 months) | G12: =Calc!L211 -> Make AI due diligence mandatory and adopt standard AI contract clauses (no training on client data, residency, audit, incident notice). | H12: TP-1, TP-2, TP-3, SE-7, LC-6
B13: Q13 | C13: Securing AI systems (AI Risk & Security) | D13: =IF(Calc!E212="","-",Calc!E212) -> 0.5 | E13: =IFERROR(MATCH(212,Calc!$B$87:$B$102,0),"-") -> 6 | F13: =Calc!I212 -> Immediate (0-3 months) | G13: =Calc!L212 -> Introduce AI red teaming before release, runtime guardrails (input / output filtering) and audit logging. | H13: SE-2, SE-3, SE-6 to SE-10, OM-2, AA-3
B14: Q14 | C14: Defending against AI-enabled threats (AI Risk & Security) | D14: =IF(Calc!E213="","-",Calc!E213) -> 0.75 | E14: =IFERROR(MATCH(213,Calc!$B$87:$B$102,0),"-") -> 16 | F14: =Calc!I213 -> Medium term (6-12 months) | G14: =Calc!L213 -> Adopt continuous exposure management and AI-specific red teaming; reduce patch cycles to days. | H14: AT-1, AT-2, AT-3, AT-4
B15: Q15 | C15: AI training, literacy & awareness (Training & Awareness) | D15: =IF(Calc!E214="","-",Calc!E214) -> 0.75 | E15: =IFERROR(MATCH(214,Calc!$B$87:$B$102,0),"-") -> 14 | F15: =Calc!I214 -> Medium term (6-12 months) | G15: =Calc!L214 -> Measure competence, refresh annually, and build an AI champions network and workforce plan. | H15: GL-4, RS-9
B16: Q16 | C16: AI strategy & executive ownership (Strategy & Value) | D16: =IF(Calc!E215="","-",Calc!E215) -> 0.5 | E16: =IFERROR(MATCH(215,Calc!$B$87:$B$102,0),"-") -> 8 | F16: =Calc!I215 -> Short term (3-6 months) | G16: =Calc!L215 -> Link the strategy to business objectives and budget; define experimentation ('sandbox') boundaries and communicate them. | H16: GL-1, GL-3
B17: Q17 | C17: Use-case portfolio & value realisation (Strategy & Value) | D17: =IF(Calc!E216="","-",Calc!E216) -> 0.5 | E17: =IFERROR(MATCH(216,Calc!$B$87:$B$102,0),"-") -> 9 | F17: =Calc!I216 -> Short term (3-6 months) | G17: =Calc!L216 -> Define benefit KPIs (financial and non-financial) at approval and assign benefit owners. | H17: GL-6, GL-5
B18: Q18 | C18: Data governance, quality & privacy for AI (Data & Technology) | D18: =IF(Calc!E217="","-",Calc!E217) -> 0.75 | E18: =IFERROR(MATCH(217,Calc!$B$87:$B$102,0),"-") -> 15 | F18: =Calc!I217 -> Medium term (6-12 months) | G18: =Calc!L217 -> Automate data-quality and lineage monitoring; operationalise data-subject rights and transfer assessments for AI. | H18: LC-1, SE-4, PR-1, PR-4, PR-5, PR-6
B19: Q19 | C19: AI architecture, integration & monitoring (Data & Technology) | D19: =IF(Calc!E218="","-",Calc!E218) -> 0.5 | E19: =IFERROR(MATCH(218,Calc!$B$87:$B$102,0),"-") -> 10 | F19: =Calc!I218 -> Short term (3-6 months) | G19: =Calc!L218 -> Centralise API / access control for AI, define agent execution authority and implement drift / performance monitoring with thresholds. | H19: LC-2, LC-3, LC-8, LC-12, OM-1, OM-4, RM-6
B20: Q20 | C20: Model risk management & validation (Data & Technology) | D20: =IF(Calc!E219="","-",Calc!E219) -> 0.5 | E20: =IFERROR(MATCH(219,Calc!$B$87:$B$102,0),"-") -> 11 | F20: =Calc!I219 -> Short term (3-6 months) | G20: =Calc!L219 -> Validate all material models before use and on a risk-based cycle; document thresholds, limitations and conditions of use. | H20: LC-9, RS-6, LC-13, OM-1

Sheet Methodology
B1: METHODOLOGY & FRAMEWORK MAPPING
B3: How the tool combines three frameworks
B4: 1) NSW AI Assessment Framework (AIAF, Digital NSW): lifecycle triggers, inherent-risk questions (AI use, decision impact, data, autonomy / reversibility), Low-Critical risk bands, pattern overrides, oversight pathways and the 8 ethics principles. 2) GT AI Ready7: the 7 pillars (33 items) are consolidated into 5 domains - AI Governance; AI Risk & Security (Protect AI Systems + Protection from AI Threats, plus AI risk management); Training & Awareness; Strategy & Value; Data & Technology - using the AI Ready7 maturity scale Partial / Informed / Repeatable / Adaptive. 3) GT AI RCM v2.1: every readiness question is mapped to the controls that evidence it, so results convert directly into a control-remediation plan.
B6: Scoring - Part A (inherent risk)
B7: Each answer scores 0-4. Weights: A1 AI use x2, A2 decision impact x3, A3 data sensitivity x2, A4 oversight & reversibility x3 (max 40). Weighted % bands: <25% Low, 25-49% Medium, 50-74% High, >=75% Critical. Overrides (AIAF 'pattern risk'): significant-effect decisions (A2=4) -> minimum High; A2=4 with oversight A4>=3 -> Critical; sensitive data (A3=4) -> minimum Medium.
B9: Scoring - Part B (readiness)
B10: Each answer maps to a maturity level 0-4 scored 0%, 25%, 50%, 75%, 100%. Domain score = average of its questions; overall readiness = equal-weighted average of the 5 domain scores. Maturity: <50% Partial, 50-69% Informed, 70-89% Repeatable, >=90% Adaptive (AI Ready7 scale).
B12: Exposure & pathway
B13: Exposure = f(inherent tier, maturity) per the matrix below. Pathways mirror the AIAF oversight model: Low -> Proceed (self-managed); Moderate -> Proceed with conditions (SME review, 90-day plan); High -> Remediate before scaling (committee oversight); Critical -> Pause high-impact AI and escalate (board / ExCo).
B15: Prioritisation
B16: Priority = gap (1 - score) x weight. Weight 1.5 for compliance obligations / mandatory requirements, +0.5 for inventory, guardrails and security when the inherent tier is High or Critical. Timing: score <=25% Immediate; 50% on a weighted item Immediate; 50% otherwise Short term; 75% Medium term; 100% Sustain.
B18: Exposure matrix
C19: Inherent tier \ Maturity | D19: Adaptive | E19: Repeatable | F19: Informed | G19: Partial
C20: Low | D20: Low | E20: Low | F20: Moderate | G20: Moderate
C21: Medium | D21: Low | E21: Moderate | F21: Moderate | G21: High
C22: High | D22: Moderate | E22: Moderate | F22: High | G22: Critical
C23: Critical | D23: Moderate | E23: High | F23: Critical | G23: Critical
B25: Question-to-framework mapping
B26: # | C26: Topic | D26: Domain (AI Ready7 items) | E26: Type | F26: AIAF principles | G26: GT AI RCM v2.1 controls | H26: Key references
B27: A1 | C27: AI use profile | D27: Inherent risk (Part A) | E27: Inherent-risk driver | F27: All (risk exposure) | G27: RM-5 tiering factor | H27: AIAF Q2, Q5; EU AI Act Art. 3
B28: A2 | C28: Decision impact | D28: Inherent risk (Part A) | E28: Inherent-risk driver | F28: All (risk exposure) | G28: RM-5 tiering factor | H28: AIAF Q7, Q8; EU AI Act Annex III
B29: A3 | C29: Data sensitivity | D29: Inherent risk (Part A) | E29: Inherent-risk driver | F29: All (risk exposure) | G29: RM-5 tiering factor | H29: AIAF Q4; Bahrain PDPL
B30: A4 | C30: Oversight & reversibility | D30: Inherent risk (Part A) | E30: Inherent-risk driver | F30: All (risk exposure) | G30: RM-5 tiering factor | H30: AIAF Q9, Q10, Q13; EU AI Act Art. 14
B31: Q5 | C31: AI governance structure & accountability | D31: AI Governance (1.1, 2.3) | E31: ⚠ Mandatory Requirement | F31: Accountability | G31: GL-1, GL-2, GL-7, AA-1 | H31: ISO/IEC 42001 cl.5, 6.2; NIST AI RMF Govern 1
B32: Q6 | C32: AI policy, acceptable use & regulatory compliance | D32: AI Governance (2.1, 2.2) | E32: ⟳ Compliance Obligation | F32: Accountability, Privacy & Security | G32: GL-5, RO-1, RO-5 | H32: ISO/IEC 42001 6.2; NIST AI RMF Map 3
B33: Q7 | C33: Responsible-AI guardrails & human oversight | D33: AI Governance (2.3, 5.2) | E33: ⚖ Ethical Consideration | F33: Fairness, Transparency & Explainability, Human-Centred Values, Contestability | G33: GL-7, RS-1, RS-4, RS-5, CO-1, CO-3 | H33: ISO/IEC 42001 cl.5.1-5.3, A.3; NIST AI RMF Govern 2; IIA Three Lines Model
B34: Q8 | C34: AI incidents, monitoring & assurance | D34: AI Governance (2.2, 7.4) | E34: ⟳ Compliance Obligation | F34: Accountability, Reliability & Safety, Contestability, Transparency & Explainability | G34: IM-1, IM-2, IM-3, AA-1, AA-2, RO-4 | H34: ISO/IEC 42001 A.2; EU AI Act Art. 5; Bahrain PDPL; CBB
B35: Q9 | C35: AI risk management framework | D35: AI Risk & Security (2.4) | E35: ⚠ Mandatory Requirement | F35: Accountability, Reliability & Safety | G35: RM-1, RM-2, RM-3, RM-5 | H35: ISO/IEC 23894; ISO/IEC 42001 6.1; NIST AI RMF Map/Measure/Manage
B36: Q10 | C36: AI risk appetite, KRIs & reporting | D36: AI Risk & Security (1.1, 4.4) | E36: ⚠ Mandatory Requirement | F36: Accountability | G36: RM-6, RM-4, GL-1 | H36: NIST AI RMF Govern 1.3; ISO 31000; CBB RM Module
B37: Q11 | C37: AI inventory & risk / impact assessment | D37: AI Risk & Security (2.4, 2.5) | E37: ⚠ Mandatory Requirement | F37: Accountability, Human, Social & Environmental Wellbeing | G37: GL-8, RM-2, RM-5, TP-2 | H37: ISO/IEC 42001 6.1, A.4, A.5; ISO/IEC 42005; EU AI Act Art. 9, 27
... B46: Q20 | C46: Model risk management & validation | D46: Data & Technology (4.4, 6.3) | E46: ☆ Recommended | F46: Reliability & Safety, Fairness | G46: LC-9, RS-6, LC-13, OM-1 | H46: MITRE ATLAS; FinCEN deepfake alert

Sheet QBank
A1: QID | B1: Option | C1: Value | D1: Status label | E1: Playback / next step | F1: Level
A2: A1 | B2: No AI in use and none planned within 12 months | C2: 0 | D2: Low | E2: Minimal current AI exposure. Readiness still matters: governance is easier to establish before adoption. | F2: Risk level 0 of 4
A3: A1 | B3: Exploratory use of public GenAI tools (e.g., ChatGPT, Copilot web) for internal productivity only | C3: 1 | D3: Low | E3: Main exposures are data leakage into public tools, inaccurate outputs and shadow AI. An acceptable-use policy and literacy training are the first priorities. | F3: Risk level 1 of 4
A4: A1 | B4: Approved enterprise GenAI tools and AI features embedded in business software across teams | C4: 2 | D4: Medium | E4: AI is part of day-to-day work. Exposure spans data protection, output quality, vendor dependence and consistent human review. | F4: Risk level 2 of 4
A5: A1 | B5: Custom or vendor-built AI / ML models supporting core processes or client services | C5: 3 | D5: High | E5: AI influences core outcomes. Model validation, monitoring, data governance and third-party assurance become essential. | F5: Risk level 3 of 4
A6: A1 | B6: AI agents or automated AI decisions acting directly on systems, customers or transactions | C6: 4 | D6: Very high | E6: Highest exposure profile: autonomous actions require execution limits, human approval points, kill-switches and continuous monitoring. | F6: Risk level 4 of 4
A7: A2 | B7: None - AI is used only for drafting, research or personal productivity | C7: 0 | D7: Low | E7: No direct decisions about people; impact limited to quality of internal work products. | F7: Risk level 0 of 4
A8: A2 | B8: Internal operational decisions with minor impact (e.g., scheduling, document triage) | C8: 1 | D8: Low | E8: Errors cause inconvenience but are easily corrected. | F8: Risk level 1 of 4
A9: A2 | B9: Customer- or client-facing outputs with limited individual impact (e.g., FAQ chatbots, marketing content) | C9: 2 | D9: Medium | E9: External stakeholders see AI outputs - disclosure, accuracy and reputational controls apply (e.g., EU AI Act Art. 50 where relevant). | F9: Risk level 2 of 4
A10: A2 | B10: Decisions materially affecting individuals' services, employment or finances, with human review | C10: 3 | D10: High | E10: Fairness, explainability, contestability and effective human oversight are required; impact assessments recommended. | F10: Risk level 3 of 4
A11: A2 | B11: Decisions with legal or similarly significant effects on individuals (credit, hiring, insurance, eligibility, health) made or determined by AI | C11: 4 | D11: Very high | E11: Likely 'high-risk' AI (e.g., EU AI Act Annex III). Full impact assessment, independent validation and committee approval required. | F11: Risk level 4 of 4
A12: A3 | B12: Public or synthetic data only | C12: 0 | D12: Low | E12: Low data-protection exposure. | F12: Risk level 0 of 4
A13: A3 | B13: Internal, non-confidential business information | C13: 1 | D13: Low | E13: Low-moderate exposure; basic data-handling rules apply. | F13: Risk level 1 of 4
... A101: Q20 | B101: Model risk management aligned to SR 11-7 / PRA SS1/23 principles, with continuous monitoring and findings tracked to closure | C101: 1 | D101: Fully met | E101: Sustain: align with SR 11-7 / PRA SS1/23 principles and report model risk to the risk committee. | F101: Level 4 - Optimised

Sheet Calc
A1: Per-question calculations
A20: Answered | B20: =SUM(D200:D219) -> 20
A21: Complete | B21: =IF(B20=20,1,0) -> 1
A25: Inherent risk
A26: A1 | B26: =IF(E200="","",E200) -> 2 | C26: 2
A27: A2 | B27: =IF(E201="","",E201) -> 2 | C27: 3
A28: A3 | B28: =IF(E202="","",E202) -> 2 | C28: 2
A29: A4 | B29: =IF(E203="","",E203) -> 1 | C29: 3
A30: Inherent % | C30: =IF(COUNT(B26:B29)<4,"",SUMPRODUCT(B26:B29,C26:C29)/(4*SUM(C26:C29))) -> 0.425
A31: Score tier | C31: =IF(C30="","",IF(C30>=0.75,"Critical",IF(C30>=0.5,"High",IF(C30>=0.25,"Medium","Low")))) -> Medium
A32: Final tier | C32: =IF(C31="","",IF(AND(B27=4,B29>=3),"Critical",IF(AND(B27=4,OR(C31="Low",C31="Medium")),"High",IF(AND(B28=4,C31="Low"),"Medium",C31)))) -> Medium
A33: Override note | C33: =IF(C31="","",IF(AND(B27=4,B29>=3),"Override: significant-effect decisions with limited oversight -> Critical",IF(AND(B27=4,OR(C31="Low",C31="Medium")),"Override: significant-effect decisions -> minimum High",IF(AND(B28=4,C31="Low"),"Override: sensitive data -> minimum Medium","No override applied")))) -> No override applied
A36: Pillar | B36: Score | C36: Maturity | D36: Target | E36: Risk statement | F36: Service | G36: Service priority | H36: Label
A37: AI Governance | B37: =IFERROR(AVERAGEIF($C$204:$C$219,A37,$E$204:$E$219),"") -> 0.625 | C37: =IF(B37="","",IF(B37>=0.9,"Adaptive",IF(B37>=0.7,"Repeatable",IF(B37>=0.5,"Informed","Partial")))) -> Informed | D37: 0.7 | E37: Without clear accountability, policy, oversight and assurance, AI is adopted inconsistently, misused and breaches regulation without anyone noticing or answering for it. | H37: Governance | I37: =IF(B37="",0,B37*100) -> 62.5 | J37: 70
A38: AI Risk & Security | B38: =IFERROR(AVERAGEIF($C$204:$C$219,A38,$E$204:$E$219),"") -> 0.5 | C38: =IF(B38="","",IF(B38>=0.9,"Adaptive",IF(B38>=0.7,"Repeatable",IF(B38>=0.5,"Informed","Partial")))) -> Informed | D38: 0.7 | E38: Without an AI risk framework, risk appetite, impact assessments, third-party controls and AI security, the organisation is exposed to unmanaged AI risk, prompt injection, data leakage, model compromise and deepfake-enabled fraud. | H38: Risk & Security | I38: =IF(B38="",0,B38*100) -> 50 | J38: 70
A39: Training & Awareness | B39: =IFERROR(AVERAGEIF($C$204:$C$219,A39,$E$204:$E$219),"") -> 0.75 | C39: =IF(B39="","",IF(B39>=0.9,"Adaptive",IF(B39>=0.7,"Repeatable",IF(B39>=0.5,"Informed","Partial")))) -> Repeatable | D39: 0.7 | E39: Low AI literacy and awareness increase unsafe use of AI tools, unchecked or biased outputs and susceptibility to AI-enabled phishing and deepfakes. | H39: Training | I39: =IF(B39="",0,B39*100) -> 75 | J39: 70
A40: Strategy & Value | B40: =IFERROR(AVERAGEIF($C$204:$C$219,A40,$E$204:$E$219),"") -> 0.5 | C40: =IF(B40="","",IF(B40>=0.9,"Adaptive",IF(B40>=0.7,"Repeatable",IF(B40>=0.5,"Informed","Partial")))) -> Informed | D40: 0.7 | E40: Without clear direction, ownership and value tracking, AI adoption is fragmented, duplicated and hard to justify. | H40: Strategy | I40: =IF(B40="",0,B40*100) -> 50 | J40: 70
A41: Data & Technology | B41: =IFERROR(AVERAGEIF($C$204:$C$219,A41,$E$204:$E$219),"") -> 0.58333333 | C41: =IF(B41="","",IF(B41>=0.9,"Adaptive",IF(B41>=0.7,"Repeatable",IF(B41>=0.5,"Informed","Partial")))) -> Informed | D41: 0.7 | E41: Weak data governance, architecture and model validation lead to inaccurate or biased outputs, privacy breaches, undetected drift and unsustainable costs. | H41: Data & Tech | I41: =IF(B41="",0,B41*100) -> 58.333333 | J41: 70
A45: Overall readiness | B45: =IF(COUNT(B37:B41)=0,"",AVERAGE(B37:B41)) -> 0.59166667
A46: Maturity | B46: =IF(B45="","",IF(B45>=0.9,"Adaptive",IF(B45>=0.7,"Repeatable",IF(B45>=0.5,"Informed","Partial")))) -> Informed
A47: Strongest pillar | B47: =IFERROR(INDEX(A37:A41,MATCH(MAX(B37:B41),B37:B41,0)),"") -> Training & Awareness | C47: =IFERROR(MAX(B37:B41),"") -> 0.75
A48: Weakest pillar | B48: =IFERROR(INDEX(A37:A41,MATCH(MIN(B37:B41),B37:B41,0)),"") -> AI Risk & Security | C48: =IFERROR(MIN(B37:B41),"") -> 0.5
A51: Exposure matrix | B51: Adaptive | C51: Repeatable | D51: Informed | E51: Partial
A52: Low | B52: Low | C52: Low | D52: Moderate | E52: Moderate
A53: Medium | B53: Low | C53: Moderate | D53: Moderate | E53: High
A54: High | B54: Moderate | C54: Moderate | D54: High | E54: Critical
A55: Critical | B55: Moderate | C55: High | D55: Critical | E55: Critical
A57: Exposure | B57: =IFERROR(INDEX($B$52:$E$55,MATCH(C32,$A$52:$A$55,0),MATCH(B46,$B$51:$E$51,0)),"") -> Moderate
A58: Pathway | B58: =IFERROR(VLOOKUP(B57,$A$60:$C$63,2,FALSE),"") -> PROCEED WITH CONDITIONS | C58: =IFERROR(VLOOKUP(B57,$A$60:$C$63,3,FALSE),"") -> Continue AI adoption, but address the identified gaps through a time-bound remediation plan (within 90 days for priority items). Obtain SME review (risk, privacy, security) for new AI use cases.
A60: Low | B60: PROCEED - SELF-MANAGED | C60: AI capability is broadly commensurate with the organisation's AI risk profile. Maintain controls, keep the AI register current and reassess annually or on material change.
A61: Moderate | B61: PROCEED WITH CONDITIONS | C61: Continue AI adoption, but address the identified gaps through a time-bound remediation plan (within 90 days for priority items). Obtain SME review (risk, privacy, security) for new AI use cases.
A62: High | B62: REMEDIATE BEFORE SCALING | C62: Readiness is insufficient for the organisation's AI risk profile. Limit AI to lower-risk uses until priority gaps are closed; place AI adoption under AI committee / executive oversight.
A63: Critical | B63: PAUSE HIGH-IMPACT AI & ESCALATE | C63: Significant AI exposure with immature controls. Escalate to the board / executive committee; do not deploy or expand high-impact AI until critical controls are in place.
A66: Partial | B66: Foundational capabilities are missing or ad hoc; AI risk is largely unmanaged.
A67: Informed | B67: Awareness and some defined practices exist, but they are not consistently implemented.
A68: Repeatable | B68: Practices are defined and consistently applied across most of the organisation.
A69: Adaptive | B69: Practices are optimised, measured and continuously improved.
A70: Maturity description | B70: =IFERROR(VLOOKUP(B46,$A$66:$B$69,2,FALSE),"") -> Awareness and some defined practices exist, but they are not consistently implemented.
A72: Narrative | B72: =IF(B21=0,"The assessment is incomplete ("&B20&" of 20 questions answered). Complete all questions in the Assessment sheet to generate the executive summary.","Based on the responses provided, "&IF('1. Profile'!$C$4="","the organisation",'1. Profile'!$C$4)&" has an overall AI readiness score of "&TEXT(B45,"0%")&", corresponding to the "&CHAR(39)&B46&CHAR(39)&" maturity level: "&LOWER(LEFT(B70,1))&MID(B70,2,300)&" Its AI use profile indicates a "&UPPER(C32)&" inherent risk tier ("&TEXT(C30,"0%")&" of maximum inherent risk), resulting in an overall AI risk exposure rating of "&UPPER(B57)&". The strongest area is "&B47&" ("&TEXT(C47,"0%")&") and the area requiring most attention is "&B48&" ("&TEXT(C48,"0%")&"). Recommended pathway: "&B58&". "&C58) -> Based on the responses provided, Grant Thornton Bahrain has an overall AI readiness score of 59%, corresponding to the 'Informed' maturity level: awareness and some defined practices exist, but they are not consistently implemented. Its AI use profile indicates a MEDIUM inherent risk tier (43% of maximum inherent risk), resulting in an overall AI risk exposure rating of MODERATE. The strongest area is Training & Awareness (75%) and the area requiring most attention is AI Risk & Security (50%). Recommended pathway: PROCEED WITH CONDITIONS. Continue AI adoption, but address the identified gaps through a time-bound remediation plan (within 90 days for priority items). Obtain SME review (risk, privacy, security) for new AI use cases.
A75: AIAF principle coverage
A76: Fairness | B76: =IFERROR(AVERAGE(E206,E217,E219),"") -> 0.58333333 | C76: Q7, Q18, Q20 | D76: =IF(B76="","",IF(B76>=0.75,"Well addressed",IF(B76>=0.5,"Partially addressed","Needs attention"))) -> Partially addressed
A77: Privacy & Security | B77: =IFERROR(AVERAGE(E205,E211,E212,E213,E217),"") -> 0.65 | C77: Q6, Q12, Q13, Q14, Q18 | D77: =IF(B77="","",IF(B77>=0.75,"Well addressed",IF(B77>=0.5,"Partially addressed","Needs attention"))) -> Partially addressed
A78: Transparency & Explainability | B78: =IFERROR(AVERAGE(E206,E207),"") -> 0.625 | C78: Q7, Q8 | D78: =IF(B78="","",IF(B78>=0.75,"Well addressed",IF(B78>=0.5,"Partially addressed","Needs attention"))) -> Partially addressed
A79: Accountability | B79: =IFERROR(AVERAGE(E204,E205,E207,E208,E209,E210,E211,E215),"") -> 0.53125 | C79: Q5, Q6, Q8, Q9, Q10, Q11, Q12, Q16 | D79: =IF(B79="","",IF(B79>=0.75,"Well addressed",IF(B79>=0.5,"Partially addressed","Needs attention"))) -> Partially addressed
A80: Human, Social & Environmental Wellbeing | B80: =IFERROR(AVERAGE(E210,E216),"") -> 0.5 | C80: Q11, Q17 | D80: =IF(B80="","",IF(B80>=0.75,"Well addressed",IF(B80>=0.5,"Partially addressed","Needs attention"))) -> Partially addressed
A81: Human-Centred Values | B81: =IFERROR(AVERAGE(E206,E214),"") -> 0.625 | C81: Q7, Q15 | D81: =IF(B81="","",IF(B81>=0.75,"Well addressed",IF(B81>=0.5,"Partially addressed","Needs attention"))) -> Partially addressed
A82: Reliability & Safety | B82: =IFERROR(AVERAGE(E207,E208,E212,E218,E219),"") -> 0.5 | C82: Q8, Q9, Q13, Q19, Q20 | D82: =IF(B82="","",IF(B82>=0.75,"Well addressed",IF(B82>=0.5,"Partially addressed","Needs attention"))) -> Partially addressed
A83: Contestability | B83: =IFERROR(AVERAGE(E206,E207),"") -> 0.625 | C83: Q7, Q8 | D83: =IF(B83="","",IF(B83>=0.75,"Well addressed",IF(B83>=0.5,"Partially addressed","Needs attention"))) -> Partially addressed
A86: Rank | B86: Priority row | C86: Roadmap row
A87: 1 | B87: =IFERROR(IF(LARGE($H$204:$H$219,A87)<0.5,"",MATCH(LARGE($H$204:$H$219,A87),$H$204:$H$219,0)+203),"") -> 208 | C87: =IFERROR(IF(LARGE($K$204:$K$219,A87)<1000,"",IF(INDEX($J$204:$J$219,MATCH(LARGE($K$204:$K$219,A87),$K$204:$K$219,0))<2,"",MATCH(LARGE($K$204:$K$219,A87),$K$204:$K$219,0)+203)),"") -> 208
A88: 2 | B88: =IFERROR(IF(LARGE($H$204:$H$219,A88)<0.5,"",MATCH(LARGE($H$204:$H$219,A88),$H$204:$H$219,0)+203),"") -> 204 | C88: =IFERROR(IF(LARGE($K$204:$K$219,A88)<1000,"",IF(INDEX($J$204:$J$219,MATCH(LARGE($K$204:$K$219,A88),$K$204:$K$219,0))<2,"",MATCH(LARGE($K$204:$K$219,A88),$K$204:$K$219,0)+203)),"") -> 204
A89: 3 | B89: =IFERROR(IF(LARGE($H$204:$H$219,A89)<0.5,"",MATCH(LARGE($H$204:$H$219,A89),$H$204:$H$219,0)+203),"") -> 209 | C89: =IFERROR(IF(LARGE($K$204:$K$219,A89)<1000,"",IF(INDEX($J$204:$J$219,MATCH(LARGE($K$204:$K$219,A89),$K$204:$K$219,0))<2,"",MATCH(LARGE($K$204:$K$219,A89),$K$204:$K$219,0)+203)),"") -> 209
A90: 4 | B90: =IFERROR(IF(LARGE($H$204:$H$219,A90)<0.5,"",MATCH(LARGE($H$204:$H$219,A90),$H$204:$H$219,0)+203),"") -> 210 | C90: =IFERROR(IF(LARGE($K$204:$K$219,A90)<1000,"",IF(INDEX($J$204:$J$219,MATCH(LARGE($K$204:$K$219,A90),$K$204:$K$219,0))<2,"",MATCH(LARGE($K$204:$K$219,A90),$K$204:$K$219,0)+203)),"") -> 210
A91: 5 | B91: =IFERROR(IF(LARGE($H$204:$H$219,A91)<0.5,"",MATCH(LARGE($H$204:$H$219,A91),$H$204:$H$219,0)+203),"") -> 211 | C91: =IFERROR(IF(LARGE($K$204:$K$219,A91)<1000,"",IF(INDEX($J$204:$J$219,MATCH(LARGE($K$204:$K$219,A91),$K$204:$K$219,0))<2,"",MATCH(LARGE($K$204:$K$219,A91),$K$204:$K$219,0)+203)),"") -> 211
A92: 6 | B92: =IFERROR(IF(LARGE($H$204:$H$219,A92)<0.5,"",MATCH(LARGE($H$204:$H$219,A92),$H$204:$H$219,0)+203),"") -> 212 | C92: =IFERROR(IF(LARGE($K$204:$K$219,A92)<1000,"",IF(INDEX($J$204:$J$219,MATCH(LARGE($K$204:$K$219,A92),$K$204:$K$219,0))<2,"",MATCH(LARGE($K$204:$K$219,A92),$K$204:$K$219,0)+203)),"") -> 212
A93: 7 | B93: =IFERROR(IF(LARGE($H$204:$H$219,A93)<0.5,"",MATCH(LARGE($H$204:$H$219,A93),$H$204:$H$219,0)+203),"") -> 206 | C93: =IFERROR(IF(LARGE($K$204:$K$219,A93)<1000,"",IF(INDEX($J$204:$J$219,MATCH(LARGE($K$204:$K$219,A93),$K$204:$K$219,0))<2,"",MATCH(LARGE($K$204:$K$219,A93),$K$204:$K$219,0)+203)),"") -> 206
A94: 8 | B94: =IFERROR(IF(LARGE($H$204:$H$219,A94)<0.5,"",MATCH(LARGE($H$204:$H$219,A94),$H$204:$H$219,0)+203),"") -> 215 | C94: =IFERROR(IF(LARGE($K$204:$K$219,A94)<1000,"",IF(INDEX($J$204:$J$219,MATCH(LARGE($K$204:$K$219,A94),$K$204:$K$219,0))<2,"",MATCH(LARGE($K$204:$K$219,A94),$K$204:$K$219,0)+203)),"") -> 215
A95: 9 | B95: =IFERROR(IF(LARGE($H$204:$H$219,A95)<0.5,"",MATCH(LARGE($H$204:$H$219,A95),$H$204:$H$219,0)+203),"") -> 216 | C95: =IFERROR(IF(LARGE($K$204:$K$219,A95)<1000,"",IF(INDEX($J$204:$J$219,MATCH(LARGE($K$204:$K$219,A95),$K$204:$K$219,0))<2,"",MATCH(LARGE($K$204:$K$219,A95),$K$204:$K$219,0)+203)),"") -> 216
A96: 10 | B96: =IFERROR(IF(LARGE($H$204:$H$219,A96)<0.5,"",MATCH(LARGE($H$204:$H$219,A96),$H$204:$H$219,0)+203),"") -> 218 | C96: =IFERROR(IF(LARGE($K$204:$K$219,A96)<1000,"",IF(INDEX($J$204:$J$219,MATCH(LARGE($K$204:$K$219,A96),$K$204:$K$219,0))<2,"",MATCH(LARGE($K$204:$K$219,A96),$K$204:$K$219,0)+203)),"") -> 218
A97: 11 | B97: =IFERROR(IF(LARGE($H$204:$H$219,A97)<0.5,"",MATCH(LARGE($H$204:$H$219,A97),$H$204:$H$219,0)+203),"") -> 219 | C97: =IFERROR(IF(LARGE($K$204:$K$219,A97)<1000,"",IF(INDEX($J$204:$J$219,MATCH(LARGE($K$204:$K$219,A97),$K$204:$K$219,0))<2,"",MATCH(LARGE($K$204:$K$219,A97),$K$204:$K$219,0)+203)),"") -> 219
A98: 12 | B98: =IFERROR(IF(LARGE($H$204:$H$219,A98)<0.5,"",MATCH(LARGE($H$204:$H$219,A98),$H$204:$H$219,0)+203),"") -> 205 | C98: =IFERROR(IF(LARGE($K$204:$K$219,A98)<1000,"",IF(INDEX($J$204:$J$219,MATCH(LARGE($K$204:$K$219,A98),$K$204:$K$219,0))<2,"",MATCH(LARGE($K$204:$K$219,A98),$K$204:$K$219,0)+203)),"") -> 205
... A102: 16 | B102: =IFERROR(IF(LARGE($H$204:$H$219,A102)<0.5,"",MATCH(LARGE($H$204:$H$219,A102),$H$204:$H$219,0)+203),"") -> 213 | C102: =IFERROR(IF(LARGE($K$204:$K$219,A102)<1000,"",IF(INDEX($J$204:$J$219,MATCH(LARGE($K$204:$K$219,A102),$K$204:$K$219,0))<2,"",MATCH(LARGE($K$204:$K$219,A102),$K$204:$K$219,0)+203)),"") -> 213
A120: AI Governance, Risk & Compliance | B120: AI Governance | C120: AI governance structure, policies and acceptable use, AI register, guardrails and human-oversight standards, RCM-based compliance reviews, ISO/IEC 42001 readiness and internal audit. | D120: =IFERROR(B37,"") -> 0.625 | E120: =IF(D120="","",IF(D120<0.5,"Priority",IF(D120<0.7,"Advised",IF(D120<0.9,"Optional","Sustain")))) -> Advised
A121: AI Risk & Cyber Resilience | B121: AI Risk & Security | C121: AI risk management framework and risk appetite, use-case risk & impact assessments, third-party AI risk, AI security audits (GT AI Security & Agent Audit Checklist), AI red teaming, deepfake-resilient processes. | D121: =IFERROR(B38,"") -> 0.5 | E121: =IF(D121="","",IF(D121<0.5,"Priority",IF(D121<0.7,"Advised",IF(D121<0.9,"Optional","Sustain")))) -> Advised
A122: Training & Awareness | B122: Training & Awareness | C122: AI literacy programmes (EU AI Act Art. 4-aligned), role-based pathways, immersive labs, deepfake & AI-phishing simulations, board AI governance sessions. | D122: =IFERROR(B39,"") -> 0.75 | E122: =IF(D122="","",IF(D122<0.5,"Priority",IF(D122<0.7,"Advised",IF(D122<0.9,"Optional","Sustain")))) -> Optional
A123: AI Strategy & Roadmap | B123: Strategy & Value | C123: AI Opportunity Discovery (where AI and automation fit), AI strategy, use-case prioritisation, value-realisation KPIs and phased roadmap. | D123: =IFERROR(B40,"") -> 0.5 | E123: =IF(D123="","",IF(D123<0.5,"Priority",IF(D123<0.7,"Advised",IF(D123<0.9,"Optional","Sustain")))) -> Advised
A124: AI-Driven Automation & Data | B124: Data & Technology | C124: Technology evaluation, data readiness, reference architecture, model validation and integration. GT AI apps in preparation: AI-powered BCP tool and AI-powered Financial Statements tool. | D124: =IFERROR(B41,"") -> 0.58333333 | E124: =IF(D124="","",IF(D124<0.5,"Priority",IF(D124<0.7,"Advised",IF(D124<0.9,"Optional","Sustain")))) -> Advised
A170: Adoption stage (from A1) | B170: =IF(B26="","",CHOOSE(B26+1,1,2,3,4,4)) -> 3
A171: Governance-supported stage | B171: =IF(B45="","",IF(B45>=0.9,5,IF(B45>=0.7,4,IF(B45>=0.5,3,IF(B45>=0.35,2,1))))) -> 3
A172: Curve position | B172: =IF(OR(B170="",B171=""),"",IF(AND(B171=5,B170>=3),5,B170)) -> 3
A173: Position label | B173: =IF(B172="","","Stage "&B172&" - "&INDEX($B$176:$B$180,B172)) -> Stage 3 - Controlled adoption
A174: Curve message | B174: =IF(B172="","",IF(B172=5,"The organisation has reached governance maturity: sustain board oversight, independent assurance and continuous improvement as AI use grows.",IF(B170>B171,"Adoption is ahead of governance: AI use is at Stage "&B170&" ("&INDEX($B$176:$B$180,B170)&") but governance currently supports Stage "&B171&" ("&INDEX($B$176:$B$180,B171)&"). Before scaling further, put in place "&INDEX($D$176:$D$180,B170)&", starting with "&B48&".",IF(B170=B171,"Governance is keeping pace with adoption at Stage "&B170&" ("&INDEX($B$176:$B$180,B170)&"). To move to Stage "&(B170+1)&" ("&INDEX($B$176:$B$180,MIN(5,B170+1))&"), put in place "&INDEX($D$176:$D$180,B170+1)&".","Governance foundations are ahead of current adoption (Stage "&B171&" vs Stage "&B170&"): the organisation can expand AI use with confidence. Next focus: "&INDEX($D$176:$D$180,B170+1)&".")))) -> Governance is keeping pace with adoption at Stage 3 (Controlled adoption). To move to Stage 4 (Enterprise enablement), put in place an AI committee, monitoring with KRIs, secure architecture and model validation.
A176: 1 | B176: Awareness | C176: Exploring AI through pilots and experiments; no approved tools yet | D176: an acceptable-use policy, AI literacy and a ban on confidential data in public AI tools
A177: 2 | B177: Use-case discovery | C177: Early use of AI tools; use cases being identified and tested | D177: an AI inventory, a use-case intake process and a named owner for every AI tool
A178: 3 | B178: Controlled adoption | C178: Approved AI tools in use across teams under defined controls | D178: risk assessment by tier, human oversight and vendor due diligence
A179: 4 | B179: Enterprise enablement | C179: AI embedded in core processes, models or agents at scale | D179: an AI committee, monitoring with KRIs, secure architecture and model validation
A180: 5 | B180: Governance maturity | C180: Oversight, assurance and controls embedded across the AI lifecycle | D180: board oversight, independent assurance and an ISO/IEC 42001-aligned management system
A199: QID | B199: Topic | C199: Pillar | D199: Answered | E199: Value | F199: Weight/Mult | G199: Gap | H199: Priority | I199: Horizon | J199: Horizon rank | K199: Sort key | L199: Recommendation | M199: RCM | N199: Type | O199: Response | P199: Status | Q199: Risk
A200: A1 | B200: AI use profile | C200: Context | D200: =IF('2. Assessment'!L10="",0,1) -> 1 | E200: =IF(D200=0,"",'2. Assessment'!F10) -> 2 | O200: ='2. Assessment'!E10 -> Approved enterprise GenAI tools and AI features embedded in business software across teams | P200: ='2. Assessment'!G10 -> Medium
A201: A2 | B201: Decision impact | C201: Context | D201: =IF('2. Assessment'!L11="",0,1) -> 1 | E201: =IF(D201=0,"",'2. Assessment'!F11) -> 2 | O201: ='2. Assessment'!E11 -> Customer- or client-facing outputs with limited individual impact (e.g., FAQ chatbots, marketing content) | P201: ='2. Assessment'!G11 -> Medium
A202: A3 | B202: Data sensitivity | C202: Context | D202: =IF('2. Assessment'!L12="",0,1) -> 1 | E202: =IF(D202=0,"",'2. Assessment'!F12) -> 2 | O202: ='2. Assessment'!E12 -> Confidential business or client information | P202: ='2. Assessment'!G12 -> Medium
A203: A4 | B203: Oversight & reversibility | C203: Context | D203: =IF('2. Assessment'!L13="",0,1) -> 1 | E203: =IF(D203=0,"",'2. Assessment'!F13) -> 1 | O203: ='2. Assessment'!E13 -> A qualified human reviews and approves every AI output before it is used | P203: ='2. Assessment'!G13 -> Low
A204: Q5 | B204: AI governance structure & accountability | C204: AI Governance | D204: =IF('2. Assessment'!L15="",0,1) -> 1 | E204: =IF(D204=0,"",'2. Assessment'!F15) -> 0.5 | F204: =1.5+IF(AND(OR(Calc!$C$32="High",Calc!$C$32="Critical"),OR(A204="Q7",A204="Q9",A204="Q11",A204="Q19")),0.5,0) -> 1.5 | G204: =IF(E204="","",1-E204) -> 0.5 | H204: =IF(E204="",-1,G204*F204*100+(20-4)/100) -> 75.16 | I204: =IF(E204="","",IF(E204<=0.25,"Immediate (0-3 months)",IF(AND(E204=0.5,F204>=1.5),"Immediate (0-3 months)",IF(E204<=0.5,"Short term (3-6 months)",IF(E204<=0.75,"Medium term (6-12 months)","Sustain"))))) -> Immediate (0-3 months) | J204: =IF(I204="",0,IF(LEFT(I204,3)="Imm",4,IF(LEFT(I204,3)="Sho",3,IF(LEFT(I204,3)="Med",2,1)))) -> 4 | K204: =IF(E204="",-1,J204*1000+H204) -> 4075.16 | L204: ='2. Assessment'!H15 -> Assign named business and technical owners to every AI system and publish a RACI across the three lines of defence. | M204: GL-1, GL-2, GL-7, AA-1 | N204: ⚠ Mandatory Requirement | O204: ='2. Assessment'!E15 -> AI committee or sponsor defined on paper; roles and decision rights partly documented | P204: ='2. Assessment'!G15 -> Partially met | Q204: Unclear accountability for AI decisions and outcomes, inconsistent approvals and no escalation route when AI fails.
A205: Q6 | B205: AI policy, acceptable use & regulatory compliance | C205: AI Governance | D205: =IF('2. Assessment'!L16="",0,1) -> 1 | E205: =IF(D205=0,"",'2. Assessment'!F16) -> 0.75 | F205: =1.5+IF(AND(OR(Calc!$C$32="High",Calc!$C$32="Critical"),OR(A205="Q7",A205="Q9",A205="Q11",A205="Q19")),0.5,0) -> 1.5 | G205: =IF(E205="","",1-E205) -> 0.25 | H205: =IF(E205="",-1,G205*F205*100+(20-5)/100) -> 37.65 | I205: =IF(E205="","",IF(E205<=0.25,"Immediate (0-3 months)",IF(AND(E205=0.5,F205>=1.5),"Immediate (0-3 months)",IF(E205<=0.5,"Short term (3-6 months)",IF(E205<=0.75,"Medium term (6-12 months)","Sustain"))))) -> Medium term (6-12 months) | J205: =IF(I205="",0,IF(LEFT(I205,3)="Imm",4,IF(LEFT(I205,3)="Sho",3,IF(LEFT(I205,3)="Med",2,1)))) -> 2 | K205: =IF(E205="",-1,J205*1000+H205) -> 2037.65 | L205: ='2. Assessment'!H16 -> Establish monthly regulatory horizon scanning and periodic compliance testing with evidence retention. | M205: GL-5, RO-1, RO-5 | N205: ⟳ Compliance Obligation | O205: ='2. Assessment'!E16 -> AI policy enforced with staff acknowledgement; obligations register maps regulations to controls and owners | P205: ='2. Assessment'!G16 -> Largely met | Q205: Misuse of AI, data leakage and breach of legal or regulatory requirements, with exposure to penalties, licence conditions and reputational harm.
A206: Q7 | B206: Responsible-AI guardrails & human oversight | C206: AI Governance | D206: =IF('2. Assessment'!L17="",0,1) -> 1 | E206: =IF(D206=0,"",'2. Assessment'!F17) -> 0.5 | F206: =1.0+IF(AND(OR(Calc!$C$32="High",Calc!$C$32="Critical"),OR(A206="Q7",A206="Q9",A206="Q11",A206="Q19")),0.5,0) -> 1 | G206: =IF(E206="","",1-E206) -> 0.5 | H206: =IF(E206="",-1,G206*F206*100+(20-6)/100) -> 50.14 | I206: =IF(E206="","",IF(E206<=0.25,"Immediate (0-3 months)",IF(AND(E206=0.5,F206>=1.5),"Immediate (0-3 months)",IF(E206<=0.5,"Short term (3-6 months)",IF(E206<=0.75,"Medium term (6-12 months)","Sustain"))))) -> Short term (3-6 months) | J206: =IF(I206="",0,IF(LEFT(I206,3)="Imm",4,IF(LEFT(I206,3)="Sho",3,IF(LEFT(I206,3)="Med",2,1)))) -> 3 | K206: =IF(E206="",-1,J206*1000+H206) -> 3050.14 | L206: ='2. Assessment'!H17 -> Apply mandatory human-in-charge controls and AI disclosure to all relevant AI; require committee approval for High / Critical uses. | M206: GL-7, RS-1, RS-4, RS-5, CO-1, CO-3 | N206: ⚖ Ethical Consideration | O206: ='2. Assessment'!E17 -> AI committee / CoE established; guardrails defined for some areas (e.g., human review of outputs) | P206: ='2. Assessment'!G17 -> Partially met | Q206: Biased or harmful outcomes, undisclosed AI use and lack of accountability for AI-supported decisions.
A207: Q8 | B207: AI incidents, monitoring & assurance | C207: AI Governance | D207: =IF('2. Assessment'!L18="",0,1) -> 1 | E207: =IF(D207=0,"",'2. Assessment'!F18) -> 0.75 | F207: =1.5+IF(AND(OR(Calc!$C$32="High",Calc!$C$32="Critical"),OR(A207="Q7",A207="Q9",A207="Q11",A207="Q19")),0.5,0) -> 1.5 | G207: =IF(E207="","",1-E207) -> 0.25 | H207: =IF(E207="",-1,G207*F207*100+(20-7)/100) -> 37.63 | I207: =IF(E207="","",IF(E207<=0.25,"Immediate (0-3 months)",IF(AND(E207=0.5,F207>=1.5),"Immediate (0-3 months)",IF(E207<=0.5,"Short term (3-6 months)",IF(E207<=0.75,"Medium term (6-12 months)","Sustain"))))) -> Medium term (6-12 months) | J207: =IF(I207="",0,IF(LEFT(I207,3)="Imm",4,IF(LEFT(I207,3)="Sho",3,IF(LEFT(I207,3)="Med",2,1)))) -> 2 | K207: =IF(E207="",-1,J207*1000+H207) -> 2037.63 | L207: ='2. Assessment'!H18 -> Implement post-incident learning and an ISO/IEC 42001 certification-readiness review. | M207: IM-1, IM-2, IM-3, AA-1, AA-2, RO-4 | N207: ⟳ Compliance Obligation | O207: ='2. Assessment'!E18 -> AI incident management with regulatory notification criteria; periodic internal audit of AI governance; assurance obtained from AI vendors | P207: ='2. Assessment'!G18 -> Largely met | Q207: Delayed response to AI failures, missed regulatory notifications and lack of defensible evidence for regulators, auditors and clients.
A208: Q9 | B208: AI risk management framework | C208: AI Risk & Security | D208: =IF('2. Assessment'!L19="",0,1) -> 1 | E208: =IF(D208=0,"",'2. Assessment'!F19) -> 0.25 | F208: =1.5+IF(AND(OR(Calc!$C$32="High",Calc!$C$32="Critical"),OR(A208="Q7",A208="Q9",A208="Q11",A208="Q19")),0.5,0) -> 1.5 | G208: =IF(E208="","",1-E208) -> 0.75 | H208: =IF(E208="",-1,G208*F208*100+(20-8)/100) -> 112.62 | I208: =IF(E208="","",IF(E208<=0.25,"Immediate (0-3 months)",IF(AND(E208=0.5,F208>=1.5),"Immediate (0-3 months)",IF(E208<=0.5,"Short term (3-6 months)",IF(E208<=0.75,"Medium term (6-12 months)","Sustain"))))) -> Immediate (0-3 months) | J208: =IF(I208="",0,IF(LEFT(I208,3)="Imm",4,IF(LEFT(I208,3)="Sho",3,IF(LEFT(I208,3)="Med",2,1)))) -> 4 | K208: =IF(E208="",-1,J208*1000+H208) -> 4112.62 | L208: ='2. Assessment'!H19 -> Formalise the methodology, approve it at executive level and pilot it on current AI initiatives. | M208: RM-1, RM-2, RM-3, RM-5 | N208: ⚠ Mandatory Requirement | O208: ='2. Assessment'!E19 -> AI risks considered informally within general IT or project risk | P208: ='2. Assessment'!G19 -> Minimal | Q208: AI risks go unidentified or are rated inconsistently, so high-risk AI is approved without proportionate controls.
A209: Q10 | B209: AI risk appetite, KRIs & reporting | C209: AI Risk & Security | D209: =IF('2. Assessment'!L20="",0,1) -> 1 | E209: =IF(D209=0,"",'2. Assessment'!F20) -> 0.5 | F209: =1.5+IF(AND(OR(Calc!$C$32="High",Calc!$C$32="Critical"),OR(A209="Q7",A209="Q9",A209="Q11",A209="Q19")),0.5,0) -> 1.5 | G209: =IF(E209="","",1-E209) -> 0.5 | H209: =IF(E209="",-1,G209*F209*100+(20-9)/100) -> 75.11 | I209: =IF(E209="","",IF(E209<=0.25,"Immediate (0-3 months)",IF(AND(E209=0.5,F209>=1.5),"Immediate (0-3 months)",IF(E209<=0.5,"Short term (3-6 months)",IF(E209<=0.75,"Medium term (6-12 months)","Sustain"))))) -> Immediate (0-3 months) | J209: =IF(I209="",0,IF(LEFT(I209,3)="Imm",4,IF(LEFT(I209,3)="Sho",3,IF(LEFT(I209,3)="Med",2,1)))) -> 4 | K209: =IF(E209="",-1,J209*1000+H209) -> 4075.11 | L209: ='2. Assessment'!H20 -> Define KRIs with thresholds and escalation for each risk category and report them to the AI committee quarterly. | M209: RM-6, RM-4, GL-1 | N209: ⚠ Mandatory Requirement | O209: ='2. Assessment'!E20 -> AI risk appetite drafted; a few indicators tracked informally | P209: ='2. Assessment'!G20 -> Partially met | Q209: No shared view of how much AI risk is acceptable - leading to reckless adoption or blocked innovation - and late detection of deteriorating AI risk.
A210: Q11 | B210: AI inventory & risk / impact assessment | C210: AI Risk & Security | D210: =IF('2. Assessment'!L21="",0,1) -> 1 | E210: =IF(D210=0,"",'2. Assessment'!F21) -> 0.5 | F210: =1.5+IF(AND(OR(Calc!$C$32="High",Calc!$C$32="Critical"),OR(A210="Q7",A210="Q9",A210="Q11",A210="Q19")),0.5,0) -> 1.5 | G210: =IF(E210="","",1-E210) -> 0.5 | H210: =IF(E210="",-1,G210*F210*100+(20-10)/100) -> 75.1 | I210: =IF(E210="","",IF(E210<=0.25,"Immediate (0-3 months)",IF(AND(E210=0.5,F210>=1.5),"Immediate (0-3 months)",IF(E210<=0.5,"Short term (3-6 months)",IF(E210<=0.75,"Medium term (6-12 months)","Sustain"))))) -> Immediate (0-3 months) | J210: =IF(I210="",0,IF(LEFT(I210,3)="Imm",4,IF(LEFT(I210,3)="Sho",3,IF(LEFT(I210,3)="Med",2,1)))) -> 4 | K210: =IF(E210="",-1,J210*1000+H210) -> 4075.1 | L210: ='2. Assessment'!H21 -> Extend assessments to all AI systems and third-party AI; set approval authority by risk tier. | M210: GL-8, RM-2, RM-5, TP-2 | N210: ⚠ Mandatory Requirement | O210: ='2. Assessment'!E21 -> AI register with owners; risk assessments performed for some AI systems using a documented method | P210: ='2. Assessment'!G21 -> Partially met | Q210: Deployment of vulnerable, non-compliant or harmful AI systems and unknown AI exposure across the organisation and its supply chain.
A211: Q12 | B211: Third-party & AI supply-chain risk | C211: AI Risk & Security | D211: =IF('2. Assessment'!L22="",0,1) -> 1 | E211: =IF(D211=0,"",'2. Assessment'!F22) -> 0.5 | F211: =1.5+IF(AND(OR(Calc!$C$32="High",Calc!$C$32="Critical"),OR(A211="Q7",A211="Q9",A211="Q11",A211="Q19")),0.5,0) -> 1.5 | G211: =IF(E211="","",1-E211) -> 0.5 | H211: =IF(E211="",-1,G211*F211*100+(20-11)/100) -> 75.09 | I211: =IF(E211="","",IF(E211<=0.25,"Immediate (0-3 months)",IF(AND(E211=0.5,F211>=1.5),"Immediate (0-3 months)",IF(E211<=0.5,"Short term (3-6 months)",IF(E211<=0.75,"Medium term (6-12 months)","Sustain"))))) -> Immediate (0-3 months) | J211: =IF(I211="",0,IF(LEFT(I211,3)="Imm",4,IF(LEFT(I211,3)="Sho",3,IF(LEFT(I211,3)="Med",2,1)))) -> 4 | K211: =IF(E211="",-1,J211*1000+H211) -> 4075.09 | L211: ='2. Assessment'!H22 -> Make AI due diligence mandatory and adopt standard AI contract clauses (no training on client data, residency, audit, incident notice). | M211: TP-1, TP-2, TP-3, SE-7, LC-6 | N211: ⟳ Compliance Obligation | O211: ='2. Assessment'!E22 -> AI questions added to vendor due diligence for some purchases; contract terms vary | P211: ='2. Assessment'!G22 -> Partially met | Q211: Client or personal data used to train vendor models, unmanaged model changes, concentration on a single provider and regulatory breaches through suppliers.
A212: Q13 | B212: Securing AI systems | C212: AI Risk & Security | D212: =IF('2. Assessment'!L23="",0,1) -> 1 | E212: =IF(D212=0,"",'2. Assessment'!F23) -> 0.5 | F212: =1.5+IF(AND(OR(Calc!$C$32="High",Calc!$C$32="Critical"),OR(A212="Q7",A212="Q9",A212="Q11",A212="Q19")),0.5,0) -> 1.5 | G212: =IF(E212="","",1-E212) -> 0.5 | H212: =IF(E212="",-1,G212*F212*100+(20-12)/100) -> 75.08 | I212: =IF(E212="","",IF(E212<=0.25,"Immediate (0-3 months)",IF(AND(E212=0.5,F212>=1.5),"Immediate (0-3 months)",IF(E212<=0.5,"Short term (3-6 months)",IF(E212<=0.75,"Medium term (6-12 months)","Sustain"))))) -> Immediate (0-3 months) | J212: =IF(I212="",0,IF(LEFT(I212,3)="Imm",4,IF(LEFT(I212,3)="Sho",3,IF(LEFT(I212,3)="Med",2,1)))) -> 4 | K212: =IF(E212="",-1,J212*1000+H212) -> 4075.08 | L212: ='2. Assessment'!H23 -> Introduce AI red teaming before release, runtime guardrails (input / output filtering) and audit logging. | M212: SE-2, SE-3, SE-6 to SE-10, OM-2, AA-3 | N212: ⚠ Mandatory Requirement | O212: ='2. Assessment'!E23 -> AI-specific threats (e.g., prompt injection, data leakage) assessed for some systems; access controls and logging in place | P212: ='2. Assessment'!G23 -> Partially met | Q212: Unauthorised access, model compromise, data exfiltration through AI and undetected misuse.
A213: Q14 | B213: Defending against AI-enabled threats | C213: AI Risk & Security | D213: =IF('2. Assessment'!L24="",0,1) -> 1 | E213: =IF(D213=0,"",'2. Assessment'!F24) -> 0.75 | F213: =1.0+IF(AND(OR(Calc!$C$32="High",Calc!$C$32="Critical"),OR(A213="Q7",A213="Q9",A213="Q11",A213="Q19")),0.5,0) -> 1 | G213: =IF(E213="","",1-E213) -> 0.25 | H213: =IF(E213="",-1,G213*F213*100+(20-13)/100) -> 25.07 | I213: =IF(E213="","",IF(E213<=0.25,"Immediate (0-3 months)",IF(AND(E213=0.5,F213>=1.5),"Immediate (0-3 months)",IF(E213<=0.5,"Short term (3-6 months)",IF(E213<=0.75,"Medium term (6-12 months)","Sustain"))))) -> Medium term (6-12 months) | J213: =IF(I213="",0,IF(LEFT(I213,3)="Imm",4,IF(LEFT(I213,3)="Sho",3,IF(LEFT(I213,3)="Med",2,1)))) -> 2 | K213: =IF(E213="",-1,J213*1000+H213) -> 2025.07 | L213: ='2. Assessment'!H24 -> Adopt continuous exposure management and AI-specific red teaming; reduce patch cycles to days. | M213: AT-1, AT-2, AT-3, AT-4 | N213: ☆ Recommended | O213: ='2. Assessment'!E24 -> Deepfake-resilient verification for payments and sensitive requests; behaviour-based detection; AI incident playbooks exercised | P213: ='2. Assessment'!G24 -> Largely met | Q213: Deepfake-enabled fraud, account compromise and faster, more scalable attacks that outpace defences.
A214: Q15 | B214: AI training, literacy & awareness | C214: Training & Awareness | D214: =IF('2. Assessment'!L25="",0,1) -> 1 | E214: =IF(D214=0,"",'2. Assessment'!F25) -> 0.75 | F214: =1.5+IF(AND(OR(Calc!$C$32="High",Calc!$C$32="Critical"),OR(A214="Q7",A214="Q9",A214="Q11",A214="Q19")),0.5,0) -> 1.5 | G214: =IF(E214="","",1-E214) -> 0.25 | H214: =IF(E214="",-1,G214*F214*100+(20-14)/100) -> 37.56 | I214: =IF(E214="","",IF(E214<=0.25,"Immediate (0-3 months)",IF(AND(E214=0.5,F214>=1.5),"Immediate (0-3 months)",IF(E214<=0.5,"Short term (3-6 months)",IF(E214<=0.75,"Medium term (6-12 months)","Sustain"))))) -> Medium term (6-12 months) | J214: =IF(I214="",0,IF(LEFT(I214,3)="Imm",4,IF(LEFT(I214,3)="Sho",3,IF(LEFT(I214,3)="Med",2,1)))) -> 2 | K214: =IF(E214="",-1,J214*1000+H214) -> 2037.56 | L214: ='2. Assessment'!H25 -> Measure competence, refresh annually, and build an AI champions network and workforce plan. | M214: GL-4, RS-9 | N214: ⟳ Compliance Obligation | O214: ='2. Assessment'!E25 -> Mandatory AI literacy before tool access; role-based pathways for developers, oversight staff and leaders; scenario-based security awareness | P214: ='2. Assessment'!G25 -> Largely met | Q214: Unsafe use, susceptibility to AI-enabled threats and poor adoption; non-compliance with the EU AI Act Art. 4 AI-literacy duty where applicable.
A215: Q16 | B215: AI strategy & executive ownership | C215: Strategy & Value | D215: =IF('2. Assessment'!L26="",0,1) -> 1 | E215: =IF(D215=0,"",'2. Assessment'!F26) -> 0.5 | F215: =1.0+IF(AND(OR(Calc!$C$32="High",Calc!$C$32="Critical"),OR(A215="Q7",A215="Q9",A215="Q11",A215="Q19")),0.5,0) -> 1 | G215: =IF(E215="","",1-E215) -> 0.5 | H215: =IF(E215="",-1,G215*F215*100+(20-15)/100) -> 50.05 | I215: =IF(E215="","",IF(E215<=0.25,"Immediate (0-3 months)",IF(AND(E215=0.5,F215>=1.5),"Immediate (0-3 months)",IF(E215<=0.5,"Short term (3-6 months)",IF(E215<=0.75,"Medium term (6-12 months)","Sustain"))))) -> Short term (3-6 months) | J215: =IF(I215="",0,IF(LEFT(I215,3)="Imm",4,IF(LEFT(I215,3)="Sho",3,IF(LEFT(I215,3)="Med",2,1)))) -> 3 | K215: =IF(E215="",-1,J215*1000+H215) -> 3050.05 | L215: ='2. Assessment'!H26 -> Link the strategy to business objectives and budget; define experimentation ('sandbox') boundaries and communicate them. | M215: GL-1, GL-3 | N215: ☆ Recommended | O215: ='2. Assessment'!E26 -> Executive sponsor named and AI strategy drafted, but not linked to business objectives or budget | P215: ='2. Assessment'!G26 -> Partially met | Q215: Lack of executive direction leads to inconsistent AI use, unmanaged risk-taking, poor-quality outputs and fragmented adoption.
A216: Q17 | B216: Use-case portfolio & value realisation | C216: Strategy & Value | D216: =IF('2. Assessment'!L27="",0,1) -> 1 | E216: =IF(D216=0,"",'2. Assessment'!F27) -> 0.5 | F216: =1.0+IF(AND(OR(Calc!$C$32="High",Calc!$C$32="Critical"),OR(A216="Q7",A216="Q9",A216="Q11",A216="Q19")),0.5,0) -> 1 | G216: =IF(E216="","",1-E216) -> 0.5 | H216: =IF(E216="",-1,G216*F216*100+(20-16)/100) -> 50.04 | I216: =IF(E216="","",IF(E216<=0.25,"Immediate (0-3 months)",IF(AND(E216=0.5,F216>=1.5),"Immediate (0-3 months)",IF(E216<=0.5,"Short term (3-6 months)",IF(E216<=0.75,"Medium term (6-12 months)","Sustain"))))) -> Short term (3-6 months) | J216: =IF(I216="",0,IF(LEFT(I216,3)="Imm",4,IF(LEFT(I216,3)="Sho",3,IF(LEFT(I216,3)="Med",2,1)))) -> 3 | K216: =IF(E216="",-1,J216*1000+H216) -> 3050.04 | L216: ='2. Assessment'!H27 -> Define benefit KPIs (financial and non-financial) at approval and assign benefit owners. | M216: GL-6, GL-5 | N216: ☆ Recommended | O216: ='2. Assessment'!E27 -> Use-case intake exists and initiatives are prioritised, but benefits are not systematically tracked | P216: ='2. Assessment'!G27 -> Partially met | Q216: Duplicated or low-value AI investment, shadow AI and inability to demonstrate return on investment.
A217: Q18 | B217: Data governance, quality & privacy for AI | C217: Data & Technology | D217: =IF('2. Assessment'!L28="",0,1) -> 1 | E217: =IF(D217=0,"",'2. Assessment'!F28) -> 0.75 | F217: =1.5+IF(AND(OR(Calc!$C$32="High",Calc!$C$32="Critical"),OR(A217="Q7",A217="Q9",A217="Q11",A217="Q19")),0.5,0) -> 1.5 | G217: =IF(E217="","",1-E217) -> 0.25 | H217: =IF(E217="",-1,G217*F217*100+(20-17)/100) -> 37.53 | I217: =IF(E217="","",IF(E217<=0.25,"Immediate (0-3 months)",IF(AND(E217=0.5,F217>=1.5),"Immediate (0-3 months)",IF(E217<=0.5,"Short term (3-6 months)",IF(E217<=0.75,"Medium term (6-12 months)","Sustain"))))) -> Medium term (6-12 months) | J217: =IF(I217="",0,IF(LEFT(I217,3)="Imm",4,IF(LEFT(I217,3)="Sho",3,IF(LEFT(I217,3)="Med",2,1)))) -> 2 | K217: =IF(E217="",-1,J217*1000+H217) -> 2037.53 | L217: ='2. Assessment'!H28 -> Automate data-quality and lineage monitoring; operationalise data-subject rights and transfer assessments for AI. | M217: LC-1, SE-4, PR-1, PR-4, PR-5, PR-6 | N217: ⟳ Compliance Obligation | O217: ='2. Assessment'!E28 -> Data readiness assessed before approval; lineage and quality monitored; minimisation, anonymisation and prompt redaction applied; DPIAs standard | P217: ='2. Assessment'!G28 -> Largely met | Q217: Data breaches, PDPL non-compliance, and biased or inaccurate outputs from poor-quality or unsuitable data.
A218: Q19 | B218: AI architecture, integration & monitoring | C218: Data & Technology | D218: =IF('2. Assessment'!L29="",0,1) -> 1 | E218: =IF(D218=0,"",'2. Assessment'!F29) -> 0.5 | F218: =1.0+IF(AND(OR(Calc!$C$32="High",Calc!$C$32="Critical"),OR(A218="Q7",A218="Q9",A218="Q11",A218="Q19")),0.5,0) -> 1 | G218: =IF(E218="","",1-E218) -> 0.5 | H218: =IF(E218="",-1,G218*F218*100+(20-18)/100) -> 50.02 | I218: =IF(E218="","",IF(E218<=0.25,"Immediate (0-3 months)",IF(AND(E218=0.5,F218>=1.5),"Immediate (0-3 months)",IF(E218<=0.5,"Short term (3-6 months)",IF(E218<=0.75,"Medium term (6-12 months)","Sustain"))))) -> Short term (3-6 months) | J218: =IF(I218="",0,IF(LEFT(I218,3)="Imm",4,IF(LEFT(I218,3)="Sho",3,IF(LEFT(I218,3)="Med",2,1)))) -> 3 | K218: =IF(E218="",-1,J218*1000+H218) -> 3050.02 | L218: ='2. Assessment'!H29 -> Centralise API / access control for AI, define agent execution authority and implement drift / performance monitoring with thresholds. | M218: LC-2, LC-3, LC-8, LC-12, OM-1, OM-4, RM-6 | N218: ☆ Recommended | O218: ='2. Assessment'!E29 -> Reference architecture drafted; approved platforms and integration patterns for most AI; basic performance monitoring | P218: ='2. Assessment'!G29 -> Partially met | Q218: Inconsistent and insecure implementations, undetected model drift or failure, excessive agent privileges and unsustainable AI costs.
A219: Q20 | B219: Model risk management & validation | C219: Data & Technology | D219: =IF('2. Assessment'!L30="",0,1) -> 1 | E219: =IF(D219=0,"",'2. Assessment'!F30) -> 0.5 | F219: =1.0+IF(AND(OR(Calc!$C$32="High",Calc!$C$32="Critical"),OR(A219="Q7",A219="Q9",A219="Q11",A219="Q19")),0.5,0) -> 1 | G219: =IF(E219="","",1-E219) -> 0.5 | H219: =IF(E219="",-1,G219*F219*100+(20-19)/100) -> 50.01 | I219: =IF(E219="","",IF(E219<=0.25,"Immediate (0-3 months)",IF(AND(E219=0.5,F219>=1.5),"Immediate (0-3 months)",IF(E219<=0.5,"Short term (3-6 months)",IF(E219<=0.75,"Medium term (6-12 months)","Sustain"))))) -> Short term (3-6 months) | J219: =IF(I219="",0,IF(LEFT(I219,3)="Imm",4,IF(LEFT(I219,3)="Sho",3,IF(LEFT(I219,3)="Med",2,1)))) -> 3 | K219: =IF(E219="",-1,J219*1000+H219) -> 3050.01 | L219: ='2. Assessment'!H30 -> Validate all material models before use and on a risk-based cycle; document thresholds, limitations and conditions of use. | M219: LC-9, RS-6, LC-13, OM-1 | N219: ☆ Recommended | O219: ='2. Assessment'!E30 -> Model inventory exists; validation performed for some material models | P219: ='2. Assessment'!G30 -> Partially met | Q219: Inaccurate, biased or unstable models drive decisions unnoticed, with regulatory exposure for financial-services clients.

Sheet Lists
A1: Yes | B1: Banking & financial services | C1: 1-50 employees | D1: Whole organisation | E1: Deployer only (uses AI built by others) | F1: Not started
A2: No | B2: Insurance | C2: 51-250 employees | D2: Business unit / function | E2: Provider (develops / sells AI systems) | F2: Planned
B3: Government & public sector | C3: 251-1,000 employees | D3: Specific AI system or use case | E3: Both provider and deployer | F3: In progress
B4: Telecommunications | C4: 1,001-5,000 employees | F4: Completed
B5: Healthcare | C5: More than 5,000 employees | F5: Deferred
B6: Hospitality & tourism
B7: Professional services
B8: Manufacturing & industry
B9: Retail & consumer
B10: Energy & utilities
B11: Education
B12: Other
